Workbook

Sheet insprint pivot
H1: Insprint Yes/No | I1: Yes | L1: Insprint Yes/No | M1: (Multiple Items) | O1: Module count for Mar 28 insprint
H2: PT Lead | I2: (All) | O2: PT lead | P2: No of US for insprint | Q2: Modules Count | R2: Module names | S2: ETA for pipeline readiness for Prod | T2: Excluded code from
A3: Count of Parent Title | B3: Column Labels | L3: Row Labels | M3: Count of Parent Title | O3: Pirtheebaa | P3: 20 | Q3: 11 | R3: PCAT Dashboard Learn SA Team manager View MMS Details Opportunity Workflow Manage SA Review Approval Transition To Delivery Define Team WRWS Estimators/Calculators | S3: completed
A4: Row Labels | B4: No | C4: Yes | D4: Grand Total | I4: Values | L4: Prompt related testing | M4: 86 | O4: Himanshu | P4: 9 | Q4: 1 | R4: PLD | T4: no
A5: Anand | B5: 5 | C5: 4 | D5: 9 | H5: Insprint Tester | I5: Count of Parent Title | J5: Average of If insprint YES - % of completion | L5: Email functionality | M5: 43 | O5: Shini | P5: 46 | Q5: 2 | R5: BPMS and DCSO | S5: Mar 24 EOD | T5: no
A6: Devika | B6: 26 | D6: 26 | H6: Mary.jacob | I6: 2 | J6: 1 | L6: Excel functionality | M6: 36 | O6: Anand | P6: 4 | Q6: 1 | R6: SI Online | S6: completed
A7: Hajara | B7: 79 | C7: 8 | D7: 87 | H7: sagarika.a.singh | I7: 6 | J7: 1 | L7: IMS BAU | M7: 28 | O7: Nandini | P7: 10 | Q7: 4 | R7: Estimator Calculator Workflow, Value Shaping, Asset Calculator,Automation Calculator | S7: PR pending
A8: Himanshu | B8: 28 | C8: 9 | D8: 37 | H8: pavithra.b.palani | I8: 2 | J8: 1 | L8: PBI report validation | M8: 27 | O8: Hajara | P8: 11 | Q8: 1 | R8: GEN AI | S8: Mar 26 EOD
A9: Jaya | B9: 34 | C9: 8 | D9: 42 | H9: abhijit.a.nandi | I9: 1 | J9: 1 | L9: External Team Integration | M9: 25 | O9: Leena | P9: 21 | Q9: 1 | R9: DSP | S9: In progress
A10: Kavi | B10: 11 | C10: 3 | D10: 14 | H10: v.b.sivakumar | I10: 2 | J10: 1 | L10: PPT/PDF Validation | M10: 21 | O10: Jaya | P10: 6 | Q10: 1 | R10: AMS_OCP_DCTA | S10: completed
A11: Leena | B11: 53 | C11: 21 | D11: 74 | H11: amresh.l.kumar | I11: 1 | J11: 1 | L11: Too many screen validation involved and complex to automate within insprint timeline | M11: 21 | O11: Kavi | P11: 3 | Q11: 2 | R11: SI OCP, DCTA-MMP | S11: completed | T11: pending 2 stories will not be considered . They can be run stand alone by insprint testers
A12: Nandini | B12: 15 | C12: 10 | D12: 25 | H12: navya.majji | I12: 4 | J12: 1 | L12: OBM (GEN AI) Not possible to automate | M12: 18 | O12: Devika | P12: 0 | Q12: 0
A13: Omkar | B13: 1 | D13: 1 | H13: Anitha.a.ramesh | I13: 3 | J13: 1 | L13: Full regression required | M13: 15 | O13: Raji | P13: 0 | Q13: 0
A14: Pirtheebaa | B14: 25 | C14: 18 | D14: 43 | H14: s.af.natarajan | I14: 1 | J14: 1 | L14: BPMS BAU | M14: 13
A15: Rajeswari | B15: 18 | D15: 18 | H15: anusha.goriparthi | I15: 1 | J15: 1 | L15: One time update related | M15: 9
A16: Shini | B16: 18 | C16: 41 | D16: 59 | H16: sathya.senthilkumar | I16: 1 | J16: 1 | L16: UI alignment and Font related | M16: 6
A17: Surbhi | B17: 12 | D17: 12 | H17: arun.thangapandian | I17: 4 | J17: 1 | L17: Story added Last 7 days of release | M17: 5
A18: Vaidheki | B18: 28 | D18: 28 | H18: a.nanditha.uddaraju | I18: 1 | J18: 1 | L18: (blank)
A19: Grand Total | B19: 353 | C19: 122 | D19: 475 | H19: ayush.ad.singh | I19: 1 | J19: 1 | L19: Grand Total | M19: 353
H20: nalluri.vishnupriya | I20: 1 | J20: 1
H21: bandi.sunanda | I21: 1 | J21: 1
H22: nitish.kumar.prusty | I22: 6 | J22: 1
H23: Bhavana.reddy.alla | I23: 2 | J23: 1
H24: r.yuvanitharsana | I24: 1 | J24: 1
H25: divya.belli | I25: 2 | J25: 1
H26: s.manmit.vanarase | I26: 3 | J26: 1
H27: divya.sree.chatla | I27: 1 | J27: 1
H28: sangeetha.pandian | I28: 1 | J28: 1
H29: ganga.m.reddy.padala | I29: 4 | J29: 1
H30: ShaliniB.Pandey | I30: 3 | J30: 1
H31: gayatri.korikana | I31: 3 | J31: 1
... H68: Grand Total | I68: 122 | J68: 0.99590164

Sheet Milestone
A1: User story Freeze Date | B1: Cut off for PT hand over | C1: Cut off for UAT hand over | D1: UAT Completion | E1: Functional Bug closure | F1: Regression | G1: Regression bug Closure | H1: Code Freeze | I1: Initial GNG decision | J1: Final Go/No Go Decision | K1: Final Go-Live
A2: 46078 | B2: 46092 | C2: 46098 | D2: 46105 | E2: 46105 | F2: 19-Mar to 23-Mar | G2: 46106 | H2: 46107 | I2: 46105 | J2: 46108 | K2: 46109

Sheet PT status
A1: Module (TextVerification) | B1: Parent Title | C1: Feature ID | D1: PT Lead | E1: Title | F1: ID | G1: Primary Tester | H1: Secondary Tester | J1: Insprint Tester | K1: Insprint Yes/No | L1: If Insprint NO - Reason | M1: Pre defined No Reason | N1: Complexity | O1: In sprint test case count | P1: If insprint YES - % of completion | Q1: Automated cases generated from GHC | R1: Useful Automated cases from GHC | S1: Tester created automated count (not given by GHC) | T1: Reviwed Final automation count | U1: Coverage for automated test case from GHC% | V1: Accuracy of Automated Test case from GHC% | W1: Test Planning | X1: BA Review | Y1: TFS upload | Z1: PT Status | AA1: Manual Test cases generated from GHC | AB1: Useful Test cases from GHC | AC1: Tester Created test case count | AD1: Reviwed Final Test case count | AE1: Coverage for Manual Test cases from GHC% | AF1: Accuracy for Manual test cases from GHC% | AG1: TFS state | AH1: Passed | AI1: Failed | AJ1: Blocked | AK1: Not Run | AL1: Total | AM1: Execution % | AN1: Pass % | AO1: Comments | AP1: Node Name | AQ1: MPOC
A2: =_xlfn.XLOOKUP(F2,'TFS Details'!F:F,'TFS Details'!D:D) -> Value Shaping | B2: =_xlfn.XLOOKUP(F2,'TFS Details'!F:F,'TFS Details'!A:A) -> Value Shaping –Enhancements | C2: =_xlfn.XLOOKUP(F2,'TFS Details'!F:F,'TFS Details'!E:E) -> 4330994 | D2: Nandini | E2: Value Shaping - As a myISP user, I want to introduce a new role "V2V Configurator" that lands on the dashboard with an action available in the Tools section, so that SMEs can navigate to the Configurator Value Tree link and configure Value Tree templates | F2: 4315785 | G2: Pawan | H2: Yasin | J2: pawan.m.kumar.singh | K2: Yes | N2: Medium | P2: 1 | Q2: 11 | R2: 3 | S2: 0 | T2: 3 | U2: 1 | V2: 0.77 | W2: Completed | X2: Completed | Y2: Completed | Z2: Completed | AA2: 27 | AB2: 21 | AC2: 0 | AD2: 21 | AE2: 1 | AF2: 0.85 | AG2: =_xlfn.XLOOKUP(F2,'TFS Details'!F:F,'TFS Details'!H:H) -> Test Complete | AH2: 21 | AI2: 0 | AJ2: 0 | AK2: 0 | AL2: =SUM(AH2:AK2) -> 21 | AM2: =IF(AH2+AI2=0,0,SUM(AH2:AI2)/AL2) -> 1 | AN2: =IF(AH2=0,0,AH2/(SUM(AH2:AJ2))) -> 1 | AP2: =_xlfn.XLOOKUP(F2,'TFS Details'!F:F,'TFS Details'!I:I) -> NGTransformers | AQ2: =_xlfn.XLOOKUP(AP2,'TFS Details'!I:I,'TFS Details'!AE:AE) -> sowjanya.kari
A3: =_xlfn.XLOOKUP(F3,'TFS Details'!F:F,'TFS Details'!D:D) -> Estimator and Calculator | B3: =_xlfn.XLOOKUP(F3,'TFS Details'!F:F,'TFS Details'!A:A) -> Estimator/Calculator - Expand-Collapse icon Type and Position | C3: =_xlfn.XLOOKUP(F3,'TFS Details'!F:F,'TFS Details'!E:E) -> 4174547 | D3: Nandini | E3: As a myISP user I should be able to see expand and collapse icon in Estimator and calculator screen as per UI revamp standards | F3: 4174533 | G3: Yuvani | H3: Sunanda | J3: bandi.sunanda | K3: Yes | N3: Medium | P3: 1 | Q3: 10 | R3: 1 | S3: 0 | T3: 1 | U3: 0.7 | V3: 1 | W3: Completed | X3: Completed | Y3: Completed | Z3: Completed | AA3: 50 | AB3: 15 | AC3: 0 | AD3: 15 | AE3: 1 | AF3: 1 | AG3: =_xlfn.XLOOKUP(F3,'TFS Details'!F:F,'TFS Details'!H:H) -> Test Complete | AH3: 15 | AI3: 0 | AJ3: 0 | AK3: 0 | AL3: 15 | AM3: =IF(AH3+AI3=0,0,SUM(AH3:AI3)/AL3) -> 1 | AN3: =IF(AH3=0,0,AH3/(SUM(AH3:AJ3))) -> 1 | AO3: bugid :4427095 | AP3: =_xlfn.XLOOKUP(F3,'TFS Details'!F:F,'TFS Details'!I:I) -> TechWarriors | AQ3: =_xlfn.XLOOKUP(AP3,'TFS Details'!I:I,'TFS Details'!AE:AE) -> sowjanya.kari
A4: =_xlfn.XLOOKUP(F4,'TFS Details'!F:F,'TFS Details'!D:D) -> Value Shaping | B4: =_xlfn.XLOOKUP(F4,'TFS Details'!F:F,'TFS Details'!A:A) -> Value Shaping –Enhancements | C4: =_xlfn.XLOOKUP(F4,'TFS Details'!F:F,'TFS Details'!E:E) -> 4330994 | D4: Nandini | E4: Value Shaping -As a myISP User - V2V Configurator - I want to access the Estimators/Calculators in read-only mode and navigate using the fixed breadcrumb path so that I can maintain workflow continuity. | F4: 4364563 | G4: Srilekha | H4: Yasin/Reshmi | J4: guddeti.srilekha | K4: Yes | N4: Complex | P4: 1 | Q4: 22 | R4: 5 | S4: 0 | T4: 5 | U4: 1 | V4: 0.7 | W4: Completed | X4: Completed | Y4: Completed | Z4: Completed | AA4: 50 | AB4: 19 | AC4: 0 | AD4: 19 | AE4: 1 | AF4: 0.7 | AG4: =_xlfn.XLOOKUP(F4,'TFS Details'!F:F,'TFS Details'!H:H) -> Test Complete | AH4: 19 | AI4: 0 | AJ4: 0 | AK4: 0 | AL4: =SUM(AH4:AK4) -> 19 | AM4: =IF(AH4+AI4=0,0,SUM(AH4:AI4)/AL4) -> 1 | AN4: =IF(AH4=0,0,AH4/(SUM(AH4:AJ4))) -> 1 | AP4: =_xlfn.XLOOKUP(F4,'TFS Details'!F:F,'TFS Details'!I:I) -> TechWarriors | AQ4: =_xlfn.XLOOKUP(AP4,'TFS Details'!I:I,'TFS Details'!AE:AE) -> sowjanya.kari
A5: =_xlfn.XLOOKUP(F5,'TFS Details'!F:F,'TFS Details'!D:D) -> Automation Calculator | B5: =_xlfn.XLOOKUP(F5,'TFS Details'!F:F,'TFS Details'!A:A) -> ROI - Automation Calculator - Default Logic | C5: =_xlfn.XLOOKUP(F5,'TFS Details'!F:F,'TFS Details'!E:E) -> 4366165 | D5: Nandini | E5: As a myISP user working on automation ROI section I want AD and AM views to mirror the Productivity Assessment layout (lever/sub-lever grid with Y1H1-Y5H5 periods) and auto-populate values based on PA completion status | F5: 4364929 | G5: Soundhar | H5: Yuvani/Sunanda | K5: No | L5: Data validation is highly complex because the required information is integrated directly from the R2 (PA) screen, to Calc ROI screen ,Specific SG‑based criteria, scenario‑dependent, | M5: Too many screen validation involved and complex to automate within insprint timeline | W5: Completed | X5: Completed | Y5: Completed | Z5: Completed | AA5: 50 | AB5: 28 | AC5: 0 | AD5: 28 | AE5: =AB5/AD5 -> 1 | AF5: 1 | AG5: =_xlfn.XLOOKUP(F5,'TFS Details'!F:F,'TFS Details'!H:H) -> Test Complete | AH5: 28 | AI5: 0 | AJ5: 0 | AK5: 0 | AL5: =SUM(AH5:AK5) -> 28 | AM5: =IF(AH5+AI5=0,0,SUM(AH5:AI5)/AL5) -> 1 | AN5: =IF(AH5=0,0,AH5/(SUM(AH5:AJ5))) -> 1 | AP5: =_xlfn.XLOOKUP(F5,'TFS Details'!F:F,'TFS Details'!I:I) -> CrazyCoders | AQ5: =_xlfn.XLOOKUP(AP5,'TFS Details'!I:I,'TFS Details'!AE:AE) -> nityanand.giri
A6: =_xlfn.XLOOKUP(F6,'TFS Details'!F:F,'TFS Details'!D:D) -> Automation Calculator | B6: =_xlfn.XLOOKUP(F6,'TFS Details'!F:F,'TFS Details'!A:A) -> ROI & Summary (Tab 8) will be as is in automation calculator with Split of GEN AI, Opera and Agentic and Ux upgrade | C6: =_xlfn.XLOOKUP(F6,'TFS Details'!F:F,'TFS Details'!E:E) -> 4405953 | D6: Nandini | E6: As a myISP user, I want all sections in the Summary tab to be displayed as accordions with expand and collapse functionality, So that I can easily navigate and review specific sections without clutter. | F6: 4364996 | G6: Soundhar | H6: Yuvani/Sunanda | J6: s.af.natarajan | K6: Yes | N6: Medium | P6: 1 | Q6: 6 | R6: 1 | S6: 0 | T6: 1 | U6: 0.7 | V6: 0.7 | W6: Completed | X6: Completed | Y6: Completed | Z6: Completed | AA6: 60 | AB6: 29 | AC6: 0 | AD6: 29 | AE6: =AB6/AA6 -> 0.48333333 | AF6: 0.4833 | AG6: =_xlfn.XLOOKUP(F6,'TFS Details'!F:F,'TFS Details'!H:H) -> Test Complete | AH6: 29 | AI6: 0 | AJ6: 0 | AK6: 0 | AL6: =SUM(AH6:AK6) -> 29 | AM6: =IF(AH6+AI6=0,0,SUM(AH6:AI6)/AL6) -> 1 | AN6: =IF(AH6=0,0,AH6/(SUM(AH6:AJ6))) -> 1 | AP6: =_xlfn.XLOOKUP(F6,'TFS Details'!F:F,'TFS Details'!I:I) -> Codeplayers | AQ6: =_xlfn.XLOOKUP(AP6,'TFS Details'!I:I,'TFS Details'!AE:AE) -> nityanand.giri
A7: =_xlfn.XLOOKUP(F7,'TFS Details'!F:F,'TFS Details'!D:D) -> Value Shaping | B7: =_xlfn.XLOOKUP(F7,'TFS Details'!F:F,'TFS Details'!A:A) -> Value Shaping –Enhancements | C7: =_xlfn.XLOOKUP(F7,'TFS Details'!F:F,'TFS Details'!E:E) -> 4330994 | D7: Nandini | E7: Value Shaping � As a myISP user, I want to be navigated to the Configurator Dashboard landing page when I click on the Tools link, so that I can continue creating the Value Tree. | F7: 4373517 | G7: Reshmi | H7: Yasin | J7: reshmi.doddi | K7: Yes | N7: Medium | P7: 1 | Q7: 10 | R7: 1 | S7: 0 | T7: 1 | U7: 0.7 | V7: 0.7 | W7: Completed | X7: Completed | Y7: Completed | Z7: Completed | AA7: 63 | AB7: 14 | AC7: 0 | AD7: 14 | AE7: 1 | AF7: 0.8 | AG7: =_xlfn.XLOOKUP(F7,'TFS Details'!F:F,'TFS Details'!H:H) -> Test Complete | AH7: 14 | AI7: 0 | AJ7: 0 | AK7: 0 | AL7: =SUM(AH7:AK7) -> 14 | AM7: =IF(AH7+AI7=0,0,SUM(AH7:AI7)/AL7) -> 1 | AN7: =IF(AH7=0,0,AH7/(SUM(AH7:AJ7))) -> 1 | AP7: =_xlfn.XLOOKUP(F7,'TFS Details'!F:F,'TFS Details'!I:I) -> Spartans | AQ7: =_xlfn.XLOOKUP(AP7,'TFS Details'!I:I,'TFS Details'!AE:AE) -> nityanand.giri
A8: =_xlfn.XLOOKUP(F8,'TFS Details'!F:F,'TFS Details'!D:D) -> Automation Calculator | B8: =_xlfn.XLOOKUP(F8,'TFS Details'!F:F,'TFS Details'!A:A) -> ROI & Summary (Tab 8) will be as is in automation calculator with Split of GEN AI, Opera and Agentic and Ux upgrade | C8: =_xlfn.XLOOKUP(F8,'TFS Details'!F:F,'TFS Details'!E:E) -> 4405953 | D8: Nandini | E8: As a myISP user I want the revamped Summary screen to include an overall summary and a ROI section that is a replica of the ROI screen with all sections So that the Summary PDF download contains all newly introduced revamp changes without missing data. | F8: 4373570 | G8: Sunanda | H8: Yuvani | K8: No | L8: Data validation is highly complex because the required information is integrated directly from the R2 (PA) screen, to Calc ROI screen ,Specific SG‑based criteria, scenario‑dependent, | M8: Too many screen validation involved and complex to automate within insprint timeline | W8: Completed | X8: Completed | Y8: Completed | Z8: Completed | AA8: 8 | AB8: 8 | AC8: 3 | AD8: 11 | AE8: 0.72 | AF8: 1 | AG8: =_xlfn.XLOOKUP(F8,'TFS Details'!F:F,'TFS Details'!H:H) -> Test Complete | AH8: 11 | AI8: 0 | AJ8: 0 | AK8: 0 | AL8: =SUM(AH8:AK8) -> 11 | AM8: =IF(AH8+AI8=0,0,SUM(AH8:AI8)/AL8) -> 1 | AN8: =IF(AH8=0,0,AH8/(SUM(AH8:AJ8))) -> 1 | AP8: =_xlfn.XLOOKUP(F8,'TFS Details'!F:F,'TFS Details'!I:I) -> Codeplayers | AQ8: =_xlfn.XLOOKUP(AP8,'TFS Details'!I:I,'TFS Details'!AE:AE) -> nityanand.giri
A9: =_xlfn.XLOOKUP(F9,'TFS Details'!F:F,'TFS Details'!D:D) -> Value Shaping | B9: =_xlfn.XLOOKUP(F9,'TFS Details'!F:F,'TFS Details'!A:A) -> Value Shaping –Enhancements | C9: =_xlfn.XLOOKUP(F9,'TFS Details'!F:F,'TFS Details'!E:E) -> 4330994 | D9: Nandini | E9: Value Shaping - [SVP] As a myISP user, I want SOP Input values linked in configurator link to be automatically populated for KPIs across a value tree , so that usability is improved and manual effort is reduced. | F9: 4376380 | G9: Yasin | H9: Reshmi | J9: shaik.yasin | K9: Yes | N9: Complex | P9: 1 | Q9: 11 | R9: 5 | W9: Completed | X9: Completed | Y9: Completed | Z9: In Progress | AA9: 10 | AB9: 7 | AC9: 4 | AD9: 11 | AE9: 0.65 | AF9: 0.7 | AG9: =_xlfn.XLOOKUP(F9,'TFS Details'!F:F,'TFS Details'!H:H) -> UAT In Test | AH9: 10 | AI9: 1 | AJ9: 0 | AK9: 0 | AL9: =SUM(AH9:AK9) -> 11 | AM9: =IF(AH9+AI9=0,0,SUM(AH9:AI9)/AL9) -> 1 | AN9: =IF(AH9=0,0,AH9/(SUM(AH9:AJ9))) -> 0.90909091 | AP9: =_xlfn.XLOOKUP(F9,'TFS Details'!F:F,'TFS Details'!I:I) -> Spartans | AQ9: =_xlfn.XLOOKUP(AP9,'TFS Details'!I:I,'TFS Details'!AE:AE) -> nityanand.giri
A10: =_xlfn.XLOOKUP(F10,'TFS Details'!F:F,'TFS Details'!D:D) -> Automation Calculator | B10: =_xlfn.XLOOKUP(F10,'TFS Details'!F:F,'TFS Details'!A:A) -> ROI - Automation Calculator - Default Logic | C10: =_xlfn.XLOOKUP(F10,'TFS Details'!F:F,'TFS Details'!E:E) -> 4366165 | D10: Nandini | E10: As a myISP user, I want the system to automatically calculate AD and AM Assessment productivity values using a default tech stack split of 50% Custom and 50% Package in the ROI tab | F10: 4362465 | G10: Soundhar | H10: Sunanda | K10: No | L10: ramya | M10: Too many screen validation involved and complex to automate within insprint timeline | W10: Completed | X10: Completed | Y10: Completed | Z10: Completed | AA10: 60 | AB10: 32 | AC10: 6 | AD10: 36 | AE10: 0.73 | AF10: 0.63 | AG10: =_xlfn.XLOOKUP(F10,'TFS Details'!F:F,'TFS Details'!H:H) -> Test Complete | AH10: 38 | AI10: 0 | AJ10: 0 | AK10: 0 | AL10: 38 | AM10: =IF(AH10+AI10=0,0,SUM(AH10:AI10)/AL10) -> 1 | AN10: =IF(AH10=0,0,AH10/(SUM(AH10:AJ10))) -> 1 | AP10: =_xlfn.XLOOKUP(F10,'TFS Details'!F:F,'TFS Details'!I:I) -> CrazyCoders | AQ10: =_xlfn.XLOOKUP(AP10,'TFS Details'!I:I,'TFS Details'!AE:AE) -> nityanand.giri
A11: =_xlfn.XLOOKUP(F11,'TFS Details'!F:F,'TFS Details'!D:D) -> Automation Calculator | B11: =_xlfn.XLOOKUP(F11,'TFS Details'!F:F,'TFS Details'!A:A) -> ROI & Summary (Tab 8) will be as is in automation calculator with Split of GEN AI, Opera and Agentic and Ux upgrade | C11: =_xlfn.XLOOKUP(F11,'TFS Details'!F:F,'TFS Details'!E:E) -> 4405953 | D11: Nandini | E11: As a myISP user, I want to view a new Overall Summary section that consolidates key cost metrics, So that I can quickly review the overall financial view before validation or submission. | F11: 4362711 | G11: Rohitha | H11: Yuvani | K11: No | L11: Data validation is highly complex because the required information is integrated directly from the R2 (PA) screen, to Calc ROI screen ,Specific SG‑based criteria, scenario‑dependent, | M11: Too many screen validation involved and complex to automate within insprint timeline | W11: Completed | X11: Completed | Y11: Completed | Z11: Completed | AA11: 8 | AB11: 7 | AC11: 4 | AD11: 11 | AE11: 0.73 | AF11: 0.97 | AG11: =_xlfn.XLOOKUP(F11,'TFS Details'!F:F,'TFS Details'!H:H) -> Test Complete | AH11: 11 | AI11: 0 | AJ11: 0 | AK11: 0 | AL11: =SUM(AH11:AK11) -> 11 | AM11: =IF(AH11+AI11=0,0,SUM(AH11:AI11)/AL11) -> 1 | AN11: =IF(AH11=0,0,AH11/(SUM(AH11:AJ11))) -> 1 | AP11: =_xlfn.XLOOKUP(F11,'TFS Details'!F:F,'TFS Details'!I:I) -> Codeplayers | AQ11: =_xlfn.XLOOKUP(AP11,'TFS Details'!I:I,'TFS Details'!AE:AE) -> nityanand.giri
A12: =_xlfn.XLOOKUP(F12,'TFS Details'!F:F,'TFS Details'!D:D) -> Automation Calculator | B12: =_xlfn.XLOOKUP(F12,'TFS Details'!F:F,'TFS Details'!A:A) -> ROI - Automation Calculator - Default Logic | C12: =_xlfn.XLOOKUP(F12,'TFS Details'!F:F,'TFS Details'!E:E) -> 4366165 | D12: Nandini | E12: As a myISP user viewing the ROI screen in the Automation Calculator I want to see Agentic AI productivity as a separate lever alongside Opera and Gen AI with a combined yearly breakdown view | F12: 4363958 | G12: Yuvani | H12: Sunanda | K12: No | L12: Data validation is highly complex because the required information is integrated directly from the R2 (PA) screen, to Calc ROI screen ,Specific SG‑based criteria, scenario‑dependent, | M12: Too many screen validation involved and complex to automate within insprint timeline | W12: Completed | X12: Completed | Y12: Completed | Z12: Completed | AA12: 60 | AB12: 27 | AC12: 5 | AD12: 32 | AE12: 0.53 | AF12: 0.45 | AG12: =_xlfn.XLOOKUP(F12,'TFS Details'!F:F,'TFS Details'!H:H) -> Test Complete | AH12: 27 | AI12: 0 | AJ12: 0 | AK12: 0 | AL12: =SUM(AH12:AK12) -> 27 | AM12: =IF(AH12+AI12=0,0,SUM(AH12:AI12)/AL12) -> 1 | AN12: =IF(AH12=0,0,AH12/(SUM(AH12:AJ12))) -> 1 | AP12: =_xlfn.XLOOKUP(F12,'TFS Details'!F:F,'TFS Details'!I:I) -> CrazyCoders | AQ12: =_xlfn.XLOOKUP(AP12,'TFS Details'!I:I,'TFS Details'!AE:AE) -> nityanand.giri
A13: =_xlfn.XLOOKUP(F13,'TFS Details'!F:F,'TFS Details'!D:D) -> Value Shaping | B13: =_xlfn.XLOOKUP(F13,'TFS Details'!F:F,'TFS Details'!A:A) -> Value Shaping –Enhancements | C13: =_xlfn.XLOOKUP(F13,'TFS Details'!F:F,'TFS Details'!E:E) -> 4330994 | D13: Nandini | E13: Value Shaping - As a myISP User - V2V Configurator - I want to access the Value Shaping tile in read-only mode and navigate using the fixed breadcrumb path so that I can maintain workflow continuity. | F13: 4364558 | G13: Samreen | H13: Yasin/Reshmi | J13: mohammad.samreen | K13: Yes | N13: Medium | P13: 1 | Q13: 17 | R13: 10 | S13: 0 | T13: 10 | U13: 1 | V13: 0.8 | W13: Completed | X13: Completed | Y13: Completed | Z13: Completed | AA13: 50 | AB13: 17 | AC13: 0 | AD13: 17 | AE13: 1 | AF13: 0.7 | AG13: =_xlfn.XLOOKUP(F13,'TFS Details'!F:F,'TFS Details'!H:H) -> Test Complete | AH13: 17 | AI13: 0 | AJ13: 0 | AK13: 0 | AL13: =SUM(AH13:AK13) -> 17 | AM13: =IF(AH13+AI13=0,0,SUM(AH13:AI13)/AL13) -> 1 | AN13: =IF(AH13=0,0,AH13/(SUM(AH13:AJ13))) -> 1 | AP13: =_xlfn.XLOOKUP(F13,'TFS Details'!F:F,'TFS Details'!I:I) -> Spartans | AQ13: =_xlfn.XLOOKUP(AP13,'TFS Details'!I:I,'TFS Details'!AE:AE) -> nityanand.giri
A14: =_xlfn.XLOOKUP(F14,'TFS Details'!F:F,'TFS Details'!D:D) -> Automation Calculator | B14: =_xlfn.XLOOKUP(F14,'TFS Details'!F:F,'TFS Details'!A:A) -> ROI - Automation Calculator - Default Logic | C14: =_xlfn.XLOOKUP(F14,'TFS Details'!F:F,'TFS Details'!E:E) -> 4366165 | D14: Nandini | E14: As a myISP user I want to see a clear system message when Productivity Assessment is not submitted for an eligible deal So that I understand that default productivity values are being applied | F14: 4361791 | G14: Sunanda | H14: Rohitha | K14: No | L14: Data validation is highly complex because the required information is integrated directly from the R2 (PA) screen, to Calc ROI screen ,Specific SG‑based criteria, scenario‑dependent, | M14: Too many screen validation involved and complex to automate within insprint timeline | W14: Completed | X14: Completed | Y14: Completed | Z14: Completed | AA14: 22 | AB14: 17 | AC14: 0 | AD14: 17 | AE14: =AB14/AA14 -> 0.77272727 | AF14: 0.77 | AG14: =_xlfn.XLOOKUP(F14,'TFS Details'!F:F,'TFS Details'!H:H) -> Test Complete | AH14: 17 | AI14: 0 | AJ14: 0 | AK14: 0 | AL14: =SUM(AH14:AK14) -> 17 | AM14: =IF(AH14+AI14=0,0,SUM(AH14:AI14)/AL14) -> 1 | AN14: =IF(AH14=0,0,AH14/(SUM(AH14:AJ14))) -> 1 | AP14: =_xlfn.XLOOKUP(F14,'TFS Details'!F:F,'TFS Details'!I:I) -> CrazyCoders | AQ14: =_xlfn.XLOOKUP(AP14,'TFS Details'!I:I,'TFS Details'!AE:AE) -> nityanand.giri
A15: =_xlfn.XLOOKUP(F15,'TFS Details'!F:F,'TFS Details'!D:D) -> Value Shaping | B15: =_xlfn.XLOOKUP(F15,'TFS Details'!F:F,'TFS Details'!A:A) -> Value Shaping –Enhancements | C15: =_xlfn.XLOOKUP(F15,'TFS Details'!F:F,'TFS Details'!E:E) -> 4330994 | D15: Nandini | E15: Value Shaping - As a myISP user, I should be able to download output (Benchmark and size of prize View) as PDF from summary screen of SVP page, so that it can be used for other purposes | F15: 4318918 | G15: Srilekha | H15: Yasin/Reshmi | K15: No | L15: cannot automate, verifying downloaded PDF sheet data with UI | M15: PPT/PDF Validation | W15: Completed | X15: Completed | Y15: Completed | Z15: Completed | AA15: 50 | AB15: 23 | AC15: 0 | AD15: 23 | AE15: 1 | AF15: 0.7 | AG15: =_xlfn.XLOOKUP(F15,'TFS Details'!F:F,'TFS Details'!H:H) -> UAT In Test | AH15: 23 | AI15: 0 | AJ15: 0 | AK15: 0 | AL15: =SUM(AH15:AK15) -> 23 | AM15: =IF(AH15+AI15=0,0,SUM(AH15:AI15)/AL15) -> 1 | AN15: =IF(AH15=0,0,AH15/(SUM(AH15:AJ15))) -> 1 | AP15: =_xlfn.XLOOKUP(F15,'TFS Details'!F:F,'TFS Details'!I:I) -> Spartans | AQ15: =_xlfn.XLOOKUP(AP15,'TFS Details'!I:I,'TFS Details'!AE:AE) -> nityanand.giri
A16: =_xlfn.XLOOKUP(F16,'TFS Details'!F:F,'TFS Details'!D:D) -> Calculator | B16: =_xlfn.XLOOKUP(F16,'TFS Details'!F:F,'TFS Details'!A:A) -> Asset Calculator - Asset accordions to be added in Asset Catalog | C16: =_xlfn.XLOOKUP(F16,'TFS Details'!F:F,'TFS Details'!E:E) -> 4331001 | D16: Nandini | E16: [Asset Calculator] - As a myISP User I want to implement Platform Asset Blueprint � Oracle & Platform Asset Blueprint � SAP Assets as taggable assets so that it aligns with business changes and the new design reframe | F16: 4328732 | G16: Yuvani | H16: Yuvani/Soundhar | J16: r.yuvanitharsana | K16: Yes | N16: Complex | P16: 1 | Q16: 19 | R16: 1 | S16: 0 | T16: 1 | U16: 0.75 | V16: 0.75 | W16: Completed | X16: Completed | Y16: Completed | Z16: Completed | AA16: 90 | AB16: 28 | AC16: 3 | AD16: 31 | AE16: =AB16/AD16 -> 0.90322581 | AF16: 0.95 | AG16: =_xlfn.XLOOKUP(F16,'TFS Details'!F:F,'TFS Details'!H:H) -> Test Complete | AH16: 31 | AI16: 0 | AJ16: 0 | AK16: 0 | AL16: =SUM(AH16:AK16) -> 31 | AM16: =IF(AH16+AI16=0,0,SUM(AH16:AI16)/AL16) -> 1 | AN16: =IF(AH16=0,0,AH16/(SUM(AH16:AJ16))) -> 1 | AP16: =_xlfn.XLOOKUP(F16,'TFS Details'!F:F,'TFS Details'!I:I) -> TitansPlus | AQ16: =_xlfn.XLOOKUP(AP16,'TFS Details'!I:I,'TFS Details'!AE:AE) -> nityanand.giri
A17: =_xlfn.XLOOKUP(F17,'TFS Details'!F:F,'TFS Details'!D:D) -> Value Shaping | B17: =_xlfn.XLOOKUP(F17,'TFS Details'!F:F,'TFS Details'!A:A) -> Value Shaping –Enhancements | C17: =_xlfn.XLOOKUP(F17,'TFS Details'!F:F,'TFS Details'!E:E) -> 4330994 | D17: Nandini | E17: Value Shaping - As a myISP user, I should be able to download output (Global View) as PDF from summary screen of SVP page, so that it can be used for other purposes | F17: 4100102 | G17: Reshmi | H17: Yasin | K17: No | L17: cannot automate, verifying downloaded PDF data with UI | M17: PPT/PDF Validation | W17: Completed | X17: Completed | Y17: Completed | Z17: Completed | AA17: 97 | AB17: 21 | AC17: 0 | AD17: 21 | AE17: 1 | AF17: 0.8 | AG17: =_xlfn.XLOOKUP(F17,'TFS Details'!F:F,'TFS Details'!H:H) -> Test Complete | AH17: 21 | AI17: 0 | AJ17: 0 | AK17: 0 | AL17: =SUM(AH17:AK17) -> 21 | AM17: =IF(AH17+AI17=0,0,SUM(AH17:AI17)/AL17) -> 1 | AN17: =IF(AH17=0,0,AH17/(SUM(AH17:AJ17))) -> 1 | AP17: =_xlfn.XLOOKUP(F17,'TFS Details'!F:F,'TFS Details'!I:I) -> Spartans | AQ17: =_xlfn.XLOOKUP(AP17,'TFS Details'!I:I,'TFS Details'!AE:AE) -> nityanand.giri
A18: =_xlfn.XLOOKUP(F18,'TFS Details'!F:F,'TFS Details'!D:D) -> Value Shaping | B18: =_xlfn.XLOOKUP(F18,'TFS Details'!F:F,'TFS Details'!A:A) -> Value Shaping –Enhancements | C18: =_xlfn.XLOOKUP(F18,'TFS Details'!F:F,'TFS Details'!E:E) -> 4330994 | D18: Nandini | E18: Value Shaping - As a myISP user, I want to export the current benchmark table data So that I can perform bulk updates efficiently while preserving data integrity and validation rules. | F18: 4368404 | G18: Pawan | H18: Yasin/Reshmi | K18: No | L18: cannot automate, verifying downloaded PDF sheet data with UI | M18: PPT/PDF Validation | W18: Completed | X18: Completed | Y18: Completed | Z18: Completed | AA18: 70 | AB18: 48 | AC18: 0 | AD18: 48 | AE18: 1 | AF18: 0.85 | AG18: UAT In Test | AH18: 48 | AI18: 0 | AJ18: 0 | AK18: 0 | AL18: 48 | AM18: =IF(AH18+AI18=0,0,SUM(AH18:AI18)/AL18) -> 1 | AN18: =IF(AH18=0,0,AH18/(SUM(AH18:AJ18))) -> 1 | AP18: =_xlfn.XLOOKUP(F18,'TFS Details'!F:F,'TFS Details'!I:I) -> Spartans | AQ18: =_xlfn.XLOOKUP(AP18,'TFS Details'!I:I,'TFS Details'!AE:AE) -> nityanand.giri
A19: =_xlfn.XLOOKUP(F19,'TFS Details'!F:F,'TFS Details'!D:D) -> Value Shaping | B19: =_xlfn.XLOOKUP(F19,'TFS Details'!F:F,'TFS Details'!A:A) -> Value Shaping –Enhancements | C19: =_xlfn.XLOOKUP(F19,'TFS Details'!F:F,'TFS Details'!E:E) -> 4330994 | D19: Nandini | E19: Value Shaping - As a myISP user, I want to enable import benchmark functionality so that I can import updated records back into Configurator Link for SA to update and modify the data efficiently based on changing requirements. | F19: 4368405 | G19: Yasin | H19: Reshmi | K19: No | L19: cannot automate, verifying downloaded excel sheet data with UI | M19: Excel functionality | W19: Completed | X19: Completed | Y19: Completed | Z19: Completed | AA19: 10 | AB19: 8 | AC19: 20 | AD19: 28 | AE19: =AB19/AD19 -> 0.28571429 | AF19: 0.6 | AG19: =_xlfn.XLOOKUP(F19,'TFS Details'!F:F,'TFS Details'!H:H) -> UAT In Test | AH19: 28 | AI19: 0 | AJ19: 0 | AK19: 0 | AL19: =SUM(AH19:AK19) -> 28 | AM19: =IF(AH19+AI19=0,0,SUM(AH19:AI19)/AL19) -> 1 | AN19: =IF(AH19=0,0,AH19/(SUM(AH19:AJ19))) -> 1 | AP19: =_xlfn.XLOOKUP(F19,'TFS Details'!F:F,'TFS Details'!I:I) -> Spartans | AQ19: =_xlfn.XLOOKUP(AP19,'TFS Details'!I:I,'TFS Details'!AE:AE) -> nityanand.giri
A20: =_xlfn.XLOOKUP(F20,'TFS Details'!F:F,'TFS Details'!D:D) -> Value Shaping | B20: =_xlfn.XLOOKUP(F20,'TFS Details'!F:F,'TFS Details'!A:A) -> Value Shaping –Enhancements | C20: =_xlfn.XLOOKUP(F20,'TFS Details'!F:F,'TFS Details'!E:E) -> 4330994 | D20: Nandini | E20: Value Shaping - [Configurator Link ]As a myISP user, I want to link the SOP inputs with client baseline and benchmark values so that user configuring value tree is improved | F20: 4368508 | G20: Yasin | H20: Reshmi | J20: shaik.yasin | K20: Yes | N20: Medium | P20: 1 | Q20: 10 | R20: 4 | W20: Completed | X20: Completed | Y20: Completed | Z20: In Progress | AA20: 10 | AB20: 10 | AC20: 0 | AD20: 10 | AE20: 1 | AF20: 1 | AG20: =_xlfn.XLOOKUP(F20,'TFS Details'!F:F,'TFS Details'!H:H) -> UAT In Test | AH20: 8 | AI20: 2 | AJ20: 0 | AK20: 0 | AL20: =SUM(AH20:AK20) -> 10 | AM20: =IF(AH20+AI20=0,0,SUM(AH20:AI20)/AL20) -> 1 | AN20: =IF(AH20=0,0,AH20/(SUM(AH20:AJ20))) -> 0.8 | AP20: =_xlfn.XLOOKUP(F20,'TFS Details'!F:F,'TFS Details'!I:I) -> Spartans | AQ20: =_xlfn.XLOOKUP(AP20,'TFS Details'!I:I,'TFS Details'!AE:AE) -> nityanand.giri
A21: =_xlfn.XLOOKUP(F21,'TFS Details'!F:F,'TFS Details'!D:D) -> Asset Calculator | B21: =_xlfn.XLOOKUP(F21,'TFS Details'!F:F,'TFS Details'!A:A) -> Asset Calculator - Asset accordions to be added in Asset Catalog | C21: =_xlfn.XLOOKUP(F21,'TFS Details'!F:F,'TFS Details'!E:E) -> 4331001 | D21: Nandini | E21: [Asset Calculator] As a myISP ,I want to implement Other Assets Accordion in Asset Catalog as taggable asset so that Asset Calculator can have this as taggable asset | F21: 4372603 | G21: Soundhar | H21: Yuvani/Sunanda | K21: No | L21: This US needs to be validated for all SG and we will have to cover multiple combinations to achieve 100% automation which is very complex | M21: Too many screen validation involved and complex to automate within insprint timeline | W21: Completed | X21: Completed | Y21: Completed | Z21: Completed | AA21: 80 | AB21: 25 | AC21: 6 | AD21: 31 | AE21: 0.8 | AF21: 0.85 | AG21: =_xlfn.XLOOKUP(F21,'TFS Details'!F:F,'TFS Details'!H:H) -> Test Complete | AH21: 31 | AI21: 0 | AJ21: 0 | AK21: 0 | AL21: =SUM(AH21:AK21) -> 31 | AM21: =IF(AH21+AI21=0,0,SUM(AH21:AI21)/AL21) -> 1 | AN21: =IF(AH21=0,0,AH21/(SUM(AH21:AJ21))) -> 1 | AP21: =_xlfn.XLOOKUP(F21,'TFS Details'!F:F,'TFS Details'!I:I) -> TitansPlus | AQ21: =_xlfn.XLOOKUP(AP21,'TFS Details'!I:I,'TFS Details'!AE:AE) -> nityanand.giri
A22: =_xlfn.XLOOKUP(F22,'TFS Details'!F:F,'TFS Details'!D:D) -> Differentiation | B22: =_xlfn.XLOOKUP(F22,'TFS Details'!F:F,'TFS Details'!A:A) -> Differentiation asset de-tagging- March | C22: =_xlfn.XLOOKUP(F22,'TFS Details'!F:F,'TFS Details'!E:E) -> 4352723 | D22: Nandini | E22: As a myIntegrated Solution Planner User, I want to de-tag the GenWizard Assets and Platforms under differentiation in SI so that acceptance criteria are achieved. | F22: 4352719 | G22: Yuvani | H22: Sunanda/Soundhar | K22: No | L22: Need to compare the data in two excel file | M22: Excel functionality | W22: Completed | X22: Completed | Y22: Completed | Z22: Completed | AA22: 40 | AB22: 10 | AC22: 0 | AD22: 10 | AE22: 1 | AF22: 1 | AG22: =_xlfn.XLOOKUP(F22,'TFS Details'!F:F,'TFS Details'!H:H) -> Test Complete | AH22: 10 | AI22: 0 | AJ22: 0 | AK22: 0 | AL22: 10 | AM22: =IF(AH22+AI22=0,0,SUM(AH22:AI22)/AL22) -> 1 | AN22: =IF(AH22=0,0,AH22/(SUM(AH22:AJ22))) -> 1 | AP22: =_xlfn.XLOOKUP(F22,'TFS Details'!F:F,'TFS Details'!I:I) -> TechCoders | AQ22: =_xlfn.XLOOKUP(AP22,'TFS Details'!I:I,'TFS Details'!AE:AE) -> Francis.Deepak
A23: =_xlfn.XLOOKUP(F23,'TFS Details'!F:F,'TFS Details'!D:D) -> Value Shaping | B23: =_xlfn.XLOOKUP(F23,'TFS Details'!F:F,'TFS Details'!A:A) -> Value Shaping –Enhancements | C23: =_xlfn.XLOOKUP(F23,'TFS Details'!F:F,'TFS Details'!E:E) -> 4330994 | D23: Nandini | E23: Value Shaping - (MFHost)As a myISP User - Configurator V2V - I want to access all myISP screens as per SME role, read-only mode and navigate using the fixed breadcrumb path so that I can maintain workflow continuity | F23: 4381608 | G23: Samreen | H23: Yasin/Reshmi | K23: No | L23: This US includes Navigation to all tiles | M23: Too many screen validation involved and complex to automate within insprint timeline | N23: Complex | W23: Completed | X23: Completed | Y23: Completed | Z23: Completed | AA23: 50 | AB23: 16 | AC23: 0 | AD23: 16 | AE23: 1 | AF23: 0.7 | AG23: PT In Test | AH23: 16 | AI23: 0 | AJ23: 0 | AK23: 0 | AL23: =SUM(AH23:AK23) -> 16 | AM23: =IF(AH23+AI23=0,0,SUM(AH23:AI23)/AL23) -> 1 | AN23: =IF(AH23=0,0,AH23/(SUM(AH23:AJ23))) -> 1 | AP23: =_xlfn.XLOOKUP(F23,'TFS Details'!F:F,'TFS Details'!I:I) -> MYISP_Revamp_UI | AQ23: =_xlfn.XLOOKUP(AP23,'TFS Details'!I:I,'TFS Details'!AE:AE) -> vikrant.r.mohite
A24: =_xlfn.XLOOKUP(F24,'TFS Details'!F:F,'TFS Details'!D:D) -> Automation Calculator | B24: =_xlfn.XLOOKUP(F24,'TFS Details'!F:F,'TFS Details'!A:A) -> ROI & Summary (Tab 8) will be as is in automation calculator with Split of GEN AI, Opera and Agentic and Ux upgrade | C24: =_xlfn.XLOOKUP(F24,'TFS Details'!F:F,'TFS Details'!E:E) -> 4405953 | D24: Nandini | E24: As a myISP user, I want the ROI section in the Summary tab to include all subsections from the ROI screen, So that I can review Agentic, Opera AI, and Gen AI percentage breakdowns across years and contract duration, along with the graphical representation | F24: 4365001 | G24: Sunanda | H24: Yuvani/Soundhar | K24: No | L24: Data validation is highly complex because the required information is integrated directly from the R2 (PA) screen, to Calc ROI screen ,Specific SG‑based criteria, scenario‑dependent, | M24: Too many screen validation involved and complex to automate within insprint timeline | W24: Completed | X24: Completed | Y24: Completed | Z24: Completed | AA24: 22 | AB24: 21 | AC24: 1 | AD24: 22 | AE24: 0.9 | AF24: 0.95 | AG24: =_xlfn.XLOOKUP(F24,'TFS Details'!F:F,'TFS Details'!H:H) -> Test Complete | AH24: 22 | AI24: 0 | AJ24: 0 | AK24: 0 | AL24: =SUM(AH24:AK24) -> 22 | AM24: =IF(AH24+AI24=0,0,SUM(AH24:AI24)/AL24) -> 1 | AN24: =IF(AH24=0,0,AH24/(SUM(AH24:AJ24))) -> 1 | AP24: =_xlfn.XLOOKUP(F24,'TFS Details'!F:F,'TFS Details'!I:I) -> Codeplayers | AQ24: =_xlfn.XLOOKUP(AP24,'TFS Details'!I:I,'TFS Details'!AE:AE) -> nityanand.giri
A25: =_xlfn.XLOOKUP(F25,'TFS Details'!F:F,'TFS Details'!D:D) -> Role Rename | B25: =_xlfn.XLOOKUP(F25,'TFS Details'!F:F,'TFS Details'!A:A) -> March Release NextGen Enhancements | C25: =_xlfn.XLOOKUP(F25,'TFS Details'!F:F,'TFS Details'!E:E) -> 4365826 | D25: Nandini | E25: Impact Check: As a Myisp user, I want the role "Enterprise SA" to be renamed to "Market Maker ESA" in myISP So that the role name clearly reflects the Market Make ESA in Value Shaping module. | F25: 4391344 | G25: Reshmi | H25: Yasin | K25: No | L25: Roles are getting deactivated which cant be automatable | M25: Full regression required | W25: Completed | X25: Completed | Y25: Completed | Z25: Completed | AA25: 65 | AB25: 5 | AC25: 0 | AD25: 5 | AE25: 1 | AF25: 0.8 | AG25: =_xlfn.XLOOKUP(F25,'TFS Details'!F:F,'TFS Details'!H:H) -> Test Complete | AH25: 5 | AI25: 0 | AJ25: 0 | AK25: 0 | AL25: =SUM(AH25:AK25) -> 5 | AM25: =IF(AH25+AI25=0,0,SUM(AH25:AI25)/AL25) -> 1 | AN25: =IF(AH25=0,0,AH25/(SUM(AH25:AJ25))) -> 1 | AP25: =_xlfn.XLOOKUP(F25,'TFS Details'!F:F,'TFS Details'!I:I) -> Spartans | AQ25: =_xlfn.XLOOKUP(AP25,'TFS Details'!I:I,'TFS Details'!AE:AE) -> nityanand.giri
A26: =_xlfn.XLOOKUP(F26,'TFS Details'!F:F,'TFS Details'!D:D) -> Advisory SA - Song | B26: =_xlfn.XLOOKUP(F26,'TFS Details'!F:F,'TFS Details'!A:A) -> PLD - Advisory SA Role | C26: =_xlfn.XLOOKUP(F26,'TFS Details'!F:F,'TFS Details'!E:E) -> 4386527 | D26: Nandini | E26: As an Advisory song SA, I want to access the Value Shaping tile in read-only mode so that I can maintain and view workflow continuity. | F26: 4373065 | G26: Srilekha | H26: Yasin | J26: guddeti.srilekha | K26: Yes | N26: Complex | P26: 1 | Q26: 25 | R26: 6 | S26: 0 | T26: 6 | U26: 1 | V26: 0.7 | W26: Completed | X26: Completed | Y26: Completed | Z26: Completed | AA26: 55 | AB26: 19 | AC26: 0 | AD26: 19 | AE26: 1 | AF26: 0.6 | AG26: =_xlfn.XLOOKUP(F26,'TFS Details'!F:F,'TFS Details'!H:H) -> UAT In Test | AH26: 19 | AI26: 0 | AJ26: 0 | AK26: 0 | AL26: =SUM(AH26:AK26) -> 19 | AM26: =IF(AH26+AI26=0,0,SUM(AH26:AI26)/AL26) -> 1 | AN26: =IF(AH26=0,0,AH26/(SUM(AH26:AJ26))) -> 1 | AP26: =_xlfn.XLOOKUP(F26,'TFS Details'!F:F,'TFS Details'!I:I) -> Spartans | AQ26: =_xlfn.XLOOKUP(AP26,'TFS Details'!I:I,'TFS Details'!AE:AE) -> nityanand.giri
A27: =_xlfn.XLOOKUP(F27,'TFS Details'!F:F,'TFS Details'!D:D) -> Drop 2 - Angular upgrade v19 to v21 | B27: =_xlfn.XLOOKUP(F27,'TFS Details'!F:F,'TFS Details'!A:A) -> Angular upgrade version 19 to version 21 - 28th March | C27: =_xlfn.XLOOKUP(F27,'TFS Details'!F:F,'TFS Details'!E:E) -> 4358702 | D27: Pirtheebaa | E27: As a myISP Solution Architect, I want to see the What Are We Solving For - MFE App migrated to Angular 21 | F27: 4358750 | G27: Vinayak | H27: Sadhik | K27: No | L27: Angular Upgrade can be covered in regression testing. | M27: Full regression required | W27: Completed | X27: Completed | Y27: Completed | Z27: Completed | AA27: 6 | AB27: 6 | AC27: 0 | AD27: 6 | AE27: 1 | AF27: 1 | AG27: =_xlfn.XLOOKUP(F27,'TFS Details'!F:F,'TFS Details'!H:H) -> Test Complete | AH27: 6 | AI27: 0 | AJ27: 0 | AK27: 0 | AL27: =SUM(AH27:AK27) -> 6 | AM27: =IF(AH27+AI27=0,0,SUM(AH27:AI27)/AL27) -> 1 | AN27: =IF(AH27=0,0,AH27/(SUM(AH27:AJ27))) -> 1 | AP27: =_xlfn.XLOOKUP(F27,'TFS Details'!F:F,'TFS Details'!I:I) -> MYISP_Revamp_UI | AQ27: =_xlfn.XLOOKUP(AP27,'TFS Details'!I:I,'TFS Details'!AE:AE) -> vikrant.r.mohite
A28: =_xlfn.XLOOKUP(F28,'TFS Details'!F:F,'TFS Details'!D:D) -> Drop 2 - Angular upgrade v19 to v21 | B28: =_xlfn.XLOOKUP(F28,'TFS Details'!F:F,'TFS Details'!A:A) -> Angular upgrade version 19 to version 21 - 28th March | C28: =_xlfn.XLOOKUP(F28,'TFS Details'!F:F,'TFS Details'!E:E) -> 4358702 | D28: Pirtheebaa | E28: As a myISP Solution Architect, I want to see the Revamp Assessment App migrated to Angular 21 | F28: 4358752 | G28: Mary | H28: Sadhik | K28: No | L28: Angular Migration | M28: Full regression required | W28: Completed | X28: Completed | Y28: Completed | Z28: Completed | AA28: 50 | AB28: 10 | AC28: 2 | AD28: 12 | AE28: 0.9 | AF28: 0.9 | AG28: =_xlfn.XLOOKUP(F28,'TFS Details'!F:F,'TFS Details'!H:H) -> Test Complete | AH28: 12 | AI28: 0 | AJ28: 0 | AK28: 0 | AL28: =SUM(AH28:AK28) -> 12 | AM28: =IF(AH28+AI28=0,0,SUM(AH28:AI28)/AL28) -> 1 | AN28: =IF(AH28=0,0,AH28/(SUM(AH28:AJ28))) -> 1 | AP28: =_xlfn.XLOOKUP(F28,'TFS Details'!F:F,'TFS Details'!I:I) -> MYISP_Revamp_UI | AQ28: =_xlfn.XLOOKUP(AP28,'TFS Details'!I:I,'TFS Details'!AE:AE) -> vikrant.r.mohite
A29: =_xlfn.XLOOKUP(F29,'TFS Details'!F:F,'TFS Details'!D:D) -> Opportunities | B29: =_xlfn.XLOOKUP(F29,'TFS Details'!F:F,'TFS Details'!A:A) -> Opportunities sorting | C29: =_xlfn.XLOOKUP(F29,'TFS Details'!F:F,'TFS Details'!E:E) -> 4364046 | D29: Pirtheebaa | E29: As a mysp user, I want to view the newly assigned MMS IDs at the top on the opportunities Table so that acceptance criteria are achieved. | F29: 4342359 | G29: Shalini | H29: Bhavana | K29: No | L29: Session Timeout Check | M29: Full regression required | W29: Completed | X29: Completed | Y29: Not Started | Z29: Completed | AA29: 30 | AB29: 8 | AC29: 2 | AD29: 8 | AE29: 0.7 | AF29: 0.7 | AG29: =_xlfn.XLOOKUP(F29,'TFS Details'!F:F,'TFS Details'!H:H) -> Test Complete | AH29: 8 | AI29: 0 | AJ29: 0 | AK29: 0 | AL29: =SUM(AH29:AK29) -> 8 | AM29: =IF(AH29+AI29=0,0,SUM(AH29:AI29)/AL29) -> 1 | AN29: =IF(AH29=0,0,AH29/(SUM(AH29:AJ29))) -> 1 | AP29: =_xlfn.XLOOKUP(F29,'TFS Details'!F:F,'TFS Details'!I:I) -> NGTransformers | AQ29: =_xlfn.XLOOKUP(AP29,'TFS Details'!I:I,'TFS Details'!AE:AE) -> sowjanya.kari
A30: Opportunity Workflow | B30: =_xlfn.XLOOKUP(F30,'TFS Details'!F:F,'TFS Details'!A:A) -> Song Updates in Reporting & Compliance | C30: =_xlfn.XLOOKUP(F30,'TFS Details'!F:F,'TFS Details'!E:E) -> 4226586 | D30: Pirtheebaa | E30: As a myISP User, I should be able to see the timestamp for the "Updated On" field in the View History of the Status Update screen so that I can accurately track when changes were made | F30: 4187518 | G30: Namrata | H30: Manisha | J30: namrata.g.umardand | K30: yes | N30: Complex | O30: 2 | P30: 1 | Q30: 10 | R30: 6 | S30: 0 | T30: 6 | U30: 0.7 | V30: 0.7 | W30: Completed | X30: Completed | Y30: In Progress | Z30: Completed | AG30: =_xlfn.XLOOKUP(F30,'TFS Details'!F:F,'TFS Details'!H:H) -> Test Complete | AH30: 24 | AI30: 0 | AJ30: 0 | AK30: 0 | AL30: =SUM(AH30:AK30) -> 24 | AM30: =IF(AH30+AI30=0,0,SUM(AH30:AI30)/AL30) -> 1 | AN30: =IF(AH30=0,0,AH30/(SUM(AH30:AJ30))) -> 1 | AP30: =_xlfn.XLOOKUP(F30,'TFS Details'!F:F,'TFS Details'!I:I) -> NGTransformers | AQ30: =_xlfn.XLOOKUP(AP30,'TFS Details'!I:I,'TFS Details'!AE:AE) -> sowjanya.kari
A31: =_xlfn.XLOOKUP(F31,'TFS Details'!F:F,'TFS Details'!D:D) -> Learn | B31: =_xlfn.XLOOKUP(F31,'TFS Details'!F:F,'TFS Details'!A:A) -> Services - Learn & Launch enhancements | C31: =_xlfn.XLOOKUP(F31,'TFS Details'!F:F,'TFS Details'!E:E) -> 4369027 | D31: Pirtheebaa | E31: As a myISP user, I want the ability to search content using hashtags and information from inside pages, so that I can quickly locate relevant learning materials and resources without having to navigate through multiple pages. | F31: 4258549 | G31: Shalini | H31: Saranya | J31: ShaliniB.Pandey | K31: Yes | N31: Medium | O31: 1 | P31: 1 | Q31: 14 | R31: 5 | S31: 0 | T31: 1 | U31: 0.7 | V31: 0.4 | W31: Completed | X31: Completed | Y31: Not Started | Z31: Completed | AA31: 28 | AB31: 2 | AC31: 5 | AD31: 7 | AE31: 0.4 | AF31: 0.4 | AG31: =_xlfn.XLOOKUP(F31,'TFS Details'!F:F,'TFS Details'!H:H) -> Test Complete | AH31: 7 | AI31: 0 | AJ31: 0 | AK31: 0 | AL31: =SUM(AH31:AK31) -> 7 | AM31: =IF(AH31+AI31=0,0,SUM(AH31:AI31)/AL31) -> 1 | AN31: =IF(AH31=0,0,AH31/(SUM(AH31:AJ31))) -> 1 | AP31: =_xlfn.XLOOKUP(F31,'TFS Details'!F:F,'TFS Details'!I:I) -> NGTransformers | AQ31: =_xlfn.XLOOKUP(AP31,'TFS Details'!I:I,'TFS Details'!AE:AE) -> sowjanya.kari
A32: =_xlfn.XLOOKUP(F32,'TFS Details'!F:F,'TFS Details'!D:D) -> SA Team manager | B32: =_xlfn.XLOOKUP(F32,'TFS Details'!F:F,'TFS Details'!A:A) -> SA Team manager User Registration Fields update and Mail POC changes | C32: =_xlfn.XLOOKUP(F32,'TFS Details'!F:F,'TFS Details'!E:E) -> 4282653 | D32: Pirtheebaa | E32: As a my Solution planner Solution Architect, I want the Alignment field to be enabled for Operations deployment in Register now pop up with an updated dropdown list , so that user can select specific alignment | F32: 4285630 | G32: Vinayak | H32: Bhavana | K32: No | L32: Email Functionality , register now popup | M32: Email functionality | W32: Completed | X32: Completed | Y32: Completed | Z32: Completed | AA32: 6 | AB32: 6 | AC32: 1 | AD32: 7 | AE32: 0.85 | AF32: 0.85 | AG32: =_xlfn.XLOOKUP(F32,'TFS Details'!F:F,'TFS Details'!H:H) -> Test Complete | AH32: 7 | AI32: 0 | AJ32: 0 | AK32: 0 | AL32: =SUM(AH32:AK32) -> 7 | AM32: =IF(AH32+AI32=0,0,SUM(AH32:AI32)/AL32) -> 1 | AN32: =IF(AH32=0,0,AH32/(SUM(AH32:AJ32))) -> 1 | AP32: =_xlfn.XLOOKUP(F32,'TFS Details'!F:F,'TFS Details'!I:I) -> GoRetro | AQ32: =_xlfn.XLOOKUP(AP32,'TFS Details'!I:I,'TFS Details'!AE:AE) -> sowjanya.kari
A33: =_xlfn.XLOOKUP(F33,'TFS Details'!F:F,'TFS Details'!D:D) -> SA Team manager | B33: =_xlfn.XLOOKUP(F33,'TFS Details'!F:F,'TFS Details'!A:A) -> SA Team manager User Registration Fields update and Mail POC changes | C33: =_xlfn.XLOOKUP(F33,'TFS Details'!F:F,'TFS Details'!E:E) -> 4282653 | D33: Pirtheebaa | E33: As a my Solution planner Solution Architect, I want the Alignment field to be enabled for Operations Deployment with an updated dropdown list in pending user requests tab, so that user can select specific alignment | F33: 4285636 | G33: Mary | H33: n.selvakumar | J33: Mary.jacob | K33: No | L33: One time update | M33: One time update related | N33: Medium | W33: Completed | X33: Completed | Y33: Completed | Z33: Completed | AA33: 30 | AB33: 6 | AC33: 2 | AD33: 8 | AE33: 0.9 | AF33: 0.9 | AG33: =_xlfn.XLOOKUP(F33,'TFS Details'!F:F,'TFS Details'!H:H) -> Test Complete | AH33: 8 | AI33: 0 | AJ33: 0 | AK33: 0 | AL33: =SUM(AH33:AK33) -> 8 | AM33: =IF(AH33+AI33=0,0,SUM(AH33:AI33)/AL33) -> 1 | AN33: =IF(AH33=0,0,AH33/(SUM(AH33:AJ33))) -> 1 | AP33: =_xlfn.XLOOKUP(F33,'TFS Details'!F:F,'TFS Details'!I:I) -> GoRetro | AQ33: =_xlfn.XLOOKUP(AP33,'TFS Details'!I:I,'TFS Details'!AE:AE) -> sowjanya.kari
A34: =_xlfn.XLOOKUP(F34,'TFS Details'!F:F,'TFS Details'!D:D) -> SA Team manager | B34: =_xlfn.XLOOKUP(F34,'TFS Details'!F:F,'TFS Details'!A:A) -> SA Team manager User Registration Fields update and Mail POC changes | C34: =_xlfn.XLOOKUP(F34,'TFS Details'!F:F,'TFS Details'!E:E) -> 4282653 | D34: Pirtheebaa | E34: As a my Solution planner Solution Architect, I want the POCs to be changed based on Deployment and Market in pending user requests tab, So that Approver/Rejection mail is sent to correct POCs | F34: 4275672 | G34: Namrata | H34: Manisha | K34: No | L34: One time update | M34: One time update related | W34: Completed | X34: Completed | Y34: In Progress | Z34: Completed | AA34: 24 | AB34: 10 | AC34: 11 | AD34: 12 | AE34: 1 | AF34: 1 | AG34: =_xlfn.XLOOKUP(F34,'TFS Details'!F:F,'TFS Details'!H:H) -> Test Complete | AH34: 24 | AI34: 0 | AJ34: 0 | AK34: 0 | AL34: =SUM(AH34:AK34) -> 24 | AM34: =IF(AH34+AI34=0,0,SUM(AH34:AI34)/AL34) -> 1 | AN34: =IF(AH34=0,0,AH34/(SUM(AH34:AJ34))) -> 1 | AP34: =_xlfn.XLOOKUP(F34,'TFS Details'!F:F,'TFS Details'!I:I) -> GoRetro | AQ34: =_xlfn.XLOOKUP(AP34,'TFS Details'!I:I,'TFS Details'!AE:AE) -> sowjanya.kari
A35: =_xlfn.XLOOKUP(F35,'TFS Details'!F:F,'TFS Details'!D:D) -> SA Team manager | B35: =_xlfn.XLOOKUP(F35,'TFS Details'!F:F,'TFS Details'!A:A) -> SA Team manager User Registration Fields update and Mail POC changes | C35: =_xlfn.XLOOKUP(F35,'TFS Details'!F:F,'TFS Details'!E:E) -> 4282653 | D35: Pirtheebaa | E35: As a my Solution planner Solution Architect, I want the POCs to be changed based on Deployment and Market in Register now pop up, So that Approver/Rejection mail is sent to correct POCs | F35: 4269089 | G35: Shalini | H35: Bhavana | K35: No | L35: Email Functionality , register now popup | M35: Email functionality | W35: Completed | X35: Completed | Y35: Not Started | Z35: Completed | AA35: 30 | AB35: 25 | AC35: 9 | AD35: 20 | AE35: 0.8 | AF35: 0.8 | AG35: =_xlfn.XLOOKUP(F35,'TFS Details'!F:F,'TFS Details'!H:H) -> Test Complete | AH35: 20 | AI35: 0 | AJ35: 0 | AK35: 0 | AL35: =SUM(AH35:AK35) -> 20 | AM35: =IF(AH35+AI35=0,0,SUM(AH35:AI35)/AL35) -> 1 | AN35: =IF(AH35=0,0,AH35/(SUM(AH35:AJ35))) -> 1 | AP35: =_xlfn.XLOOKUP(F35,'TFS Details'!F:F,'TFS Details'!I:I) -> GoRetro | AQ35: =_xlfn.XLOOKUP(AP35,'TFS Details'!I:I,'TFS Details'!AE:AE) -> sowjanya.kari
A36: =_xlfn.XLOOKUP(F36,'TFS Details'!F:F,'TFS Details'!D:D) -> SA Team manager | B36: =_xlfn.XLOOKUP(F36,'TFS Details'!F:F,'TFS Details'!A:A) -> SA Team manager User Registration Fields update and Mail POC changes | C36: =_xlfn.XLOOKUP(F36,'TFS Details'!F:F,'TFS Details'!E:E) -> 4282653 | D36: Pirtheebaa | E36: As a my Solution planner Solution Architect, I want the Registration pop-up to include the mentioned changes for Adding and updating fields ,so that users are able to see the required changes | F36: 4269111 | G36: Vinayak | H36: Bhavana | K36: No | L36: Email Functionality , register now popup | M36: Email functionality | W36: Completed | X36: Completed | Y36: Completed | Z36: Completed | AA36: 6 | AB36: 5 | AC36: 16 | AD36: 21 | AE36: 0.66 | AF36: 0.7 | AG36: =_xlfn.XLOOKUP(F36,'TFS Details'!F:F,'TFS Details'!H:H) -> Test Complete | AH36: 21 | AI36: 0 | AJ36: 0 | AK36: 0 | AL36: 21 | AM36: =IF(AH36+AI36=0,0,SUM(AH36:AI36)/AL36) -> 1 | AN36: =IF(AH36=0,0,AH36/(SUM(AH36:AJ36))) -> 1 | AP36: =_xlfn.XLOOKUP(F36,'TFS Details'!F:F,'TFS Details'!I:I) -> GoRetro | AQ36: =_xlfn.XLOOKUP(AP36,'TFS Details'!I:I,'TFS Details'!AE:AE) -> sowjanya.kari
A37: =_xlfn.XLOOKUP(F37,'TFS Details'!F:F,'TFS Details'!D:D) -> Common | B37: =_xlfn.XLOOKUP(F37,'TFS Details'!F:F,'TFS Details'!A:A) -> Comma formatting in all raise request emails | C37: =_xlfn.XLOOKUP(F37,'TFS Details'!F:F,'TFS Details'!E:E) -> 4387609 | D37: Pirtheebaa | E37: As a myISP User, I should be able to see the SG Revenue($M) value displayed in dollar millions with proper comma formatting in all raise request emails so that the recipients can quickly understand and interpret the revenue | F37: 4373609 | G37: Mary | H37: n.selvakumar | K37: No | L37: Email Functionality | M37: Email functionality | W37: Completed | X37: Completed | Y37: Completed | Z37: Completed | AA37: 36 | AB37: 7 | AC37: 0 | AD37: 7 | AE37: 1 | AF37: 1 | AG37: =_xlfn.XLOOKUP(F37,'TFS Details'!F:F,'TFS Details'!H:H) -> UAT In Test | AH37: 7 | AI37: 0 | AJ37: 0 | AK37: 0 | AL37: =SUM(AH37:AK37) -> 7 | AM37: =IF(AH37+AI37=0,0,SUM(AH37:AI37)/AL37) -> 1 | AN37: =IF(AH37=0,0,AH37/(SUM(AH37:AJ37))) -> 1 | AO37: Delivered for UAT | AP37: =_xlfn.XLOOKUP(F37,'TFS Details'!F:F,'TFS Details'!I:I) -> TechPhantoms | AQ37: =_xlfn.XLOOKUP(AP37,'TFS Details'!I:I,'TFS Details'!AE:AE) -> sowjanya.kari
A38: =_xlfn.XLOOKUP(F38,'TFS Details'!F:F,'TFS Details'!D:D) -> Learn | B38: =_xlfn.XLOOKUP(F38,'TFS Details'!F:F,'TFS Details'!A:A) -> Services - Learn & Launch enhancements | C38: =_xlfn.XLOOKUP(F38,'TFS Details'!F:F,'TFS Details'!E:E) -> 4369575 | D38: Pirtheebaa | E38: As a myISP user, I want to see new steps added under the Solution Components & Define team tabs when the Gen-AI toggle is enabled. | F38: 4372140 | G38: Shalini | H38: Saranya | J38: ShaliniB.Pandey | K38: Yes | N38: Medium | O38: 1 | P38: 1 | Q38: 14 | R38: 5 | S38: 0 | T38: 1 | U38: 0.7 | V38: 0.4 | W38: Completed | X38: Completed | Y38: Not Started | Z38: Completed | AA38: 30 | AB38: 20 | AC38: 4 | AD38: 23 | AE38: 0.9 | AF38: 0.9 | AG38: =_xlfn.XLOOKUP(F38,'TFS Details'!F:F,'TFS Details'!H:H) -> PT In Test | AH38: 23 | AI38: 0 | AJ38: 0 | AK38: 0 | AL38: =SUM(AH38:AK38) -> 23 | AM38: =IF(AH38+AI38=0,0,SUM(AH38:AI38)/AL38) -> 1 | AN38: =IF(AH38=0,0,AH38/(SUM(AH38:AJ38))) -> 1 | AP38: =_xlfn.XLOOKUP(F38,'TFS Details'!F:F,'TFS Details'!I:I) -> NGTransformers | AQ38: =_xlfn.XLOOKUP(AP38,'TFS Details'!I:I,'TFS Details'!AE:AE) -> sowjanya.kari
A39: View MMS Details | B39: =_xlfn.XLOOKUP(F39,'TFS Details'!F:F,'TFS Details'!A:A) -> Diel hierarchy - rolled up revenue | C39: =_xlfn.XLOOKUP(F39,'TFS Details'!F:F,'TFS Details'!E:E) -> 4378908 | D39: Pirtheebaa | E39: As a MyISP user reviewing MMS Details, I want to see a Rolled‑Up Revenue view by Service Group (AMS, IMS, etc.) under the Deal Hierarchy section, so that I can easily understand the combined revenue of parent and child for each service group | F39: 4378894 | G39: Vinayak | H39: Janardhan | J39: Vinayak.sangale | K39: Yes | N39: Complex | O39: 1 | P39: 1 | Q39: 7 | R39: 6 | S39: 0 | T39: 7 | U39: 0.85 | V39: 0.85 | W39: Completed | X39: Completed | Y39: Completed | Z39: Completed | AA39: 6 | AB39: 6 | AC39: 1 | AD39: 7 | AE39: 0.85 | AF39: 1 | AG39: =_xlfn.XLOOKUP(F39,'TFS Details'!F:F,'TFS Details'!H:H) -> Test Complete | AH39: 7 | AI39: 0 | AJ39: 0 | AK39: 0 | AL39: =SUM(AH39:AK39) -> 7 | AM39: =IF(AH39+AI39=0,0,SUM(AH39:AI39)/AL39) -> 1 | AN39: =IF(AH39=0,0,AH39/(SUM(AH39:AJ39))) -> 1 | AP39: =_xlfn.XLOOKUP(F39,'TFS Details'!F:F,'TFS Details'!I:I) -> GoRetro | AQ39: =_xlfn.XLOOKUP(AP39,'TFS Details'!I:I,'TFS Details'!AE:AE) -> sowjanya.kari
A40: =_xlfn.XLOOKUP(F40,'TFS Details'!F:F,'TFS Details'!D:D) -> myCalendar | B40: =_xlfn.XLOOKUP(F40,'TFS Details'!F:F,'TFS Details'!A:A) -> March Release NextGen Enhancements | C40: =_xlfn.XLOOKUP(F40,'TFS Details'!F:F,'TFS Details'!E:E) -> 4365826 | D40: Pirtheebaa | E40: As a MySP user, I want the "Add Event" button to be positioned in the top-right corner of the My Calendar screen popup So that I can quickly and intuitively create a new event without scrolling or searching for the action | F40: 4366103 | G40: Mary | H40: Bhavana | K40: No | L40: UI Design Change, can not be validated | M40: UI alignment and Font related | W40: Completed | X40: Completed | Y40: Completed | Z40: Completed | AA40: 30 | AB40: 9 | AC40: 1 | AD40: 10 | AE40: 0.95 | AF40: 0.95 | AG40: =_xlfn.XLOOKUP(F40,'TFS Details'!F:F,'TFS Details'!H:H) -> Test Complete | AH40: 10 | AI40: 0 | AJ40: 0 | AK40: 0 | AL40: =SUM(AH40:AK40) -> 10 | AM40: =IF(AH40+AI40=0,0,SUM(AH40:AI40)/AL40) -> 1 | AN40: =IF(AH40=0,0,AH40/(SUM(AH40:AJ40))) -> 1 | AP40: =_xlfn.XLOOKUP(F40,'TFS Details'!F:F,'TFS Details'!I:I) -> TechPhantoms | AQ40: =_xlfn.XLOOKUP(AP40,'TFS Details'!I:I,'TFS Details'!AE:AE) -> sowjanya.kari
A41: =_xlfn.XLOOKUP(F41,'TFS Details'!F:F,'TFS Details'!D:D) -> ESA to Market Maker ESA | B41: =_xlfn.XLOOKUP(F41,'TFS Details'!F:F,'TFS Details'!A:A) -> March Release NextGen Enhancements | C41: =_xlfn.XLOOKUP(F41,'TFS Details'!F:F,'TFS Details'!E:E) -> 4365826 | D41: Pirtheebaa | E41: As a Myisp user, I want the role "Enterprise SA" to be renamed to "Market Maker ESA" in myISP So that the role name clearly reflects the Market Make ESA in across myISP. | F41: 4366122 | G41: Namrata | H41: Manisha | K41: No | L41: Related to MMS External app | M41: External Team Integration | W41: Completed | X41: Completed | Y41: In Progress | Z41: Completed | AA41: 25 | AB41: 16 | AC41: 10 | AD41: 10 | AE41: 1 | AF41: 0.8 | AG41: =_xlfn.XLOOKUP(F41,'TFS Details'!F:F,'TFS Details'!H:H) -> Test Complete | AH41: 24 | AI41: 0 | AJ41: 0 | AK41: 0 | AL41: =SUM(AH41:AK41) -> 24 | AM41: =IF(AH41+AI41=0,0,SUM(AH41:AI41)/AL41) -> 1 | AN41: =IF(AH41=0,0,AH41/(SUM(AH41:AJ41))) -> 1 | AP41: =_xlfn.XLOOKUP(F41,'TFS Details'!F:F,'TFS Details'!I:I) -> TechPhantoms | AQ41: =_xlfn.XLOOKUP(AP41,'TFS Details'!I:I,'TFS Details'!AE:AE) -> sowjanya.kari
A42: Opportunity Workflow | B42: =_xlfn.XLOOKUP(F42,'TFS Details'!F:F,'TFS Details'!A:A) -> Advisory SA Role Sync in DFD, PLD, Define Team | C42: =_xlfn.XLOOKUP(F42,'TFS Details'!F:F,'TFS Details'!E:E) -> 4366466 | D42: Pirtheebaa | E42: As a myISP user, I should be able to enable one text area for "Advisory SA - Song" role to add the comment in the "Status Update" screen from "Log Status" Ui for Song Service Status | F42: 4366141 | G42: Vinayak | H42: Janardhan | J42: Vinayak.sangale | K42: Yes | N42: Medium | O42: 1 | P42: 1 | Q42: 6 | R42: 5 | S42: 0 | T42: 6 | U42: 0.85 | V42: 0.85 | W42: Completed | X42: Completed | Y42: Completed | Z42: Completed | AA42: 6 | AB42: 6 | AC42: 0 | AD42: 6 | AE42: 1 | AF42: 1 | AG42: =_xlfn.XLOOKUP(F42,'TFS Details'!F:F,'TFS Details'!H:H) -> UAT In Test | AH42: 6 | AI42: 0 | AJ42: 0 | AK42: 0 | AL42: =SUM(AH42:AK42) -> 6 | AM42: =IF(AH42+AI42=0,0,SUM(AH42:AI42)/AL42) -> 1 | AN42: =IF(AH42=0,0,AH42/(SUM(AH42:AJ42))) -> 1 | AO42: Delivered To UAT | AP42: =_xlfn.XLOOKUP(F42,'TFS Details'!F:F,'TFS Details'!I:I) -> NGTransformers | AQ42: =_xlfn.XLOOKUP(AP42,'TFS Details'!I:I,'TFS Details'!AE:AE) -> sowjanya.kari
A43: Manage SA | B43: =_xlfn.XLOOKUP(F43,'TFS Details'!F:F,'TFS Details'!A:A) -> March Release NextGen Enhancements | C43: =_xlfn.XLOOKUP(F43,'TFS Details'!F:F,'TFS Details'!E:E) -> 4365826 | D43: Pirtheebaa | E43: As a myIntegrated Solution Planner User, I want to rename "Solution To Win Approach " value to "Solution To Win Score" inside Utilities tile under manage so that acceptance criteria are achieved. | F43: 4370557 | G43: Mary | H43: n.selvakumar | J43: Mary.jacob | K43: Yes | N43: Simple | O43: 9 | P43: 1 | Q43: 12 | R43: 6 | S43: 1 | T43: 7 | U43: 0.75 | V43: 0.75 | W43: Completed | X43: Completed | Y43: Completed | Z43: Completed | AA43: 20 | AB43: 6 | AC43: 1 | AD43: 7 | AE43: 0.95 | AF43: 0.95 | AG43: =_xlfn.XLOOKUP(F43,'TFS Details'!F:F,'TFS Details'!H:H) -> Test Complete | AH43: 7 | AI43: 0 | AJ43: 0 | AK43: 0 | AL43: =SUM(AH43:AK43) -> 7 | AM43: =IF(AH43+AI43=0,0,SUM(AH43:AI43)/AL43) -> 1 | AN43: =IF(AH43=0,0,AH43/(SUM(AH43:AJ43))) -> 1 | AP43: =_xlfn.XLOOKUP(F43,'TFS Details'!F:F,'TFS Details'!I:I) -> NGTransformers | AQ43: =_xlfn.XLOOKUP(AP43,'TFS Details'!I:I,'TFS Details'!AE:AE) -> sowjanya.kari
A44: =_xlfn.XLOOKUP(F44,'TFS Details'!F:F,'TFS Details'!D:D) -> SA Team manager | B44: =_xlfn.XLOOKUP(F44,'TFS Details'!F:F,'TFS Details'!A:A) -> SA Team manager User Registration Fields update and Mail POC changes | C44: =_xlfn.XLOOKUP(F44,'TFS Details'!F:F,'TFS Details'!E:E) -> 4282653 | D44: Pirtheebaa | E44: As a my Solution planner Solution Architect, I want the SA team manager screen to include the mentioned changes for Adding and updating fields ,so that users are able to see the required changes | F44: 4371534 | G44: Namrata | H44: Manisha | K44: No | L44: One time update included | M44: One time update related | W44: Completed | X44: Completed | Y44: In Progress | Z44: Completed | AA44: 24 | AB44: 9 | AC44: 9 | AD44: 9 | AE44: 1 | AF44: 1 | AG44: =_xlfn.XLOOKUP(F44,'TFS Details'!F:F,'TFS Details'!H:H) -> Test Complete | AH44: 24 | AI44: 0 | AJ44: 0 | AK44: 0 | AL44: =SUM(AH44:AK44) -> 24 | AM44: =IF(AH44+AI44=0,0,SUM(AH44:AI44)/AL44) -> 1 | AN44: =IF(AH44=0,0,AH44/(SUM(AH44:AJ44))) -> 1 | AP44: =_xlfn.XLOOKUP(F44,'TFS Details'!F:F,'TFS Details'!I:I) -> GoRetro | AQ44: =_xlfn.XLOOKUP(AP44,'TFS Details'!I:I,'TFS Details'!AE:AE) -> sowjanya.kari
A45: Define Team | B45: =_xlfn.XLOOKUP(F45,'TFS Details'!F:F,'TFS Details'!A:A) -> Advisory SA Role Sync in DFD, PLD, Define Team | C45: =_xlfn.XLOOKUP(F45,'TFS Details'!F:F,'TFS Details'!E:E) -> 4366466 | D45: Pirtheebaa | E45: As a Myisp user, I want the role Sync "Advisory SA - Song" role in define team screen under SA category So that the assigned role name populate in define team as read only. | F45: 4369531 | G45: Shalini | H45: Bhavana | K45: No | L45: Partially can we automated interlinked with PLD Screen | M45: Too many screen validation involved and complex to automate within insprint timeline | W45: Completed | X45: Completed | Y45: Not Started | Z45: Completed | AA45: 50 | AB45: 30 | AC45: 2 | AD45: 15 | AE45: 0.7 | AF45: 0.7 | AG45: =_xlfn.XLOOKUP(F45,'TFS Details'!F:F,'TFS Details'!H:H) -> UAT In Test | AH45: 15 | AI45: 0 | AJ45: 0 | AK45: 0 | AL45: =SUM(AH45:AK45) -> 15 | AM45: =IF(AH45+AI45=0,0,SUM(AH45:AI45)/AL45) -> 1 | AN45: =IF(AH45=0,0,AH45/(SUM(AH45:AJ45))) -> 1 | AP45: =_xlfn.XLOOKUP(F45,'TFS Details'!F:F,'TFS Details'!I:I) -> TechPhantoms | AQ45: =_xlfn.XLOOKUP(AP45,'TFS Details'!I:I,'TFS Details'!AE:AE) -> sowjanya.kari
A46: =_xlfn.XLOOKUP(F46,'TFS Details'!F:F,'TFS Details'!D:D) -> Learn | B46: =_xlfn.XLOOKUP(F46,'TFS Details'!F:F,'TFS Details'!A:A) -> Services - Learn & Launch enhancements | C46: =_xlfn.XLOOKUP(F46,'TFS Details'!F:F,'TFS Details'!E:E) -> 4369575 | D46: Pirtheebaa | E46: As a myISP user, I want to see �BPMS� as a support option alongside AMS, SI, and IMS in both the �Email� and �Raise a Ticket� support sections So that I can easily raise BPMS-related support requests. | F46: 4369533 | G46: Vinayak | H46: Bhavana | K46: No | L46: Email functionality | M46: Email functionality | W46: Completed | X46: Completed | Y46: Completed | Z46: Completed | AA46: 6 | AB46: 6 | AC46: 0 | AD46: 6 | AE46: 1 | AF46: 1 | AG46: =_xlfn.XLOOKUP(F46,'TFS Details'!F:F,'TFS Details'!H:H) -> Test Complete | AH46: 6 | AI46: 0 | AJ46: 0 | AK46: 0 | AL46: =SUM(AH46:AK46) -> 6 | AM46: =IF(AH46+AI46=0,0,SUM(AH46:AI46)/AL46) -> 1 | AN46: =IF(AH46=0,0,AH46/(SUM(AH46:AJ46))) -> 1 | AP46: =_xlfn.XLOOKUP(F46,'TFS Details'!F:F,'TFS Details'!I:I) -> NGTransformers | AQ46: =_xlfn.XLOOKUP(AP46,'TFS Details'!I:I,'TFS Details'!AE:AE) -> sowjanya.kari
A47: Review Approval | B47: =_xlfn.XLOOKUP(F47,'TFS Details'!F:F,'TFS Details'!A:A) -> March Release NextGen Enhancements | C47: =_xlfn.XLOOKUP(F47,'TFS Details'!F:F,'TFS Details'!E:E) -> 4365826 | D47: Pirtheebaa | E47: Impact Check: As a Myisp user, I want the role "Enterprise SA" to be renamed to "Market Maker ESA" in myISP So that the role name clearly reflects the Market Make ESA in Solution Review & Approvals and Reporting & Compliance screens | F47: 4371399 | G47: Shalini | H47: Anitha | K47: No | L47: Related to MMS External app | M47: External Team Integration | W47: Completed | X47: Completed | Y47: Not Started | Z47: Completed | AA47: 50 | AB47: 20 | AC47: 4 | AD47: 11 | AE47: 0.9 | AF47: 0.9 | AG47: =_xlfn.XLOOKUP(F47,'TFS Details'!F:F,'TFS Details'!H:H) -> UAT In Test | AH47: 11 | AI47: 0 | AJ47: 0 | AK47: 0 | AL47: =SUM(AH47:AK47) -> 11 | AM47: =IF(AH47+AI47=0,0,SUM(AH47:AI47)/AL47) -> 1 | AN47: =IF(AH47=0,0,AH47/(SUM(AH47:AJ47))) -> 1 | AP47: =_xlfn.XLOOKUP(F47,'TFS Details'!F:F,'TFS Details'!I:I) -> CodeCrafters | AQ47: =_xlfn.XLOOKUP(AP47,'TFS Details'!I:I,'TFS Details'!AE:AE) -> sona.job
A48: Review Approval | B48: =_xlfn.XLOOKUP(F48,'TFS Details'!F:F,'TFS Details'!A:A) -> Revamp- Tier 2 city | C48: =_xlfn.XLOOKUP(F48,'TFS Details'!F:F,'TFS Details'!E:E) -> 4059417 | D48: Pirtheebaa | E48: As a Solution Architect, I want the ability to enter decimal values in the FTE and LCR fields under the Tier 2 City tab | F48: 4269036 | G48: Vinayak | H48: Janardhan | J48: Vinayak.sangale | K48: Yes | N48: Medium | O48: 1 | P48: 1 | Q48: 8 | R48: 5 | S48: 0 | T48: 8 | U48: 0.85 | V48: 0.85 | W48: Completed | X48: Completed | Y48: Completed | Z48: Completed | AA48: 6 | AB48: 6 | AC48: 2 | AD48: 8 | AE48: 0.75 | AF48: 1 | AG48: =_xlfn.XLOOKUP(F48,'TFS Details'!F:F,'TFS Details'!H:H) -> Test Complete | AH48: 8 | AI48: 0 | AJ48: 0 | AK48: 0 | AL48: =SUM(AH48:AK48) -> 8 | AM48: =IF(AH48+AI48=0,0,SUM(AH48:AI48)/AL48) -> 1 | AN48: =IF(AH48=0,0,AH48/(SUM(AH48:AJ48))) -> 1 | AP48: =_xlfn.XLOOKUP(F48,'TFS Details'!F:F,'TFS Details'!I:I) -> CodeCrafters | AQ48: =_xlfn.XLOOKUP(AP48,'TFS Details'!I:I,'TFS Details'!AE:AE) -> sona.job
A49: =_xlfn.XLOOKUP(F49,'TFS Details'!F:F,'TFS Details'!D:D) -> Reporting & Compliance -Tier 2 City | B49: =_xlfn.XLOOKUP(F49,'TFS Details'!F:F,'TFS Details'!A:A) -> Revamp- Tier 2 city | C49: =_xlfn.XLOOKUP(F49,'TFS Details'!F:F,'TFS Details'!E:E) -> 4059417 | D49: Pirtheebaa | E49: As a MYISP developer, I want to Restrict Tier 2 City Selection to Single Option for AMS, SI & IMS SG | F49: 4233240 | G49: Namrata | H49: Manisha | K49: No | L49: This US includes Navigation to all tiles | M49: Full regression required | W49: Completed | X49: Completed | Y49: In Progress | Z49: Completed | AA49: 25 | AB49: 19 | AC49: 10 | AD49: 10 | AE49: 1 | AF49: 0.75 | AG49: =_xlfn.XLOOKUP(F49,'TFS Details'!F:F,'TFS Details'!H:H) -> Test Complete | AH49: 24 | AI49: 0 | AJ49: 0 | AK49: 0 | AL49: =SUM(AH49:AK49) -> 24 | AM49: =IF(AH49+AI49=0,0,SUM(AH49:AI49)/AL49) -> 1 | AN49: =IF(AH49=0,0,AH49/(SUM(AH49:AJ49))) -> 1 | AP49: =_xlfn.XLOOKUP(F49,'TFS Details'!F:F,'TFS Details'!I:I) -> CodeCrafters | AQ49: =_xlfn.XLOOKUP(AP49,'TFS Details'!I:I,'TFS Details'!AE:AE) -> sona.job
A50: Review Approval | B50: =_xlfn.XLOOKUP(F50,'TFS Details'!F:F,'TFS Details'!A:A) -> March Release NextGen Enhancements | C50: =_xlfn.XLOOKUP(F50,'TFS Details'!F:F,'TFS Details'!E:E) -> 4365826 | D50: Pirtheebaa | E50: As a myISP user, I want to enable "KDA Adherence Score - Status" for IMS SG in reporting & compliance section | F50: 4227683 | G50: Vinayak | H50: Janardhan | J50: Manisha.m.sharma | K50: Yes | N50: Complex | O50: 10 | P50: 1 | Q50: 8 | R50: 8 | S50: 2 | T50: 10 | U50: 0.85 | V50: 0.85 | W50: Completed | X50: Completed | Y50: Completed | Z50: Completed | AA50: 6 | AB50: 6 | AD50: 8 | AE50: 0.75 | AF50: 1 | AG50: =_xlfn.XLOOKUP(F50,'TFS Details'!F:F,'TFS Details'!H:H) -> UAT In Test | AH50: 8 | AI50: 0 | AJ50: 0 | AK50: 0 | AL50: =SUM(AH50:AK50) -> 8 | AM50: =IF(AH50+AI50=0,0,SUM(AH50:AI50)/AL50) -> 1 | AN50: =IF(AH50=0,0,AH50/(SUM(AH50:AJ50))) -> 1 | AO50: Delivered To UAT | AP50: =_xlfn.XLOOKUP(F50,'TFS Details'!F:F,'TFS Details'!I:I) -> CodeCrafters | AQ50: =_xlfn.XLOOKUP(AP50,'TFS Details'!I:I,'TFS Details'!AE:AE) -> sona.job
A51: Review Approval | B51: =_xlfn.XLOOKUP(F51,'TFS Details'!F:F,'TFS Details'!A:A) -> Enhancement for Generative AI tab for AMS | C51: =_xlfn.XLOOKUP(F51,'TFS Details'!F:F,'TFS Details'!E:E) -> 4317843 | D51: Pirtheebaa | E51: AMS - Generative AI Tab: As a mySolutionPlanner developer, I want to make enhancement changes in Generative AI tab for AMS service group, so that the issues that are currently faced by SAs are resolved. | F51: 4317672 | G51: Shalini | H51: Anitha | J51: ShaliniB.Pandey | K51: yes | N51: Complex | O51: 3 | P51: 1 | Q51: 20 | R51: 10 | S51: 0 | T51: 10 | U51: 0.7 | V51: 0.4 | W51: Completed | X51: Completed | Y51: Not Started | Z51: Completed | AA51: 50 | AB51: 20 | AC51: 0 | AD51: 20 | AE51: 0.9 | AF51: 0.9 | AG51: =_xlfn.XLOOKUP(F51,'TFS Details'!F:F,'TFS Details'!H:H) -> UAT In Test | AH51: 20 | AI51: 0 | AJ51: 0 | AK51: 0 | AL51: =SUM(AH51:AK51) -> 20 | AM51: =IF(AH51+AI51=0,0,SUM(AH51:AI51)/AL51) -> 1 | AN51: =IF(AH51=0,0,AH51/(SUM(AH51:AJ51))) -> 1 | AP51: =_xlfn.XLOOKUP(F51,'TFS Details'!F:F,'TFS Details'!I:I) -> CodeCrafters | AQ51: =_xlfn.XLOOKUP(AP51,'TFS Details'!I:I,'TFS Details'!AE:AE) -> sona.job
A52: Opportunities | B52: =_xlfn.XLOOKUP(F52,'TFS Details'!F:F,'TFS Details'!A:A) -> Song Deals Compliant Logic Update | C52: =_xlfn.XLOOKUP(F52,'TFS Details'!F:F,'TFS Details'!E:E) -> 4317244 | D52: Pirtheebaa | E52: Song Compliant Logic Update - As a myISP User, I want to update the "Song Compliance Logic" in the Opportunities screen, so that users can quickly assess the compliance health of each deal. | F52: 3997998 | G52: Shalini | H52: Anitha | K52: No | L52: One time update US | M52: One time update related | W52: Completed | X52: Completed | Y52: Not Started | Z52: Completed | AA52: 50 | AB52: 40 | AC52: 0 | AD52: 40 | AE52: 0.8 | AF52: 0.8 | AG52: =_xlfn.XLOOKUP(F52,'TFS Details'!F:F,'TFS Details'!H:H) -> UAT In Test | AH52: 40 | AI52: 0 | AJ52: 0 | AK52: 0 | AL52: =SUM(AH52:AK52) -> 40 | AM52: =IF(AH52+AI52=0,0,SUM(AH52:AI52)/AL52) -> 1 | AN52: =IF(AH52=0,0,AH52/(SUM(AH52:AJ52))) -> 1 | AO52: Delivered to UAT with 80% completion | AP52: =_xlfn.XLOOKUP(F52,'TFS Details'!F:F,'TFS Details'!I:I) -> DevNinjas | AQ52: =_xlfn.XLOOKUP(AP52,'TFS Details'!I:I,'TFS Details'!AE:AE) -> sona.job
A53: =_xlfn.XLOOKUP(F53,'TFS Details'!F:F,'TFS Details'!D:D) -> DFD-myISP | B53: =_xlfn.XLOOKUP(F53,'TFS Details'!F:F,'TFS Details'!A:A) -> Song Deals Compliant Logic Update | C53: =_xlfn.XLOOKUP(F53,'TFS Details'!F:F,'TFS Details'!E:E) -> 4317244 | D53: Pirtheebaa | E53: Song Compliant Logic Update[RA] - As a myISP user, I want to see "Overall Song Delivery Approver" role added in Review Approvals dashboard so that User can approve the required deals needed to achieve Song Compliance. | F53: 4174501 | G53: Vinayak | H53: Anitha | K53: No | L53: Email functionality | M53: Email functionality | W53: Completed | X53: Completed | Y53: Completed | Z53: Completed | AA53: 6 | AB53: 6 | AC53: 1 | AD53: 7 | AE53: 0.85 | AF53: 0.9 | AG53: =_xlfn.XLOOKUP(F53,'TFS Details'!F:F,'TFS Details'!H:H) -> UAT In Test | AH53: 7 | AI53: 0 | AJ53: 0 | AK53: 0 | AL53: =SUM(AH53:AK53) -> 7 | AM53: =IF(AH53+AI53=0,0,SUM(AH53:AI53)/AL53) -> 1 | AN53: =IF(AH53=0,0,AH53/(SUM(AH53:AJ53))) -> 1 | AO53: Delivered to parallel UAT | AP53: =_xlfn.XLOOKUP(F53,'TFS Details'!F:F,'TFS Details'!I:I) -> CodeCrafters | AQ53: =_xlfn.XLOOKUP(AP53,'TFS Details'!I:I,'TFS Details'!AE:AE) -> sona.job
A54: =_xlfn.XLOOKUP(F54,'TFS Details'!F:F,'TFS Details'!D:D) -> DFD-myISP | B54: =_xlfn.XLOOKUP(F54,'TFS Details'!F:F,'TFS Details'!A:A) -> Song Deals Compliant Logic Update | C54: =_xlfn.XLOOKUP(F54,'TFS Details'!F:F,'TFS Details'!E:E) -> 4317244 | D54: Pirtheebaa | E54: Song Compliant Logic Update[RA] - As a myISP User,I want to provide onetime update for the existing deals and update the RAG , Score as per updated Song Compliance Logic so that all historical and active deals reflect accurate compliance status - RA Screen | F54: 4317269 | G54: Namrata/manisha/Bhavana | H54: Logapriya/Harish | K54: No | L54: One time update | M54: One time update related | W54: Completed | X54: Completed | Y54: In Progress | Z54: Completed | AA54: 24 | AB54: 9 | AC54: 11 | AD54: 11 | AE54: 1 | AF54: 0.7 | AG54: =_xlfn.XLOOKUP(F54,'TFS Details'!F:F,'TFS Details'!H:H) -> UAT In Test | AH54: 24 | AI54: 0 | AJ54: 0 | AK54: 0 | AL54: =SUM(AH54:AK54) -> 24 | AM54: =IF(AH54+AI54=0,0,SUM(AH54:AI54)/AL54) -> 1 | AN54: =IF(AH54=0,0,AH54/(SUM(AH54:AJ54))) -> 1 | AP54: =_xlfn.XLOOKUP(F54,'TFS Details'!F:F,'TFS Details'!I:I) -> CodeCrafters | AQ54: =_xlfn.XLOOKUP(AP54,'TFS Details'!I:I,'TFS Details'!AE:AE) -> sona.job
A55: =_xlfn.XLOOKUP(F55,'TFS Details'!F:F,'TFS Details'!D:D) -> DFD-myISP | B55: =_xlfn.XLOOKUP(F55,'TFS Details'!F:F,'TFS Details'!A:A) -> Song Deals Compliant Logic Update | C55: =_xlfn.XLOOKUP(F55,'TFS Details'!F:F,'TFS Details'!E:E) -> 4317244 | D55: Pirtheebaa | E55: Song Compliant Logic Update [RA] - As a myISP User, I want to update the "Song Compliance Logic" in the Opportunities screen, so that users can quickly assess the compliance health of each deal. - Copy | F55: 4320775 | G55: Namrata/manisha/sadhik | H55: Logapriya/Harish | K55: No | L55: One time update | M55: One time update related | W55: Completed | X55: Completed | Y55: In Progress | Z55: Completed | AA55: 30 | AB55: 20 | AC55: 15 | AD55: 15 | AE55: 1 | AF55: 0.85 | AG55: =_xlfn.XLOOKUP(F55,'TFS Details'!F:F,'TFS Details'!H:H) -> UAT In Test | AH55: 24 | AI55: 0 | AJ55: 0 | AK55: 0 | AL55: 24 | AM55: =IF(AH55+AI55=0,0,SUM(AH55:AI55)/AL55) -> 1 | AN55: =IF(AH55=0,0,AH55/(SUM(AH55:AJ55))) -> 1 | AP55: =_xlfn.XLOOKUP(F55,'TFS Details'!F:F,'TFS Details'!I:I) -> CodeCrafters | AQ55: =_xlfn.XLOOKUP(AP55,'TFS Details'!I:I,'TFS Details'!AE:AE) -> sona.job
A56: Review Approval | B56: =_xlfn.XLOOKUP(F56,'TFS Details'!F:F,'TFS Details'!A:A) -> Value Shaping –Enhancements | C56: =_xlfn.XLOOKUP(F56,'TFS Details'!F:F,'TFS Details'!E:E) -> 4330994 | D56: Pirtheebaa | E56: Value Shaping - As a myISP User - Configurator V2V - I want to access the Review Approvals tile in read-only mode and navigate using the fixed breadcrumb path so that I can maintain workflow continuity. | F56: 4364543 | G56: Mary | H56: Bhavana | J56: Bhavana.reddy.alla | K56: Yes | N56: Complex | O56: 2 | P56: 1 | Q56: 30 | R56: 2 | S56: 0 | T56: 2 | U56: 0.5 | V56: 0.5 | W56: Completed | X56: Completed | Y56: Completed | Z56: Completed | AA56: 46 | AB56: 7 | AC56: 2 | AD56: 9 | AE56: 0.9 | AF56: 0.9 | AG56: =_xlfn.XLOOKUP(F56,'TFS Details'!F:F,'TFS Details'!H:H) -> Test Complete | AH56: 9 | AI56: 0 | AJ56: 0 | AK56: 0 | AL56: =SUM(AH56:AK56) -> 9 | AM56: =IF(AH56+AI56=0,0,SUM(AH56:AI56)/AL56) -> 1 | AN56: =IF(AH56=0,0,AH56/(SUM(AH56:AJ56))) -> 1 | AO56: Delivered for UAT | AP56: =_xlfn.XLOOKUP(F56,'TFS Details'!F:F,'TFS Details'!I:I) -> CodeCrafters | AQ56: =_xlfn.XLOOKUP(AP56,'TFS Details'!I:I,'TFS Details'!AE:AE) -> sona.job
A57: Estimators/Calculators | B57: =_xlfn.XLOOKUP(F57,'TFS Details'!F:F,'TFS Details'!A:A) -> Angular upgrade version 19 to version 21 - 28th March | C57: =_xlfn.XLOOKUP(F57,'TFS Details'!F:F,'TFS Details'!E:E) -> 4358702 | D57: Pirtheebaa | E57: As a myISP Solution Architect, I want to see the Estimators/Calculators App migrated to Angular 21 | F57: 4358748 | G57: Shalini | H57: Sadhik | K57: No | L57: Angular upgrade,Regression | M57: Full regression required | W57: Completed | X57: Completed | Y57: Not Started | Z57: Completed | AA57: 30 | AB57: 2 | AC57: 17 | AD57: 17 | AE57: 0.4 | AF57: 0.4 | AG57: =_xlfn.XLOOKUP(F57,'TFS Details'!F:F,'TFS Details'!H:H) -> Test Complete | AH57: 17 | AI57: 0 | AJ57: 0 | AK57: 0 | AL57: =SUM(AH57:AK57) -> 17 | AM57: =IF(AH57+AI57=0,0,SUM(AH57:AI57)/AL57) -> 1 | AN57: =IF(AH57=0,0,AH57/(SUM(AH57:AJ57))) -> 1 | AP57: =_xlfn.XLOOKUP(F57,'TFS Details'!F:F,'TFS Details'!I:I) -> MYISP_Revamp_UI | AQ57: =_xlfn.XLOOKUP(AP57,'TFS Details'!I:I,'TFS Details'!AE:AE) -> vikrant.r.mohite
A58: Review Approval | B58: =_xlfn.XLOOKUP(F58,'TFS Details'!F:F,'TFS Details'!A:A) -> PLD - Advisory SA Role | C58: =_xlfn.XLOOKUP(F58,'TFS Details'!F:F,'TFS Details'!E:E) -> 4386527 | D58: Pirtheebaa | E58: As an Advisory song SA, I want to access the Review Approvals tile in read-only mode so that I can maintain and view workflow continuity. | F58: 4373043 | G58: Mary | H58: Bhavana | J58: Mary.jacob | K58: Yes | N58: Simple | O58: 12 | P58: 1 | Q58: 47 | R58: 12 | S58: 0 | T58: 12 | U58: 0.5 | V58: 0.5 | W58: Completed | X58: Completed | Y58: Completed | Z58: Completed | AA58: 42 | AB58: 7 | AC58: 2 | AD58: 9 | AE58: 0.9 | AF58: 0.9 | AG58: =_xlfn.XLOOKUP(F58,'TFS Details'!F:F,'TFS Details'!H:H) -> UAT In Test | AH58: 9 | AI58: 0 | AJ58: 0 | AK58: 0 | AL58: =SUM(AH58:AK58) -> 9 | AM58: =IF(AH58+AI58=0,0,SUM(AH58:AI58)/AL58) -> 1 | AN58: =IF(AH58=0,0,AH58/(SUM(AH58:AJ58))) -> 1 | AO58: Delivered for UAT | AP58: =_xlfn.XLOOKUP(F58,'TFS Details'!F:F,'TFS Details'!I:I) -> CodeCrafters | AQ58: =_xlfn.XLOOKUP(AP58,'TFS Details'!I:I,'TFS Details'!AE:AE) -> sona.job
A59: =_xlfn.XLOOKUP(F59,'TFS Details'!F:F,'TFS Details'!D:D) -> Role Rename | B59: =_xlfn.XLOOKUP(F59,'TFS Details'!F:F,'TFS Details'!A:A) -> March Release NextGen Enhancements | C59: =_xlfn.XLOOKUP(F59,'TFS Details'!F:F,'TFS Details'!E:E) -> 4365826 | D59: Pirtheebaa | E59: Impact Check: As a Myisp user, I want the role "Enterprise SA" to be renamed to "Market Maker ESA" in myISP So that the role name clearly reflects the Market Make ESA in mentioned modules . | F59: 4391260 | G59: Namrata | H59: Manisha | K59: No | L59: Related to MMS External app | M59: External Team Integration | W59: Completed | X59: Completed | Y59: In Progress | Z59: Completed | AA59: 27 | AB59: 23 | AC59: 10 | AD59: 10 | AE59: 1 | AF59: 0.9 | AG59: =_xlfn.XLOOKUP(F59,'TFS Details'!F:F,'TFS Details'!H:H) -> UAT In Test | AH59: 24 | AI59: 0 | AJ59: 0 | AK59: 0 | AL59: =SUM(AH59:AK59) -> 24 | AM59: =IF(AH59+AI59=0,0,SUM(AH59:AI59)/AL59) -> 1 | AN59: =IF(AH59=0,0,AH59/(SUM(AH59:AJ59))) -> 1 | AP59: =_xlfn.XLOOKUP(F59,'TFS Details'!F:F,'TFS Details'!I:I) -> GoRetro | AQ59: =_xlfn.XLOOKUP(AP59,'TFS Details'!I:I,'TFS Details'!AE:AE) -> sowjanya.kari
A60: =_xlfn.XLOOKUP(F60,'TFS Details'!F:F,'TFS Details'!D:D) -> Role Rename | B60: =_xlfn.XLOOKUP(F60,'TFS Details'!F:F,'TFS Details'!A:A) -> March Release NextGen Enhancements | C60: =_xlfn.XLOOKUP(F60,'TFS Details'!F:F,'TFS Details'!E:E) -> 4365826 | D60: Pirtheebaa | E60: Impact Check: As a Myisp user, I want the role "Enterprise SA" to be renamed to "Market Maker ESA" in myISP So that the role name clearly reflects the Market Make ESA in mentioned scopes | F60: 4391283 | G60: Shalini | H60: Anitha | K60: No | L60: One time update US from MMS | M60: One time update related | W60: Completed | X60: Completed | Y60: Not Started | Z60: Completed | AA60: 31 | AB60: 24 | AC60: 0 | AD60: 24 | AE60: 0.9 | AF60: 0.9 | AG60: =_xlfn.XLOOKUP(F60,'TFS Details'!F:F,'TFS Details'!H:H) -> UAT In Test | AH60: 24 | AI60: 0 | AJ60: 0 | AK60: 0 | AL60: =SUM(AH60:AK60) -> 24 | AM60: =IF(AH60+AI60=0,0,SUM(AH60:AI60)/AL60) -> 1 | AN60: =IF(AH60=0,0,AH60/(SUM(AH60:AJ60))) -> 1 | AO60: Delivered to UAT | AP60: =_xlfn.XLOOKUP(F60,'TFS Details'!F:F,'TFS Details'!I:I) -> NGTransformers | AQ60: =_xlfn.XLOOKUP(AP60,'TFS Details'!I:I,'TFS Details'!AE:AE) -> sowjanya.kari
A61: Transition To Delivery | B61: =_xlfn.XLOOKUP(F61,'TFS Details'!F:F,'TFS Details'!A:A) -> Value Shaping –Enhancements | C61: =_xlfn.XLOOKUP(F61,'TFS Details'!F:F,'TFS Details'!E:E) -> 4330994 | D61: Pirtheebaa | E61: Value Shaping - As a myISP User - Configurator V2V - I want to access the Transition To Delivery tile in read-only mode and navigate using the fixed breadcrumb path so that I can maintain workflow continuity. | F61: 4364562 | G61: Vinayak | H61: Anitha | J61: Anitha.a.ramesh | K61: Yes | N61: Simple | O61: 1 | P61: 1 | Q61: 28 | R61: 5 | S61: 0 | T61: 5 | U61: 0.6 | V61: 0.6 | W61: Completed | X61: Completed | Y61: Completed | Z61: Completed | AA61: 13 | AB61: 13 | AC61: 0 | AD61: 13 | AE61: 0.9 | AF61: 0.9 | AG61: =_xlfn.XLOOKUP(F61,'TFS Details'!F:F,'TFS Details'!H:H) -> Test Complete | AH61: 13 | AI61: 0 | AJ61: 0 | AK61: 0 | AL61: =SUM(AH61:AK61) -> 13 | AM61: =IF(AH61+AI61=0,0,SUM(AH61:AI61)/AL61) -> 1 | AN61: =IF(AH61=0,0,AH61/(SUM(AH61:AJ61))) -> 1 | AO61: Delivered to UAT | AP61: =_xlfn.XLOOKUP(F61,'TFS Details'!F:F,'TFS Details'!I:I) -> Pirates | AQ61: =_xlfn.XLOOKUP(AP61,'TFS Details'!I:I,'TFS Details'!AE:AE) -> pandidurai.ks
A62: Transition To Delivery | B62: =_xlfn.XLOOKUP(F62,'TFS Details'!F:F,'TFS Details'!A:A) -> PLD - Advisory SA Role | C62: =_xlfn.XLOOKUP(F62,'TFS Details'!F:F,'TFS Details'!E:E) -> 4386527 | D62: Pirtheebaa | E62: As an Advisory song SA, I want to access the Transition To Delivery tile in read-only mode so that I can maintain and view workflow continuity. | F62: 4373066 | G62: Vinayak | H62: Anitha | J62: Bhavana.reddy.alla | K62: Yes | N62: Medium | O62: 1 | P62: 1 | Q62: 25 | R62: 5 | S62: 0 | T62: 5 | U62: 0.7 | V62: 0.7 | W62: Completed | X62: Completed | Y62: Completed | Z62: Completed | AA62: 10 | AB62: 10 | AC62: 0 | AD62: 10 | AE62: 0.9 | AF62: 0.9 | AG62: =_xlfn.XLOOKUP(F62,'TFS Details'!F:F,'TFS Details'!H:H) -> UAT In Test | AH62: 10 | AI62: 0 | AJ62: 0 | AK62: 0 | AL62: =SUM(AH62:AK62) -> 10 | AM62: =IF(AH62+AI62=0,0,SUM(AH62:AI62)/AL62) -> 1 | AN62: =IF(AH62=0,0,AH62/(SUM(AH62:AJ62))) -> 1 | AO62: Delivered To UAT | AP62: =_xlfn.XLOOKUP(F62,'TFS Details'!F:F,'TFS Details'!I:I) -> Pirates | AQ62: =_xlfn.XLOOKUP(AP62,'TFS Details'!I:I,'TFS Details'!AE:AE) -> pandidurai.ks
A63: Define Team | B63: =_xlfn.XLOOKUP(F63,'TFS Details'!F:F,'TFS Details'!A:A) -> Value Shaping –Enhancements | C63: =_xlfn.XLOOKUP(F63,'TFS Details'!F:F,'TFS Details'!E:E) -> 4330994 | D63: Pirtheebaa | E63: Value Shaping - As a myISP User - Configurator V2V - I want to access the Define Team tile in read-only mode and navigate using the fixed breadcrumb path so that I can maintain workflow continuity. | F63: 4364419 | G63: Vinayak | H63: Anitha | J63: namrata.g.umardand | K63: Yes | N63: Medium | O63: 1 | P63: 1 | Q63: 13 | R63: 5 | S63: 0 | T63: 5 | U63: 0.6 | V63: 0.7 | W63: Completed | X63: Completed | Y63: Completed | Z63: Completed | AA63: 34 | AB63: 14 | AC63: 0 | AD63: 14 | AE63: 0.9 | AF63: 0.9 | AG63: =_xlfn.XLOOKUP(F63,'TFS Details'!F:F,'TFS Details'!H:H) -> Test Complete | AH63: 14 | AI63: 0 | AJ63: 0 | AK63: 0 | AL63: =SUM(AH63:AK63) -> 14 | AM63: =IF(AH63+AI63=0,0,SUM(AH63:AI63)/AL63) -> 1 | AN63: =IF(AH63=0,0,AH63/(SUM(AH63:AJ63))) -> 1 | AO63: Delivered to UAT | AP63: =_xlfn.XLOOKUP(F63,'TFS Details'!F:F,'TFS Details'!I:I) -> TechPhantoms | AQ63: =_xlfn.XLOOKUP(AP63,'TFS Details'!I:I,'TFS Details'!AE:AE) -> sowjanya.kari
A64: WRWS | B64: =_xlfn.XLOOKUP(F64,'TFS Details'!F:F,'TFS Details'!A:A) -> Value Shaping –Enhancements | C64: =_xlfn.XLOOKUP(F64,'TFS Details'!F:F,'TFS Details'!E:E) -> 4330994 | D64: Pirtheebaa | E64: Value Shaping - As a myISP User - Configurator V2V - I want to access the WRWS tile in read-only mode and navigate using the fixed breadcrumb path so that I can maintain workflow continuity. | F64: 4364536 | G64: Mary | H64: n.selvakumar | J64: Manisha.m.sharma | K64: Yes | N64: Complex | O64: 9 | P64: 1 | Q64: 7 | R64: 7 | S64: 2 | T64: 9 | U64: 0.85 | V64: 0.85 | W64: Completed | X64: Completed | Y64: Completed | Z64: Completed | AA64: 70 | AB64: 7 | AC64: 0 | AD64: 7 | AE64: 1 | AF64: 1 | AG64: =_xlfn.XLOOKUP(F64,'TFS Details'!F:F,'TFS Details'!H:H) -> Test Complete | AH64: 7 | AI64: 0 | AJ64: 0 | AK64: 0 | AL64: =SUM(AH64:AK64) -> 7 | AM64: =IF(AH64+AI64=0,0,SUM(AH64:AI64)/AL64) -> 1 | AN64: =IF(AH64=0,0,AH64/(SUM(AH64:AJ64))) -> 1 | AO64: Delivered for UAT | AP64: =_xlfn.XLOOKUP(F64,'TFS Details'!F:F,'TFS Details'!I:I) -> TechWarriors | AQ64: =_xlfn.XLOOKUP(AP64,'TFS Details'!I:I,'TFS Details'!AE:AE) -> sowjanya.kari
A65: Opportunity Workflow | B65: =_xlfn.XLOOKUP(F65,'TFS Details'!F:F,'TFS Details'!A:A) -> Value Shaping –Enhancements | C65: =_xlfn.XLOOKUP(F65,'TFS Details'!F:F,'TFS Details'!E:E) -> 4330994 | D65: Pirtheebaa | E65: Value Shaping - As a myISP User - Configurator V2V - I want to access the Opportunity Workflow in read-only mode and navigate using the fixed breadcrumb path so that I can maintain workflow continuity. | F65: 4364567 | G65: Mary | H65: Anitha | J65: Anitha.a.ramesh | K65: Yes | N65: Simple | O65: 1 | P65: 1 | Q65: 26 | R65: 5 | S65: 0 | T65: 5 | U65: 0.6 | V65: 0.6 | W65: Completed | X65: Completed | Y65: Completed | Z65: Completed | AA65: 70 | AB65: 7 | AC65: 0 | AD65: 7 | AE65: 0.9 | AF65: 0.9 | AG65: =_xlfn.XLOOKUP(F65,'TFS Details'!F:F,'TFS Details'!H:H) -> Test Complete | AH65: 7 | AI65: 0 | AJ65: 0 | AK65: 0 | AL65: =SUM(AH65:AK65) -> 7 | AM65: =IF(AH65+AI65=0,0,SUM(AH65:AI65)/AL65) -> 1 | AN65: =IF(AH65=0,0,AH65/(SUM(AH65:AJ65))) -> 1 | AO65: Delivered for UAT | AP65: =_xlfn.XLOOKUP(F65,'TFS Details'!F:F,'TFS Details'!I:I) -> TechWarriors | AQ65: =_xlfn.XLOOKUP(AP65,'TFS Details'!I:I,'TFS Details'!AE:AE) -> sowjanya.kari
A66: Estimators/Calculators | B66: =_xlfn.XLOOKUP(F66,'TFS Details'!F:F,'TFS Details'!A:A) -> PLD - Advisory SA Role | C66: =_xlfn.XLOOKUP(F66,'TFS Details'!F:F,'TFS Details'!E:E) -> 4386527 | D66: Pirtheebaa | E66: As an Advisory song SA, I want to access the Estimators/Calculators tile in read-only mode so that I can maintain and view workflow continuity. | F66: 4373070 | G66: Mary | H66: Anitha | J66: Anitha.a.ramesh | K66: Yes | N66: Simple | O66: 1 | P66: 1 | Q66: 10 | R66: 5 | S66: 0 | T66: 5 | U66: 0.9 | V66: 0.9 | W66: Completed | X66: Completed | Y66: Completed | Z66: Completed | AA66: 26 | AB66: 15 | AC66: 0 | AD66: 15 | AE66: 0.95 | AF66: 0.95 | AG66: =_xlfn.XLOOKUP(F66,'TFS Details'!F:F,'TFS Details'!H:H) -> UAT In Test | AH66: 15 | AI66: 0 | AJ66: 0 | AK66: 0 | AL66: =SUM(AH66:AK66) -> 15 | AM66: =IF(AH66+AI66=0,0,SUM(AH66:AI66)/AL66) -> 1 | AN66: =IF(AH66=0,0,AH66/(SUM(AH66:AJ66))) -> 1 | AO66: Delivered for UAT | AP66: =_xlfn.XLOOKUP(F66,'TFS Details'!F:F,'TFS Details'!I:I) -> TechWarriors | AQ66: =_xlfn.XLOOKUP(AP66,'TFS Details'!I:I,'TFS Details'!AE:AE) -> sowjanya.kari
A67: WRWS | B67: =_xlfn.XLOOKUP(F67,'TFS Details'!F:F,'TFS Details'!A:A) -> PLD - Advisory SA Role | C67: =_xlfn.XLOOKUP(F67,'TFS Details'!F:F,'TFS Details'!E:E) -> 4386527 | D67: Pirtheebaa | E67: As an Advisory song SA, I want to access the WRWS tile in read-only mode so that I can maintain and view workflow continuity. | F67: 4373007 | G67: Mary | H67: Anitha | J67: namrata.g.umardand | K67: Yes | N67: Medium | O67: 1 | P67: 1 | Q67: 10 | R67: 6 | S67: 0 | T67: 6 | U67: 0.7 | V67: 0.7 | W67: Completed | X67: Completed | Y67: Completed | Z67: Completed | AA67: 26 | AB67: 13 | AC67: 0 | AD67: 13 | AE67: 0.95 | AF67: 0.95 | AG67: =_xlfn.XLOOKUP(F67,'TFS Details'!F:F,'TFS Details'!H:H) -> UAT In Test | AH67: 13 | AI67: 0 | AJ67: 0 | AK67: 0 | AL67: =SUM(AH67:AK67) -> 13 | AM67: =IF(AH67+AI67=0,0,SUM(AH67:AI67)/AL67) -> 1 | AN67: =IF(AH67=0,0,AH67/(SUM(AH67:AJ67))) -> 1 | AO67: Delivered to UAT | AP67: =_xlfn.XLOOKUP(F67,'TFS Details'!F:F,'TFS Details'!I:I) -> TechWarriors | AQ67: =_xlfn.XLOOKUP(AP67,'TFS Details'!I:I,'TFS Details'!AE:AE) -> sowjanya.kari
A68: =_xlfn.XLOOKUP(F68,'TFS Details'!F:F,'TFS Details'!D:D) -> Role Rename | B68: =_xlfn.XLOOKUP(F68,'TFS Details'!F:F,'TFS Details'!A:A) -> March Release NextGen Enhancements | C68: =_xlfn.XLOOKUP(F68,'TFS Details'!F:F,'TFS Details'!E:E) -> 4365826 | D68: Pirtheebaa | E68: Impact Check: As a Myisp user, I want the role "Enterprise SA" to be renamed to "Market Maker ESA" in myISP So that the role name clearly reflects the Market Make ESA in mentioned scopes | F68: 4391289 | G68: Namrata | H68: Manisha | K68: No | L68: Related to MMS External app | M68: External Team Integration | W68: Completed | X68: Completed | Y68: In Progress | Z68: Completed | AA68: 24 | AB68: 18 | AC68: 10 | AD68: 10 | AE68: 1 | AF68: 0.9 | AG68: =_xlfn.XLOOKUP(F68,'TFS Details'!F:F,'TFS Details'!H:H) -> UAT In Test | AH68: 24 | AI68: 0 | AJ68: 0 | AK68: 0 | AL68: =SUM(AH68:AK68) -> 24 | AM68: =IF(AH68+AI68=0,0,SUM(AH68:AI68)/AL68) -> 1 | AN68: =IF(AH68=0,0,AH68/(SUM(AH68:AJ68))) -> 1 | AP68: =_xlfn.XLOOKUP(F68,'TFS Details'!F:F,'TFS Details'!I:I) -> TechWarriors | AQ68: =_xlfn.XLOOKUP(AP68,'TFS Details'!I:I,'TFS Details'!AE:AE) -> sowjanya.kari
A69: =_xlfn.XLOOKUP(F69,'TFS Details'!F:F,'TFS Details'!D:D) -> DFD-myISP | B69: =_xlfn.XLOOKUP(F69,'TFS Details'!F:F,'TFS Details'!A:A) -> Song Deals Compliant Logic Update | C69: =_xlfn.XLOOKUP(F69,'TFS Details'!F:F,'TFS Details'!E:E) -> 4317244 | D69: Pirtheebaa | E69: Song Compliant Logic Update -(MFHost) As a myISP User - I want to access all myISP screens as per Solution Reviewer role, read-only mode and navigate using the fixed breadcrumb path so that I can maintain workflow continuity | F69: 4386412 | G69: Mary | H69: Anitha | K69: No | L69: This US includes Navigation to all tiles | M69: Full regression required | W69: Completed | X69: Completed | Y69: Completed | Z69: Completed | AA69: 48 | AB69: 13 | AC69: 2 | AD69: 15 | AE69: 0.95 | AF69: 0.95 | AG69: =_xlfn.XLOOKUP(F69,'TFS Details'!F:F,'TFS Details'!H:H) -> UAT In Test | AH69: 15 | AI69: 0 | AJ69: 0 | AK69: 0 | AL69: =SUM(AH69:AK69) -> 15 | AM69: =IF(AH69+AI69=0,0,SUM(AH69:AI69)/AL69) -> 1 | AN69: =IF(AH69=0,0,AH69/(SUM(AH69:AJ69))) -> 1 | AO69: Delievred to UAT | AP69: =_xlfn.XLOOKUP(F69,'TFS Details'!F:F,'TFS Details'!I:I) -> MYISP_Revamp_UI | AQ69: =_xlfn.XLOOKUP(AP69,'TFS Details'!I:I,'TFS Details'!AE:AE) -> vikrant.r.mohite
A70: =_xlfn.XLOOKUP(F70,'TFS Details'!F:F,'TFS Details'!D:D) -> BPMS Onboarding | B70: =_xlfn.XLOOKUP(F70,'TFS Details'!F:F,'TFS Details'!A:A) -> BPMS Reporting & Compliance UI Suggestions post demo call | C70: =_xlfn.XLOOKUP(F70,'TFS Details'!F:F,'TFS Details'!E:E) -> 4316934 | D70: Shini | E70: As a myIntegrated Solution Planner user, I should be able to see Ripple On/Off toggle for Productivity Grid in Generative AI screen under Reporting & Compliance screen for BPMS Opportunity | F70: 4113135 | G70: Pavithra | J70: sagarika.a.singh | K70: Yes | N70: Medium | O70: 6 | P70: 1 | Q70: 6 | R70: 4 | S70: 0 | T70: 4 | U70: 0.6 | V70: 0.5 | W70: Completed | X70: Completed | Y70: Completed | Z70: Completed | AA70: 18 | AB70: 4 | AC70: 2 | AD70: 5 | AE70: 0.78 | AF70: 0.7 | AG70: =_xlfn.XLOOKUP(F70,'TFS Details'!F:F,'TFS Details'!H:H) -> Test Complete | AH70: 5 | AI70: 0 | AJ70: 0 | AK70: 0 | AL70: =SUM(AH70:AK70) -> 5 | AM70: =IF(AH70+AI70=0,0,SUM(AH70:AI70)/AL70) -> 1 | AN70: =IF(AH70=0,0,AH70/(SUM(AH70:AJ70))) -> 1 | AP70: =_xlfn.XLOOKUP(F70,'TFS Details'!F:F,'TFS Details'!I:I) -> CodeCrafters | AQ70: =_xlfn.XLOOKUP(AP70,'TFS Details'!I:I,'TFS Details'!AE:AE) -> sona.job
A71: =_xlfn.XLOOKUP(F71,'TFS Details'!F:F,'TFS Details'!D:D) -> BPMS Onboarding | B71: =_xlfn.XLOOKUP(F71,'TFS Details'!F:F,'TFS Details'!A:A) -> BPMS Reporting & Compliance UI Suggestions post demo call | C71: =_xlfn.XLOOKUP(F71,'TFS Details'!F:F,'TFS Details'!E:E) -> 4316934 | D71: Shini | E71: As a my solution planner solution architect, Read more & hide should be available in description for Maturity Index and Due Diligence Questionnaire for BPMS Opportunity | F71: 4113172 | G71: Pavithra | J71: pavithra.b.palani | K71: Yes | N71: Simple | O71: 1 | P71: 1 | Q71: 16 | R71: 3 | S71: 1 | T71: 1 | U71: 0.65 | V71: 0.7 | W71: Completed | X71: Completed | Y71: Completed | Z71: Completed | AA71: 16 | AB71: 3 | AC71: 2 | AD71: 5 | AE71: 0.75 | AF71: 0.7 | AG71: =_xlfn.XLOOKUP(F71,'TFS Details'!F:F,'TFS Details'!H:H) -> Test Complete | AH71: 5 | AI71: 0 | AJ71: 0 | AK71: 0 | AL71: =SUM(AH71:AK71) -> 5 | AM71: =IF(AH71+AI71=0,0,SUM(AH71:AI71)/AL71) -> 1 | AN71: =IF(AH71=0,0,AH71/(SUM(AH71:AJ71))) -> 1 | AP71: =_xlfn.XLOOKUP(F71,'TFS Details'!F:F,'TFS Details'!I:I) -> CodeCrafters | AQ71: =_xlfn.XLOOKUP(AP71,'TFS Details'!I:I,'TFS Details'!AE:AE) -> sona.job
A72: =_xlfn.XLOOKUP(F72,'TFS Details'!F:F,'TFS Details'!D:D) -> BPMS Onboarding | B72: =_xlfn.XLOOKUP(F72,'TFS Details'!F:F,'TFS Details'!A:A) -> BPMS Reporting & Compliance UI Suggestions post demo call | C72: =_xlfn.XLOOKUP(F72,'TFS Details'!F:F,'TFS Details'!E:E) -> 4316934 | D72: Shini | E72: As a my solution planner solution architect, I want all dropdown values to be displayed in alphabetical order, with the "Other Reasons" option always appearing last | F72: 4113178 | G72: Pavithra | J72: pavithra.b.palani | K72: Yes | N72: Simple | O72: 1 | P72: 1 | Q72: 8 | R72: 4 | S72: 1 | T72: 1 | U72: 0.9 | V72: 0.55 | W72: Completed | X72: Completed | Y72: Completed | Z72: Completed | AA72: 18 | AB72: 8 | AC72: 1 | AD72: 8 | AE72: 0.9 | AF72: 0.8 | AG72: =_xlfn.XLOOKUP(F72,'TFS Details'!F:F,'TFS Details'!H:H) -> Test Complete | AH72: 8 | AI72: 0 | AJ72: 0 | AK72: 0 | AL72: =SUM(AH72:AK72) -> 8 | AM72: =IF(AH72+AI72=0,0,SUM(AH72:AI72)/AL72) -> 1 | AN72: =IF(AH72=0,0,AH72/(SUM(AH72:AJ72))) -> 1 | AP72: =_xlfn.XLOOKUP(F72,'TFS Details'!F:F,'TFS Details'!I:I) -> CodeCrafters | AQ72: =_xlfn.XLOOKUP(AP72,'TFS Details'!I:I,'TFS Details'!AE:AE) -> sona.job
A73: =_xlfn.XLOOKUP(F73,'TFS Details'!F:F,'TFS Details'!D:D) -> DCSO | B73: =_xlfn.XLOOKUP(F73,'TFS Details'!F:F,'TFS Details'!A:A) -> myISP - Online SI API's for DSCO | C73: =_xlfn.XLOOKUP(F73,'TFS Details'!F:F,'TFS Details'!E:E) -> 4275381 | D73: Shini | E73: DCSO SI- API: As a mySolutionPlanner developer, I want the Persist Solution line Across Solution Operations, so that user can maintain consistency and traceability of a demand across different solution versions and operations. | F73: 4275371 | G73: Arun | J73: arun.thangapandian | K73: No | L73: Full regression required | M73: Full regression required | N73: Complex | W73: Completed | X73: Completed | Y73: Completed | Z73: In Progress | AA73: 50 | AB73: 20 | AC73: 1 | AD73: 21 | AE73: 0.9 | AF73: 0.4 | AG73: =_xlfn.XLOOKUP(F73,'TFS Details'!F:F,'TFS Details'!H:H) -> UAT In Test | AH73: 18 | AI73: 0 | AJ73: 0 | AK73: 0 | AL73: =SUM(AH73:AK73) -> 18 | AM73: =IF(AH73+AI73=0,0,SUM(AH73:AI73)/AL73) -> 1 | AN73: =IF(AH73=0,0,AH73/(SUM(AH73:AJ73))) -> 1 | AO73: 4414032 4428646 4434960 | AP73: =_xlfn.XLOOKUP(F73,'TFS Details'!F:F,'TFS Details'!I:I) -> TechWizards | AQ73: =_xlfn.XLOOKUP(AP73,'TFS Details'!I:I,'TFS Details'!AE:AE) -> mervinkumar.manickam
A74: =_xlfn.XLOOKUP(F74,'TFS Details'!F:F,'TFS Details'!D:D) -> DCSO | B74: =_xlfn.XLOOKUP(F74,'TFS Details'!F:F,'TFS Details'!A:A) -> myISP - Digital DCSO | C74: =_xlfn.XLOOKUP(F74,'TFS Details'!F:F,'TFS Details'!E:E) -> 4278081 | D74: Shini | E74: As a Solution Architect, I want to enable Generate DCSO for multiple versions into an Opportunity-level DCSO(multiple SGs) so that I can have a unified view of staffing data | F74: 4278129 | G74: Arun | J74: arun.thangapandian | K74: Yes | N74: Simple | O74: 6 | P74: 1 | Q74: 6 | R74: 4 | S74: 2 | T74: 6 | U74: 0.5 | V74: 0.4 | W74: Completed | X74: Completed | Y74: Completed | Z74: Completed | AA74: 12 | AB74: 5 | AC74: 1 | AD74: 6 | AE74: 0.85 | AF74: 0.6 | AG74: =_xlfn.XLOOKUP(F74,'TFS Details'!F:F,'TFS Details'!H:H) -> UAT In Test | AH74: 6 | AI74: 0 | AJ74: 0 | AK74: 0 | AL74: =SUM(AH74:AK74) -> 6 | AM74: =IF(AH74+AI74=0,0,SUM(AH74:AI74)/AL74) -> 1 | AN74: =IF(AH74=0,0,AH74/(SUM(AH74:AJ74))) -> 1 | AP74: =_xlfn.XLOOKUP(F74,'TFS Details'!F:F,'TFS Details'!I:I) -> TechStars | AQ74: =_xlfn.XLOOKUP(AP74,'TFS Details'!I:I,'TFS Details'!AE:AE) -> mohanraj.a.selvaraj
A75: =_xlfn.XLOOKUP(F75,'TFS Details'!F:F,'TFS Details'!D:D) -> BPMS Onboarding | B75: =_xlfn.XLOOKUP(F75,'TFS Details'!F:F,'TFS Details'!A:A) -> Solution Simplification mandatory field updates | C75: =_xlfn.XLOOKUP(F75,'TFS Details'!F:F,'TFS Details'!E:E) -> 4316945 | D75: Shini | E75: As a BPMS User, I should be able to save Solution Simplification screen without mandatory checks on ?PriceOne used for Stage 0/1/2A? and ?Approval Committee Approach Followed? so that I can proceed smoothly without validation errors. | F75: 4279597 | G75: Sakshi | J75: s.namdev.suryawanshi | K75: Yes | N75: Medium | O75: 2 | P75: 1 | Q75: 6 | R75: 5 | S75: 2 | T75: 2 | U75: 1 | V75: 0.6 | W75: Completed | X75: Completed | Y75: Completed | Z75: Completed | AA75: 6 | AB75: 2 | AC75: 2 | AD75: 2 | AE75: 0.5 | AF75: 0.5 | AG75: =_xlfn.XLOOKUP(F75,'TFS Details'!F:F,'TFS Details'!H:H) -> Test Complete | AH75: 2 | AI75: 0 | AJ75: 0 | AK75: 0 | AL75: =SUM(AH75:AK75) -> 2 | AM75: =IF(AH75+AI75=0,0,SUM(AH75:AI75)/AL75) -> 1 | AN75: =IF(AH75=0,0,AH75/(SUM(AH75:AJ75))) -> 1 | AP75: =_xlfn.XLOOKUP(F75,'TFS Details'!F:F,'TFS Details'!I:I) -> CodeCrafters | AQ75: =_xlfn.XLOOKUP(AP75,'TFS Details'!I:I,'TFS Details'!AE:AE) -> sona.job
A76: =_xlfn.XLOOKUP(F76,'TFS Details'!F:F,'TFS Details'!D:D) -> BPMS Onboarding | B76: =_xlfn.XLOOKUP(F76,'TFS Details'!F:F,'TFS Details'!A:A) -> Solution Simplification mandatory field updates | C76: =_xlfn.XLOOKUP(F76,'TFS Details'!F:F,'TFS Details'!E:E) -> 4316945 | D76: Shini | E76: As a BPMS User, I should be able to see Solution Simplification marked as compliant if ?PriceOne used for Stage 0/1/2A? and ?Approval Committee Approach Followed? are filled in the solution simplification screen so that the compliance score is updated. | F76: 4279677 | G76: Sakshi | J76: s.namdev.suryawanshi | K76: Yes | N76: Medium | O76: 3 | P76: 1 | Q76: 8 | R76: 6 | S76: 3 | T76: 3 | U76: 1 | V76: 0.7 | W76: Completed | X76: Completed | Y76: Completed | Z76: Completed | AA76: 10 | AB76: 5 | AC76: 3 | AD76: 3 | AE76: 0.5 | AF76: 0.5 | AG76: =_xlfn.XLOOKUP(F76,'TFS Details'!F:F,'TFS Details'!H:H) -> Test Complete | AH76: 3 | AI76: 0 | AJ76: 0 | AK76: 0 | AL76: =SUM(AH76:AK76) -> 3 | AM76: =IF(AH76+AI76=0,0,SUM(AH76:AI76)/AL76) -> 1 | AN76: =IF(AH76=0,0,AH76/(SUM(AH76:AJ76))) -> 1 | AP76: =_xlfn.XLOOKUP(F76,'TFS Details'!F:F,'TFS Details'!I:I) -> CodeCrafters | AQ76: =_xlfn.XLOOKUP(AP76,'TFS Details'!I:I,'TFS Details'!AE:AE) -> sona.job
A77: =_xlfn.XLOOKUP(F77,'TFS Details'!F:F,'TFS Details'!D:D) -> DCSO | B77: =_xlfn.XLOOKUP(F77,'TFS Details'!F:F,'TFS Details'!A:A) -> myISP - Digital DCSO | C77: =_xlfn.XLOOKUP(F77,'TFS Details'!F:F,'TFS Details'!E:E) -> 4278081 | D77: Shini | E77: As a Solution Architect, I want to Generate DCSO for selected SG versions from the SI / IMS Digital DCSO screen, so that I can create accurate staffing overviews for each solution group. | F77: 4281629 | G77: Arun | J77: sagarika.a.singh | K77: Yes | N77: Complex | O77: 10 | P77: 1 | Q77: 10 | R77: 6 | S77: 4 | T77: 10 | U77: 0.45 | V77: 0.45 | W77: Completed | X77: Completed | Y77: Completed | Z77: Completed | AA77: 12 | AB77: 8 | AC77: 6 | AD77: 14 | AE77: 0.6 | AF77: 0.6 | AG77: =_xlfn.XLOOKUP(F77,'TFS Details'!F:F,'TFS Details'!H:H) -> UAT In Test | AH77: 14 | AI77: 0 | AJ77: 0 | AK77: 0 | AL77: =SUM(AH77:AK77) -> 14 | AM77: =IF(AH77+AI77=0,0,SUM(AH77:AI77)/AL77) -> 1 | AN77: =IF(AH77=0,0,AH77/(SUM(AH77:AJ77))) -> 1 | AO77: 4426302 | AP77: =_xlfn.XLOOKUP(F77,'TFS Details'!F:F,'TFS Details'!I:I) -> TechStars | AQ77: =_xlfn.XLOOKUP(AP77,'TFS Details'!I:I,'TFS Details'!AE:AE) -> mohanraj.a.selvaraj
A78: =_xlfn.XLOOKUP(F78,'TFS Details'!F:F,'TFS Details'!D:D) -> BPMS Onboarding | B78: =_xlfn.XLOOKUP(F78,'TFS Details'!F:F,'TFS Details'!A:A) -> Capco Template - Enhancement | C78: =_xlfn.XLOOKUP(F78,'TFS Details'!F:F,'TFS Details'!E:E) -> 4317373 | D78: Shini | E78: As a BPMS SA, I want the Capco template to automatically format revenue numbers with commas | F78: 4309748 | G78: Jeba | K78: No | L78: Capco Template has Mail Functionality So it Can't be automated | M78: Email functionality | O78: 5 | W78: Completed | X78: Completed | Y78: Completed | Z78: Completed | AA78: 35 | AB78: 3 | AC78: 0 | AD78: 3 | AE78: 0.5 | AF78: 0.7 | AG78: =_xlfn.XLOOKUP(F78,'TFS Details'!F:F,'TFS Details'!H:H) -> Test Complete | AH78: 3 | AI78: 0 | AJ78: 0 | AK78: 0 | AL78: =SUM(AH78:AK78) -> 3 | AM78: =IF(AH78+AI78=0,0,SUM(AH78:AI78)/AL78) -> 1 | AN78: =IF(AH78=0,0,AH78/(SUM(AH78:AJ78))) -> 1 | AP78: =_xlfn.XLOOKUP(F78,'TFS Details'!F:F,'TFS Details'!I:I) -> CodeCrafters | AQ78: =_xlfn.XLOOKUP(AP78,'TFS Details'!I:I,'TFS Details'!AE:AE) -> sona.job
A79: =_xlfn.XLOOKUP(F79,'TFS Details'!F:F,'TFS Details'!D:D) -> DCSO | B79: =_xlfn.XLOOKUP(F79,'TFS Details'!F:F,'TFS Details'!A:A) -> myISP - Digital DCSO | C79: =_xlfn.XLOOKUP(F79,'TFS Details'!F:F,'TFS Details'!E:E) -> 4278081 | D79: Shini | E79: As a Solution Architect, I want to land on the Digital DCSO section from last activity tab if user have recently made changes to Digital DCSO for all SGs so that I can generate and manage DCSO files efficiently. | F79: 4311857 | G79: Arun | J79: arun.thangapandian | K79: Yes | N79: Medium | O79: 7 | P79: 1 | Q79: 7 | R79: 4 | S79: 3 | T79: 7 | U79: 0.5 | V79: 0.4 | W79: Completed | X79: Completed | Y79: Completed | Z79: Completed | AA79: 12 | AB79: 5 | AC79: 2 | AD79: 7 | AE79: 0.7 | AF79: 0.4 | AG79: =_xlfn.XLOOKUP(F79,'TFS Details'!F:F,'TFS Details'!H:H) -> UAT In Test | AH79: 7 | AI79: 0 | AJ79: 0 | AK79: 0 | AL79: =SUM(AH79:AK79) -> 7 | AM79: =IF(AH79+AI79=0,0,SUM(AH79:AI79)/AL79) -> 1 | AN79: =IF(AH79=0,0,AH79/(SUM(AH79:AJ79))) -> 1 | AP79: =_xlfn.XLOOKUP(F79,'TFS Details'!F:F,'TFS Details'!I:I) -> NGTransformers | AQ79: =_xlfn.XLOOKUP(AP79,'TFS Details'!I:I,'TFS Details'!AE:AE) -> sowjanya.kari
A80: =_xlfn.XLOOKUP(F80,'TFS Details'!F:F,'TFS Details'!D:D) -> BPMS Onboarding | B80: =_xlfn.XLOOKUP(F80,'TFS Details'!F:F,'TFS Details'!A:A) -> RA BPMS Feedback | C80: =_xlfn.XLOOKUP(F80,'TFS Details'!F:F,'TFS Details'!E:E) -> 4275996 | D80: Shini | E80: As a CXTA and Tfo stakeholder, I want the document upload to be optional in TfO and CXTA tabs so that I can initiate approval stages without being blocked when supporting documents are not yet available. | F80: 4337740 | G80: Mohamed | J80: m.sheik.fusulee.a | K80: Yes | N80: Complex | O80: 1 | P80: 1 | Q80: 8 | R80: 4 | S80: 2 | T80: 6 | U80: 0.6 | V80: 0.6 | W80: Completed | X80: Completed | Y80: Completed | Z80: Completed | AA80: 15 | AB80: 4 | AC80: 8 | AD80: 12 | AE80: 0.4 | AF80: 0.4 | AG80: =_xlfn.XLOOKUP(F80,'TFS Details'!F:F,'TFS Details'!H:H) -> Test Complete | AH80: 12 | AI80: 0 | AJ80: 0 | AK80: 0 | AL80: =SUM(AH80:AK80) -> 12 | AM80: =IF(AH80+AI80=0,0,SUM(AH80:AI80)/AL80) -> 1 | AN80: =IF(AH80=0,0,AH80/(SUM(AH80:AJ80))) -> 1 | AP80: =_xlfn.XLOOKUP(F80,'TFS Details'!F:F,'TFS Details'!I:I) -> BPMSBloggers | AQ80: =_xlfn.XLOOKUP(AP80,'TFS Details'!I:I,'TFS Details'!AE:AE) -> sona.job
A81: =_xlfn.XLOOKUP(F81,'TFS Details'!F:F,'TFS Details'!D:D) -> DCSO | B81: =_xlfn.XLOOKUP(F81,'TFS Details'!F:F,'TFS Details'!A:A) -> myISP - Digital DCSO | C81: =_xlfn.XLOOKUP(F81,'TFS Details'!F:F,'TFS Details'!E:E) -> 4278081 | D81: Shini | E81: As a myISP Solution Architect , I want to access DCSO for all SGs based on roles assigned, so that I can generate, update, publish, and manage DCSO versions, while other roles should have only read‑only access for visibility. | F81: 4341403 | G81: Pavithra | J81: nitish.kumar.prusty | K81: Yes | N81: Complex | O81: 5 | P81: 1 | Q81: 5 | R81: 3 | S81: 2 | T81: 5 | U81: 0.4 | V81: 0.4 | W81: Completed | X81: Completed | Y81: Completed | Z81: Completed | AA81: 16 | AB81: 4 | AC81: 1 | AD81: 5 | AE81: 0.8 | AF81: 0.6 | AG81: =_xlfn.XLOOKUP(F81,'TFS Details'!F:F,'TFS Details'!H:H) -> UAT In Test | AH81: 5 | AI81: 0 | AJ81: 0 | AK81: 0 | AL81: =SUM(AH81:AK81) -> 5 | AM81: =IF(AH81+AI81=0,0,SUM(AH81:AI81)/AL81) -> 1 | AN81: =IF(AH81=0,0,AH81/(SUM(AH81:AJ81))) -> 1 | AO81: bug id : 4438224 (deferred to may release) | AP81: =_xlfn.XLOOKUP(F81,'TFS Details'!F:F,'TFS Details'!I:I) -> TechStars | AQ81: =_xlfn.XLOOKUP(AP81,'TFS Details'!I:I,'TFS Details'!AE:AE) -> mohanraj.a.selvaraj
A82: =_xlfn.XLOOKUP(F82,'TFS Details'!F:F,'TFS Details'!D:D) -> DCSO | B82: =_xlfn.XLOOKUP(F82,'TFS Details'!F:F,'TFS Details'!A:A) -> myISP - Digital DCSO | C82: =_xlfn.XLOOKUP(F82,'TFS Details'!F:F,'TFS Details'!E:E) -> 4278081 | D82: Shini | E82: As a Solution Architect, I want the system to Filter the DCSO line items based on certain conditions , so that the DCSO generated provide accurate results to user. | F82: 4355886 | G82: Shital | K82: No | L82: Validation should be done in the Downloded Excel file | M82: Excel functionality | N82: Medium | W82: Completed | X82: Completed | Y82: Completed | Z82: In Progress | AA82: 20 | AB82: 9 | AC82: 0 | AD82: 9 | AE82: 1 | AF82: 0.98 | AG82: =_xlfn.XLOOKUP(F82,'TFS Details'!F:F,'TFS Details'!H:H) -> UAT In Test | AH82: 9 | AI82: 0 | AJ82: 0 | AK82: 0 | AL82: =SUM(AH82:AK82) -> 9 | AM82: =IF(AH82+AI82=0,0,SUM(AH82:AI82)/AL82) -> 1 | AN82: =IF(AH82=0,0,AH82/(SUM(AH82:AJ82))) -> 1 | AP82: =_xlfn.XLOOKUP(F82,'TFS Details'!F:F,'TFS Details'!I:I) -> TechStars | AQ82: =_xlfn.XLOOKUP(AP82,'TFS Details'!I:I,'TFS Details'!AE:AE) -> mohanraj.a.selvaraj
A83: =_xlfn.XLOOKUP(F83,'TFS Details'!F:F,'TFS Details'!D:D) -> Mobilization Calculator | B83: =_xlfn.XLOOKUP(F83,'TFS Details'!F:F,'TFS Details'!A:A) -> Mobilization - CXTA Calculator : CXTA enhancements | C83: =_xlfn.XLOOKUP(F83,'TFS Details'!F:F,'TFS Details'!E:E) -> 4358815 | D83: Shini | E83: Mobilization CXTA Calculator : As a mySP CXTA user I should be able to see the field CXIL renamed to "Transition Executive" under Execution Preparation so that it is as per Business standards | F83: 4358192 | G83: Lakshmi | J83: lakshmi.e.j | K83: Yes | N83: Simple | O83: 2 | P83: 1 | Q83: 7 | R83: 4 | S83: 1 | T83: 2 | U83: 0.7 | V83: 0.6 | W83: Completed | X83: Completed | Y83: Completed | Z83: Completed | AA83: 8 | AB83: 6 | AC83: 0 | AD83: 3 | AE83: 1 | AF83: 1 | AG83: =_xlfn.XLOOKUP(F83,'TFS Details'!F:F,'TFS Details'!H:H) -> Test Complete | AH83: 6 | AI83: 0 | AJ83: 0 | AK83: 0 | AL83: =SUM(AH83:AK83) -> 6 | AM83: =IF(AH83+AI83=0,0,SUM(AH83:AI83)/AL83) -> 1 | AN83: =IF(AH83=0,0,AH83/(SUM(AH83:AJ83))) -> 1 | AO83: 4412622 | AP83: =_xlfn.XLOOKUP(F83,'TFS Details'!F:F,'TFS Details'!I:I) -> CodeCatalyst | AQ83: =_xlfn.XLOOKUP(AP83,'TFS Details'!I:I,'TFS Details'!AE:AE) -> nityanand.giri
A84: =_xlfn.XLOOKUP(F84,'TFS Details'!F:F,'TFS Details'!D:D) -> Mobilization Calculator | B84: =_xlfn.XLOOKUP(F84,'TFS Details'!F:F,'TFS Details'!A:A) -> Mobilization - CXTA Calculator : CXTA enhancements | C84: =_xlfn.XLOOKUP(F84,'TFS Details'!F:F,'TFS Details'!E:E) -> 4358815 | D84: Shini | E84: Mobilization - CXTA Calculator : As a mySP CXTA user I need to add fields under Deal Details section so that it is as per Business standards | F84: 4358812 | G84: Lakshmi | J84: lakshmi.e.j | K84: Yes | N84: Complex | O84: 5 | P84: 1 | Q84: 7 | R84: 5 | S84: 0 | T84: 5 | U84: 0.8 | V84: 0.8 | W84: Completed | X84: Completed | Y84: Completed | Z84: Completed | AA84: 8 | AB84: 2 | AC84: 10 | AD84: 13 | AE84: 0.4 | AF84: 0.4 | AG84: =_xlfn.XLOOKUP(F84,'TFS Details'!F:F,'TFS Details'!H:H) -> Test Complete | AH84: 13 | AI84: 0 | AJ84: 0 | AK84: 0 | AL84: =SUM(AH84:AK84) -> 13 | AM84: =IF(AH84+AI84=0,0,SUM(AH84:AI84)/AL84) -> 1 | AN84: =IF(AH84=0,0,AH84/(SUM(AH84:AJ84))) -> 1 | AP84: =_xlfn.XLOOKUP(F84,'TFS Details'!F:F,'TFS Details'!I:I) -> CodeCatalyst | AQ84: =_xlfn.XLOOKUP(AP84,'TFS Details'!I:I,'TFS Details'!AE:AE) -> nityanand.giri
A85: =_xlfn.XLOOKUP(F85,'TFS Details'!F:F,'TFS Details'!D:D) -> DCSO | B85: =_xlfn.XLOOKUP(F85,'TFS Details'!F:F,'TFS Details'!A:A) -> myISP - Digital DCSO | C85: =_xlfn.XLOOKUP(F85,'TFS Details'!F:F,'TFS Details'!E:E) -> 4278081 | D85: Shini | E85: As a Solution Architect, I want a new tab for DCSO Versions inside the Digital DCSO for AMS SG , so that I can generate and manage multiple DCSO versions efficiently | F85: 4359566 | G85: Arun | J85: arun.thangapandian | K85: Yes | N85: Simple | O85: 8 | P85: 1 | Q85: 8 | R85: 6 | S85: 2 | T85: 8 | U85: 0.5 | V85: 0.4 | W85: Completed | X85: Completed | Y85: Completed | Z85: Completed | AA85: 12 | AB85: 5 | AC85: 6 | AD85: 11 | AE85: 0.45 | AF85: 0.3 | AG85: =_xlfn.XLOOKUP(F85,'TFS Details'!F:F,'TFS Details'!H:H) -> UAT In Test | AH85: 11 | AI85: 0 | AJ85: 0 | AK85: 0 | AL85: =SUM(AH85:AK85) -> 11 | AM85: =IF(AH85+AI85=0,0,SUM(AH85:AI85)/AL85) -> 1 | AN85: =IF(AH85=0,0,AH85/(SUM(AH85:AJ85))) -> 1 | AO85: 4423576: | AP85: =_xlfn.XLOOKUP(F85,'TFS Details'!F:F,'TFS Details'!I:I) -> TechStars | AQ85: =_xlfn.XLOOKUP(AP85,'TFS Details'!I:I,'TFS Details'!AE:AE) -> mohanraj.a.selvaraj
A86: =_xlfn.XLOOKUP(F86,'TFS Details'!F:F,'TFS Details'!D:D) -> DCSO | B86: =_xlfn.XLOOKUP(F86,'TFS Details'!F:F,'TFS Details'!A:A) -> myISP - Digital DCSO | C86: =_xlfn.XLOOKUP(F86,'TFS Details'!F:F,'TFS Details'!E:E) -> 4278081 | D86: Shini | E86: As a Solution Architect, I want to Generate DCSO for selected SG versions from the AMS Digital DCSO screen, so that I can create accurate staffing overviews for each solution group | F86: 4359567 | G86: Arun | J86: arun.thangapandian | K86: Yes | N86: Complex | O86: 8 | P86: 1 | Q86: 8 | R86: 4 | S86: 4 | T86: 8 | U86: 0.5 | V86: 0.4 | W86: Completed | X86: Completed | Y86: Completed | Z86: Completed | AA86: 11 | AB86: 7 | AC86: 6 | AD86: 13 | AE86: 0.5 | AF86: 0.5 | AG86: =_xlfn.XLOOKUP(F86,'TFS Details'!F:F,'TFS Details'!H:H) -> UAT In Test | AH86: 13 | AI86: 0 | AJ86: 0 | AK86: 0 | AL86: =SUM(AH86:AK86) -> 13 | AM86: =IF(AH86+AI86=0,0,SUM(AH86:AI86)/AL86) -> 1 | AN86: =IF(AH86=0,0,AH86/(SUM(AH86:AJ86))) -> 1 | AO86: 4423576: | AP86: =_xlfn.XLOOKUP(F86,'TFS Details'!F:F,'TFS Details'!I:I) -> TechStars | AQ86: =_xlfn.XLOOKUP(AP86,'TFS Details'!I:I,'TFS Details'!AE:AE) -> mohanraj.a.selvaraj
A87: =_xlfn.XLOOKUP(F87,'TFS Details'!F:F,'TFS Details'!D:D) -> DCSO | B87: =_xlfn.XLOOKUP(F87,'TFS Details'!F:F,'TFS Details'!A:A) -> myISP - Digital DCSO | C87: =_xlfn.XLOOKUP(F87,'TFS Details'!F:F,'TFS Details'!E:E) -> 4278081 | D87: Shini | E87: As a Solution Architect, I want the DCSO grid to dynamically update based on user actions for AMS SG, so that I can view accurate status and perform subsequent actions easily. | F87: 4359568 | G87: Heena | J87: h.kouser | K87: Yes | N87: Complex | O87: 10 | P87: 1 | Q87: 10 | R87: 5 | S87: 5 | T87: 10 | U87: 0.5 | V87: 0.3 | W87: Completed | X87: Completed | Y87: Completed | Z87: In Progress | AA87: 38 | AB87: 4 | AC87: 15 | AD87: 15 | AE87: 0.5 | AF87: 0.4 | AG87: =_xlfn.XLOOKUP(F87,'TFS Details'!F:F,'TFS Details'!H:H) -> UAT In Test | AH87: 13 | AI87: 0 | AJ87: 0 | AK87: 0 | AL87: =SUM(AH87:AK87) -> 13 | AM87: =IF(AH87+AI87=0,0,SUM(AH87:AI87)/AL87) -> 1 | AN87: =IF(AH87=0,0,AH87/(SUM(AH87:AJ87))) -> 1 | AO87: UI bug: 4425268, 4425283(M), 4423855 | AP87: =_xlfn.XLOOKUP(F87,'TFS Details'!F:F,'TFS Details'!I:I) -> TechStars | AQ87: =_xlfn.XLOOKUP(AP87,'TFS Details'!I:I,'TFS Details'!AE:AE) -> mohanraj.a.selvaraj
A88: =_xlfn.XLOOKUP(F88,'TFS Details'!F:F,'TFS Details'!D:D) -> DCSO | B88: =_xlfn.XLOOKUP(F88,'TFS Details'!F:F,'TFS Details'!A:A) -> myISP - Digital DCSO | C88: =_xlfn.XLOOKUP(F88,'TFS Details'!F:F,'TFS Details'!E:E) -> 4278081 | D88: Shini | E88: As a Solution Architect, I want a new tab for DCSO Versions inside the Digital DCSO for SI / IMS SG , so that I can generate and manage multiple DCSO versions efficiently | F88: 4359569 | G88: Heena | J88: h.kouser | K88: Yes | O88: 5 | P88: 1 | Q88: 5 | R88: 5 | S88: 5 | T88: 5 | U88: 0.4 | V88: 0.3 | W88: Completed | X88: Completed | Y88: Completed | Z88: Completed | AA88: 20 | AB88: 2 | AC88: 5 | AD88: 5 | AE88: 0.4 | AF88: 0.3 | AG88: =_xlfn.XLOOKUP(F88,'TFS Details'!F:F,'TFS Details'!H:H) -> UAT In Test | AH88: 5 | AI88: 0 | AJ88: 0 | AK88: 0 | AL88: =SUM(AH88:AK88) -> 5 | AM88: =IF(AH88+AI88=0,0,SUM(AH88:AI88)/AL88) -> 1 | AN88: =IF(AH88=0,0,AH88/(SUM(AH88:AJ88))) -> 1 | AO88: 4443655 Closed | AP88: =_xlfn.XLOOKUP(F88,'TFS Details'!F:F,'TFS Details'!I:I) -> TechStars | AQ88: =_xlfn.XLOOKUP(AP88,'TFS Details'!I:I,'TFS Details'!AE:AE) -> mohanraj.a.selvaraj
A89: =_xlfn.XLOOKUP(F89,'TFS Details'!F:F,'TFS Details'!D:D) -> DCSO | B89: =_xlfn.XLOOKUP(F89,'TFS Details'!F:F,'TFS Details'!A:A) -> myISP - Digital DCSO | C89: =_xlfn.XLOOKUP(F89,'TFS Details'!F:F,'TFS Details'!E:E) -> 4278081 | D89: Shini | E89: As a Solution Architect, I want to view and manage generated DCSOs in a grid for AMS SG, so that I can track status and perform actions | F89: 4359570 | G89: Heena | J89: nitish.kumar.prusty | K89: Yes | N89: Complex | O89: 6 | P89: 1 | Q89: 6 | R89: 5 | S89: 1 | T89: 6 | U89: 0.7 | V89: 0.7 | W89: Completed | X89: Completed | Y89: Completed | Z89: In Progress | AA89: 50 | AB89: 2 | AC89: 7 | AD89: 7 | AE89: 0.6 | AF89: 0.4 | AG89: =_xlfn.XLOOKUP(F89,'TFS Details'!F:F,'TFS Details'!H:H) -> UAT In Test | AH89: 6 | AI89: 0 | AJ89: 0 | AK89: 0 | AL89: =SUM(AH89:AK89) -> 6 | AM89: =IF(AH89+AI89=0,0,SUM(AH89:AI89)/AL89) -> 1 | AN89: =IF(AH89=0,0,AH89/(SUM(AH89:AJ89))) -> 1 | AO89: 4423511 Closed | AP89: =_xlfn.XLOOKUP(F89,'TFS Details'!F:F,'TFS Details'!I:I) -> TechStars | AQ89: =_xlfn.XLOOKUP(AP89,'TFS Details'!I:I,'TFS Details'!AE:AE) -> mohanraj.a.selvaraj
A90: =_xlfn.XLOOKUP(F90,'TFS Details'!F:F,'TFS Details'!D:D) -> DCSO | B90: =_xlfn.XLOOKUP(F90,'TFS Details'!F:F,'TFS Details'!A:A) -> myISP - Digital DCSO | C90: =_xlfn.XLOOKUP(F90,'TFS Details'!F:F,'TFS Details'!E:E) -> 4278081 | D90: Shini | E90: As a Solution Architect, I want to upload the DCSO template back into MyISP for IMS/ SI / AMS SG so that I can validate changes and sync with staffing and pricing tools. | F90: 4359571 | G90: Heena | K90: No | L90: Excel Validation and more functionality is covered.(Temparing/ adding additon row to excel is not possible in automation) | M90: Excel functionality | W90: Completed | X90: Completed | Y90: Completed | Z90: In Progress | AA90: 40 | AB90: 1 | AC90: 24 | AD90: 24 | AE90: 0.4 | AF90: 0.3 | AG90: =_xlfn.XLOOKUP(F90,'TFS Details'!F:F,'TFS Details'!H:H) -> UAT In Test | AH90: 24 | AI90: 0 | AJ90: 0 | AK90: 0 | AL90: =SUM(AH90:AK90) -> 24 | AM90: =IF(AH90+AI90=0,0,SUM(AH90:AI90)/AL90) -> 1 | AN90: =IF(AH90=0,0,AH90/(SUM(AH90:AJ90))) -> 1 | AO90: 4443431, 4443521, 4443476, 4443655 Closed- 4427354, 4429664(H),4429516,4428859 | AP90: =_xlfn.XLOOKUP(F90,'TFS Details'!F:F,'TFS Details'!I:I) -> TechStars | AQ90: =_xlfn.XLOOKUP(AP90,'TFS Details'!I:I,'TFS Details'!AE:AE) -> mohanraj.a.selvaraj
A91: =_xlfn.XLOOKUP(F91,'TFS Details'!F:F,'TFS Details'!D:D) -> DCSO | B91: =_xlfn.XLOOKUP(F91,'TFS Details'!F:F,'TFS Details'!A:A) -> myISP - Digital DCSO | C91: =_xlfn.XLOOKUP(F91,'TFS Details'!F:F,'TFS Details'!E:E) -> 4278081 | D91: Shini | E91: As a Solution Architect, I want to download the generated DCSO file for AMS SG so that I can review and update staffing details offline before uploading | F91: 4359572 | G91: Heena | K91: No | L91: Automation not feasible because the application checks integrity of the exported Excel file.If the file is modified and uploaded again through automation, the system detects it as a tampered file and rejects it. | M91: Excel functionality | N91: Complex | W91: Completed | X91: Completed | Y91: Completed | Z91: In Progress | AA91: 10 | AB91: 2 | AC91: 6 | AD91: 6 | AE91: 0.4 | AF91: 0.2 | AG91: =_xlfn.XLOOKUP(F91,'TFS Details'!F:F,'TFS Details'!H:H) -> UAT In Test | AH91: 6 | AI91: 0 | AJ91: 0 | AK91: 0 | AL91: =SUM(AH91:AK91) -> 6 | AM91: =IF(AH91+AI91=0,0,SUM(AH91:AI91)/AL91) -> 1 | AN91: =IF(AH91=0,0,AH91/(SUM(AH91:AJ91))) -> 1 | AO91: 4429278, 4428859(Duplicate to 4427541), 4429516(H) | AP91: =_xlfn.XLOOKUP(F91,'TFS Details'!F:F,'TFS Details'!I:I) -> TechStars | AQ91: =_xlfn.XLOOKUP(AP91,'TFS Details'!I:I,'TFS Details'!AE:AE) -> mohanraj.a.selvaraj
A92: =_xlfn.XLOOKUP(F92,'TFS Details'!F:F,'TFS Details'!D:D) -> DCSO | B92: =_xlfn.XLOOKUP(F92,'TFS Details'!F:F,'TFS Details'!A:A) -> myISP - Digital DCSO | C92: =_xlfn.XLOOKUP(F92,'TFS Details'!F:F,'TFS Details'!E:E) -> 4278081 | D92: Shini | E92: As a Solution Architect, I want to land on the Digital DCSO section when I click on Digital DCSO from the Opportunity workflow for AMS SG so that I can generate and manage DCSO files efficiently. | F92: 4359573 | G92: Shital | J92: s.manmit.vanarase | K92: Yes | N92: SImple | O92: 6 | P92: 1 | Q92: 6 | R92: 6 | S92: 0 | T92: 6 | U92: 0.86 | V92: 0.7 | W92: Completed | X92: Completed | Y92: Completed | Z92: Completed | AA92: 15 | AB92: 6 | AC92: 7 | AD92: 7 | AE92: 0.86 | AF92: 0.86 | AG92: =_xlfn.XLOOKUP(F92,'TFS Details'!F:F,'TFS Details'!H:H) -> UAT In Test | AH92: 7 | AI92: 0 | AJ92: 0 | AK92: 0 | AL92: =SUM(AH92:AK92) -> 7 | AM92: =IF(AH92+AI92=0,0,SUM(AH92:AI92)/AL92) -> 1 | AN92: =IF(AH92=0,0,AH92/(SUM(AH92:AJ92))) -> 1 | AO92: 4422932-Deffered | AP92: =_xlfn.XLOOKUP(F92,'TFS Details'!F:F,'TFS Details'!I:I) -> TechWarriors | AQ92: =_xlfn.XLOOKUP(AP92,'TFS Details'!I:I,'TFS Details'!AE:AE) -> sowjanya.kari
A93: =_xlfn.XLOOKUP(F93,'TFS Details'!F:F,'TFS Details'!D:D) -> DCSO | B93: =_xlfn.XLOOKUP(F93,'TFS Details'!F:F,'TFS Details'!A:A) -> myISP - Digital DCSO | C93: =_xlfn.XLOOKUP(F93,'TFS Details'!F:F,'TFS Details'!E:E) -> 4278081 | D93: Shini | E93: As a Solution Architect, I want to land on the Digital DCSO section when I click on Digital DCSO from the Opportunity workflow for SI SG so that I can generate and manage DCSO files efficiently. | F93: 4359574 | G93: Shital | J93: s.manmit.vanarase | K93: Yes | N93: SImple | O93: 6 | P93: 1 | Q93: 6 | R93: 6 | S93: 0 | T93: 6 | U93: 0.86 | V93: 0.7 | W93: Completed | X93: Completed | Y93: Completed | Z93: Completed | AA93: 15 | AB93: 6 | AC93: 7 | AD93: 7 | AE93: 0.86 | AF93: 0.86 | AG93: =_xlfn.XLOOKUP(F93,'TFS Details'!F:F,'TFS Details'!H:H) -> UAT In Test | AH93: 7 | AI93: 0 | AJ93: 0 | AK93: 0 | AL93: =SUM(AH93:AK93) -> 7 | AM93: =IF(AH93+AI93=0,0,SUM(AH93:AI93)/AL93) -> 1 | AN93: =IF(AH93=0,0,AH93/(SUM(AH93:AJ93))) -> 1 | AP93: =_xlfn.XLOOKUP(F93,'TFS Details'!F:F,'TFS Details'!I:I) -> TechWarriors | AQ93: =_xlfn.XLOOKUP(AP93,'TFS Details'!I:I,'TFS Details'!AE:AE) -> sowjanya.kari
A94: =_xlfn.XLOOKUP(F94,'TFS Details'!F:F,'TFS Details'!D:D) -> DCSO | B94: =_xlfn.XLOOKUP(F94,'TFS Details'!F:F,'TFS Details'!A:A) -> myISP - Digital DCSO | C94: =_xlfn.XLOOKUP(F94,'TFS Details'!F:F,'TFS Details'!E:E) -> 4278081 | D94: Shini | E94: As a Solution Architect, I want to land on the Digital DCSO section when I click on Digital DCSO from the Opportunity workflow for IMS SG so that I can generate and manage DCSO files efficiently. | F94: 4359575 | G94: Shital | J94: s.manmit.vanarase | K94: Yes | N94: SImple | O94: 6 | P94: 1 | Q94: 6 | R94: 6 | S94: 0 | T94: 6 | U94: 0.86 | V94: 0.7 | W94: Completed | X94: Completed | Y94: Completed | Z94: Completed | AA94: 15 | AB94: 6 | AC94: 7 | AD94: 7 | AE94: 0.86 | AF94: 0.86 | AG94: =_xlfn.XLOOKUP(F94,'TFS Details'!F:F,'TFS Details'!H:H) -> UAT In Test | AH94: 7 | AI94: 0 | AJ94: 0 | AK94: 0 | AL94: =SUM(AH94:AK94) -> 7 | AM94: =IF(AH94+AI94=0,0,SUM(AH94:AI94)/AL94) -> 1 | AN94: =IF(AH94=0,0,AH94/(SUM(AH94:AJ94))) -> 1 | AP94: =_xlfn.XLOOKUP(F94,'TFS Details'!F:F,'TFS Details'!I:I) -> TechWarriors | AQ94: =_xlfn.XLOOKUP(AP94,'TFS Details'!I:I,'TFS Details'!AE:AE) -> sowjanya.kari
A95: =_xlfn.XLOOKUP(F95,'TFS Details'!F:F,'TFS Details'!D:D) -> DCSO | B95: =_xlfn.XLOOKUP(F95,'TFS Details'!F:F,'TFS Details'!A:A) -> myISP - Digital DCSO | C95: =_xlfn.XLOOKUP(F95,'TFS Details'!F:F,'TFS Details'!E:E) -> 4278081 | D95: Shini | E95: As a Solution Architect, I want to add a new section under Digital Documentation named Digital DCSO for AMS in the opportunity workflow, so that I can manage DCSO-related functionalities in one place. | F95: 4359576 | G95: Shital | J95: sagarika.a.singh | K95: Yes | N95: SImple | O95: 3 | P95: 1 | Q95: 3 | R95: 3 | S95: 0 | T95: 3 | U95: 1 | V95: 1 | W95: Completed | X95: Completed | Y95: Completed | Z95: Completed | AA95: 10 | AB95: 2 | AC95: 3 | AD95: 3 | AE95: 0.66 | AF95: 0.66 | AG95: =_xlfn.XLOOKUP(F95,'TFS Details'!F:F,'TFS Details'!H:H) -> UAT In Test | AH95: 3 | AI95: 0 | AJ95: 0 | AK95: 0 | AL95: =SUM(AH95:AK95) -> 3 | AM95: =IF(AH95+AI95=0,0,SUM(AH95:AI95)/AL95) -> 1 | AN95: =IF(AH95=0,0,AH95/(SUM(AH95:AJ95))) -> 1 | AP95: =_xlfn.XLOOKUP(F95,'TFS Details'!F:F,'TFS Details'!I:I) -> TechWarriors | AQ95: =_xlfn.XLOOKUP(AP95,'TFS Details'!I:I,'TFS Details'!AE:AE) -> sowjanya.kari
A96: =_xlfn.XLOOKUP(F96,'TFS Details'!F:F,'TFS Details'!D:D) -> DCSO | B96: =_xlfn.XLOOKUP(F96,'TFS Details'!F:F,'TFS Details'!A:A) -> myISP - Digital DCSO | C96: =_xlfn.XLOOKUP(F96,'TFS Details'!F:F,'TFS Details'!E:E) -> 4278081 | D96: Shini | E96: As a Solution Architect, I want to add a new section Digital DCSO inside the Digital Documentation for AMS SG, so that I can manage DCSO-related functionalities. | F96: 4359577 | G96: Shital | J96: sagarika.a.singh | K96: Yes | N96: SImple | O96: 11 | P96: 1 | Q96: 11 | R96: 6 | S96: 5 | T96: 11 | U96: 0.6 | V96: 0.6 | W96: Completed | X96: Completed | Y96: Completed | Z96: Completed | AA96: 20 | AB96: 8 | AC96: 11 | AD96: 11 | AE96: 0.72 | AF96: 0.72 | AG96: =_xlfn.XLOOKUP(F96,'TFS Details'!F:F,'TFS Details'!H:H) -> UAT In Test | AH96: 11 | AI96: 0 | AJ96: 0 | AK96: 0 | AL96: =SUM(AH96:AK96) -> 11 | AM96: =IF(AH96+AI96=0,0,SUM(AH96:AI96)/AL96) -> 1 | AN96: =IF(AH96=0,0,AH96/(SUM(AH96:AJ96))) -> 1 | AP96: =_xlfn.XLOOKUP(F96,'TFS Details'!F:F,'TFS Details'!I:I) -> Pirates | AQ96: =_xlfn.XLOOKUP(AP96,'TFS Details'!I:I,'TFS Details'!AE:AE) -> pandidurai.ks
A97: =_xlfn.XLOOKUP(F97,'TFS Details'!F:F,'TFS Details'!D:D) -> DCSO | B97: =_xlfn.XLOOKUP(F97,'TFS Details'!F:F,'TFS Details'!A:A) -> myISP - Digital DCSO | C97: =_xlfn.XLOOKUP(F97,'TFS Details'!F:F,'TFS Details'!E:E) -> 4278081 | D97: Shini | E97: As a Solution Architect, I want to add a new section under Digital Documentation named Digital DCSO for SI in the opportunity workflow, so that I can manage DCSO-related functionalities in one place. | F97: 4359578 | G97: Lakshmi | J97: lakshmi.e.j | K97: Yes | N97: Simple | O97: 3 | P97: 1 | Q97: 3 | R97: 2 | S97: 1 | T97: 3 | U97: 0.8 | V97: 0.7 | W97: Completed | X97: Completed | Y97: Completed | Z97: Completed | AA97: 10 | AB97: 5 | AC97: 0 | AD97: 3 | AE97: 1 | AF97: 1 | AG97: =_xlfn.XLOOKUP(F97,'TFS Details'!F:F,'TFS Details'!H:H) -> UAT In Test | AH97: 5 | AI97: 0 | AJ97: 0 | AK97: 0 | AL97: =SUM(AH97:AK97) -> 5 | AM97: =IF(AH97+AI97=0,0,SUM(AH97:AI97)/AL97) -> 1 | AN97: =IF(AH97=0,0,AH97/(SUM(AH97:AJ97))) -> 1 | AP97: =_xlfn.XLOOKUP(F97,'TFS Details'!F:F,'TFS Details'!I:I) -> TechWarriors | AQ97: =_xlfn.XLOOKUP(AP97,'TFS Details'!I:I,'TFS Details'!AE:AE) -> sowjanya.kari
A98: =_xlfn.XLOOKUP(F98,'TFS Details'!F:F,'TFS Details'!D:D) -> DCSO | B98: =_xlfn.XLOOKUP(F98,'TFS Details'!F:F,'TFS Details'!A:A) -> myISP - Digital DCSO | C98: =_xlfn.XLOOKUP(F98,'TFS Details'!F:F,'TFS Details'!E:E) -> 4278081 | D98: Shini | E98: As a Solution Architect, I want to add a new section Digital DCSO inside the Digital Documentation for SI SG, so that I can manage DCSO-related functionalities. | F98: 4359579 | G98: Lakshmi | J98: lakshmi.e.j | K98: Yes | N98: Medium | O98: 5 | P98: 1 | Q98: 5 | R98: 3 | S98: 2 | T98: 5 | U98: 0.7 | V98: 0.7 | W98: Completed | X98: Completed | Y98: Completed | Z98: Completed | AA98: 10 | AB98: 2 | AC98: 6 | AD98: 8 | AE98: 0.4 | AF98: 0.4 | AG98: =_xlfn.XLOOKUP(F98,'TFS Details'!F:F,'TFS Details'!H:H) -> UAT In Test | AH98: 8 | AI98: 0 | AJ98: 0 | AK98: 0 | AL98: =SUM(AH98:AK98) -> 8 | AM98: =IF(AH98+AI98=0,0,SUM(AH98:AI98)/AL98) -> 1 | AN98: =IF(AH98=0,0,AH98/(SUM(AH98:AJ98))) -> 1 | AP98: =_xlfn.XLOOKUP(F98,'TFS Details'!F:F,'TFS Details'!I:I) -> Pirates | AQ98: =_xlfn.XLOOKUP(AP98,'TFS Details'!I:I,'TFS Details'!AE:AE) -> pandidurai.ks
A99: =_xlfn.XLOOKUP(F99,'TFS Details'!F:F,'TFS Details'!D:D) -> DCSO | B99: =_xlfn.XLOOKUP(F99,'TFS Details'!F:F,'TFS Details'!A:A) -> myISP - Digital DCSO | C99: =_xlfn.XLOOKUP(F99,'TFS Details'!F:F,'TFS Details'!E:E) -> 4278081 | D99: Shini | E99: As a Solution Architect, I want to add a new section under Digital Documentation named Digital DCSO for IMS in the opportunity workflow, so that I can manage DCSO-related functionalities in one place. | F99: 4359580 | G99: Lakshmi | J99: lakshmi.e.j | K99: Yes | N99: Simple | O99: 3 | P99: 1 | Q99: 3 | R99: 2 | S99: 1 | T99: 3 | U99: 0.8 | V99: 0.7 | W99: Completed | X99: Completed | Y99: Completed | Z99: Completed | AA99: 10 | AB99: 5 | AC99: 0 | AD99: 3 | AE99: 1 | AF99: 1 | AG99: =_xlfn.XLOOKUP(F99,'TFS Details'!F:F,'TFS Details'!H:H) -> UAT In Test | AH99: 5 | AI99: 0 | AJ99: 0 | AK99: 0 | AL99: =SUM(AH99:AK99) -> 5 | AM99: =IF(AH99+AI99=0,0,SUM(AH99:AI99)/AL99) -> 1 | AN99: =IF(AH99=0,0,AH99/(SUM(AH99:AJ99))) -> 1 | AP99: =_xlfn.XLOOKUP(F99,'TFS Details'!F:F,'TFS Details'!I:I) -> TechWarriors | AQ99: =_xlfn.XLOOKUP(AP99,'TFS Details'!I:I,'TFS Details'!AE:AE) -> sowjanya.kari
A100: =_xlfn.XLOOKUP(F100,'TFS Details'!F:F,'TFS Details'!D:D) -> DCSO | B100: =_xlfn.XLOOKUP(F100,'TFS Details'!F:F,'TFS Details'!A:A) -> myISP - Digital DCSO | C100: =_xlfn.XLOOKUP(F100,'TFS Details'!F:F,'TFS Details'!E:E) -> 4278081 | D100: Shini | E100: As a Solution Architect, I want to add a new section Digital DCSO inside the Digital Documentation for IMS SG, so that I can manage DCSO-related functionalities. | F100: 4359581 | G100: Lakshmi | J100: lakshmi.e.j | K100: Yes | N100: Medium | O100: 5 | P100: 1 | Q100: 5 | R100: 4 | S100: 1 | T100: 5 | U100: 0.7 | V100: 0.65 | W100: Completed | X100: Completed | Y100: Completed | Z100: Completed | AA100: 10 | AB100: 2 | AC100: 6 | AD100: 8 | AE100: 0.4 | AF100: 0.4 | AG100: =_xlfn.XLOOKUP(F100,'TFS Details'!F:F,'TFS Details'!H:H) -> UAT In Test | AH100: 8 | AI100: 0 | AJ100: 0 | AK100: 0 | AL100: =SUM(AH100:AK100) -> 8 | AM100: =IF(AH100+AI100=0,0,SUM(AH100:AI100)/AL100) -> 1 | AN100: =IF(AH100=0,0,AH100/(SUM(AH100:AJ100))) -> 1 | AP100: =_xlfn.XLOOKUP(F100,'TFS Details'!F:F,'TFS Details'!I:I) -> Pirates | AQ100: =_xlfn.XLOOKUP(AP100,'TFS Details'!I:I,'TFS Details'!AE:AE) -> pandidurai.ks
...

Sheet Automation pocs
A1: Leads | B1: Functional POC to work with automation SME | C1: Automation POC
A2: Pirtheebaa | B2: Janardhan.veluri Saranya.datla n.selvakumar | C2: Kamali & Ashish | D2: 1. Maintainence of regression automated cases and running for each rls 2. Maintainence of insprint automated cases and running for each rls 3. From the P1 manual regression cases - we have to analyze and automate whatever possible 4. Code merge, head less execution and pipeline execution
A3: Himanshu | B3: logapriya.govindaraj k.p.palanisamy | C3: Sarthak
A4: Devika | B4: kristapati.v.reddy
A5: Anand | B5: k.tamilzharasu | C5: Ashish/pujitha/Suchitha/nathiya
A6: Raji | B6: shivaprasad.malekar
A7: Jaya | B7: Abhijit.a.nandi/sriram.a.karthikeyan | C7: Sanjana/Riya
A8: Kavi | B8: bhavana.pamidi/sathya.senthilkumar | C8: Ashish/Ruchitha
A9: Hajara/Leena | B9: rose.benedict and ritwik.sathishmohan | C9: Surabhi
A10: Nandini | B10: naga.v.pachipulusu r.maheen.abu.backer vadde.bindu | C10: Ruchitha

Sheet TFS Details
A1: Parent Title | B1: mySP Initiative | C1: Sub Initiative | D1: TextVerification | E1: Parent | F1: ID | G1: Title | H1: State | I1: Node Name | J1: Testing POC | K1: Planned for PT Date | L1: Actual PT Date | M1: Planned UAT Date | N1: Actual UAT Date | O1: Assigned To | P1: Production Deployment Date | Q1: Story Points | R1: Original Estimate | S1: Priority | T1: ETA | U1: UT Results Attached | V1: Code Review Completed | W1: Created By | X1: Created Date | Y1: Tags | Z1: Area Path | AA1: Iteration Path | AB1: Plan | AC1: Remaining | AD1: TextVerification1 | AE1: ExternalRef ID
A2: AMS SCA MVP2 March 28th Release Scope | B2: Rapid Soln | C2: GenAI | D2: AMS Solution Configuration Agent | E2: 4318876 | F2: 4330638 | G2: As a myISP AMS SCA Agent user, I want to configure multiple cost detail rows and use a clear and reliable profile/group name matching approach so that I can efficiently maintain solution standard cost configurations. | H2: UAT In Test | I2: agentcrafters | J2: Damodaran, J. <j.damodaran@accenture.com> | K2: 46087.229 | L2: 46091.901 | M2: 46091.021 | N2: 46092.91 | O2: Panchal, Dhwani <dhwani.panchal@accenture.com> | P2: 46109.229 | Q2: 1.5 | S2: 2 | U2: Yes | V2: Yes | W2: Pradhan, Kiran <kiran.pradhan@accenture.com> | X2: 46041.812 | Y2: Parallel UAT; SSA - SCA (MVP2) | Z2: AutomationProcess_29697\mySPRapidSolutioning\agentcrafters | AA2: AutomationProcess_29697\mySolutionPlanner | AD2: AMS Solution flow | AE2: shwetha.shriyan
A3: AMS SCA MVP2 March 28th Release Scope | B3: Rapid Soln | C3: GenAI | D3: AMS Solution Configuration Agent | E3: 4318876 | F3: 4351206 | G3: As an AMS SCA agent user, I want to download the EID template, import a Named Resource Report (NRR), and include profiles into the Active tab so that profiles are created efficiently without manual entry. | H3: UAT In Test | I3: agentcrafters | J3: Damodaran, J. <j.damodaran@accenture.com> | K3: 46085.229 | L3: 46087.229 | M3: 46091.021 | N3: 46094.684 | O3: Panchal, Dhwani <dhwani.panchal@accenture.com> | P3: 46109.229 | Q3: 1.25 | S3: 2 | U3: Yes | V3: Yes | W3: Rani Agurla, Sowmya <sowmya.rani.agurla@accenture.com> | X3: 46055.93 | Y3: Parallel UAT; SSA - SCA (MVP2) | Z3: AutomationProcess_29697\mySPRapidSolutioning\agentcrafters | AA3: AutomationProcess_29697\mySolutionPlannerIntegratedSolutionPlatform | AD3: AMS Solution flow | AE3: shwetha.shriyan
A4: AMS SCA MVP2 March 28th Release Scope | B4: Rapid Soln | C4: GenAI | D4: AMS Solution Configuration Agent | E4: 4318876 | F4: 4351207 | G4: As a AMS SCA User I want to provide Generative AI details to an AI agent in natural language So that the Gen AI configuration is automatically saved to my solution version Without manually filling out the Gen AI screen fields | H4: UAT In Test | I4: agentcrafters | J4: Damodaran, J. <j.damodaran@accenture.com> | K4: 46085.229 | L4: 46086.861 | M4: 46091.021 | N4: 46090.822 | O4: Panchal, Dhwani <dhwani.panchal@accenture.com> | P4: 46109.229 | Q4: 0.75 | S4: 2 | U4: Yes | V4: Yes | W4: Rani Agurla, Sowmya <sowmya.rani.agurla@accenture.com> | X4: 46055.934 | Y4: Parallel UAT; SSA - SCA (MVP2) | Z4: AutomationProcess_29697\mySPRapidSolutioning\agentcrafters | AA4: AutomationProcess_29697\mySolutionPlannerIntegratedSolutionPlatform | AD4: AMS Solution flow | AE4: shwetha.shriyan
A5: AMS SCA MVP2 March 28th Release Scope | B5: Rapid Soln | C5: GenAI | D5: AMS Solution Configuration Agent | E5: 4318876 | F5: 4351271 | G5: As an AMS SCA Agent User, I want to configure Rate Cards via Agent‑based Excel Import/Export, so that rate card details can be configured without manual UI navigation. | H5: UAT In Test | I5: agentcrafters | J5: Damodaran, J. <j.damodaran@accenture.com> | K5: 46085.229 | L5: 46092.062 | M5: 46088.021 | N5: 46101.028 | O5: Panchal, Dhwani <dhwani.panchal@accenture.com> | P5: 46109.229 | Q5: 2.5 | S5: 2 | U5: Yes | V5: Yes | W5: Rani Agurla, Sowmya <sowmya.rani.agurla@accenture.com> | X5: 46055.976 | Y5: Parallel UAT; SSA - SCA (MVP2) | Z5: AutomationProcess_29697\mySPRapidSolutioning\agentcrafters | AA5: AutomationProcess_29697\mySolutionPlannerIntegratedSolutionPlatform | AD5: AMS Solution flow | AE5: shwetha.shriyan
A6: AMS SCA MVP2 March 28th Release Scope | B6: Rapid Soln | C6: GenAI | D6: AMS Solution Configuration Agent | E6: 4318876 | F6: 4351286 | G6: As a AMS SCA Agent user, I want to map and unmap, Delete, Copy, add Groups functionalities via agent, so that I can configure & do the actions via agnet by providing the prompt. | H6: UAT In Test | I6: agentcrafters | J6: Damodaran, J. <j.damodaran@accenture.com> | K6: 46085.229 | L6: 46087.011 | M6: 46088.021 | N6: 46091.957 | O6: Panchal, Dhwani <dhwani.panchal@accenture.com> | P6: 46109.229 | Q6: 1.25 | S6: 2 | U6: Yes | V6: Yes | W6: Rani Agurla, Sowmya <sowmya.rani.agurla@accenture.com> | X6: 46055.984 | Y6: parallel testing; SSA - SCA (MVP2) | Z6: AutomationProcess_29697\mySPRapidSolutioning\agentcrafters | AA6: AutomationProcess_29697\mySolutionPlannerIntegratedSolutionPlatform | AD6: AMS Solution flow | AE6: shwetha.shriyan
A7: AMS SCA MVP2 March 28th Release Scope | B7: Rapid Soln | C7: GenAI | D7: AMS Solution Configuration Agent | E7: 4318876 | F7: 4351288 | G7: As a myISP AMS SCA Agent user, I want to update the Costing screen PMO Tax configuration functionality in agent, so that I can perform PMO Tax configuration via agent without navigating UI screens. | H7: UAT In Test | I7: agentcrafters | J7: Damodaran, J. <j.damodaran@accenture.com> | K7: 46085.229 | L7: 46092.859 | M7: 46088.021 | N7: 46094.99 | O7: Panchal, Dhwani <dhwani.panchal@accenture.com> | P7: 46109.229 | Q7: 1.25 | S7: 2 | U7: Yes | V7: Yes | W7: Rani Agurla, Sowmya <sowmya.rani.agurla@accenture.com> | X7: 46055.987 | Y7: SSA - SCA (MVP2) | Z7: AutomationProcess_29697\mySPRapidSolutioning\agentcrafters | AA7: AutomationProcess_29697\mySolutionPlannerIntegratedSolutionPlatform | AD7: AMS Solution flow | AE7: shwetha.shriyan
A8: AMS SCA MVP2 March 28th Release Scope | B8: Rapid Soln | C8: GenAI | D8: AMS Solution Configuration Agent | E8: 4318876 | F8: 4353128 | G8: As a myISP AMS SCA Agent user, I want the Agent to automatically correct any mismatch between Pyramid totals and Ramp?Up totals during version creation, so that version creation and OCP generation complete successfully without manual intervention. | H8: UAT In Test | I8: agentcrafters | J8: Damodaran, J. <j.damodaran@accenture.com> | K8: 46085.229 | L8: 46086.86 | M8: 46088.021 | N8: 46099.731 | O8: Panchal, Dhwani <dhwani.panchal@accenture.com> | P8: 46109.229 | Q8: 1 | S8: 2 | U8: Yes | V8: Yes | W8: Pradhan, Kiran <kiran.pradhan@accenture.com> | X8: 46056.716 | Y8: Parallel UAT; SSA - SCA (MVP2) | Z8: AutomationProcess_29697\mySPRapidSolutioning\agentcrafters | AA8: AutomationProcess_29697\mySolutionPlannerIntegratedSolutionPlatform | AD8: AMS Solution flow | AE8: shwetha.shriyan
A9: AMS SCA MVP2 March 28th Release Scope | B9: Rapid Soln | C9: GenAI | D9: AMS Solution Configuration Agent | E9: 4318876 | F9: 4354556 | G9: As a myISP AMS Solution Configuration Agent user I want to sync Solution Version data to MSDA from both OCP simulation and Pricing Factor screen So that Multi-Service Deal Analytics has the latest pricing and deal information for reporting and analysis | H9: UAT In Test | I9: agentcrafters | J9: Damodaran, J. <j.damodaran@accenture.com> | K9: 46085.229 | L9: 46085.753 | M9: 46088.021 | N9: 46099.994 | O9: Panchal, Dhwani <dhwani.panchal@accenture.com> | P9: 46109.229 | Q9: 0.75 | S9: 2 | U9: Yes | V9: Yes | W9: Pradhan, Kiran <kiran.pradhan@accenture.com> | X9: 46057.727 | Y9: SSA - SCA (MVP2) | Z9: AutomationProcess_29697\mySPRapidSolutioning\agentcrafters | AA9: AutomationProcess_29697\mySolutionPlannerIntegratedSolutionPlatform | AD9: AMS Solution flow | AE9: shwetha.shriyan
A10: AMS SCA MVP2 March 28th Release Scope | B10: Rapid Soln | C10: GenAI | D10: AMS Solution Configuration Agent | E10: 4318876 | F10: 4355494 | G10: As a AMS SCA User I want the Solution Configuration Agent to configure Deal?Wide Year?on?Year Custom Margin based on my Prompt instruction, So that I can update pricing inputs without navigating through the UI. | H10: UAT In Test | I10: agentcrafters | J10: Damodaran, J. <j.damodaran@accenture.com> | K10: 46085.229 | L10: 46085.753 | M10: 46091.021 | N10: 46091.941 | O10: Panchal, Dhwani <dhwani.panchal@accenture.com> | P10: 46109.229 | Q10: 1.25 | S10: 2 | U10: Yes | V10: Yes | W10: Rani Agurla, Sowmya <sowmya.rani.agurla@accenture.com> | X10: 46057.949 | Y10: Parallel UAT; SSA - SCA (MVP2) | Z10: AutomationProcess_29697\mySPRapidSolutioning\agentcrafters | AA10: AutomationProcess_29697\mySolutionPlannerIntegratedSolutionPlatform | AD10: AMS Solution flow | AE10: shwetha.shriyan
A11: AMS SCA MVP2 March 28th Release Scope | B11: Rapid Soln | C11: GenAI | D11: AMS Solution Configuration Agent | E11: 4318876 | F11: 4361594 | G11: As a myISP AMS Solution Configuration Agent I want the staffing screen to automatically ensure that resources are allocated in pairs for both Transition and Service Delivery phases . | H11: UAT In Test | I11: agentcrafters | J11: Damodaran, J. <j.damodaran@accenture.com> | K11: 46085.229 | L11: 46084.049 | M11: 46088.021 | N11: 46091.859 | O11: Panchal, Dhwani <dhwani.panchal@accenture.com> | P11: 46109.229 | Q11: 1 | S11: 2 | U11: Yes | V11: Yes | W11: Pradhan, Kiran <kiran.pradhan@accenture.com> | X11: 46063.79 | Y11: Parallel UAT; SSA - SCA (MVP2) | Z11: AutomationProcess_29697\mySPRapidSolutioning\agentcrafters | AA11: AutomationProcess_29697\mySolutionPlannerIntegratedSolutionPlatform | AD11: AMS Solution flow | AE11: shwetha.shriyan
A12: AMS SCA MVP2 March 28th Release Scope | B12: Rapid Soln | C12: GenAI | D12: AMS Solution Configuration Agent | E12: 4318876 | F12: 4381785 | G12: As an AMS SCA User, I want the AI agent to populate Load Type correctly for India profiles | H12: UAT In Test | I12: agentcrafters | J12: Damodaran, J. <j.damodaran@accenture.com> | K12: 46085.229 | L12: 46084.979 | M12: 46088.021 | N12: 46087.972 | O12: Panchal, Dhwani <dhwani.panchal@accenture.com> | P12: 46109.229 | Q12: 1 | S12: 2 | U12: Yes | V12: Yes | W12: Pradhan, Kiran <kiran.pradhan@accenture.com> | X12: 46073.569 | Y12: Parallel UAT; SSA - SCA (MVP2) | Z12: AutomationProcess_29697\mySPRapidSolutioning\agentcrafters | AA12: AutomationProcess_29697\mySolutionPlannerIntegratedSolutionPlatform | AD12: AMS Solution flow | AE12: shwetha.shriyan
A13: AMS SCA MVP2 March 28th Release Scope | B13: Rapid Soln | C13: GenAI | D13: AMS Solution Configuration Agent | E13: 4318876 | F13: 4385949 | G13: As a AMS SCA User , I want the Contract Offering to automatically populate based on the selected AMS Service Type | H13: UAT In Test | I13: agentcrafters | J13: Damodaran, J. <j.damodaran@accenture.com> | K13: 46087.229 | L13: 46090.717 | M13: 46091.021 | N13: 46091.797 | O13: Panchal, Dhwani <dhwani.panchal@accenture.com> | P13: 46109.229 | Q13: 1 | S13: 2 | U13: Yes | V13: Yes | W13: Pradhan, Kiran <kiran.pradhan@accenture.com> | X13: 46073.667 | Y13: Parallel UAT; SSA - SCA (MVP2) | Z13: AutomationProcess_29697\mySPRapidSolutioning\agentcrafters | AA13: AutomationProcess_29697\mySolutionPlannerIntegratedSolutionPlatform | AD13: AMS Solution flow | AE13: shwetha.shriyan
... A16: AMS MVP1 – Refactoring Scope for Mar 28 (Profiles, Groups, Group‑wide Pricing, Other Cost, Planner Agent) | B16: Rapid Soln | C16: GenAI | D16: AMS Refactoring Scope | E16: 4390112 | F16: 4390301 | G16: As an AMS SCA agent user, I want to configure solution parameters and country?based profiles via the agent so that parameters and profiles are saved correctly without manual UI updates. | H16: UAT In Test | I16: agentcrafters | J16: Damodaran, J. <j.damodaran@accenture.com> | K16: 46092.979 | L16: 46085.708 | M16: 46094.062 | N16: 46093.944 | O16: Panchal, Dhwani <dhwani.panchal@accenture.com> | P16: 46109.229 | Q16: 1.5 | S16: 2 | U16: Yes | V16: NA | W16: Rani Agurla, Sowmya <sowmya.rani.agurla@accenture.com> | X16: 46077.73 | Y16: Parallel UAT; SSA - SCA (MVP2) | Z16: AutomationProcess_29697\mySPRapidSolutioning\agentcrafters | AA16: AutomationProcess_29697\mySolutionPlannerIntegratedSolutionPlatform | AD16: AMS SCA MVP1 | AE16: shwetha.shriyan
A17: AMS MVP1 – Refactoring Scope for Mar 28 (Profiles, Groups, Group‑wide Pricing, Other Cost, Planner Agent) | B17: Rapid Soln | C17: GenAI | D17: AMS Refactoring Scope | E17: 4390112 | F17: 4390312 | G17: As an AMS SCA agent user, I want to create groups via the agent so that group details are saved correctly without manual UI updates. | H17: UAT In Test | I17: agentcrafters | J17: Damodaran, J. <j.damodaran@accenture.com> | K17: 46092.979 | L17: 46085.708 | M17: 46094.062 | N17: 46092.229 | O17: Panchal, Dhwani <dhwani.panchal@accenture.com> | P17: 46109.229 | Q17: 1.25 | S17: 2 | V17: NA | W17: Rani Agurla, Sowmya <sowmya.rani.agurla@accenture.com> | X17: 46077.74 | Y17: Parallel UAT; SSA - SCA (MVP2) | Z17: AutomationProcess_29697\mySPRapidSolutioning\agentcrafters | AA17: AutomationProcess_29697\mySolutionPlannerIntegratedSolutionPlatform | AD17: AMS SCA MVP1 | AE17: shwetha.shriyan
A18: AMS MVP1 – Refactoring Scope for Mar 28 (Profiles, Groups, Group‑wide Pricing, Other Cost, Planner Agent) | B18: Rapid Soln | C18: GenAI | D18: AMS Refactoring Scope | E18: 4390112 | F18: 4390744 | G18: As an AMS SCA agent user, I want to configure Other Cost via the agent so that other cost details are saved correctly without manual UI updates. | H18: UAT In Test | I18: agentcrafters | J18: Damodaran, J. <j.damodaran@accenture.com> | K18: 46092.979 | L18: 46085.229 | M18: 46094.062 | N18: 46092.988 | O18: Panchal, Dhwani <dhwani.panchal@accenture.com> | P18: 46109.229 | Q18: 1.25 | S18: 2 | U18: Yes | V18: NA | W18: Rani Agurla, Sowmya <sowmya.rani.agurla@accenture.com> | X18: 46077.895 | Y18: Parallel UAT; SSA - SCA (MVP2) | Z18: AutomationProcess_29697\mySPRapidSolutioning\agentcrafters | AA18: AutomationProcess_29697\mySolutionPlannerIntegratedSolutionPlatform | AD18: AMS SCA MVP1 | AE18: shwetha.shriyan
A19: AMS MVP1 – Refactoring Scope for Mar 28 (Profiles, Groups, Group‑wide Pricing, Other Cost, Planner Agent) | B19: Rapid Soln | C19: GenAI | D19: AMS Refactoring Scope | E19: 4390112 | F19: 4390789 | G19: As an AMS SCA agent user, I want the planner agent to map my request to the correct sequence of agents so that solution actions are executed in the right order based on defined orchestration rules. | H19: UAT In Test | I19: agentcrafters | J19: Damodaran, J. <j.damodaran@accenture.com> | K19: 46092.979 | L19: 46090.856 | M19: 46094.062 | N19: 46093.017 | O19: Panchal, Dhwani <dhwani.panchal@accenture.com> | P19: 46109.229 | Q19: 2.1 | S19: 2 | U19: Yes | V19: NA | W19: Rani Agurla, Sowmya <sowmya.rani.agurla@accenture.com> | X19: 46077.939 | Y19: Parallel UAT; SSA - SCA (MVP2) | Z19: AutomationProcess_29697\mySPRapidSolutioning\agentcrafters | AA19: AutomationProcess_29697\mySolutionPlannerIntegratedSolutionPlatform | AD19: AMS SCA MVP1 | AE19: shwetha.shriyan
A20: AMS SCA MVP2 March 28th Release Scope | B20: Rapid Soln | C20: GenAI | D20: AMS Solution Configuration Agent | E20: 4318876 | F20: 4399124 | G20: As an AMS SCA User, I want an Agentic AI to capture and populate Gen AI configuration details using a natural-language prompt, so that the Gen AI tab is auto-filled and saved to my solution version without manual data entry. | H20: UAT In Test | I20: agentcrafters | J20: Damodaran, J. <j.damodaran@accenture.com> | K20: 46090.229 | L20: 46090.87 | M20: 46092.021 | N20: 46091.915 | O20: Panchal, Dhwani <dhwani.panchal@accenture.com> | P20: 46109.229 | Q20: 1.25 | S20: 2 | U20: Yes | V20: Yes | W20: Pradhan, Kiran <kiran.pradhan@accenture.com> | X20: 46083.683 | Y20: CCB Approved; Change in Requirement; Development Request; Parallel UAT | Z20: AutomationProcess_29697\mySPRapidSolutioning\agentcrafters | AA20: AutomationProcess_29697\mySolutionPlannerIntegratedSolutionPlatform | AD20: AMS Solution flow | AE20: shwetha.shriyan
A21: ESA role rename to Market Maker ESA | B21: Platform Consolidation | C21: DFD | D21: DFD | E21: 4384974 | F21: 4385147 | G21: As a DFD requestor, instead of ESA, I should get Market Maker ESA role name in DFD once the assignment is done from either PLD or Define team | H21: UAT In Test | I21: BackDoorGuardians | J21: Jain, Himanshu <himanshu.m.jain@accenture.com> | K21: 46091.229 | L21: 46090.683 | M21: 46094.229 | N21: 46097.661 | O21: Sudheer, Nadupuru <nadupuru.sudheer@accenture.com> | P21: 46109.229 | Q21: 3 | S21: 2 | U21: Yes | V21: Yes | W21: Vijay Deshpande, Prajakta <p.vijay.deshpande@accenture.com> | X21: 46073.646 | Z21: AutomationProcess_29697\BackDoorGuardians | AA21: AutomationProcess_29697\mySolutionPlannerIntegratedSolutionPlatform | AD21: DFD Enhancement | AE21: sona.job
A22: Advisory SA - PLD cancellation and Status sync across DFD, PLD and Define Team | B22: Platform Consolidation | C22: DFD | D22: DFD | E22: 4371748 | F22: 4373596 | G22: [Advisory SA - Song] As a DFD user, I should be able to receive the Advisory SA assignment/cancellation details from PLD, so the status should be in sync | H22: UAT In Test | I22: BackDoorGuardians | J22: Jain, Himanshu <himanshu.m.jain@accenture.com> | K22: 46091.979 | L22: 46085.978 | M22: 46098.229 | N22: 46097.876 | O22: Sudheer, Nadupuru <nadupuru.sudheer@accenture.com> | P22: 46109.229 | Q22: 5 | S22: 2 | U22: Yes | V22: Yes | W22: Vijay Deshpande, Prajakta <p.vijay.deshpande@accenture.com> | X22: 46072.069 | Z22: AutomationProcess_29697\BackDoorGuardians | AA22: AutomationProcess_29697\mySolutionPlannerIntegratedSolutionPlatform | AD22: DFD - Advisory SA | AE22: sona.job
A23: [DFD Enhancement] Routing logic update for SA and SME types and Copyright year update | B23: Platform Consolidation | C23: DFD | D23: DFD | E23: 4328940 | F23: 4381777 | G23: As a DFD requestor, I should get GenAI specific mails when GenAI/LLM in Scope is selected as Yes in SA requests | H23: Test Complete | I23: BackDoorGuardians | J23: Jain, Himanshu <himanshu.m.jain@accenture.com> | K23: 46086.979 | L23: 46086.981 | M23: 46092.229 | O23: Goriparthi, Anusha <anusha.goriparthi@accenture.com> | P23: 46109.229 | Q23: 3 | S23: 2 | U23: Yes | V23: Yes | W23: Vijay Deshpande, Prajakta <p.vijay.deshpande@accenture.com> | X23: 46073.561 | Y23: UAT Testing Not Required | Z23: AutomationProcess_29697\BackDoorGuardians | AA23: AutomationProcess_29697\mySolutionPlannerIntegratedSolutionPlatform | AD23: DFD - GenAI routing | AE23: sona.job
A24: [DFD Enhancement] Routing logic update for SA and SME types and Copyright year update | B24: Platform Consolidation | C24: DFD | D24: DFD | E24: 4328940 | F24: 4350042 | G24: As a DFD requestor, I should get the updated year as 2001-2026 in all DFD mails | H24: Test Complete | I24: BackDoorGuardians | J24: Jain, Himanshu <himanshu.m.jain@accenture.com> | K24: 46087.979 | L24: 46087.977 | M24: 46094.229 | O24: Goriparthi, Anusha <anusha.goriparthi@accenture.com> | P24: 46109.229 | Q24: 5 | S24: 2 | U24: Yes | V24: Yes | W24: Vijay Deshpande, Prajakta <p.vijay.deshpande@accenture.com> | X24: 46055.677 | Y24: Mar28th_DFDStories; Po Input; UAT Testing Not Required | Z24: AutomationProcess_29697\BackDoorGuardians | AA24: AutomationProcess_29697\mySolutionPlannerIntegratedSolutionPlatform | AD24: DFD - Mail | AE24: sona.job
A25: [DFD Enhancement] Routing logic update for SA and SME types and Copyright year update | B25: Platform Consolidation | C25: DFD | D25: DFD | E25: 4328940 | F25: 4328943 | G25: As a DFD user, I should get updated routing logic for SC.GlobalNetwork.Platform.SAP.SA DL | H25: Test Complete | I25: BackDoorGuardians | J25: Jain, Himanshu <himanshu.m.jain@accenture.com> | K25: 46090.979 | L25: 46090.999 | M25: 46094.229 | O25: Ishwar Jaxanni, Manjunath <m.ishwar.jaxanni@accenture.com> | P25: 46109.229 | Q25: 5 | S25: 2 | U25: Yes | V25: Yes | W25: Vijay Deshpande, Prajakta <p.vijay.deshpande@accenture.com> | X25: 46041.456 | Y25: Mar28th_DFDStories; UAT Testing Not Required | Z25: AutomationProcess_29697\BackDoorGuardians | AA25: AutomationProcess_29697\mySolutionPlannerIntegratedSolutionPlatform | AD25: DFD Routing | AE25: sona.job
A26: [DFD Enhancement] Routing logic update for SA and SME types and Copyright year update | B26: Platform Consolidation | C26: DFD | D26: DFD | E26: 4328940 | F26: 4342214 | G26: As a DFD user, I should get, GenWiz_sa_assignment@accenture.com DL added in Automation and Gen AI SME routing logic | H26: Test Complete | I26: BackDoorGuardians | J26: Jain, Himanshu <himanshu.m.jain@accenture.com> | K26: 46086.979 | L26: 46086.968 | M26: 46091.229 | O26: Goriparthi, Anusha <anusha.goriparthi@accenture.com> | P26: 46109.229 | Q26: 3 | S26: 2 | U26: Yes | V26: Yes | W26: Vijay Deshpande, Prajakta <p.vijay.deshpande@accenture.com> | X26: 46050.787 | Y26: Mar28th_DFDStories; UAT Testing Not Required | Z26: AutomationProcess_29697\BackDoorGuardians | AA26: AutomationProcess_29697\mySolutionPlannerIntegratedSolutionPlatform | AD26: DFD - Routing | AE26: sona.job
A27: Is this a Global Capability Centre (GCC) or Captive opportunity? field changes and sync between DFD and Define Team | B27: Platform Consolidation | C27: DFD | D27: DFD | E27: 4048583 | F27: 4316367 | G27: As a DFD Requestor, I should get the updated routing logic for Captive DLs based on the campaign name in Technology SA request | H27: Test Complete | I27: BackDoorGuardians | J27: Jain, Himanshu <himanshu.m.jain@accenture.com> | K27: 46091.979 | L27: 46091.999 | M27: 46094.229 | O27: Ishwar Jaxanni, Manjunath <m.ishwar.jaxanni@accenture.com> | P27: 46109.229 | Q27: 3 | S27: 3 | U27: Yes | V27: Yes | W27: Vijay Deshpande, Prajakta <p.vijay.deshpande@accenture.com> | X27: 46029.734 | Y27: Mar28th_DFDStories; UAT Testing Not Required | Z27: AutomationProcess_29697\BackDoorGuardians | AA27: AutomationProcess_29697\mySolutionPlannerIntegratedSolutionPlatform | AD27: DFD - GCC field update | AE27: sona.job
A28: RA BPMS Feedback | B28: Platform Consolidation | C28: NextGen | D28: BPMS Onboarding | E28: 4275996 | F28: 4337740 | G28: As a CXTA and Tfo stakeholder, I want the document upload to be optional in TfO and CXTA tabs so that I can initiate approval stages without being blocked when supporting documents are not yet available. | H28: Test Complete | I28: BPMSBloggers | J28: Vv, Shini <shini.vv@accenture.com> | K28: 46085.229 | L28: 46085.833 | M28: 46090.229 | N28: 46093.848 | O28: Panchal, Dhwani <dhwani.panchal@accenture.com> | P28: 46109.229 | Q28: 3 | S28: 2 | U28: Yes | V28: Yes | W28: Thangaraj, Dinesh <dinesh.thangaraj@accenture.com> | X28: 46045.706 | Y28: Parallel UAT; PO inputs | Z28: AutomationProcess_29697\mySPIntegratedSolutionPlatform\myISP_BPMS\BPMSBloggers | AA28: AutomationProcess_29697 | AD28: Reviewer Approver | AE28: sona.job
A29: TfO Internal Approvals: Enable auto‑approval when lead does not approve the approval request | B29: Platform Consolidation | C29: myISP_BPMS | D29: BPMS Onboarding | E29: 4368357 | F29: 4368356 | G29: As a PMO or Super User, I want the ability to set an approver as Auto Approver so that approvals across all stages can be automatically processed without manual intervention | H29: Test Complete | I29: BPMSBloggers | J29: Vv, Shini <shini.vv@accenture.com> | K29: 46080.229 | L29: 46083.797 | M29: 46091.021 | N29: 46091.042 | O29: Panchal, Dhwani <dhwani.panchal@accenture.com> | P29: 46109.229 | Q29: 1 | S29: 2 | U29: Yes | V29: Yes | W29: Thangaraj, Dinesh <dinesh.thangaraj@accenture.com> | X29: 46067.806 | Y29: BPMS RA; Parallel UAT | Z29: AutomationProcess_29697\mySPIntegratedSolutionPlatform\myISP_BPMS\BPMSBloggers | AA29: AutomationProcess_29697 | AD29: Reviewer Approver | AE29: sona.job
A30: Custom meeting slots for BPMS meeting scheduler | B30: Platform Consolidation | C30: myISP_BPMS | D30: BPMS Onboarding | E30: 4368359 | F30: 4368358 | G30: As a BPMS SA , I want to select a ?Custom? meeting slot and provide start and end times so that I can request meetings outside predefined time options and have them synchronized with the Outlook meeting invite. | H30: Test Complete | I30: BPMSBloggers | J30: Vv, Shini <shini.vv@accenture.com> | K30: 46084.229 | L30: 46084.81 | M30: 46087.229 | N30: 46088.055 | O30: Panchal, Dhwani <dhwani.panchal@accenture.com> | P30: 46109.229 | Q30: 3 | S30: 2 | U30: Yes | V30: Yes | W30: Thangaraj, Dinesh <dinesh.thangaraj@accenture.com> | X30: 46067.815 | Y30: BPMS RA; Parallel UAT | Z30: AutomationProcess_29697\mySPIntegratedSolutionPlatform\myISP_BPMS\BPMSBloggers | AA30: AutomationProcess_29697 | AD30: Reviewer Approver | AE30: sona.job
A31: VMM out of scope status and risk and compliance auto insert block for Foxtrot Q1 = No | B31: Platform Consolidation | C31: myISP_BPMS | D31: BPMS Onboarding | E31: 4368361 | F31: 4368360 | G31: As a BPMS SA/PMO, I want the system to prevent auto?inserting the Risk & Compliance approval request when Foxtrot Q1 is answered as NO, so that incorrect approval requests do not progress further in the workflow. | H31: Test Complete | I31: BPMSBloggers | J31: Vv, Shini <shini.vv@accenture.com> | K31: 46087.229 | L31: 46084.82 | M31: 46093.229 | N31: 46094.042 | O31: Panchal, Dhwani <dhwani.panchal@accenture.com> | P31: 46109.229 | Q31: 3 | S31: 2 | U31: Yes | V31: Yes | W31: Thangaraj, Dinesh <dinesh.thangaraj@accenture.com> | X31: 46067.828 | Y31: BPMS RA; Parallel UAT | Z31: AutomationProcess_29697\mySPIntegratedSolutionPlatform\myISP_BPMS\BPMSBloggers | AA31: AutomationProcess_29697 | AD31: Reviewer Approver | AE31: sona.job
A32: Diel hierarchy - rolled up revenue | B32: Platform Consolidation | C32: myISP_BPMS | D32: BPMS Onboarding | E32: 4378908 | F32: 4376360 | G32: As a BPMS stakeholder, I want the auto?assignment logic during auto insert to use rolled?up revenue instead of BPMS Net Revenue so that final approvers are selected accurately based on the full deal value. | H32: Test Complete | I32: BPMSBloggers | J32: Vv, Shini <shini.vv@accenture.com> | K32: 46086.229 | L32: 46086.68 | M32: 46093.229 | N32: 46093.849 | O32: Panchal, Dhwani <dhwani.panchal@accenture.com> | P32: 46109.229 | Q32: 1 | S32: 2 | U32: Yes | V32: Yes | W32: Thangaraj, Dinesh <dinesh.thangaraj@accenture.com> | X32: 46072.617 | Y32: BPMS RA; Parallel UAT | Z32: AutomationProcess_29697\mySPIntegratedSolutionPlatform\myISP_BPMS\BPMSBloggers | AA32: AutomationProcess_29697 | AD32: Reviewer Approver | AE32: sona.job
A33: March Release DLC Revamp - Gen AI | B33: Platform Consolidation | C33: GenAI | D33: GEN AI | E33: 4260380 | F33: 4387310 | G33: [GEN AI - DLC] - Ingestion of DLC Documents for Deal Level Canvas | H33: UAT In Test | I33: Code Mavin | J33: Ayyubkhan, Hajara <hajara.ayyubkhan@accenture.com> | K33: 46094.625 | L33: 46097.696 | M33: 46094.229 | N33: 46098.667 | O33: Jaiswal, Shivani <shivani.b.jaiswal@accenture.com> | P33: 46109.229 | Q33: 3 | S33: 2 | U33: Yes | V33: Yes | W33: Kumar, Akash <akash.ce.kumar@accenture.com> | X33: 46076.543 | Y33: GEN AI; LLM | Z33: AutomationProcess_29697\myISP_DSP\Code Mavin | AA33: AutomationProcess_29697\mySolutionPlannerIntegratedSolutionPlatform | AD33: GEN AI - DLC | AE33: n.d.krishnakumar
A34: March Release DLC Revamp - Gen AI | B34: Platform Consolidation | C34: GenAI | D34: GEN AI | E34: 4260380 | F34: 4387348 | G34: [GEN AI - DLC] - File Type Flagging to Control DLC and HSP Processing | H34: UAT In Test | I34: Code Mavin | J34: Ayyubkhan, Hajara <hajara.ayyubkhan@accenture.com> | K34: 46090.229 | L34: 46093.639 | M34: 46094.229 | N34: 46098.669 | O34: Jaiswal, Shivani <shivani.b.jaiswal@accenture.com> | P34: 46109.229 | Q34: 3 | S34: 2 | U34: Yes | V34: Yes | W34: Kumar, Akash <akash.ce.kumar@accenture.com> | X34: 46076.562 | Y34: GEN AI; LLM | Z34: AutomationProcess_29697\myISP_DSP\Code Mavin | AA34: AutomationProcess_29697\mySolutionPlannerIntegratedSolutionPlatform | AD34: GEN AI - DLC | AE34: n.d.krishnakumar
A35: March Release DLC Revamp - Gen AI | B35: Platform Consolidation | C35: GenAI | D35: GEN AI | E35: 4260380 | F35: 4387360 | G35: [GEN AI - DLC] - Generate Recommendations from Similar Past Opportunities | H35: UAT In Test | I35: Code Mavin | J35: Ayyubkhan, Hajara <hajara.ayyubkhan@accenture.com> | K35: 46094.229 | L35: 46097.696 | M35: 46094.062 | N35: 46098.674 | O35: Jaiswal, Shivani <shivani.b.jaiswal@accenture.com> | P35: 46109.229 | Q35: 5 | S35: 2 | U35: Yes | V35: Yes | W35: Kumar, Akash <akash.ce.kumar@accenture.com> | X35: 46076.57 | Y35: GEN AI; LLM | Z35: AutomationProcess_29697\myISP_DSP\Code Mavin | AA35: AutomationProcess_29697\mySolutionPlannerIntegratedSolutionPlatform | AD35: GEN AI - DLC | AE35: n.d.krishnakumar
A36: March Release DLC Revamp - Gen AI | B36: Platform Consolidation | C36: GenAI | D36: GEN AI | E36: 4260380 | F36: 4387679 | G36: [GEN AI - DLC] - Pre-Processing of DLC Documents for Nudge-Based Recommendations | H36: UAT In Test | I36: Code Mavin | J36: Ayyubkhan, Hajara <hajara.ayyubkhan@accenture.com> | K36: 46094.229 | L36: 46097.694 | M36: 46093.229 | N36: 46098.674 | O36: Jaiswal, Shivani <shivani.b.jaiswal@accenture.com> | P36: 46109.229 | Q36: 5 | S36: 2 | U36: Yes | V36: Yes | W36: Kumar, Akash <akash.ce.kumar@accenture.com> | X36: 46076.775 | Y36: GEN AI; LLM | Z36: AutomationProcess_29697\myISP_DSP\Code Mavin | AA36: AutomationProcess_29697\mySolutionPlannerIntegratedSolutionPlatform | AD36: GEN AI - DLC | AE36: n.d.krishnakumar
A37: GEN AI March Enhancements | B37: Platform Consolidation | C37: GenAI | D37: GEN AI | E37: 4319932 | F37: 4370867 | G37: [GEN AI - RFP Synthesis] New nudges to be added in Scope section under RFP Synthesis for Security, IX, Ops and S&C Services. | H37: UAT In Test | I37: Code Mavin | J37: Das, Leena <leena.a.das@accenture.com> | K37: 46090.229 | L37: 46085.229 | M37: 46094.229 | N37: 46094.583 | O37: Jaiswal, Shivani <shivani.b.jaiswal@accenture.com> | P37: 46109.229 | Q37: 3 | S37: 2 | U37: Yes | V37: Yes | W37: Venkata Durgarao, Adabala <a.venkata.durgarao@accenture.com> | X37: 46070.427 | Y37: parallel testing; Parallel UAT; RFP | Z37: AutomationProcess_29697\myISP_DSP\Code Mavin | AA37: AutomationProcess_29697\mySolutionPlannerIntegratedSolutionPlatform | AD37: RFP Synthesis | AE37: n.d.krishnakumar
A38: GEN AI March Enhancements | B38: Platform Consolidation | C38: GenAI | D38: GEN AI | E38: 4319932 | F38: 4371414 | G38: [GEN AI - RFP Synthesis] New nudges to be visible in the output documents for RFP Synthesis for Security , Ops, IX and S&C services. | H38: UAT In Test | I38: Code Mavin | J38: Das, Leena <leena.a.das@accenture.com> | K38: 46090.229 | L38: 46085.229 | M38: 46091.229 | N38: 46091.658 | O38: Jaiswal, Shivani <shivani.b.jaiswal@accenture.com> | P38: 46109.229 | Q38: 5 | S38: 2 | U38: Yes | V38: Yes | W38: Venkata Durgarao, Adabala <a.venkata.durgarao@accenture.com> | X38: 46070.498 | Y38: parallel testing; Parallel UAT; RFP | Z38: AutomationProcess_29697\myISP_DSP\Code Mavin | AA38: AutomationProcess_29697\mySolutionPlannerIntegratedSolutionPlatform | AD38: RFP Synthesis | AE38: n.d.krishnakumar
A39: GEN AI March Enhancements | B39: Platform Consolidation | C39: GenAI | D39: GEN AI | E39: 4319932 | F39: 4311485 | G39: [GEN AI - RFP Synthesis] Business Value section from Opportunity Context Refinement with updated prompts as same as Technology service for Security, S&C, Ops and IX services. | H39: UAT In Test | I39: Code Mavin | J39: Das, Leena <leena.a.das@accenture.com> | K39: 46091.229 | L39: 46087.037 | M39: 46094.062 | N39: 46093.708 | O39: Jaiswal, Shivani <shivani.b.jaiswal@accenture.com> | P39: 46109.229 | Q39: 5 | S39: 2 | U39: Yes | V39: Yes | W39: Venkata Durgarao, Adabala <a.venkata.durgarao@accenture.com> | X39: 46027.386 | Y39: parallel testing; Parallel UAT; RFP | Z39: AutomationProcess_29697\myISP_DSP\Code Mavin | AA39: AutomationProcess_29697\mySolutionPlannerIntegratedSolutionPlatform | AD39: RFP Synthesis | AE39: n.d.krishnakumar
... A50: March Release DLC Revamp - Gen AI | B50: Platform Consolidation | C50: GenAI | D50: Gen AI | E50: 4260380 | F50: 4267715 | G50: [Gen AI - DLC] - As a myISP user, I should be able to generate a contextual response from the top 5 opportunities filtered by given criteria so that SA can select one opportunity, under Recommendation From Past Solution. | H50: UAT In Test | I50: Code Mavin | J50: Das, Leena <leena.a.das@accenture.com> | K50: 46097.229 | L50: 46095.229 | M50: 46094.229 | N50: 46097.229 | O50: Jaiswal, Shivani <shivani.b.jaiswal@accenture.com> | P50: 46109.229 | Q50: 5 | S50: 2 | U50: Yes | V50: Yes | W50: Verma, Sarita <sarita.verma@accenture.com> | X50: 45993.761 | Y50: DLC; GenAI_DLC_Revamp; March 28th myISP; Parallel UAT | Z50: AutomationProcess_29697\myISP_DSP\Code Mavin | AA50: AutomationProcess_29697\mySolutionPlannerIntegratedSolutionPlatform | AD50: GEN AI - DLC | AE50: n.d.krishnakumar
A51: Mobilization - CXTA Calculator : CXTA enhancements | B51: V2V | C51: Calculator | D51: Mobilization Calculator | E51: 4358815 | F51: 4358192 | G51: Mobilization CXTA Calculator : As a mySP CXTA user I should be able to see the field CXIL renamed to "Transition Executive" under Execution Preparation so that it is as per Business standards | H51: Test Complete | I51: CodeCatalyst | J51: Vv, Shini <shini.vv@accenture.com> | K51: 46087.938 | L51: 46086.926 | M51: 46097.229 | N51: 46097.905 | O51: Panchal, Dhwani <dhwani.panchal@accenture.com> | P51: 46109.229 | Q51: 3 | S51: 2 | U51: Yes | V51: Yes | W51: Mohan, Vindhiya <vindhiya.mohan@accenture.com> | X51: 46062.642 | Z51: AutomationProcess_29697\mySPVisionToValue\CodeCatalyst | AA51: AutomationProcess_29697\Backlog | AD51: BPMS - CXTA | AE51: nityanand.giri
A52: Mobilization - CXTA Calculator : CXTA enhancements | B52: V2V | C52: Calculator | D52: Mobilization Calculator | E52: 4358815 | F52: 4358812 | G52: Mobilization CXTA Calculator : As a mySP CXTA user I need to add fields under Deal Details section so that it is as per Business standards | H52: Test Complete | I52: CodeCatalyst | J52: Vv, Shini <shini.vv@accenture.com> | K52: 46092.938 | L52: 46091.713 | M52: 46097.229 | N52: 46097.906 | O52: Panchal, Dhwani <dhwani.panchal@accenture.com> | P52: 46109.229 | Q52: 8 | S52: 2 | U52: Yes | V52: Yes | W52: Mohan, Vindhiya <vindhiya.mohan@accenture.com> | X52: 46063.031 | Z52: AutomationProcess_29697\mySPVisionToValue\CodeCatalyst | AA52: AutomationProcess_29697\Backlog | AD52: BPMS - CXTA | AE52: nityanand.giri
A53: Value Shaping –Enhancements | B53: V2V | C53: V2V | D53: Value Shaping | E53: 4330994 | F53: 4364543 | G53: Value Shaping - As a myISP User - Configurator V2V - I want to access the Review Approvals tile in read-only mode and navigate using the fixed breadcrumb path so that I can maintain workflow continuity. | H53: Test Complete | I53: CodeCrafters | J53: Krishnan, Pirtheebaa <pirtheebaa.krishnan@accenture.com> | K53: 46091.229 | L53: 46087.033 | M53: 46097.229 | N53: 46095.001 | O53: Rama Naidu Mutyala, V. <v.rama.naidu.mutyala@accenture.com> | P53: 46109.229 | Q53: 1 | S53: 2 | U53: Yes | V53: Yes | W53: Pandey, Ansh <ansh.pandey@accenture.com> | X53: 46065.497 | Z53: AutomationProcess_29697\mySPIntegratedSolutionPlatform\CodeCrafters | AA53: AutomationProcess_29697 | AD53: Value Shaping - Configurator Link | AE53: sona.job
A54: March Release NextGen Enhancements | B54: Platform Consolidation | C54: NextGen | D54: ESA to Market Maker ESA | E54: 4365826 | F54: 4371399 | G54: Impact Check: As a Myisp user, I want the role "Enterprise SA" to be renamed to "Market Maker ESA" in myISP So that the role name clearly reflects the Market Make ESA in Solution Review & Approvals and Reporting & Compliance screens | H54: UAT In Test | I54: CodeCrafters | J54: Krishnan, Pirtheebaa <pirtheebaa.krishnan@accenture.com> | K54: 46085.229 | L54: 46085.229 | M54: 46090.229 | N54: 46091.008 | O54: Ravindra Yadav, Niraj <niraj.ravindra.yadav@accenture.com> | P54: 46109.229 | Q54: 1 | S54: 2 | U54: Yes | V54: Yes | W54: Verma, Sarita <sarita.verma@accenture.com> | X54: 46070.489 | Y54: March 28th myISP | Z54: AutomationProcess_29697\mySPIntegratedSolutionPlatform\CodeCrafters | AA54: AutomationProcess_29697\mySolutionPlannerIntegratedSolutionPlatform\R52 | AD54: Role Rename | AE54: sona.job
A55: Enterprise SA should have Read–Write access to the Reporting & Compliance module | B55: Platform Consolidation | C55: myISP_BPMS | D55: BPMS Onboarding | E55: 4387610 | F55: 4372114 | G55: As a Enterprise SA, I should be able to have Read-Write access to the Reporting & Compliance module (Maturity Index, Due Diligence, Solution Simplification) so that I can update compliance information for my solutions. | H55: Test Complete | I55: CodeCrafters | J55: Vv, Shini <shini.vv@accenture.com> | K55: 46080.229 | L55: 46087.229 | M55: 46091.021 | N55: 46092.685 | O55: Panchal, Dhwani <dhwani.panchal@accenture.com> | P55: 46109.229 | Q55: 1 | S55: 2 | U55: Yes | V55: Yes | W55: Rajendra Anikhindi, Akshata <a.rajendra.anikhindi@accenture.com> | X55: 46071.447 | Y55: BPMS; Parallel UAT | Z55: AutomationProcess_29697\mySPIntegratedSolutionPlatform\CodeCrafters | AA55: AutomationProcess_29697\mySolutionPlannerIntegratedSolutionPlatform | AD55: ESA access | AE55: sona.job
A56: Diel hierarchy - rolled up revenue | B56: Platform Consolidation | C56: myISP_BPMS | D56: BPMS Onboarding | E56: 4378908 | F56: 4367436 | G56: As a myIntegrated Solution Planner (myISP) user, I want BPMS Net Revenue to be rolled up across and used consistently wherever BPMS Net Revenue is referenced, so that the CCI Delta against the target margin (27%) is calculated accurately | H56: Test Complete | I56: CodeCrafters | J56: Vv, Shini <shini.vv@accenture.com> | K56: 46092.229 | L56: 46086.927 | M56: 46095.062 | N56: 46094.713 | O56: Panchal, Dhwani <dhwani.panchal@accenture.com> | P56: 46109.229 | Q56: 1 | S56: 2 | U56: Yes | V56: Yes | W56: Saraogi, Aaditi <aaditi.saraogi@accenture.com> | X56: 46066.644 | Y56: 46109 | Z56: AutomationProcess_29697\mySPIntegratedSolutionPlatform\CodeCrafters | AA56: AutomationProcess_29697 | AD56: Reporting & Compliance | AE56: sona.job
A57: Diel hierarchy - rolled up revenue | B57: Platform Consolidation | C57: myISP_BPMS | D57: BPMS Onboarding | E57: 4378908 | F57: 4367455 | G57: As a BPMS Solution Architect, I Want to See Rolled Up BPMS Revenue used in the Global Watchlist Flag under operations Attributes of reporting & Compliance | H57: Test Complete | I57: CodeCrafters | J57: Vv, Shini <shini.vv@accenture.com> | K57: 46092.229 | L57: 46087.229 | M57: 46095.062 | N57: 46094.229 | O57: Panchal, Dhwani <dhwani.panchal@accenture.com> | P57: 46109.229 | Q57: 1 | S57: 2 | U57: Yes | V57: Yes | W57: Saraogi, Aaditi <aaditi.saraogi@accenture.com> | X57: 46066.656 | Y57: 3/28/2026 12:00:00 AM; Parallel UAT | Z57: AutomationProcess_29697\mySPIntegratedSolutionPlatform\CodeCrafters | AA57: AutomationProcess_29697 | AD57: Reporting & Compliance | AE57: sona.job
A58: IPC Calculator | Updated RAG logic for IPC Delivery Toolkit and IPC Lead PMO | B58: V2V | C58: Calculator | D58: IPC Calculator | E58: 4341338 | F58: 4343702 | G58: As a mySP user, I want to view the updated RAG logic for IPC DCT and IPC Lead PMO in KDA Variance Analysis | H58: PT In Test | I58: CodeCrafters | J58: Selvamani, Kavichandrika <k.b.selvamani@accenture.com> | K58: 46090.229 | L58: 46087.024 | M58: 46098.229 | N58: 46087.033 | O58: Kumar, Amresh <amresh.l.kumar@accenture.com> | P58: 46109.229 | Q58: 1 | S58: 2 | U58: Yes | V58: Yes | W58: Pandey, Ansh <ansh.pandey@accenture.com> | X58: 46051.613 | Y58: UAT Testing Not Required | Z58: AutomationProcess_29697\mySPIntegratedSolutionPlatform\CodeCrafters | AA58: AutomationProcess_29697 | AD58: KDA Variance Analysis | AE58: sona.job
A59: Updating the logic for populating the Deal Rag Status in KDA Variance Analysis Report | B59: Rapid Soln | C59: OCP | D59: AMS, SI, OCP | E59: 4316161 | F59: 4316297 | G59: AMS, SI-OCP: As a mySolutionPlanner developer, I want to update the logic for deal RAG status to display in KDA Variance Analysis when the user triggers KDA, so that RAG color is aligned with the RAG color displayed for Adherence score in View KDA. | H59: UAT In Test | I59: CodeCrafters | J59: Damodaran, J. <j.damodaran@accenture.com> | K59: 46092.229 | L59: 46090.651 | M59: 46094.062 | N59: 46094.98 | O59: Panchal, Dhwani <dhwani.panchal@accenture.com> | P59: 46109.229 | Q59: 3 | S59: 2 | U59: Yes | V59: Yes | W59: Sharma, Megha <megha.bo.sharma@accenture.com> | X59: 46029.668 | Y59: AMS; OCP; Parallel UAT; SI | Z59: AutomationProcess_29697\mySPIntegratedSolutionPlatform\CodeCrafters | AA59: AutomationProcess_29697\mySolutionPlannerRapidSolutioning\R63\Sprint159 | AD59: KDA Variance Analysis | AE59: sona.job
A60: Updating the logic for populating the Deal Rag Status in KDA Variance Analysis Report | B60: Rapid Soln | C60: OCP | D60: AMS, SI, DCTA | E60: 4316161 | F60: 4316299 | G60: AMS, SI-DCTA: As a mySolutionPlanner developer, I want to update the logic for deal RAG status to display in KDA Variance Analysis when the user triggers KDA, so that RAG color is aligned with the RAG color displayed for Adherence score in View KDA. | H60: UAT In Test | I60: CodeCrafters | J60: Damodaran, J. <j.damodaran@accenture.com> | K60: 46092.229 | L60: 46090.651 | M60: 46094.062 | N60: 46094.982 | O60: Panchal, Dhwani <dhwani.panchal@accenture.com> | P60: 46109.229 | Q60: 1 | S60: 2 | U60: Yes | V60: Yes | W60: Sharma, Megha <megha.bo.sharma@accenture.com> | X60: 46029.669 | Y60: AMS; DCTA; Parallel UAT; SI | Z60: AutomationProcess_29697\mySPIntegratedSolutionPlatform\CodeCrafters | AA60: AutomationProcess_29697\mySolutionPlannerRapidSolutioning\R63\Sprint159 | AD60: KDA Variance Analysis | AE60: sona.job
A61: Song Deals Compliant Logic Update | B61: Platform Consolidation | C61: Calculator | D61: DFD-myISP | E61: 4317244 | F61: 4317269 | G61: Song Compliant Logic Update[RA] - As a myISP User,I want to provide onetime update for the existing deals and update the RAG , Score as per updated Song Compliance Logic so that all historical and active deals reflect accurate compliance status - RA Screen | H61: UAT In Test | I61: CodeCrafters | J61: Krishnan, Pirtheebaa <pirtheebaa.krishnan@accenture.com> | K61: 46092.229 | L61: 46092.229 | M61: 46097.979 | N61: 46097.932 | O61: Ravindra Yadav, Niraj <niraj.ravindra.yadav@accenture.com> | P61: 46109.229 | Q61: 3 | S61: 2 | U61: Yes | V61: NA | W61: Mohan, Vindhiya <vindhiya.mohan@accenture.com> | X61: 46030.614 | Y61: Parallel UAT | Z61: AutomationProcess_29697\mySPIntegratedSolutionPlatform\CodeCrafters | AA61: AutomationProcess_29697 | AD61: Compliant Status | AE61: sona.job
A62: Enhancement for Generative AI tab for AMS | B62: Rapid Soln | C62: NextGen | D62: AMS | E62: 4317843 | F62: 4317672 | G62: AMS - Generative AI Tab: As a mySolutionPlanner developer, I want to make enhancement changes in Generative AI tab for AMS service group, so that the issues that are currently faced by SAs are resolved. | H62: UAT In Test | I62: CodeCrafters | J62: Krishnan, Pirtheebaa <pirtheebaa.krishnan@accenture.com> | K62: 46090.683 | L62: 46091.672 | M62: 46097.229 | N62: 46097.962 | O62: Ravindra Yadav, Niraj <niraj.ravindra.yadav@accenture.com> | P62: 46109.229 | Q62: 3 | S62: 2 | U62: Yes | V62: Yes | W62: Sharma, Megha <megha.bo.sharma@accenture.com> | X62: 46030.814 | Y62: AMS; GEN AI; Parallel UAT; PO inputs | Z62: AutomationProcess_29697\mySPIntegratedSolutionPlatform\CodeCrafters | AA62: AutomationProcess_29697\mySolutionPlannerRapidSolutioning\R53\Sprint135 | AD62: Generative AI | AE62: sona.job
A63: Song Deals Compliant Logic Update | B63: Platform Consolidation | C63: Calculator | D63: DFD-myISP | E63: 4317244 | F63: 4320775 | G63: Song Compliant Logic Update [RA] - As a myISP User, I want to update the "Song Compliance Logic" in the Opportunities screen, so that users can quickly assess the compliance health of each deal. - Copy | H63: UAT In Test | I63: CodeCrafters | J63: Krishnan, Pirtheebaa <pirtheebaa.krishnan@accenture.com> | K63: 46092.229 | L63: 46092.89 | M63: 46097.979 | N63: 46097.94 | O63: Ravindra Yadav, Niraj <niraj.ravindra.yadav@accenture.com> | P63: 46109.229 | Q63: 3 | S63: 2 | U63: Yes | V63: Yes | W63: Mohan, Vindhiya <vindhiya.mohan@accenture.com> | X63: 46035.54 | Y63: Parallel UAT | Z63: AutomationProcess_29697\mySPIntegratedSolutionPlatform\CodeCrafters | AA63: AutomationProcess_29697 | AD63: Compliant Status | AE63: sona.job
A64: Revamp- Tier 2 city | B64: Platform Consolidation | C64: GenAI | D64: Reporting & Compliance -Tier 2 City | E64: 4059417 | F64: 4269036 | G64: As a Solution Architect, I want the ability to enter decimal values in the FTE and LCR fields under the Tier 2 City tab | H64: Test Complete | I64: CodeCrafters | J64: Krishnan, Pirtheebaa <pirtheebaa.krishnan@accenture.com> | K64: 46084.229 | L64: 46083.833 | O64: Sangale, Vinayak L. <vinayak.l.sangale@accenture.com> | P64: 46109.229 | Q64: 1 | S64: 2 | U64: Yes | V64: Yes | W64: Laha, Subarna <subarna.laha@accenture.com> | X64: 45994.703 | Y64: CR; Reporting & Compliance Revamp; Tier 2 City; UAT Testing Not Required; UI_Revamp | Z64: AutomationProcess_29697\mySPIntegratedSolutionPlatform\CodeCrafters | AA64: AutomationProcess_29697\mySolutionPlannerV2V\R64 | AD64: Reporting & Compliance -Tier 2 City | AE64: sona.job
A65: Solution Simplification mandatory field updates | B65: Platform Consolidation | C65: myISP_BPMS | D65: BPMS Onboarding | E65: 4316945 | F65: 4279597 | G65: As a BPMS User, I should be able to save Solution Simplification screen without mandatory checks on ?PriceOne used for Stage 0/1/2A? and ?Approval Committee Approach Followed? so that I can proceed smoothly without validation errors. | H65: Test Complete | I65: CodeCrafters | J65: Vv, Shini <shini.vv@accenture.com> | K65: 46092.229 | L65: 46085.869 | M65: 46097.229 | N65: 46098.709 | O65: Panchal, Dhwani <dhwani.panchal@accenture.com> | P65: 46109.229 | Q65: 3 | S65: 1 | U65: Yes | V65: Yes | W65: Rajendra Anikhindi, Akshata <a.rajendra.anikhindi@accenture.com> | X65: 46007.497 | Y65: BPMS; CR; Parallel UAT; Pilot Testing | Z65: AutomationProcess_29697\mySPIntegratedSolutionPlatform\CodeCrafters | AA65: AutomationProcess_29697 | AD65: Solution Simplification screen | AE65: sona.job
A66: Solution Simplification mandatory field updates | B66: Platform Consolidation | C66: myISP_BPMS | D66: BPMS Onboarding | E66: 4316945 | F66: 4279677 | G66: As a BPMS User, I should be able to see Solution Simplification marked as compliant if ?PriceOne used for Stage 0/1/2A? and ?Approval Committee Approach Followed? are filled in the solution simplification screen so that the compliance score is updated. | H66: Test Complete | I66: CodeCrafters | J66: Vv, Shini <shini.vv@accenture.com> | K66: 46092.229 | L66: 46085.871 | M66: 46097.229 | N66: 46097.229 | O66: Panchal, Dhwani <dhwani.panchal@accenture.com> | P66: 46109.229 | Q66: 3 | S66: 1 | U66: Yes | V66: Yes | W66: Rajendra Anikhindi, Akshata <a.rajendra.anikhindi@accenture.com> | X66: 46007.51 | Y66: BPMS; CR; Parallel UAT; Pilot Testing | Z66: AutomationProcess_29697\mySPIntegratedSolutionPlatform\CodeCrafters | AA66: AutomationProcess_29697 | AD66: Solution Simplification score | AE66: sona.job
A67: Capco Template - Enhancement | B67: Platform Consolidation | C67: myISP_BPMS | D67: BPMS Onboarding | E67: 4317373 | F67: 4309748 | G67: As a BPMS SA, I want the Capco template to automatically format revenue numbers with commas | H67: Test Complete | I67: CodeCrafters | J67: Vv, Shini <shini.vv@accenture.com> | K67: 46087.979 | L67: 46087.229 | M67: 46093.229 | N67: 46093.745 | O67: Panchal, Dhwani <dhwani.panchal@accenture.com> | P67: 46109.229 | Q67: 1 | S67: 2 | U67: Yes | V67: Yes | W67: Saraogi, Aaditi <aaditi.saraogi@accenture.com> | X67: 46023.679 | Y67: 46109 | Z67: AutomationProcess_29697\mySPIntegratedSolutionPlatform\CodeCrafters | AA67: AutomationProcess_29697 | AD67: Capco Template | AE67: sona.job
A68: Revamp- Tier 2 city | B68: Platform Consolidation | C68: GenAI | D68: Reporting & Compliance -Tier 2 City | E68: 4059417 | F68: 4233240 | G68: As a MYISP developer, I want to Restrict Tier 2 City Selection to Single Option for AMS, SI & IMS SG | H68: Test Complete | I68: CodeCrafters | J68: Krishnan, Pirtheebaa <pirtheebaa.krishnan@accenture.com> | K68: 46080.229 | L68: 46084.229 | O68: Sharma, Manisha <m.manisha@accenture.com> | P68: 46109.229 | Q68: 1 | S68: 2 | U68: Yes | V68: Yes | W68: Laha, Subarna <subarna.laha@accenture.com> | X68: 45968.824 | Y68: CR; Reporting & Compliance Revamp; Tier 2 City; UAT Testing Not Required; UI_Revamp | Z68: AutomationProcess_29697\mySPIntegratedSolutionPlatform\CodeCrafters | AA68: AutomationProcess_29697\mySolutionPlannerV2V\R64\Sprint160 | AD68: Reporting & Compliance -Tier 2 City | AE68: sona.job
A69: March Release NextGen Enhancements | B69: Platform Consolidation | C69: NextGen | D69: myISP Enhancements | E69: 4365826 | F69: 4227683 | G69: As a myISP user, I want to enable "KDA Adherence Score - Status" for IMS SG in reporting & compliance section | H69: UAT In Test | I69: CodeCrafters | J69: Krishnan, Pirtheebaa <pirtheebaa.krishnan@accenture.com> | K69: 46079.678 | L69: 46083.833 | M69: 46087.229 | N69: 46088.016 | O69: Ravindra Yadav, Niraj <niraj.ravindra.yadav@accenture.com> | P69: 46109.229 | Q69: 1 | S69: 2 | U69: Yes | V69: Yes | W69: Verma, Sarita <sarita.verma@accenture.com> | X69: 45964.793 | Y69: Feb 21st myISP; March 28th myISP; Parallel UAT | Z69: AutomationProcess_29697\mySPIntegratedSolutionPlatform\CodeCrafters | AA69: AutomationProcess_29697\mySolutionPlannerV2V\R49\Sprint121 | AD69: Reporting & Compliance | AE69: sona.job
A70: Song Deals Compliant Logic Update | B70: Platform Consolidation | C70: Calculator | D70: DFD-myISP | E70: 4317244 | F70: 4174501 | G70: Song Compliant Logic Update[RA] - As a myISP user, I want to see "Overall Song Delivery Approver" role added in Review Approvals dashboard so that User can approve the required deals needed to achieve Song Compliance. | H70: UAT In Test | I70: CodeCrafters | J70: Krishnan, Pirtheebaa <pirtheebaa.krishnan@accenture.com> | K70: 46085.229 | L70: 46084.229 | M70: 46090.229 | N70: 46093.772 | O70: Ravindra Yadav, Niraj <niraj.ravindra.yadav@accenture.com> | P70: 46109.229 | Q70: 5 | S70: 2 | U70: Yes | V70: Yes | W70: Kumar, Abhishek <a.iw.kumar@accenture.com> | X70: 45947.512 | Y70: March 28th myISP; Parallel UAT | Z70: AutomationProcess_29697\mySPIntegratedSolutionPlatform\CodeCrafters | AA70: AutomationProcess_29697 | AD70: Compliant Status | AE70: sona.job
A71: BPMS Reporting & Compliance UI Suggestions post demo call | B71: Platform Consolidation | C71: myISP_BPMS | D71: BPMS Onboarding | E71: 4316934 | F71: 4113135 | G71: As a myIntegrated Solution Planner user, I should be able to see Ripple On/Off toggle for Productivity Grid in Generative AI screen under Reporting & Compliance screen for BPMS Opportunity | H71: Test Complete | I71: CodeCrafters | J71: Vv, Shini <shini.vv@accenture.com> | K71: 46091.229 | L71: 46085.865 | M71: 46094.229 | N71: 46094.902 | O71: Panchal, Dhwani <dhwani.panchal@accenture.com> | P71: 46109.229 | Q71: 3 | S71: 2 | U71: Yes | V71: Yes | W71: Rajendra Anikhindi, Akshata <a.rajendra.anikhindi@accenture.com> | X71: 45902.853 | Y71: BPMS; Parallel UAT | Z71: AutomationProcess_29697\mySPIntegratedSolutionPlatform\CodeCrafters | AA71: AutomationProcess_29697 | AD71: R&C UI Suggestion | AE71: sona.job
A72: BPMS Reporting & Compliance UI Suggestions post demo call | B72: Platform Consolidation | C72: myISP_BPMS | D72: BPMS Onboarding | E72: 4316934 | F72: 4113172 | G72: As a my solution planner solution architect, Read more & hide should be available in description for Maturity Index and Due Diligence Questionnaire for BPMS Opportunity | H72: Test Complete | I72: CodeCrafters | J72: Vv, Shini <shini.vv@accenture.com> | K72: 46084.229 | L72: 46083.801 | M72: 46087.229 | N72: 46087.986 | O72: Panchal, Dhwani <dhwani.panchal@accenture.com> | P72: 46109.229 | Q72: 1 | S72: 2 | U72: Yes | V72: Yes | W72: Rajendra Anikhindi, Akshata <a.rajendra.anikhindi@accenture.com> | X72: 45902.949 | Y72: BPMS; Parallel UAT | Z72: AutomationProcess_29697\mySPIntegratedSolutionPlatform\CodeCrafters | AA72: AutomationProcess_29697 | AD72: R&C UI Suggestions | AE72: sona.job
A73: BPMS Reporting & Compliance UI Suggestions post demo call | B73: Platform Consolidation | C73: myISP_BPMS | D73: BPMS Onboarding | E73: 4316934 | F73: 4113178 | G73: As a my solution planner solution architect, I want all dropdown values to be displayed in alphabetical order, with the "Other Reasons" option always appearing last | H73: Test Complete | I73: CodeCrafters | J73: Vv, Shini <shini.vv@accenture.com> | K73: 46091.229 | L73: 46083.799 | M73: 46094.229 | N73: 46094.901 | O73: Panchal, Dhwani <dhwani.panchal@accenture.com> | P73: 46109.229 | Q73: 1 | S73: 2 | U73: Yes | V73: Yes | W73: Rajendra Anikhindi, Akshata <a.rajendra.anikhindi@accenture.com> | X73: 45902.962 | Y73: BPMS; Parallel UAT | Z73: AutomationProcess_29697\mySPIntegratedSolutionPlatform\CodeCrafters | AA73: AutomationProcess_29697 | AD73: R&C UI Suggestion | AE73: sona.job
A74: Diel hierarchy - rolled up revenue | B74: Platform Consolidation | C74: myISP_BPMS | D74: BPMS Onboarding | E74: 4378908 | F74: 4392743 | G74: As a BPMS User, I should be able to auto?trigger the Fast Track Solutioning (FTS) email on Operations attributes screen save based on opportunity criteria using rolled?up BPMS revenue for FTS calculation | H74: Test Complete | I74: CodeCrafters | J74: Vv, Shini <shini.vv@accenture.com> | K74: 46092.229 | L74: 46094.722 | M74: 46095.062 | N74: 46094.229 | O74: Panchal, Dhwani <dhwani.panchal@accenture.com> | P74: 46109.229 | Q74: 1 | S74: 2 | U74: Yes | V74: Yes | W74: Rajendra Anikhindi, Akshata <a.rajendra.anikhindi@accenture.com> | X74: 46078.997 | Y74: BPMS; CR; Development Request; Parallel UAT | Z74: AutomationProcess_29697\mySPIntegratedSolutionPlatform\CodeCrafters | AA74: AutomationProcess_29697\mySolutionPlannerIntegratedSolutionPlatform\R62\Sprint156 | AD74: Fast Track Solutioning (FTS) mail | AE74: sona.job
A75: PLD - Advisory SA Role | B75: Platform Consolidation | C75: NextGen | D75: Advisory SA - Song | E75: 4386527 | F75: 4373043 | G75: As an Advisory song SA, I want to access the Review Approvals tile in read-only mode so that I can maintain and view workflow continuity. | H75: UAT In Test | I75: CodeCrafters | J75: Krishnan, Pirtheebaa <pirtheebaa.krishnan@accenture.com> | K75: 46092.229 | L75: 46087.034 | M75: 46097.979 | N75: 46095.001 | O75: Ravindra Yadav, Niraj <niraj.ravindra.yadav@accenture.com> | P75: 46109.229 | Q75: 3 | S75: 2 | U75: Yes | V75: Yes | W75: Basty Ananth Shenoy <basty.ananth.shenoy@accenture.com> | X75: 46071.694 | Z75: AutomationProcess_29697\mySPIntegratedSolutionPlatform\CodeCrafters | AA75: AutomationProcess_29697 | AD75: PLD Enhancement | AE75: sona.job
A76: Diel hierarchy - rolled up revenue | B76: Platform Consolidation | C76: myISP_BPMS | D76: BPMS Onboarding | E76: 4378908 | F76: 4378825 | G76: As a BPMS User, I should be able to view and update the FTS toggle based on defined criteria using rolled?up BPMS revenue, with the ability to manually override when required, so that system compliance is ensured. | H76: Test Complete | I76: CodeCrafters | J76: Vv, Shini <shini.vv@accenture.com> | K76: 46092.229 | L76: 46086.93 | M76: 46095.062 | N76: 46094.229 | O76: Panchal, Dhwani <dhwani.panchal@accenture.com> | P76: 46109.229 | Q76: 1 | S76: 2 | U76: Yes | V76: Yes | W76: Saraogi, Aaditi <aaditi.saraogi@accenture.com> | X76: 46072.685 | Y76: BPMS; CR; Development Request; Parallel UAT | Z76: AutomationProcess_29697\mySPIntegratedSolutionPlatform\CodeCrafters | AA76: AutomationProcess_29697\mySolutionPlannerIntegratedSolutionPlatform\R62\Sprint156 | AD76: Fast Track Solutioning (FTS) section | AE76: sona.job
A77: ROI & Summary (Tab 8) will be as is in automation calculator with Split of GEN AI, Opera and Agentic and Ux upgrade | B77: V2V | C77: Calculator | D77: Automation Calculator | E77: 4405953 | F77: 4373570 | G77: As a myISP user I want the revamped Summary screen to include an overall summary and a ROI section that is a replica of the ROI screen with all sections So that the Summary PDF download contains all newly introduced revamp changes without missing data. | H77: Test Complete | I77: Codeplayers | J77: Baskaran, Nandini <nandini.baskaran@accenture.com> | K77: 46092.229 | L77: 46093.667 | O77: Sunanda, Bandi <bandi.sunanda@accenture.com> | P77: 46109.229 | Q77: 8 | S77: 1 | U77: Yes | V77: Yes | W77: Anandhapadmanaban, Megana <m.anandhapadmanaban@accenture.com> | X77: 46071.944 | Y77: UAT Testing Not Required | Z77: AutomationProcess_29697\mySPVisionToValue\Codeplayers | AA77: AutomationProcess_29697 | AD77: ROI - Default PA values | AE77: nityanand.giri
A78: ROI & Summary (Tab 8) will be as is in automation calculator with Split of GEN AI, Opera and Agentic and Ux upgrade | B78: V2V | C78: Calculator | D78: Automation Calculator | E78: 4405953 | F78: 4362711 | G78: As a myISP user, I want to view a new Overall Summary section that consolidates key cost metrics, So that I can quickly review the overall financial view before validation or submission. | H78: Test Complete | I78: Codeplayers | J78: Baskaran, Nandini <nandini.baskaran@accenture.com> | K78: 46090.229 | L78: 46091.062 | O78: Sunanda, Bandi <bandi.sunanda@accenture.com> | P78: 46109.229 | Q78: 5 | S78: 1 | U78: Yes | V78: Yes | W78: Anandhapadmanaban, Megana <m.anandhapadmanaban@accenture.com> | X78: 46064.622 | Y78: UAT Testing Not Required | Z78: AutomationProcess_29697\mySPVisionToValue\Codeplayers | AA78: AutomationProcess_29697 | AD78: ROI - Default PA values | AE78: nityanand.giri
A79: ROI & Summary (Tab 8) will be as is in automation calculator with Split of GEN AI, Opera and Agentic and Ux upgrade | B79: V2V | C79: Calculator | D79: Automation Calculator | E79: 4405953 | F79: 4364996 | G79: As a myISP user, I want all sections in the Summary tab to be displayed as accordions with expand and collapse functionality, So that I can easily navigate and review specific sections without clutter. | H79: Test Complete | I79: Codeplayers | J79: Baskaran, Nandini <nandini.baskaran@accenture.com> | K79: 46091.229 | L79: 46092.659 | O79: Sunanda, Bandi <bandi.sunanda@accenture.com> | P79: 46109.229 | Q79: 5 | S79: 1 | U79: Yes | V79: Yes | W79: Anandhapadmanaban, Megana <m.anandhapadmanaban@accenture.com> | X79: 46065.609 | Y79: UAT Testing Not Required | Z79: AutomationProcess_29697\mySPVisionToValue\Codeplayers | AA79: AutomationProcess_29697 | AD79: ROI - Default PA values | AE79: nityanand.giri
A80: ROI & Summary (Tab 8) will be as is in automation calculator with Split of GEN AI, Opera and Agentic and Ux upgrade | B80: V2V | C80: Calculator | D80: Automation Calculator | E80: 4405953 | F80: 4365001 | G80: As a myISP user, I want the ROI section in the Summary tab to include all subsections from the ROI screen, So that I can review Agentic, Opera AI, and Gen AI percentage breakdowns across years and contract duration, along with the graphical representation | H80: Test Complete | I80: Codeplayers | J80: Baskaran, Nandini <nandini.baskaran@accenture.com> | K80: 46091.229 | L80: 46092.659 | O80: Sunanda, Bandi <bandi.sunanda@accenture.com> | P80: 46109.229 | Q80: 8 | S80: 1 | U80: Yes | V80: Yes | W80: Anandhapadmanaban, Megana <m.anandhapadmanaban@accenture.com> | X80: 46065.613 | Y80: UAT Testing Not Required | Z80: AutomationProcess_29697\mySPVisionToValue\Codeplayers | AA80: AutomationProcess_29697 | AD80: ROI - Default PA values | AE80: nityanand.giri
A81: Billable Expense as % of Price | B81: Rapid Soln | C81: DCTA | D81: SI OCP | E81: 4371610 | F81: 4367405 | G81: As a myISP SA, I want to send new definition type for billable expense in the expense tab in pricing input screen to OCP for calculations | H81: UAT In Test | I81: CodingCrusaders | J81: Selvamani, Kavichandrika <k.b.selvamani@accenture.com> | K81: 46095.062 | L81: 46093.986 | M81: 46098.229 | N81: 46099.663 | O81: Manasa, Gunnam <gunnam.manasa@accenture.com> | P81: 46109.229 | Q81: 11 | S81: 2 | U81: Yes | V81: Yes | W81: Aggarwal, Sugandha <sugandha.a.aggarwal@accenture.com> | X81: 46066.603 | Y81: Parallel UAT | Z81: AutomationProcess_29697\mySPRapidSolutioning\CodingCrusaders | AA81: AutomationProcess_29697\mySolutionPlannerRapidSolutioning\R63\Sprint158 | AD81: SI OCP | AE81: K.devaraj
A82: BPMS OCP: Cost/FTE/Year report | B82: Rapid Soln | C82: OCP | D82: BPMS | E82: 4272104 | F82: 4271903 | G82: BPMS OCP- As a mySolutionPlanner developer, I want to add new tab under financial section of detailed report and make changes in Resource Level View Report when the user trigger Pricing, so users can view the Benchmark report with all the required details. | H82: UAT In Test | I82: CodingCrusaders | J82: Damodaran, J. <j.damodaran@accenture.com> | K82: 46095.062 | L82: 46093.986 | M82: 46098.229 | N82: 46099.089 | O82: Panchal, Dhwani <dhwani.panchal@accenture.com> | P82: 46109.229 | Q82: 14 | S82: 2 | U82: Yes | V82: Yes | W82: Sharma, Megha <megha.bo.sharma@accenture.com> | X82: 45999.385 | Y82: BPMS; DCTA; OCP; Parallel UAT; Po Input | Z82: AutomationProcess_29697\mySPRapidSolutioning\CodingCrusaders | AA82: AutomationProcess_29697\mySolutionPlannerRapidSolutioning\R63\Sprint158 | AD82: Financial Section | AE82: K.devaraj
A83: Price to Client after Negotiation Contingency calculation | B83: Rapid Soln | C83: OCP | D83: IMS OCP | E83: 4351343 | F83: 4344835 | G83: IMS-OCP: As a mySolutionPlanner developer, I want to populate Negotiation Contingency and Price to Client after Negotiation Contingency fields in OCP reports | H83: UAT In Test | I83: CodingCrusaders | J83: Damodaran, J. <j.damodaran@accenture.com> | K83: 46092.062 | L83: 46090.987 | M83: 46094.229 | N83: 46094.06 | O83: Panchal, Dhwani <dhwani.panchal@accenture.com> | P83: 46109.229 | Q83: 5 | S83: 2 | U83: Yes | V83: Yes | W83: Vijay Deshpande, Prajakta <p.vijay.deshpande@accenture.com> | X83: 46052.435 | Y83: 28th March Release; OCP | Z83: AutomationProcess_29697\mySPRapidSolutioning\CodingCrusaders | AA83: AutomationProcess_29697\mySolutionPlannerIntegratedSolutionPlatform | AD83: IMS OCP Reports | AE83: K.devaraj
A84: IPC Calculator | Updated RAG logic for IPC Delivery Toolkit and IPC Lead PMO | B84: V2V | C84: Calculator | D84: IPC Calculator | E84: 4341338 | F84: 4343705 | G84: As a mySP user, I want to view the updated RAG logic for IPC DCT and IPC Lead PMO in SIVT Report | H84: Test Complete | I84: Cognilytics | J84: Kalaivanan, Devika <devika.kalaivanan@accenture.com> | K84: 46091.104 | L84: 46091.085 | M84: 46097.979 | O84: Kolluru, Krishna Chaitanya <krishna.c.kolluru@accenture.com> | P84: 46109.229 | Q84: 4 | S84: 2 | U84: Yes | V84: Yes | W84: Pandey, Ansh <ansh.pandey@accenture.com> | X84: 46051.614 | Y84: UAT Testing Not Required | Z84: AutomationProcess_29697\mySPIntegratedSolutionPlatform\Cognilytics | AA84: AutomationProcess_29697 | AD84: SIVT Report | AE84: anil.kadiri
A85: Generative AI productivity calculation by Year on Year productivity % in separate columns | B85: Platform Consolidation | C85: myISP_BPMS | D85: BPMS Onboarding | E85: 4385941 | F85: 4367327 | G85: As a BPMS reporting Layer User, I want Incremental GenAI Productivity ? YoY, Initial Productivity ? YoY, and Total Productivity ? YoY to be exposed in the BPMS Reporting Layer as separate columns for Year 1 through Year 10. | H85: Test Complete | I85: Cognilytics | J85: Kalaivanan, Devika <devika.kalaivanan@accenture.com> | K85: 46092.229 | L85: 46092.928 | M85: 46094.062 | N85: 46098.234 | O85: Panchal, Dhwani <dhwani.panchal@accenture.com> | P85: 46109.229 | Q85: 5 | S85: 2 | U85: Yes | V85: Yes | W85: Saraogi, Aaditi <aaditi.saraogi@accenture.com> | X85: 46066.542 | Y85: 46109 | Z85: AutomationProcess_29697\mySPIntegratedSolutionPlatform\Cognilytics | AA85: AutomationProcess_29697 | AD85: Reporting layer | AE85: anil.kadiri
A86: Client name should be mapped to MasterCustomerNM in Mob architect , CXTA email & Reporting Layer | B86: Platform Consolidation | C86: myISP_BPMS | D86: BPMS Onboarding | E86: 4371914 | F86: 4371950 | G86: [Technical] As a PMO user, I want to verify that the MasterCustomerNM is available in BPMS reporting layer so that user has better insights on client details | H86: Test Complete | I86: Cognilytics | J86: Kalaivanan, Devika <devika.kalaivanan@accenture.com> | K86: 46093.104 | L86: 46092.927 | M86: 46098.979 | N86: 46097.725 | O86: Ravindra Yadav, Niraj <niraj.ravindra.yadav@accenture.com> | P86: 46109.229 | Q86: 5 | S86: 2 | U86: Yes | V86: Yes | W86: Rajendra Anikhindi, Akshata <a.rajendra.anikhindi@accenture.com> | X86: 46071.019 | Y86: BPMS | Z86: AutomationProcess_29697\mySPIntegratedSolutionPlatform\Cognilytics | AA86: AutomationProcess_29697 | AD86: MasterCustomerNM | AE86: anil.kadiri
A87: Benchmark Report - Add a column for Lead SA - Operations | B87: Platform Consolidation | C87: myISP_BPMS | D87: BPMS Onboarding | E87: 4371834 | F87: 4371951 | G87: As a BPMS User, I should be able to view the Lead SA - Operations field in the Benchmark Report so that I can get insights into the resource assigned to an Opportunity. | H87: Test Complete | I87: Cognilytics | J87: Kalaivanan, Devika <devika.kalaivanan@accenture.com> | K87: 46085.229 | L87: 46085.902 | M87: 46093.979 | N87: 46087.677 | O87: Panchal, Dhwani <dhwani.panchal@accenture.com> | P87: 46109.229 | Q87: 5 | S87: 2 | U87: Yes | V87: Yes | W87: Rajendra Anikhindi, Akshata <a.rajendra.anikhindi@accenture.com> | X87: 46071.04 | Y87: BPMS | Z87: AutomationProcess_29697\mySPIntegratedSolutionPlatform\Cognilytics | AA87: AutomationProcess_29697\mySolutionPlannerIntegratedSolutionPlatform | AD87: Lead SA – Operations | AE87: anil.kadiri
A88: Reporting Layer: CXTA Fields to be added | B88: Platform Consolidation | C88: myISP_BPMS | D88: BPMS Onboarding | E88: 4371836 | F88: 4371954 | G88: As a myISP User, I should be able to include a new sheet named BPMS CXTA Details in the BPMS reporting layer so that CXTA details can be visible to PMOs. | H88: Test Complete | I88: Cognilytics | J88: Kalaivanan, Devika <devika.kalaivanan@accenture.com> | K88: 46092.958 | L88: 46092.86 | M88: 46098.979 | N88: 46099.003 | O88: Ravindra Yadav, Niraj <niraj.ravindra.yadav@accenture.com> | P88: 46109.229 | Q88: 7 | S88: 2 | U88: Yes | V88: Yes | W88: Rajendra Anikhindi, Akshata <a.rajendra.anikhindi@accenture.com> | X88: 46071.051 | Y88: BPMS | Z88: AutomationProcess_29697\mySPIntegratedSolutionPlatform\Cognilytics | AA88: AutomationProcess_29697\mySolutionPlannerIntegratedSolutionPlatform | AD88: BPMS CXTA Details | AE88: anil.kadiri
A89: Client name should be mapped to MasterCustomerNM in Mob architect , CXTA email & Reporting Layer | B89: Platform Consolidation | C89: myISP_BPMS | D89: BPMS Onboarding | E89: 4371914 | F89: 4371955 | G89: As a myISP User, I should be able to new fields added in the BPMS reporting layer so that PMOs can better insights | H89: Test Complete | I89: Cognilytics | J89: Kalaivanan, Devika <devika.kalaivanan@accenture.com> | K89: 46093.104 | L89: 46092.927 | M89: 46098.979 | N89: 46097.996 | O89: Panchal, Dhwani <dhwani.panchal@accenture.com> | P89: 46109.229 | Q89: 7 | S89: 2 | U89: Yes | V89: Yes | W89: Rajendra Anikhindi, Akshata <a.rajendra.anikhindi@accenture.com> | X89: 46071.062 | Y89: BPMS | Z89: AutomationProcess_29697\mySPIntegratedSolutionPlatform\Cognilytics | AA89: AutomationProcess_29697\mySolutionPlannerIntegratedSolutionPlatform | AD89: BPMS Reporting Layer | AE89: anil.kadiri
A90: Advisory SA Role Sync in DFD, PLD, Define Team | B90: Platform Consolidation | C90: Analytics | D90: Analytics | E90: 4366466 | F90: 4369456 | G90: As a myISP user, I want to enable "Advisory SA - SONG" role and assignments in a data dump (Reporting Layer and SA Assignment layer) for across SG. | H90: UAT In Test | I90: Cognilytics | J90: Kalaivanan, Devika <devika.kalaivanan@accenture.com> | K90: 46095.104 | L90: 46094.894 | M90: 46098.938 | N90: 46097.774 | O90: Ravindra Yadav, Niraj <niraj.ravindra.yadav@accenture.com> | P90: 46109.229 | Q90: 6 | S90: 2 | U90: Yes | V90: Yes | W90: Verma, Sarita <sarita.verma@accenture.com> | X90: 46069.549 | Y90: Analytics; March 28th myISP | Z90: AutomationProcess_29697\mySPIntegratedSolutionPlatform\Cognilytics | AA90: AutomationProcess_29697\mySolutionPlanner\R45\Sprint 111 | AD90: PMO Reports | AE90: anil.kadiri
A91: March Release Analytics Enhancements | B91: Platform Consolidation | C91: NextGen | D91: ESA to Market Maker ESA | E91: 4365879 | F91: 4369602 | G91: As a Myisp user, I want the role "Enterprise SA" to be renamed to "Market Maker ESA" in myISP So that the role name clearly reflects the Market Make ESA in Analytics Reports. | H91: Test Complete | I91: Cognilytics | J91: Kalaivanan, Devika <devika.kalaivanan@accenture.com> | K91: 46093.104 | L91: 46091.854 | M91: 46098.979 | N91: 46098.004 | O91: Ravindra Yadav, Niraj <niraj.ravindra.yadav@accenture.com> | P91: 46109.229 | Q91: 6 | S91: 2 | U91: Yes | V91: Yes | W91: Verma, Sarita <sarita.verma@accenture.com> | X91: 46069.659 | Y91: Analytics; March 28th myISP | Z91: AutomationProcess_29697\mySPIntegratedSolutionPlatform\Cognilytics | AA91: AutomationProcess_29697\mySolutionPlannerIntegratedSolutionPlatform\R52 | AD91: Role Rename | AE91: anil.kadiri
A92: March Release Analytics Enhancements | B92: Platform Consolidation | C92: NextGen | D92: Analytics | E92: 4365879 | F92: 4366137 | G92: As a myISP user, I should be able to enable list of BPMS - Operations (Offerings) in Alignment filter column and below filtered grid columns so that in SA Bandwidth Report so that calendar details should show based on the Offerings. | H92: Test Complete | I92: Cognilytics | J92: Kalaivanan, Devika <devika.kalaivanan@accenture.com> | K92: 46091.104 | L92: 46090.936 | M92: 46095.062 | N92: 46093.001 | O92: Panchal, Dhwani <dhwani.panchal@accenture.com> | P92: 46109.229 | Q92: 3 | S92: 1 | U92: Yes | V92: Yes | W92: Verma, Sarita <sarita.verma@accenture.com> | X92: 46065.852 | Y92: Analytics; Calendar; March 28th myISP | Z92: AutomationProcess_29697\mySPIntegratedSolutionPlatform\Cognilytics | AA92: AutomationProcess_29697\mySolutionPlannerIntegratedSolutionPlatform\R52 | AD92: SA Bandwidth Reports | AE92: anil.kadiri
A93: March Release Analytics Enhancements | B93: Platform Consolidation | C93: Analytics | D93: Analytics | E93: 4365879 | F93: 4358784 | G93: As a myISP user, I want to rename/deactivate for "IE SA" column in a data dump (Reporting Layer and SA Assignment layer) for mentioned roles so that IE SA can see the assignment for few applicable roles only for each Service Level in concatenated based. | H93: UAT In Test | I93: Cognilytics | J93: Kalaivanan, Devika <devika.kalaivanan@accenture.com> | K93: 46087.938 | L93: 46088.068 | M93: 46094.979 | N93: 46093.674 | O93: Ravindra Yadav, Niraj <niraj.ravindra.yadav@accenture.com> | P93: 46109.229 | Q93: 5 | S93: 2 | U93: Yes | V93: NA | W93: Verma, Sarita <sarita.verma@accenture.com> | X93: 46062.912 | Y93: Analytics; March 28th myISP | Z93: AutomationProcess_29697\mySPIntegratedSolutionPlatform\Cognilytics | AA93: AutomationProcess_29697\mySolutionPlanner\R45\Sprint 111 | AD93: PMO Report | AE93: anil.kadiri
A94: ROI - Automation Calculator - Default Logic | B94: V2V | C94: Calculator | D94: Automation Calculator | E94: 4366165 | F94: 4361791 | G94: As a myISP user I want to see a clear system message when Productivity Assessment is not submitted for an eligible deal So that I understand that default productivity values are being applied | H94: Test Complete | I94: CrazyCoders | J94: Baskaran, Nandini <nandini.baskaran@accenture.com> | K94: 46091.021 | L94: 46088.062 | O94: Sunanda, Bandi <bandi.sunanda@accenture.com> | P94: 46109.229 | Q94: 5 | S94: 1 | U94: Yes | V94: Yes | W94: Anandhapadmanaban, Megana <m.anandhapadmanaban@accenture.com> | X94: 46063.966 | Y94: UAT Testing Not Required | Z94: AutomationProcess_29697\mySPVisionToValue\CrazyCoders | AA94: AutomationProcess_29697\mySolutionPlannerV2V\R64\Sprint160 | AD94: ROI - Default PA values | AE94: nityanand.giri
A95: ROI - Automation Calculator - Default Logic | B95: V2V | C95: Calculator | D95: Automation Calculator | E95: 4366165 | F95: 4364929 | G95: As a myISP user working on automation ROI section I want AD and AM views to mirror the Productivity Assessment layout (lever/sub-lever grid with Y1H1-Y5H5 periods) and auto-populate values based on PA completion status | H95: Test Complete | I95: CrazyCoders | J95: Baskaran, Nandini <nandini.baskaran@accenture.com> | K95: 46093.021 | L95: 46093.667 | O95: Sunanda, Bandi <bandi.sunanda@accenture.com> | P95: 46109.229 | Q95: 8 | S95: 1 | U95: Yes | V95: Yes | W95: Anandhapadmanaban, Megana <m.anandhapadmanaban@accenture.com> | X95: 46065.565 | Y95: UAT Testing Not Required | Z95: AutomationProcess_29697\mySPVisionToValue\CrazyCoders | AA95: AutomationProcess_29697\mySolutionPlannerV2V\R64\Sprint160 | AD95: ROI - Default PA values | AE95: nityanand.giri
A96: ROI - Automation Calculator - Default Logic | B96: V2V | C96: Calculator | D96: Automation Calculator | E96: 4366165 | F96: 4363958 | G96: As a myISP user viewing the ROI screen in the Automation Calculator I want to see Agentic AI productivity as a separate lever alongside Opera and Gen AI with a combined yearly breakdown view | H96: Test Complete | I96: CrazyCoders | J96: Baskaran, Nandini <nandini.baskaran@accenture.com> | K96: 46091.021 | L96: 46091.062 | O96: Ramkumar, Yuvanitharsana <r.yuvanitharsana@accenture.com> | P96: 46109.229 | Q96: 8 | S96: 1 | U96: Yes | V96: Yes | W96: Anandhapadmanaban, Megana <m.anandhapadmanaban@accenture.com> | X96: 46064.99 | Y96: UAT Testing Not Required | Z96: AutomationProcess_29697\mySPVisionToValue\CrazyCoders | AA96: AutomationProcess_29697\mySolutionPlannerV2V\R64\Sprint160 | AD96: ROI - Default PA values | AE96: nityanand.giri
A97: ROI - Automation Calculator - Default Logic | B97: V2V | C97: Calculator | D97: Automation Calculator | E97: 4366165 | F97: 4362465 | G97: As a myISP user, I want the system to automatically calculate AD and AM Assessment productivity values using a default tech stack split of 50% Custom and 50% Package in the ROI tab | H97: Test Complete | I97: CrazyCoders | J97: Baskaran, Nandini <nandini.baskaran@accenture.com> | K97: 46093.021 | L97: 46093.667 | O97: Sunanda, Bandi <bandi.sunanda@accenture.com> | P97: 46109.229 | Q97: 8 | S97: 1 | U97: Yes | V97: Yes | W97: Anandhapadmanaban, Megana <m.anandhapadmanaban@accenture.com> | X97: 46064.502 | Y97: UAT Testing Not Required | Z97: AutomationProcess_29697\mySPVisionToValue\CrazyCoders | AA97: AutomationProcess_29697\mySolutionPlannerV2V\R64\Sprint160 | AD97: ROI - Default PA values | AE97: nityanand.giri
A98: OCP/DCTA - Updating the logic for Calculating productivity assessment values in Recommended Productivity section | B98: Rapid Soln | C98: OCP | D98: OCP/DCTA | E98: 4364026 | F98: 4364038 | G98: AMS OCP/DCTA: As a mySolutionPlanner developer, I want to populate updated Lever values for AD and AM (Custom and Package) in OCP and DCTA reports | H98: UAT In Test | I98: CreativeCoders | J98: Damodaran, J. <j.damodaran@accenture.com> | K98: 46094.938 | L98: 46094.694 | M98: 46097.229 | N98: 46098.031 | O98: Ravindra Yadav, Niraj <niraj.ravindra.yadav@accenture.com> | P98: 46109.229 | Q98: 5 | S98: 2 | U98: Yes | V98: Yes | W98: Vijay Deshpande, Prajakta <p.vijay.deshpande@accenture.com> | X98: 46065.398 | Y98: Parallel UAT | Z98: AutomationProcess_29697\mySPRapidSolutioning\CreativeCoders | AA98: AutomationProcess_29697\mySolutionPlannerIntegratedSolutionPlatform | AD98: OCP/DCTA Productivity Report | AE98: K.devaraj
A99: Sending Roles and Open for SA notes to MSDA along with Cost Description and Category | B99: Rapid Soln | C99: OCP | D99: IMS OCP | E99: 4371602 | F99: 4362959 | G99: As myISP SA, I want to share Roles field from Labor JSON and Open for SA Notes field from Cost and Labor JSON to MSDA so that better reporting and comprehensive analysis can be done | H99: Ready for UAT | I99: CreativeCoders | J99: Damodaran, J. <j.damodaran@accenture.com> | K99: 46087.979 | L99: 46087.762 | M99: 46093.229 | N99: 46094.688 | O99: Panchal, Dhwani <dhwani.panchal@accenture.com> | P99: 46109.229 | Q99: 5 | S99: 2 | U99: Yes | V99: Yes | W99: Aggarwal, Sugandha <sugandha.a.aggarwal@accenture.com> | X99: 46064.652 | Y99: Parallel UAT | Z99: AutomationProcess_29697\mySPRapidSolutioning\CreativeCoders | AA99: AutomationProcess_29697\mySolutionPlannerRapidSolutioning\R55\Sprint139 | AD99: IMS OCP | AE99: K.devaraj
A100: OCP/DCTA - Updating the logic for Calculating productivity assessment values in Recommended Productivity section | B100: Rapid Soln | C100: OCP | D100: Pricing | E100: 4364026 | F100: 4364983 | G100: AMS OCP/DCTA: As a mySolutionPlanner developer, I should get productivity values from Productivity Assessment in KDA Report, and the values should be in sync | H100: UAT In Test | I100: CreativeCoders | J100: Damodaran, J. <j.damodaran@accenture.com> | K100: 46094.938 | L100: 46094.694 | M100: 46097.229 | N100: 46098.021 | O100: Ravindra Yadav, Niraj <niraj.ravindra.yadav@accenture.com> | P100: 46109.229 | Q100: 5 | S100: 2 | U100: Yes | V100: Yes | W100: Vijay Deshpande, Prajakta <p.vijay.deshpande@accenture.com> | X100: 46065.59 | Y100: Parallel UAT | Z100: AutomationProcess_29697\mySPRapidSolutioning\CreativeCoders | AA100: AutomationProcess_29697\mySolutionPlannerIntegratedSolutionPlatform | AD100: Pricing - KDA Report | AE100: K.devaraj
