Workbook

Sheet insprint pivot
H1: Insprint Yes/No | I1: Yes | L1: Insprint Yes/No | M1: (Multiple Items) | O1: Module count for Mar 28 insprint
H2: PT Lead | I2: (All) | O2: PT lead | P2: No of US for insprint | Q2: Modules Count | R2: Module names | S2: ETA for pipeline readiness for Prod | T2: Excluded code from
A3: Count of Parent Title | B3: Column Labels | L3: Row Labels | M3: Count of Parent Title | O3: Pirtheebaa | P3: 20 | Q3: 11 | R3: PCAT Dashboard Learn SA Team manager View MMS Details Opportunity Workflow Manage SA Review Approval Transition To Delivery Define Team WRWS Estimators/Calculators | S3: completed
A4: Row Labels | B4: No | C4: Yes | D4: (blank) | E4: Partial | F4: Grand Total | I4: Values | L4: Power BI report validation | M4: 60 | O4: Himanshu | P4: 9 | Q4: 1 | R4: PLD | T4: no
A5: Anand | B5: 16 | C5: 6 | E5: 8 | F5: 30 | H5: Insprint Tester | I5: Count of Parent Title | J5: Average of If insprint YES - % of completion | L5: Complex user story which involves multiple screen validation and multiple roles validation and requires more time to automate | M5: 39 | O5: Shini | P5: 46 | Q5: 2 | R5: BPMS and DCSO | S5: Mar 24 EOD | T5: no
A6: Devika | B6: 59 | E6: 4 | F6: 63 | H6: k.tamilzharasu | I6: 2 | J6: 0.8 | L6: Fresh Deal creation required everytime | M6: 27 | O6: Anand | P6: 4 | Q6: 1 | R6: SI Online | S6: completed
A7: Hajara | B7: 26 | C7: 13 | D7: 1 | E7: 23 | F7: 63 | H7: r.maheen.abu.backer | I7: 3 | J7: 0.55 | L7: IMS BAU | M7: 20 | O7: Nandini | P7: 10 | Q7: 4 | R7: Estimator Calculator Workflow, Value Shaping, Asset Calculator,Automation Calculator | S7: PR pending
A8: Himanshu | B8: 5 | E8: 7 | F8: 12 | H8: nitish.kumar.prusty | I8: 2 | J8: 0.525 | L8: Technical US - Full regression Required | M8: 17 | O8: Hajara | P8: 11 | Q8: 1 | R8: GEN AI | S8: Mar 26 EOD
A9: Jaya | B9: 13 | C9: 4 | E9: 15 | F9: 32 | H9: s.boya.kumarii | I9: 1 | J9: 0.45 | L9: Complex KDA metrics validation in excel | M9: 16 | O9: Leena | P9: 21 | Q9: 1 | R9: DSP | S9: In progress
A10: Kavi | B10: 17 | C10: 2 | E10: 7 | F10: 26 | H10: sairam.pamarthi | I10: 3 | J10: 0.43333333 | L10: LLM Dynamic response generation User story which is not partially automatable | M10: 15 | O10: Jaya | P10: 6 | Q10: 1 | R10: AMS_OCP_DCTA | S10: completed
A11: Leena | B11: 27 | C11: 16 | E11: 31 | F11: 74 | H11: lakshmi.e.j | I11: 7 | J11: 0.41428571 | L11: PCW User Story | M11: 15 | O11: Kavi | P11: 3 | Q11: 2 | R11: SI OCP, DCTA-MMP | S11: completed | T11: pending 2 stories will not be considered . They can be run stand alone by insprint testers
A12: Nandini | B12: 42 | C12: 65 | E12: 33 | F12: 140 | H12: n.sargurunathan | I12: 1 | J12: 0.4 | L12: 200+ nudges validation and resposne time greater than 15 mins | M12: 11 | O12: Devika | P12: 0 | Q12: 0
A13: Omkar | B13: 7 | F13: 7 | H13: santhwana.m.r | I13: 3 | J13: 0.36666667 | L13: BPMS BAU | M13: 11 | O13: Raji | P13: 0 | Q13: 0
A14: Pirtheebaa | B14: 10 | C14: 37 | E14: 6 | F14: 53 | H14: nithish.mode | I14: 7 | J14: 0.31428571 | L14: Agent SCA Testing | M14: 9
A15: Rajeswari | B15: 18 | C15: 6 | F15: 24 | H15: karnati.aruna.jyothi | I15: 1 | J15: 0.3 | L15: MDA Power BI to DSP Integration | M15: 8
A16: Shini | B16: 17 | C16: 36 | E16: 6 | F16: 59 | H16: r.e.muthusamy | I16: 1 | J16: 0.3 | L16: Everytime new User validation | M16: 8
A17: Surbhi | B17: 4 | D17: 2 | F17: 6 | H17: amresh.l.kumar | I17: 1 | J17: 0.3 | L17: external Integration validation | M17: 8
A18: Vaidheki | B18: 20 | D18: 1 | F18: 21 | H18: sai.Priyanka.vasa | I18: 1 | J18: 0.25 | L18: User story validation for SM and Above career level | M18: 7
A19: Grand Total | B19: 281 | C19: 185 | D19: 4 | E19: 140 | F19: 610 | H19: shaik.yasin | I19: 1 | J19: 0.25 | L19: Complex User story will be delivered April 28th and not enough time to complete Insprint | M19: 5
H20: gayatri.korikana | I20: 2 | J20: 0.25 | L20: (blank) | M20: 4
H21: ganga.m.reddy.padala | I21: 4 | J21: 0.25 | L21: Removed Screen Validation cannot be automated because x path will not be found | M21: 3
H22: jeba.momin | I22: 2 | J22: 0.25 | L22: Basic email validation after just login | M22: 2
H23: pujitha.r.gogireddy | I23: 4 | J23: 0.2375 | L23: Grand Total | M23: 285
H24: m.sheik.fusulee.a | I24: 6 | J24: 0.23333333
H25: naga.v.pachipulusu | I25: 3 | J25: 0.21666667
H26: vignesh.jagathisan | I26: 3 | J26: 0.2
H27: bandi.sunanda | I27: 5 | J27: 0.2
H28: vadde.bindu | I28: 1 | J28: 0.2
H29: Saranya.datla | I29: 4 | J29: 0.2
H30: nalluri.vishnupriya | I30: 1 | J30: 0.2
H31: shivaprasad.malekar | I31: 2 | J31: 0.2
H32: arun.thangapandian | I32: 5 | J32: 0.19
H33: pawan.m.kumar.singh | I33: 2 | J33: 0.175
H34: Mary.jacob | I34: 5 | J34: 0.16
H35: s.af.natarajan | I35: 2 | J35: 0.15
... H71: Grand Total | I71: 185 | J71: 0.17567568

Sheet insprint
I1: Insprint Yes/No | J1: No
I2: PT Lead | J2: (All)
A3: Count of Title | B3: Column Labels
A4: Lead | B4: No | C4: Yes | D4: (blank) | E4: Partial | F4: Grand Total | I4: Predefined Reason | J4: Count of Title
A5: Anand | B5: 16 | C5: 6 | E5: 9 | F5: 31 | I5: Power BI report validation | J5: 60
A6: Devika | B6: 59 | E6: 4 | F6: 63 | I6: Complex user story which involves multiple screen validation and multiple roles validation and requires more time to automate | J6: 39
A7: Hajara | B7: 26 | C7: 13 | D7: 1 | E7: 23 | F7: 63 | I7: Fresh Deal creation required everytime | J7: 27
A8: Himanshu | B8: 5 | E8: 7 | F8: 12 | I8: IMS BAU | J8: 20
A9: Jaya | B9: 13 | C9: 4 | E9: 15 | F9: 32 | I9: Complex KDA metrics validation in excel | J9: 17
A10: Kavi | B10: 18 | C10: 2 | E10: 7 | F10: 27 | I10: Technical US - Full regression Required | J10: 17
A11: Leena | B11: 27 | C11: 16 | E11: 31 | F11: 74 | I11: LLM Dynamic response generation User story which is not partially automatable | J11: 15
A12: Nandini | B12: 42 | C12: 65 | E12: 33 | F12: 140 | I12: PCW User Story | J12: 15
A13: Pirtheebaa | B13: 10 | C13: 37 | E13: 6 | F13: 53 | I13: 200+ nudges validation and resposne time greater than 15 mins | J13: 11
A14: Rajeswari | B14: 18 | C14: 6 | F14: 24 | I14: BPMS BAU | J14: 11
A15: Shini | B15: 17 | C15: 38 | E15: 6 | F15: 61 | I15: Agent SCA Testing | J15: 9
A16: Grand Total | B16: 251 | C16: 187 | D16: 1 | E16: 141 | F16: 580 | I16: MDA Power BI to DSP Integration | J16: 8
I17: external Integration validation | J17: 8
I18: Everytime new User validation | J18: 8
I19: User story validation for SM and Above career level | J19: 7
I20: Complex User story will be delivered April 28th and not enough time to complete Insprint | J20: 5
I21: Removed Screen Validation cannot be automated because x path will not be found | J21: 3
I22: Basic email validation after just login | J22: 2
I23: Grand Total | J23: 282
A26: Insprint Yes/No | B26: Yes
A27: If insprint YES - % of completion | B27: 0
C29: Values
A30: PT Lead | B30: Insprint Tester | C30: Count of Title | D30: Average of If insprint YES - % of completion
A31: Hajara | B31: sujana.panigrahi | C31: 2 | D31: 0
B32: reshma.sundar | C32: 1 | D32: 0
A33: Leena | B33: Naveen.arunachalam | C33: 4 | D33: 0
B34: prasanna.pandian | C34: 1 | D34: 0
B35: navya.majji | C35: 5 | D35: 0
A36: Nandini | B36: bhavana.reddy.alla | C36: 1 | D36: 0
B37: r.yuvanitharsana | C37: 1 | D37: 0
B38: guddeti.srilekha | C38: 1 | D38: 0
A39: Pirtheebaa | B39: Manisha.m.sharma | C39: 6 | D39: 0
A40: Shini | B40: lakshmi.e.j | C40: 4 | D40: 0
A41: Grand Total | C41: 26 | D41: 0

Sheet Milestone
A1: User story Freeze Date | B1: Cut off for PT hand over | C1: Cut off for UAT hand over | D1: UAT Completion | E1: Functional Bug closure | F1: Regression | G1: Regression bug Closure | H1: Code Freeze | I1: Initial GNG decision | J1: Final Go/No Go Decision | K1: Final Go-Live
A2: 46111 | B2: 46134 | C2: 46140 | D2: 46147 | E2: 46147 | F2: 29-April to 4-May | G2: 46148 | H2: 46148 | I2: 46147 | J2: 46150 | K2: 46151

Sheet Detail1
A1: Details for Count of Title - Pre defined No Reason: Excel Validation, Insprint Yes/No: No, PT Lead: Anand (+)
A3: Module (TextVerification) | B3: Parent Title | C3: Feature ID | D3: PT Lead | E3: Title | F3: ID | G3: Primary tester | H3: Secondary Tester | I3: Insprint Tester | J3: Insprint Yes/No | K3: If Insprint NO - Reason | L3: Pre defined No Reason | M3: Complexity | N3: In sprint test case count | O3: If insprint YES - % of completion | P3: Automated cases generated from GHC | Q3: Useful Automated cases from GHC | R3: Tester created automated count (not given by GHC) | S3: Reviwed Final automation count | T3: Coverage for automated test case from GHC% | U3: Accuracy of Automated Test case from GHC% | V3: Test Planning | W3: BA Review | X3: TFS upload | Y3: PT Status | Z3: Manual Test cases generated from GHC | AA3: Useful Test cases from GHC | AB3: Tester Created test case count | AC3: Reviwed Final Test case count | AD3: Coverage for Manual Test cases from GHC% | AE3: Accuracy for Manual test cases from GHC% | AF3: TFS state | AG3: Passed | AH3: Failed | AI3: Blocked | AJ3: Not Run | AK3: Total | AL3: Execution % | AM3: Pass % | AN3: Comments | AO3: Node Name | AP3: MPOC
A4: DCSO | B4: myISP - Digital DCSO Summary sections addition and Other changes | C4: 4446711 | D4: Shini | E4: As a Solution Architect, I want imported DCSO editable fields retained when Generate is clicked again for IMS/AMS/SI and mandatory Excel header comments added, so that my data is preserved and the template is self-guiding | F4: 4462742 | G4: Arun | J4: No | K4: Excel inport export functionality | L4: Excel Validation | V4: Not Started | W4: Not Started | X4: Not Started | Y4: Not Started | AF4: New | AG4: 0 | AH4: 0 | AI4: 0 | AJ4: 0 | AK4: 0 | AL4: 0 | AM4: 0 | AO4: TechStars | AP4: mohanraj.a.selvaraj
A5: DCSO | B5: myISP - Digital DCSO Summary sections addition and Other changes | C5: 4446711 | D5: Shini | E5: As a DCSO user, I want the Skill Reference field in the DCSO template to be editable, mandatory and location-validated, so that the correct skill reference is always captured accurately and incorrect entries are flagged before submission | F5: 4451600 | G5: Shital | I5: s.manmit.vanarase | J5: No | K5: Excel Export Import Functionality | L5: Excel Validation | V5: Completed | W5: Completed | X5: Not Started | Y5: Not Started | AF5: New | AG5: 0 | AH5: 0 | AI5: 0 | AJ5: 0 | AK5: 0 | AL5: 0 | AM5: 0 | AO5: TechStars | AP5: mohanraj.a.selvaraj
A6: PCW | B6: PCW - IPC Toolkit Cost Update | C6: 4368214 | D6: Anand | E6: As a PCW user, I want IPC API integrations updated to align with the Differentiation screen decommissioning so that auto-sync workflows function via the new Attach Calculator DB. | F6: 4467805 | G6: Sairam | H6: Naveen S | J6: No | K6: PCW User Story | L6: Excel Validation
A7: PCW | B7: PCW - IPC Toolkit Cost Update | C7: 4368214 | D7: Anand | E7: As a PCW user, I want to see 3 new IPC exemption reasons in the 'Reasons for not configuring IPC' dropdown on the Pricing sheet so that the exemption rationale is captured consistently between PCW and myISP | F7: 4467788 | G7: Naveen S | H7: Sairam | J7: No | K7: PCW User Story | L7: Excel Validation
A8: myISP SI | B8: Expand format limit for staffing OU | C8: 4445149 | D8: Anand | E8: As a Solution Architect, I want the offline utility for the Staffing Baseline to support exporting and importing up to 5000 records, so that I can efficiently manage large staffing datasets without system or UI limitations. | F8: 4033020 | G8: Viji | H8: Sairam | J8: No | K8: Offline Utility OU related(Excel) Functionality Cannot be Automated | L8: Excel Validation | V8: In Progress | W8: Not Started | X8: Not Started | Y8: Not Started | AF8: New | AG8: 0 | AH8: 0 | AI8: 0 | AJ8: 0 | AK8: 0 | AL8: 0 | AM8: 0 | AO8: TechAvengers | AP8: mervinkumar.manickam
A9: Solution Review Agent | B9: [Gen AI - SRA] - Addition of Weighted average, Score, RAG columns in the Review Output Document. | C9: 4393834 | D9: Hajara | E9: [Gen AI - SRA] - Solution to Win Excel Checklist Upgrade - As a myISP User, I should be able to view additional columns in the Review Agent Output document displaying accurate RAG insights for L2-level nudges. | F9: 4392744 | G9: Pratik | H9: Vignesh | I9: p.haribhau.tadke | J9: No | K9: Excel Related functionality cannot be automated | L9: Excel Validation | V9: Completed | W9: Not Started | X9: Not Started | Y9: Not Started | AF9: New | AG9: 0 | AH9: 0 | AI9: 0 | AJ9: 5 | AK9: 5 | AL9: 0 | AM9: 0 | AO9: Gen AI - Solution Review Agent | AP9: n.d.krishnakumar
A10: Review Agent | B10: [SSA - SRA] - Displaying appropriate error messages when DSP ingestion failed. | C10: 4447242 | D10: Hajara | E10: [SSA - SRA] - As a MyISP user, I want to see the exact reason for a DSP ingestion failure displayed in the error message. | F10: 4447244 | G10: Harshitha | H10: Reshma | I10: h.udhayakumar | J10: No | K10: Upload functionality not feasible to automate | L10: Excel Validation | V10: In Progress | W10: Not Started | X10: Not Started | Y10: Not Started | AF10: New | AG10: 0 | AH10: 0 | AI10: 0 | AJ10: 12 | AK10: 12 | AL10: 0 | AM10: 0 | AO10: Gen AI - Solution Review Agent | AP10: n.d.krishnakumar
A11: CDAT | B11: CDAT Gen AI Enhancements. | C11: 4443461 | D11: Hajara | E11: As a myISP user, I want the assessment output to be downloaded in both Excel and Word format, so that I can analyze nudge data, findings, gap analysis, and document processing status | F11: 4429175 | G11: Narmatha | H11: Komal | I11: n.g.senthil.kumar | J11: No | K11: This involves the data validation in excel file, which is not feasible as we need to validate for all nudges in all 3 SG | L11: Excel Validation | V11: Not Started | W11: Not Started | X11: Not Started | Y11: Not Started | AF11: Active | AG11: 0 | AH11: 0 | AI11: 0 | AJ11: 0 | AK11: 0 | AL11: 0 | AM11: 0 | AO11: GENAI-CDAT | AP11: n.d.krishnakumar
A12: Value Shaping | B12: Value Shaping CR | May Scope | C12: 4446213 | D12: Nandini | E12: VS - As a myISP user I want Total Value Potential summary included in PDF and Excel downloads, So that exported artifacts retain the same value insights seen in the application. | F12: 4439529 | G12: Yasin | H12: Bindu | J12: No | K12: cannot automate, verifying downloaded PDF and excel data with UI | L12: Excel Validation | V12: Completed | W12: In Progress | X12: Not Started | Y12: Not Started | Z12: 35 | AA12: 27 | AC12: 27 | AF12: Active | AG12: 0 | AH12: 0 | AI12: 0 | AJ12: 0 | AK12: 0 | AL12: 0 | AM12: 0 | AO12: Spartans | AP12: nityanand.giri
A13: Value Shaping | B13: Value Shaping CR | May Scope | C13: 4446213 | D13: Nandini | E13: VS - As a myISP User I want the Benchmark Target tooltip to show the actual benchmark source, So that I can validate benchmark credibility directly while reviewing KPI details. | F13: 4438585 | G13: Yasin | H13: Bindu | J13: No | K13: cannot automate, verifying downloaded excel data with UI tool tip | L13: Excel Validation | V13: Completed | W13: In Progress | X13: Not Started | Y13: Not Started | Z13: 35 | AA13: 27 | AC13: 27 | AF13: Active | AG13: 0 | AH13: 0 | AI13: 0 | AJ13: 0 | AK13: 0 | AL13: 0 | AM13: 0 | AO13: Spartans | AP13: nityanand.giri
A14: IPC Calculator | B14: IPC Calculator | Package and Cost screen UI changes | C14: 4313249 | D14: Nandini | E14: As a mySP user, I should be able to see an auto created version of IPC from WRWS with updated cost in standard package when solution version is created for the first time | F14: 4372864 | G14: Srilekha | H14: Pawan | J14: No | K14: This story has a lot of calculation with dependancy on excel based validations | L14: Excel Validation | V14: In Progress | W14: Not Started | X14: Not Started | Y14: Not Started | AF14: New | AG14: 0 | AH14: 0 | AI14: 0 | AJ14: 0 | AK14: 0 | AL14: 0 | AM14: 0 | AO14: TechWarriors | AP14: sowjanya.kari
A15: Mobilization Calculator | B15: Mobilization Calculator -Bottom Up CRs | C15: 4232673 | D15: Nandini | E15: As a Mobilization SME, i should be able to see the Phase Wise Cost Summary in the Ramp Summary export | F15: 4368362 | G15: Reshmi | H15: Pawan | J15: No | K15: Excel template Import/Export related US and data validation | L15: Excel Validation | V15: Completed | W15: Not Started | X15: Not Started | Y15: Not Started | AF15: New | AG15: 0 | AH15: 0 | AI15: 0 | AJ15: 19 | AK15: 19 | AL15: 0 | AM15: 0 | AO15: Everest | AP15: nityanand.giri
A16: IPC Calculator | B16: IPC Calculator | Package and Cost screen UI changes | C16: 4313249 | D16: Nandini | E16: As a mySP user, I want to see the updated UI of Package and Cost screen due to the updated cost of standard package | F16: 4354055 | G16: Srilekha | H16: Pawan | J16: No | K16: It is completly new UI changes which included calculations using excel sheet | L16: Excel Validation | V16: In Progress | W16: Not Started | X16: Not Started | Y16: Not Started | AF16: Active | AG16: 0 | AH16: 0 | AI16: 0 | AJ16: 0 | AK16: 0 | AL16: 0 | AM16: 0 | AO16: TitansPlus | AP16: nityanand.giri
A17: Value Shaping | B17: Value Shaping –Enhancements | C17: 4330994 | D17: Nandini | E17: Value Shaping - As a myISP user, I should be able to download output (Global View) as excel from summary screen of SVP page, so that it can be used for other purposes | F17: 4318913 | G17: Bindu | H17: Yasin | J17: No | K17: cannot automate, verifying downloaded excel data with UI | L17: Excel Validation | V17: In Progress | W17: Not Started | X17: Not Started | Y17: Not Started | AF17: Active | AG17: 0 | AH17: 0 | AI17: 0 | AJ17: 0 | AK17: 0 | AL17: 0 | AM17: 0 | AO17: Spartans | AP17: nityanand.giri
A18: Value Shaping | B18: Value Shaping –Enhancements | C18: 4330994 | D18: Nandini | E18: Value Shaping - As a myISP user, I should be able to download output (Benchmark and size of prize View) as excel from summary screen of SVP page, so that it can be used for other purposes | F18: 4165234 | G18: Yasin | H18: Bindu | J18: No | K18: cannot automate, verifying downloaded excel data with UI | L18: Excel Validation | V18: Completed | W18: In Progress | X18: Not Started | Y18: Not Started | Z18: 35 | AA18: 29 | AC18: 29 | AF18: Active | AG18: 0 | AH18: 0 | AI18: 0 | AJ18: 0 | AK18: 0 | AL18: 0 | AM18: 0 | AO18: Spartans | AP18: nityanand.giri
A19: Value Shaping | B19: Value Shaping –Enhancements | C19: 4330994 | D19: Nandini | E19: Value Shaping - As a myISP user, I should be able to download output (Tree View) as excel from summary screen of SVP page, so that it can be used for other purposes | F19: 4165232 | G19: Yasin | H19: Bindu | J19: No | K19: cannot automate, verifying downloaded excel data with UI | L19: Excel Validation | V19: Completed | W19: In Progress | X19: Not Started | Y19: Not Started | Z19: 35 | AA19: 22 | AC19: 22 | AF19: Active | AG19: 0 | AH19: 0 | AI19: 0 | AJ19: 0 | AK19: 0 | AL19: 0 | AM19: 0 | AO19: Spartans | AP19: nityanand.giri
A20: Value Shaping | B20: Value Shaping –Enhancements | C20: 4330994 | D20: Nandini | E20: Value Shaping -As a myISP user, I should be able to download output (Tech Transformation View) as excel from summary screen of SVP page, so that it can be used for other purposes | F20: 4165224 | G20: Bindu | H20: Yasin | J20: No | K20: cannot automate, verifying downloaded excel data with UI | L20: Excel Validation | V20: Completed | W20: In Progress | X20: Not Started | Y20: Not Started | AF20: Active | AG20: 0 | AH20: 0 | AI20: 0 | AJ20: 0 | AK20: 0 | AL20: 0 | AM20: 0 | AO20: Spartans | AP20: nityanand.giri
A21: Value Shaping | B21: Value Shaping –Enhancements | C21: 4330994 | D21: Nandini | E21: Value Shaping - As a myISP user, I should be able to download output (Value Led AM View) as excel from summary screen of SVP page, so that it can be used for other purposes | F21: 4165212 | G21: Bindu | H21: Yasin | J21: No | K21: cannot automate, verifying downloaded excel data with UI | L21: Excel Validation | V21: Completed | W21: In Progress | X21: Not Started | Y21: Not Started | AF21: Active | AG21: 0 | AH21: 0 | AI21: 0 | AJ21: 0 | AK21: 0 | AL21: 0 | AM21: 0 | AO21: Spartans | AP21: nityanand.giri
A22: Value Shaping | B22: Value Shaping –Enhancements | C22: 4330994 | D22: Nandini | E22: Value Shaping - As a myISP user, I should be able to download output (360 Dimension View) as excel from summary screen of SVP page, so that it can be used for other purposes | F22: 4165210 | G22: Yasin | H22: Bindu | J22: No | K22: cannot automate, verifying downloaded excel data with UI | L22: Excel Validation | V22: Completed | W22: In Progress | X22: Not Started | Y22: Not Started | Z22: 57 | AA22: 32 | AC22: 32 | AF22: Active | AG22: 0 | AH22: 0 | AI22: 0 | AJ22: 0 | AK22: 0 | AL22: 0 | AM22: 0 | AO22: Spartans | AP22: nityanand.giri
A23: Calculator | B23: Attach Calculator | C23: 4372279 | D23: Nandini | E23: [Attach Calculator] AMS As a myISP user, I want to implement Document download functionality in Attach calculator, so that the Attach Calculator experience aligns with defined business standards | F23: 4367506 | G23: Amalarasi | H23: Sunanda | J23: No | K23: cannot automate, verifying downloaded excel data with UI | L23: Excel Validation | V23: In Progress | W23: Not Started | X23: Not Started | Y23: Not Started | AF23: Active | AG23: 0 | AH23: 0 | AI23: 0 | AJ23: 0 | AK23: 0 | AL23: 0 | AM23: 0 | AO23: TitansPlus | AP23: nityanand.giri
A24: SI | B24: Dynamic Target Pricing - Remaining Scope - May Release | C24: 4422839 | D24: Anand | E24: SI | As a SA, Role Type should be mandatory for applicable SSGs on Staffing Baseline - OU | F24: 4449779 | G24: Viji | H24: Sairam | J24: No | K24: Offline Utility OU related(Excel) Functionality Cannot be Automated | L24: Excel Validation | V24: In Progress | W24: Not Started | X24: Not Started | Y24: Not Started | AF24: In Development | AG24: 0 | AH24: 0 | AI24: 0 | AJ24: 0 | AK24: 0 | AL24: 0 | AM24: 0 | AO24: TechAvengers | AP24: mervinkumar.manickam
A25: CON-CAS - PCW | B25: Standard Role Implementation in PCW & Online SI - May Release | C25: 4436131 | D25: Anand | E25: PCW - Add Technology Role and Standard Role Columns in Staffing Baseline for CON-CAS | F25: 4450157 | G25: Naveen S | H25: Viji | J25: No | K25: PCW User Story | L25: Excel Validation | V25: In Progress | W25: Not Started | X25: Not Started | Y25: Not Started | AF25: New | AG25: 0 | AH25: 0 | AI25: 0 | AJ25: 0 | AK25: 0 | AL25: 0 | AM25: 0 | AO25: Tech Ensemble | AP25: mervinkumar.manickam
A26: AMS OCP | B26: AMS-OCP: AMS - Cluster based KDA Phase 1 - OCP KDA UI and Excel reports | C26: 4438595 | D26: Jaya | E26: AMS-OCP-View KDA Excel: As a mySolutionPlanner user, I want the KDA Excel download to include one additional tab per configured cluster showing the cluster-specific KDA matrix, So that use can view the updated View KDA excel report. | F26: 4449948 | G26: Ayush | H26: Anu | J26: No | K26: Export excels Validation | L26: Excel Validation | V26: Not Started | W26: Not Started | X26: Not Started | Y26: Not Started | AF26: Active | AG26: 0 | AH26: 0 | AI26: 0 | AJ26: 0 | AK26: 0 | AL26: 0 | AM26: 0 | AO26: CreativeCoders | AP26: K.devaraj
A27: BPMS OCP | B27: BPMS Negotiation Contingency | C27: 4446028 | D27: Jaya | E27: BPMS - As a myISP SA, I want to enter a negotiation contingency % in Solution Workbench so that the system calculates and displays the negotiation contingency value in Financials and sends it to all downstream modules. | F27: 4444316 | G27: Anu | H27: Ayush | J27: No | K27: cannot be automated, it involves calculation and excel reports validation | L27: Excel Validation | V27: Completed | W27: Completed | X27: Not Started | Y27: In Progress | Z27: 20 | AA27: 18 | AB27: 2 | AC27: 20 | AD27: 0.95 | AE27: 1 | AF27: PT In Test | AG27: 5 | AH27: 0 | AI27: 0 | AJ27: 15 | AK27: 20 | AL27: 0.25 | AM27: 1 | AO27: CreativeCoders | AP27: K.devaraj
A28: AMS | B28: AMS: Increasing Staffing records in LBS UI for OU report | C28: 4443033 | D28: Jaya | E28: AMS: As a mySolutionPlanner user, I want the Staffing screen LBS tab to display up to 4,000 records in the UI, So that the UI record display limit is aligned with the OU export and import limit of 4,000 records. | F28: 4443034 | G28: Priyanka | H28: Ayush | J28: No | K28: Export and import report of OU staffing cannot be validated | L28: Excel Validation | M28: Complex | V28: Completed | W28: In Progress | X28: Not Started | Y28: Not Started | Z28: 15 | AF28: New | AG28: 0 | AH28: 0 | AI28: 0 | AJ28: 0 | AK28: 0 | AL28: 0 | AM28: 0 | AO28: TechMavericks | AP28: Francis.Deepak
A29: BPMS DCTA | B29: BPMS Negotiation Contingency | C29: 4446028 | D29: Jaya | E29: As a myISP SA I want the Negotiation Contingency to be displayed on the Financials screen for DCTA route deals So that I can review the contingency buffer applied to pricing without switching to BPMS, enabling complete financial visibility in one view. | F29: 4440929 | G29: Jothika | H29: Anu | J29: No | K29: cannot be automated, it involves calculation and excel reports validation | L29: Excel Validation | V29: Completed | W29: Completed | X29: Not Started | Y29: In Progress | Z29: 20 | AA29: 20 | AB29: 0 | AC29: 20 | AD29: 1 | AE29: 1 | AF29: PT In Test | AG29: 5 | AH29: 0 | AI29: 0 | AJ29: 15 | AK29: 20 | AL29: 0.25 | AM29: 1 | AO29: Simulators | AP29: K.devaraj
A30: IMS Multi tower pricing | B30: IMS Multi Tower pricing (IMS+SI+CON) | C30: 4439712 | D30: Jaya | E30: IMS-OCP > CY/FY/MOM/Graph view reports: s a mySolutionPlanner user, I want the CY, FY, Month-on-Month (MoM), and Graph View reports to be enabled and available for SI (SI+CON) in addition to IMS, accessible at the deal level only (IMS or SI+CON) | F30: 4439840 | G30: Sriram | H30: Jothika | J30: No | K30: Excel Parts cannot be validated | L30: Excel Validation | V30: Not Started | W30: Not Started | X30: Not Started | Y30: Not Started | AF30: Active | AG30: 0 | AH30: 0 | AI30: 0 | AJ30: 0 | AK30: 0 | AL30: 0 | AM30: 0 | AO30: CodingCrusaders | AP30: K.devaraj
A31: DCSO | B31: myISP DCSO - Delivery Lead Assignments | C31: 4446526 | D31: Shini | E31: As a Delivery Lead, I want to be able to download and import DCSO files from the DCSO screen so that I can review, share and upload DCSO data without depending on other team members. | F31: 4445991 | G31: Arun | H31: Pavithra | I31: arun.thangapandian | J31: No | K31: Export Import Functionality | L31: Excel Validation | V31: Not Started | W31: Not Started | X31: Not Started | Y31: Not Started | AF31: New | AG31: 0 | AH31: 0 | AI31: 0 | AJ31: 0 | AK31: 0 | AL31: 0 | AM31: 0 | AO31: TechStars | AP31: mohanraj.a.selvaraj
A32: DCSO | B32: myISP - Digital DCSO Reports | C32: 4462171 | D32: Shini | E32: As a Solution Architect, I want to export DCSO Report data for offline sharing and analysis | F32: 4462198 | G32: Jeba | H32: Sakshi | I32: jeba.momin | J32: No | K32: Export data functionality | L32: Excel Validation | V32: Not Started | W32: Not Started | X32: Not Started | Y32: Not Started | AF32: New | AG32: 0 | AH32: 0 | AI32: 0 | AJ32: 0 | AK32: 0 | AL32: 0 | AM32: 0 | AO32: SolutionDataLake | AP32: vishal.v.nadpurohit
A33: DCSO | B33: myISP - Digital DCSO Summary sections addition and Other changes | C33: 4446711 | D33: Shini | E33: As a Solution Architect, I want Transition and SD resource line items to be merged into a single row when they belong to the same group in the DCSO report so that the report is concise and easier to review | F33: 4425029 | G33: Arun | H33: Shital | I33: arun.thangapandian | J33: No | K33: Export Import Functionality | L33: Excel Validation | V33: Not Started | W33: Not Started | X33: Not Started | Y33: Not Started | AF33: New | AG33: 0 | AH33: 0 | AI33: 0 | AJ33: 0 | AK33: 0 | AL33: 0 | AM33: 0 | AO33: TechStars | AP33: mohanraj.a.selvaraj
A34: DCSO | B34: myISP- Digital DCSO - Publish functionality | C34: 4420374 | D34: Shini | E34: **As a** Solution Architect **I want** the system to validate that each resource line's FTE Start Date is at least 16 calendar days ahead of the Publish Date when I click Publish **So that** Publish is successful | F34: 4422310 | G34: Mahesh | H34: Nithish | J34: No | K34: Excel sheet validation | L34: Excel Validation | V34: Completed | W34: Not Started | X34: Not Started | Y34: Not Started | AF34: In Development | AG34: 0 | AH34: 0 | AI34: 0 | AJ34: 0 | AK34: 0 | AL34: 0 | AM34: 0 | AO34: TechStars | AP34: mohanraj.a.selvaraj
A35: DCSO | B35: myISP- Digital DCSO - Publish functionality | C35: 4420374 | D35: Shini | E35: **As a** Solution Architect **I want** the Publish icon to be enabled only after a DCSO has been successfully imported **So that** I cannot accidentally publish incomplete or unimported DCSO data to the HR tool | F35: 4278131 | G35: Mahesh | H35: Nithish | J35: No | K35: Import Functionaity | L35: Excel Validation | V35: Completed | W35: Not Started | X35: Not Started | Y35: Not Started | AF35: In Development | AG35: 0 | AH35: 0 | AI35: 0 | AJ35: 0 | AK35: 4 | AL35: 0 | AM35: 0 | AO35: TechStars | AP35: mohanraj.a.selvaraj
A36: SI DCTA | B36: Billable expense parameter split in Financial UI | C36: 4446026 | D36: Kavi | E36: As a myISP SA, I want to view 6 billable expense metrics on the KDA screen for the DCTA route (same as OCP), so that I can accurately assess financials with and without billable expense for DCTA engagements. | F36: 4435817 | G36: Sohana | H36: Amresh | J36: No | K36: Require excel report validation | L36: Excel Validation | V36: Not Started | W36: Not Started | X36: Not Started | Y36: Not Started | AF36: Active | AG36: 0 | AH36: 0 | AI36: 0 | AJ36: 0 | AK36: 0 | AL36: 0 | AM36: 0 | AO36: Simulators | AP36: K.devaraj
A37: SI KDA | B37: WFH - ATCI and WFH ATCP to include updated logic from DNP | C37: 4250760 | D37: Kavi | E37: As a mysolution planner Solution Architect, I want the WFO details to fetch from SI DNP screen and update in SI KDA(DATA/MMP-FFP/OCP/DCTA KDA) So that user can view updated logic for WFH metrics in view KDA | F37: 4429069 | G37: Sai/Bhavana | H37: Sathya | J37: No | K37: Involves calculation & excel report validation is not possible | L37: Excel Validation | V37: Completed | W37: Completed | X37: Not Started | Y37: Not Started | Z37: 14 | AA37: 12 | AB37: 0 | AC37: 12 | AD37: 1 | AE37: 0.8 | AF37: Active | AG37: 0 | AH37: 0 | AI37: 0 | AJ37: 12 | AK37: 12 | AL37: 0 | AM37: 0 | AO37: Insurgents | AP37: K.devaraj
A38: IPC Calculator | B38: IPC Calculator | New Exemption Reasons | C38: 4428652 | D38: Kavi | E38: As a myISP user, I want Harmonized KDA to reflect the same IPC RAG outcome for the three new exemption reasons so that downstream governance reporting remains aligned. | F38: 4428664 | G38: Amresh | H38: Sohana | J38: No | K38: Require excel report validation | L38: Excel Validation | V38: Not Started | W38: Not Started | X38: Not Started | Y38: Not Started | AF38: Ready for Test | AG38: 0 | AH38: 0 | AI38: 0 | AJ38: 0 | AK38: 0 | AL38: 0 | AM38: 0 | AO38: Insurgents | AP38: K.devaraj
A39: Differentiation | B39: Differentiation Decommission | C39: 4372017 | D39: Kavi | E39: SI only- As a Solution Architect I want the Harmonized KDA report to consume Attach Calculator index score in place of Differentiation So that Harmonized KDA report data remains accurate after the Differentiation screen is decommissioned | F39: 4445144 | G39: Amresh | H39: Sohana | J39: No | K39: Require excel report validation | L39: Excel Validation | V39: Not Started | W39: Not Started | X39: Not Started | Y39: Not Started | AF39: Active | AG39: 0 | AH39: 0 | AI39: 0 | AJ39: 0 | AK39: 0 | AL39: 0 | AM39: 0 | AO39: Simulators | AP39: K.devaraj
A40: SI KDA | B40: WFH - ATCI and WFH ATCP to include updated logic from DNP | C40: 4250760 | D40: Kavi | E40: As a mysolution planner Solution Architect, I want the WFH ATCI and WFH ATCP fields in SI KDA(OCP KDA route) to include the updated logic from DNP, So that user can view updated logic for WFH metrics | F40: 4371721 | G40: Sai/Bhavana | H40: Sathya | J40: No | K40: Involves calculation & excel report validation is not possible | L40: Excel Validation | V40: Completed | W40: Completed | X40: Not Started | Y40: Not Started | Z40: 17 | AA40: 16 | AB40: 0 | AC40: 16 | AD40: 1 | AE40: 0.9 | AF40: Active | AG40: 0 | AH40: 0 | AI40: 0 | AJ40: 16 | AK40: 16 | AL40: 0 | AM40: 0 | AO40: Insurgents | AP40: K.devaraj
A41: SI KDA | B41: WFH - ATCI and WFH ATCP to include updated logic from DNP | C41: 4250760 | D41: Kavi | E41: As a Solution Architect , I want the YearonYear (YoY) values received from DNP to be updated in SI WFH metrics and displayed for existing deals, So that existing records correctly reflect YoY data from DNP | F41: 4367388 | G41: Sai/Bhavana | H41: Sathya | J41: No | K41: Involves calculation &excel report validation of YOY Split for all KDAs is not possible | L41: Excel Validation | V41: Completed | W41: Completed | X41: Not Started | Y41: Not Started | Z41: 16 | AA41: 14 | AB41: 0 | AC41: 14 | AD41: 1 | AE41: 0.8 | AF41: Active | AG41: 0 | AH41: 0 | AI41: 0 | AJ41: 14 | AK41: 14 | AL41: 0 | AM41: 0 | AO41: Insurgents | AP41: K.devaraj
A42: SI KDA | B42: WFH - ATCI and WFH ATCP to include updated logic from DNP | C42: 4250760 | D42: Kavi | E42: As a mysolution planner Solution Architect, I want the WFH ATCI and WFH ATCP fields in Harmonized KDA, Analytics to show the updated logic from SI KDA, So that user can view updated logic for WFH metrics | F42: 4312145 | G42: Sai/Bhavana | H42: Sathya | J42: No | K42: Excel report validation is not possible | L42: Excel Validation | V42: Completed | W42: Completed | X42: Not Started | Y42: Not Started | Z42: 17 | AA42: 16 | AB42: 1 | AC42: 17 | AD42: 0.94117647 | AE42: 0.85 | AF42: Active | AG42: 0 | AH42: 0 | AI42: 0 | AJ42: 17 | AK42: 17 | AL42: 0 | AM42: 0 | AO42: Insurgents | AP42: K.devaraj
A43: SI KDA | B43: WFH - ATCI and WFH ATCP to include updated logic from DNP | C43: 4250760 | D43: Kavi | E43: As a mysolution planner Solution Architect, I want to view WFH% details for ATCI and ATCP with an option to expand and see Y1-Y10 values in SI DATA KDA , So that user can view YoY details | F43: 4252811 | G43: Sai/Bhavana | H43: Sathya | J43: No | K43: Involves calculation & excel report validation of YOY Split is not possible | L43: Excel Validation | V43: Completed | W43: Completed | X43: Not Started | Y43: Not Started | Z43: 16 | AA43: 15 | AB43: 1 | AC43: 16 | AD43: 0.9375 | AE43: 0.85 | AF43: Active | AG43: 0 | AH43: 0 | AI43: 0 | AJ43: 16 | AK43: 16 | AL43: 0 | AM43: 0 | AO43: Insurgents | AP43: K.devaraj
A44: SI KDA | B44: WFH - ATCI and WFH ATCP to include updated logic from DNP | C44: 4250760 | D44: Kavi | E44: As a mysolution planner Solution Architect, I want the WFH ATCI and WFH ATCP fields in SI KDA(DATA KDA) to include the updated logic from DNP, So that user can view updated logic for WFH metrics | F44: 4250789 | G44: Sai/Bhavana | H44: Sathya | J44: No | K44: Involves calculation & excel report validation is not possible | L44: Excel Validation | V44: Completed | W44: Completed | X44: Not Started | Y44: Not Started | Z44: 17 | AA44: 16 | AB44: 0 | AC44: 16 | AD44: 1 | AE44: 0.9 | AF44: Active | AG44: 0 | AH44: 0 | AI44: 0 | AJ44: 16 | AK44: 16 | AL44: 0 | AM44: 0 | AO44: Insurgents | AP44: K.devaraj
A45: SI KDA | B45: WFH - ATCI and WFH ATCP to include updated logic from DNP | C45: 4250760 | D45: Kavi | E45: As a mysolution planner Solution Architect, I want to view WFH% details for ATCI and ATCP with an option to expand and see Y1-Y10 values in SI OCP KDA , So that user can view YoY details | F45: 4416213 | G45: Sai/Bhavana | H45: Sathya | J45: No | K45: Involves calculation & excel report validation of YOY Split is not possible | L45: Excel Validation | V45: Completed | W45: Completed | X45: Not Started | Y45: Not Started | Z45: 16 | AA45: 15 | AB45: 1 | AC45: 16 | AD45: 0.9375 | AE45: 0.85 | AF45: Active | AG45: 0 | AH45: 0 | AI45: 0 | AJ45: 16 | AK45: 16 | AL45: 0 | AM45: 0 | AO45: Insurgents | AP45: K.devaraj
A46: SI KDA | B46: WFH - ATCI and WFH ATCP to include updated logic from DNP | C46: 4250760 | D46: Kavi | E46: As a mysolution planner Solution Architect, I want to view WFH% details for ATCI and ATCP with an option to expand and see Y1-Y10 values in SI DCTA KDA , So that user can view YoY details | F46: 4416199 | G46: Sai/Bhavana | H46: Sathya | J46: No | K46: Involves calculation & excel report validation of YOY Split is not possible | L46: Excel Validation | V46: Completed | W46: Completed | X46: Not Started | Y46: Not Started | Z46: 16 | AA46: 15 | AB46: 1 | AC46: 17 | AD46: 0.88235294 | AE46: 0.85 | AF46: Active | AG46: 0 | AH46: 0 | AI46: 0 | AJ46: 17 | AK46: 17 | AL46: 0 | AM46: 0 | AO46: Insurgents | AP46: K.devaraj
A47: SI KDA | B47: WFH - ATCI and WFH ATCP to include updated logic from DNP | C47: 4250760 | D47: Kavi | E47: As a mysolution planner Solution Architect, I want to view WFH% details for ATCI and ATCP with an option to expand and see Y1-Y10 values in SI MMP-FFP KDA , So that user can view YoY details | F47: 4416198 | G47: Sai/Bhavana | H47: Sathya | J47: No | K47: Involves calculation & excel report validation of YOY Split is not possible | L47: Excel Validation | V47: Completed | W47: Completed | X47: Not Started | Y47: Not Started | Z47: 16 | AA47: 16 | AB47: 1 | AC47: 17 | AD47: 0.94117647 | AE47: 0.9 | AF47: Active | AG47: 0 | AH47: 0 | AI47: 0 | AJ47: 17 | AK47: 17 | AL47: 0 | AM47: 0 | AO47: Insurgents | AP47: K.devaraj
A48: SI KDA | B48: WFH - ATCI and WFH ATCP to include updated logic from DNP | C48: 4250760 | D48: Kavi | E48: As a mysolution planner Solution Architect, I want the WFH ATCI and WFH ATCP fields in SI KDA(DCTA KDA route) to include the updated logic from DNP, So that user can view updated logic for WFH metrics | F48: 4413836 | G48: Sai/Bhavana | H48: Sathya | J48: No | K48: Involves calculation & excel report validation is not possible | L48: Excel Validation | V48: Completed | W48: Completed | X48: Not Started | Y48: Not Started | Z48: 18 | AA48: 17 | AB48: 0 | AC48: 17 | AD48: 1 | AE48: 0.85 | AF48: Active | AG48: 0 | AH48: 0 | AI48: 0 | AJ48: 17 | AK48: 17 | AL48: 0 | AM48: 0 | AO48: Insurgents | AP48: K.devaraj
A49: SI KDA | B49: WFH - ATCI and WFH ATCP to include updated logic from DNP | C49: 4250760 | D49: Kavi | E49: As a mysolution planner Solution Architect, I want the WFH ATCI and WFH ATCP fields in SI KDA(MMP-FFP route) to include the updated logic from DNP, So that user can view updated logic for WFH metrics | F49: 4413833 | G49: Sai/Bhavana | H49: Sathya | J49: No | K49: Involves calculation & excel report validation is not possible | L49: Excel Validation | V49: Completed | W49: Completed | X49: Not Started | Y49: Not Started | Z49: 18 | AA49: 18 | AB49: 0 | AC49: 18 | AD49: 1 | AE49: 0.9 | AF49: Active | AG49: 0 | AH49: 0 | AI49: 0 | AJ49: 18 | AK49: 18 | AL49: 0 | AM49: 0 | AO49: Insurgents | AP49: K.devaraj
A50: Differentiation | B50: Differentiation Decommission | C50: 4372017 | D50: Kavi | E50: AMS/SI As a Solution Architect I want the KDA report to consume Attach Calculator index score in place of Differentiation So that KDA report data remains accurate after the Differentiation screen is decommissioned | F50: 4372033 | G50: Amresh | H50: Sohana | J50: No | K50: Require excel report validation | L50: Excel Validation | V50: Not Started | W50: Not Started | X50: Not Started | Y50: Not Started | AF50: Active | AG50: 0 | AH50: 0 | AI50: 0 | AJ50: 0 | AK50: 0 | AL50: 0 | AM50: 0 | AO50: Simulators | AP50: K.devaraj
A51: IPC Calculator | B51: IPC Calculator | New Exemption Reasons | C51: 4428652 | D51: Kavi | E51: As a myISP user, I want View KDA to apply the same exemption behavior for the three new IPC reasons so that governance output remains consistent with existing logic. | F51: 4428656 | G51: Amresh | H51: Sohana | J51: No | K51: Require excel report validation | L51: Excel Validation | V51: Not Started | W51: Not Started | X51: Not Started | Y51: Not Started | AF51: Ready for Test | AG51: 0 | AH51: 0 | AI51: 0 | AJ51: 0 | AK51: 0 | AL51: 0 | AM51: 0 | AO51: Insurgents | AP51: K.devaraj
A52: Online SI | B52: Dynamic Target Pricing - Remaining Scope - May Release | C52: 4422839 | D52: Kavi | E52: As a SA, I want MMP FFP Role (Accenture Role/Rate) populated in Staffing Baseline and exported to MMP FFP template | F52: 4423306 | G52: Sohana | H52: Amresh | J52: No | K52: Require FFP excel template validation | L52: Excel Validation | V52: Not Started | W52: Not Started | X52: Not Started | Y52: Not Started | AF52: In Development | AG52: 0 | AH52: 0 | AI52: 0 | AJ52: 0 | AK52: 0 | AL52: 0 | AM52: 0 | AO52: DevStormers | AP52: mervinkumar.manickam
A53: Differentiation | B53: Differentiation Decommission | C53: 4372017 | D53: Kavi | E53: As a Solution Architect I want the MMP-FFP report to be updated to use Attach Calculator data in place of Differentiation So that MMP-FFP reporting remains accurate after the Differentiation screen is decommissioned | F53: 4372031 | G53: Sohana | H53: Amresh | J53: No | K53: Require excel report validation | L53: Excel Validation | V53: Not Started | W53: Not Started | X53: Not Started | Y53: Not Started | AF53: In Development | AG53: 0 | AH53: 0 | AI53: 0 | AJ53: 0 | AK53: 0 | AL53: 0 | AM53: 0 | AO53: DevStormers | AP53: mervinkumar.manickam
A54: Offline Utility | B54: Dynamic Target Pricing - Remaining Scope - May Release | C54: 4422839 | D54: Kavi | E54: As a SA, add MMP FFP Role column next to Role Type in Staffing Baseline - OU changes | F54: 4390542 | G54: Manisa | H54: Sathya | J54: No | K54: Involves OU Excel Validations | L54: Excel Validation | V54: Not Started | W54: Not Started | X54: Not Started | Y54: Not Started | AF54: In Development | AG54: 0 | AH54: 0 | AI54: 0 | AJ54: 0 | AK54: 0 | AL54: 0 | AM54: 0 | AO54: TechWizards | AP54: mervinkumar.manickam
A55: FFP | B55: Dynamic Target Pricing - Remaining Scope - May Release | C55: 4422839 | D55: Kavi | E55: As a SA, add MMP FFP Role column next to Role Type in Staffing Baseline | F55: 4390540 | G55: Manisa | H55: Sathya | J55: No | K55: Involves Excel Validations | L55: Excel Validation | V55: Not Started | W55: Not Started | X55: Not Started | Y55: Not Started | AF55: In Development | AG55: 0 | AH55: 0 | AI55: 0 | AJ55: 0 | AK55: 0 | AL55: 0 | AM55: 0 | AO55: TechWizards | AP55: mervinkumar.manickam
A56: Online SI | B56: |Query | 11th Oct | UAT | PCW|MMP FFP| Not Getting value for Activity (BPMS) column for MMP FFP template when generated via Online, however PCW offline export template is displaying value. | C56: 4165954 | D56: Kavi | E56: Online SI FFP | As a Solution Architect, I want to see Activity(BPMS only) in FFP Template when BPMS SG is solutioned in SI Staffing Baseline | F56: 4183616 | G56: Sohana | H56: Amresh | J56: No | K56: Require FFP excel template validation | L56: Excel Validation | V56: Not Started | W56: Not Started | X56: Not Started | Y56: Not Started | AF56: Ready to Deploy | AG56: 0 | AH56: 0 | AI56: 0 | AJ56: 0 | AK56: 0 | AL56: 0 | AM56: 0 | AO56: DevStormers | AP56: mervinkumar.manickam
A57: Differentiation | B57: Differentiation Decommission | C57: 4372017 | D57: Kavi | E57: As a Solution Architect I want DCTA to be updated to use Attach Calculator data in place of Differentiation So that DCTA functionality remains accurate after the Differentiation screen is decommissioned | F57: 4362070 | G57: Amresh | H57: Sohana | J57: No | K57: Require excel report validation & Calculation | L57: Excel Validation | V57: Not Started | W57: Not Started | X57: Not Started | Y57: Not Started | AF57: In Development | AG57: 0 | AH57: 0 | AI57: 0 | AJ57: 0 | AK57: 0 | AL57: 0 | AM57: 0 | AO57: TechSprinters | AP57: mervinkumar.manickam
A58: SI MMP FFP | B58: SI-MMP FFP, Data: Updating the logic for populating the Deal Rag Status in KDA Variance Analysis Report | C58: 4441807 | D58: Kavi | E58: SI-MMP FFP: As a mySolutionPlanner developer, I want to update the logic for deal RAG status to display in KDA Variance Analysis when the user triggers KDA, so that RAG color is aligned with the RAG color displayed for Adherence score in View KDA. | F58: 4443542 | G58: Sathya | H58: Bhavana | J58: No | K58: Offline Utility OU related(Excel) Functionality Cannot be Automated | L58: Excel Validation | V58: Completed | W58: In Progress | X58: Not Started | Y58: Not Started | AF58: Active | AG58: 0 | AH58: 0 | AI58: 0 | AJ58: 0 | AK58: 0 | AL58: 0 | AM58: 0 | AO58: CodeCrafters | AP58: sona.job
A59: CDAT | B59: BPMS Onboarding to CDAT | C59: 4459051 | D59: Rajeswari | E59: As a CDAT Lead, I want to download links for the PMO Extract & CDAT Online Extract Download via PMO Dashboard | F59: 4449532 | G59: Sowndarya | H59: Pavithra | J59: No | K59: Excel validation | L59: Excel Validation | V59: In Progress | W59: Not Started | X59: Not Started | Y59: Not Started | Z59: 40 | AF59: New | AG59: 0 | AH59: 0 | AI59: 0 | AJ59: 0 | AK59: 0 | AL59: 0 | AM59: 0 | AO59: TechTribe | AP59: pandidurai.ks
A60: CDAT | B60: BPMS Onboarding to CDAT | C60: 4459051 | D60: Rajeswari | E60: As a CDAT SME user or CDAT CM SME or CDAT Reviewer, I want a new editable dropdown field "Contract Submission Status" on the Assessment Details page | F60: 4449651 | G60: Jabeen | H60: Shiva | J60: No | K60: Excel validation | L60: Excel Validation | V60: In Progress | W60: Not Started | X60: Not Started | Y60: Not Started | Z60: 40 | AF60: Active | AG60: 0 | AH60: 0 | AI60: 0 | AJ60: 0 | AK60: 0 | AL60: 0 | AM60: 0 | AO60: TechTribe | AP60: pandidurai.ks
A61: SI Data | B61: SI-MMP FFP, Data: Updating the logic for populating the Deal Rag Status in KDA Variance Analysis Report | C61: 4441807 | D61: Kavi | E61: SI-Data: As a mySolutionPlanner developer, I want to update the logic for deal RAG status to display in KDA Variance Analysis when the user triggers KDA, so that RAG color is aligned with the RAG color displayed for Adherence score in View KDA. | F61: 4440942 | G61: Sathya | H61: Bhavana | J61: No | K61: Offline Utility OU related(Excel) Functionality Cannot be Automated | L61: Excel Validation | V61: Completed | W61: In Progress | X61: Not Started | Y61: Not Started | AF61: Active | AG61: 0 | AH61: 0 | AI61: 0 | AJ61: 0 | AK61: 0 | AL61: 0 | AM61: 0 | AO61: CodeCrafters | AP61: sona.job
A62: CDAT | B62: BPMS Onboarding to CDAT | C62: 4459051 | D62: Rajeswari | E62: As a CDAT PMO, I want to Onboard BPMS Opportunities to PMO Tracker Dashboard with Filtering, MMS ID Hyperlink, and Standard PMO Edit Access | F62: 4450388 | G62: Jabeen | H62: Shiva | J62: No | K62: Excel validation | L62: Excel Validation | V62: In Progress | W62: Not Started | X62: Not Started | Y62: Not Started | Z62: 40 | AF62: Active | AG62: 0 | AH62: 0 | AI62: 0 | AJ62: 0 | AK62: 0 | AL62: 0 | AM62: 0 | AO62: TechTribe | AP62: pandidurai.ks
A63: myISP_ DNP | B63: DNP - seat charges WFO design change (YOY WFO % level) - Online SI and PCW | C63: 4262937 | D63: Anand | E63: As a Solution Architect, I want to add Adjustment % at the Contract Year level in the DNP screen so that, I can calculate Seat Charges (Work from Office) based on the yearly adjustment %- Cart & Copy | F63: 4335613 | G63: Viji | H63: Kiruthiga | J63: No | K63: Different combinations of Sourec version (PCW) needs to be checked which is not feasible to automate | L63: Excel Validation | V63: In Progress | W63: Not Started | X63: Not Started | Y63: Not Started | AF63: In Development | AG63: 0 | AH63: 0 | AI63: 0 | AJ63: 0 | AK63: 0 | AL63: 0 | AM63: 0 | AO63: DevStormers | AP63: mervinkumar.manickam
A64: PCW | B64: IPC Calculator | Cost Update to Standard Package | C64: 4341363 | D64: Anand | E64: PCW - IPC Toolkit Cost Update | F64: 4368214 | G64: Sneha | H64: Naveen S | J64: No | K64: PCW User Story | L64: Excel Validation | V64: In Progress | W64: Not Started | X64: Not Started | Y64: Not Started | AF64: In Development | AG64: 0 | AH64: 0 | AI64: 0 | AJ64: 4 | AK64: 4 | AL64: 0 | AM64: 0 | AO64: Tech Ensemble | AP64: mervinkumar.manickam
A65: PCW | B65: DNP - seat charges WFO design change (YOY WFO % level) - Online SI and PCW | C65: 4262937 | D65: Anand | E65: API - Save the Adjustment % of Hourly Seat Charges from DNP Baseline into YoY adjustment % columns for all the Contract Years across the Deal Duration | F65: 4265946 | G65: Sairam | H65: Naveen S | J65: No | K65: PCW User Story | L65: Excel Validation | V65: In Progress | W65: Not Started | X65: Not Started | Y65: Not Started | AF65: Active | AG65: 0 | AH65: 0 | AI65: 0 | AJ65: 0 | AK65: 0 | AL65: 0 | AM65: 0 | AO65: TechAvatar | AP65: mervinkumar.manickam
A66: CDAT | B66: BPMS Onboarding to CDAT | C66: 4459051 | D66: Rajeswari | E66: As a CDAT SME / CDAT CM SME / Lead SA, I want to add comment on number of GAPS on BPMS Assessment Outcome Screen | F66: 4450401 | G66: Pavithra | H66: Sowndarya | J66: No | K66: Excel validation | L66: Excel Validation | V66: In Progress | W66: Not Started | X66: Not Started | Y66: Not Started | Z66: 65 | AF66: Active | AG66: 0 | AH66: 0 | AI66: 0 | AJ66: 0 | AK66: 0 | AL66: 0 | AM66: 0 | AO66: TechTribe | AP66: pandidurai.ks
A67: PCW | B67: MMP FFP Export update - May release | C67: 4436136 | D67: Anand | E67: PCW - Update the FFP Roles at SSG level in Staffing Baseline | F67: 4368139 | G67: Kiruthiga | H67: Sneha | J67: No | K67: PCW User Story | L67: Excel Validation | V67: In Progress | W67: Not Started | X67: Not Started | Y67: Not Started | AF67: In Development | AG67: 0 | AH67: 0 | AI67: 0 | AJ67: 0 | AK67: 0 | AL67: 0 | AM67: 0 | AO67: Tech Ensemble | AP67: mervinkumar.manickam
A68: Online SI | B68: Rate card screen UI change | C68: 4151502 | D68: Anand | E68: As a SA, I need to fix Ratecard UI display and redesign tab order for improved user journey | F68: 4351779 | G68: Kiruthiga | H68: Naveen S | J68: No | K68: UI Improvement and Offline utility OU (excel) functionality cannot be automated | L68: Excel Validation | V68: Completed | W68: Not Started | X68: Not Started | Y68: In Progress | Z68: 52 | AA68: 25 | AB68: 5 | AD68: 0.9 | AE68: 0.95 | AF68: PT In Test | AG68: 7 | AH68: 3 | AI68: 0 | AJ68: 20 | AK68: 30 | AL68: 0.33333333 | AM68: 0.7 | AN68: 4468481(L),4469090(M),4467094(L) | AO68: TechWizards | AP68: mervinkumar.manickam
A69: PCW | B69: IPC Calculator | Cost Update to Standard Package | C69: 4341363 | D69: Anand | E69: PCW - IPC Month-of-Month ACN Cost Conversion to Deal Currency in DNP Baseline and DNP Forecast | F69: 4439846 | G69: Naveen S | H69: Sneha | J69: No | K69: PCW User Story | L69: Excel Validation | V69: In Progress | W69: Not Started | X69: Not Started | Y69: Not Started | AF69: In Development | AG69: 0 | AH69: 0 | AI69: 0 | AJ69: 0 | AK69: 0 | AL69: 0 | AM69: 0 | AO69: Tech Ensemble | AP69: mervinkumar.manickam
A70: myISP UI | B70: PCW CRs - Jan Release | C70: 4268320 | D70: Anand | E70: Export the Fixed cost types to Online SDL even if no matching profile is available in Staffing for PCW versions | F70: 4187514 | G70: Naveen S | J70: No | K70: PCW User Story | L70: Excel Validation | V70: In Progress | W70: Not Started | X70: Not Started | Y70: Not Started | AF70: Active | AG70: 0 | AH70: 0 | AI70: 0 | AJ70: 0 | AK70: 0 | AL70: 0 | AM70: 0 | AO70: DevStormers | AP70: mervinkumar.manickam
A71: myISP_ DNP | B71: DNP - seat charges WFO design change (YOY WFO % level) - Online SI and PCW | C71: 4262937 | D71: Anand | E71: As a Solution Architect, I want to add Adjustment % at the Contract Year level in the DNP screen so that, I can calculate Seat Charges (Work from Office) based on the yearly adjustment %- OU changes. | F71: 4317632 | G71: Viji | H71: Kiruthiga | J71: No | K71: Offline Utility OU related(Excel) Functionality Cannot be Automated | L71: Excel Validation | V71: In Progress | W71: Not Started | X71: Not Started | Y71: Not Started | AF71: In Development | AG71: 0 | AH71: 0 | AI71: 0 | AJ71: 0 | AK71: 0 | AL71: 0 | AM71: 0 | AO71: DevStormers | AP71: mervinkumar.manickam
A72: PCW | B72: IPC Calculator | Cost Update to Standard Package | C72: 4341363 | D72: Anand | E72: Add new IPC Cost Types for PCW versions and update existing IPC Cost Type | F72: 4368217 | G72: Viji | H72: Sneha | J72: No | K72: PCW User Story | L72: Excel Validation | V72: In Progress | W72: Not Started | X72: Not Started | Y72: Not Started | AF72: Ready for Test | AG72: 0 | AH72: 0 | AI72: 0 | AJ72: 0 | AK72: 0 | AL72: 0 | AM72: 0 | AO72: DevStormers | AP72: mervinkumar.manickam
A73: PCW | B73: PCW Enhancements and User Feedback - March Release | C73: 4389866 | D73: Anand | E73: Carting - IPC Toolkit cost in PCW versions | F73: 4361280 | G73: Sneha | H73: Sairam | J73: No | K73: PCW User Story | L73: Excel Validation | V73: In Progress | W73: Not Started | X73: Not Started | Y73: Not Started | AF73: Active | AG73: 0 | AH73: 0 | AI73: 0 | AJ73: 0 | AK73: 0 | AL73: 0 | AM73: 0 | AO73: DevStormers | AP73: mervinkumar.manickam
A74: PCW | B74: PCW Enhancements and User Feedback - March Release | C74: 4389866 | D74: Anand | E74: PCW API | Move Rate Card Career Level from Solution Level to Solution Version Level with One-Time Data Migration | F74: 4436185 | G74: Sneha | H74: Viji | J74: No | K74: PCW User Story | L74: Excel Validation | V74: In Progress | W74: Not Started | X74: Not Started | Y74: Not Started | AF74: New | AG74: 0 | AH74: 0 | AI74: 0 | AJ74: 0 | AK74: 0 | AL74: 0 | AM74: 0 | AO74: TechAvatar | AP74: mervinkumar.manickam
A75: PCW | B75: MMP FFP Export update - May release | C75: 4436136 | D75: Anand | E75: PCW - MMP FFP Export: Send only filtered staffing rows to API for Role Type, Accenture Role/Rate and Pricing Workstream identification | F75: 4436093 | G75: Viji | H75: Kiruthiga | J75: No | K75: PCW User Story | L75: Excel Validation | V75: In Progress | W75: Not Started | X75: Not Started | Y75: Not Started | AF75: New | AG75: 0 | AH75: 0 | AI75: 0 | AJ75: 0 | AK75: 0 | AL75: 0 | AM75: 0 | AO75: Tech Ensemble | AP75: mervinkumar.manickam
A76: PCW | B76: DNP Simplification - May Release | C76: 4436144 | D76: Anand | E76: PCW - Auto-populate Local Currency in DNP sheets when Local Currency is blank | F76: 4435907 | G76: Naveen S | H76: Kiruthiga | J76: No | K76: PCW User Story | L76: Excel Validation | V76: In Progress | W76: Not Started | X76: Not Started | Y76: Not Started | AF76: Active | AG76: 0 | AH76: 0 | AI76: 0 | AJ76: 0 | AK76: 0 | AL76: 0 | AM76: 0 | AO76: Tech Ensemble | AP76: mervinkumar.manickam
A77: OCP | B77: Online SI CR - March | C77: 4283187 | D77: Anand | E77: As a SA i want to automatically update Staffing Baseline when Rate Per Hour is changed in Rate Card | F77: 4431151 | G77: Sneha | H77: Viji | J77: No | K77: Excel related needs to generate all pricing routes, SDL,OCP,DCTA and MMP FFP. Hence it is not feasibile to automate | L77: Excel Validation | V77: In Progress | W77: Not Started | X77: Not Started | Y77: Not Started | AF77: In Development | AG77: 0 | AH77: 0 | AI77: 0 | AJ77: 7 | AK77: 7 | AL77: 0 | AM77: 0 | AO77: TechWizards | AP77: mervinkumar.manickam
A78: SI - PCW | B78: Standard Role Implementation in PCW & Online SI - May Release | C78: 4436131 | D78: Anand | E78: PCW - Add a new field in Pricing to determine if the deal is Pure Technology Service deal | F78: 4412404 | G78: Sairam | H78: Naveen S | J78: No | K78: PCW User Story | L78: Excel Validation | V78: In Progress | W78: Not Started | X78: Not Started | Y78: Not Started | AF78: New | AG78: 0 | AH78: 0 | AI78: 0 | AJ78: 0 | AK78: 0 | AL78: 0 | AM78: 0 | AO78: Tech Ensemble | AP78: mervinkumar.manickam
A79: SI - PCW | B79: Standard Role Implementation in PCW & Online SI - May Release | C79: 4436131 | D79: Anand | E79: API - Identify if the deal is Pure Technology Service/Capability Deal | F79: 4412401 | G79: Sneha | H79: Viji | J79: No | K79: PCW User Story | L79: Excel Validation | V79: In Progress | W79: Not Started | X79: Not Started | Y79: Not Started | AF79: New | AG79: 0 | AH79: 0 | AI79: 0 | AJ79: 5 | AK79: 5 | AL79: 0 | AM79: 0 | AO79: TechAvatar | AP79: mervinkumar.manickam
A80: PCW | B80: Standard Role Implementation in PCW & Online SI - May Release | C80: 4436131 | D80: Anand | E80: Handle 'Overwrite Role Type' column during carting and copying to create myISP PCW versions | F80: 4423815 | G80: Naveen S | H80: Sneha | J80: No | K80: PCW User Story | L80: Excel Validation | V80: In Progress | W80: Not Started | X80: Not Started | Y80: Not Started | AF80: In Development | AG80: 0 | AH80: 0 | AI80: 0 | AJ80: 0 | AK80: 0 | AL80: 0 | AM80: 0 | AO80: DevStormers | AP80: mervinkumar.manickam
A81: CDAT | B81: BPMS Onboarding to CDAT | C81: 4459051 | D81: Rajeswari | E81: As a CDAT PMO user, I want the ability to upload an exported excel Upload for Edited PMO Export | F81: 4448602 | G81: Pavithra | H81: Sowndarya | J81: No | K81: Excel validation | L81: Excel Validation | V81: In Progress | W81: Not Started | X81: Not Started | Y81: Not Started | Z81: 66 | AF81: Active | AG81: 0 | AH81: 0 | AI81: 0 | AJ81: 0 | AK81: 0 | AL81: 0 | AM81: 0 | AO81: TechTribe | AP81: pandidurai.ks

Sheet PT status
A1: Module (TextVerification) | B1: Parent Title | C1: Feature ID | D1: PT Lead | E1: Title | F1: ID | G1: Primary Tester | H1: Secondary Tester | I1: Insprint Tester | J1: Insprint Yes/No | K1: If Insprint NO/Partial - Reason | L1: Pre defined No Reason | M1: Complexity | N1: In sprint test case count | O1: If insprint YES - % of completion | P1: Automated cases generated from GHC | Q1: Useful Automated cases from GHC | R1: Tester created automated count (not given by GHC) | S1: Reviewed Final automation count | T1: Coverage for automated test case from GHC% | U1: Accuracy of Automated Test case from GHC% | V1: Test Planning | W1: BA Review | X1: TFS upload | Y1: PT Status | Z1: Manual Test cases generated from GHC | AA1: Useful Test cases from GHC | AB1: Tester Created test case count | AC1: Reviwed Final Test case count | AD1: Coverage for Manual Test cases from GHC% | AE1: Accuracy for Manual test cases from GHC% | AF1: TFS state | AG1: Passed | AH1: Failed | AI1: Blocked | AJ1: Not Run | AK1: Total | AL1: Execution % | AM1: Pass % | AN1: Comments | AO1: Node Name | AP1: MPOC
A2: =_xlfn.XLOOKUP(F2,'TFS Details'!F:F,'TFS Details'!D:D) -> Learn | B2: =_xlfn.XLOOKUP(F2,'TFS Details'!F:F,'TFS Details'!A:A) -> Services - Learn & Launch enhancements with BPMS support button | C2: =_xlfn.XLOOKUP(F2,'TFS Details'!F:F,'TFS Details'!E:E) -> 4443474 | D2: Pirtheebaa | E2: As a myISP user, I want to see "BPMS" as a support option alongside AMS, SI, and IMS in both the "Email" and "Raise a Ticket" support sections on all 10-step screens. So that I can easily raise BPMS-related support requests. | F2: 4435598 | G2: Mary | H2: Janardhan/Sadhik | I2: Mary.jacob | J2: Partial | K2: Email Functionality included.Till email functionality we can automate | L2: Email validation | M2: Medium | N2: 5 | O2: 0.05 | P2: 20 | Q2: 5 | R2: 1 | V2: Completed | W2: Completed | X2: Completed | Y2: Completed | Z2: 55 | AA2: 11 | AB2: 0 | AC2: 11 | AD2: 0.95 | AE2: 0.8 | AF2: =_xlfn.XLOOKUP(F2,'TFS Details'!F:F,'TFS Details'!H:H) -> Test Complete | AG2: 11 | AH2: 0 | AI2: 0 | AJ2: 0 | AK2: =SUM(AG2:AJ2) -> 11 | AL2: =IF(AG2+AH2=0,0,SUM(AG2:AH2)/AK2) -> 1 | AM2: =IF(AG2=0,0,AG2/(SUM(AG2:AI2))) -> 1 | AO2: =_xlfn.XLOOKUP(F2,'TFS Details'!F:F,'TFS Details'!I:I) -> MYISP_Revamp_UI | AP2: =_xlfn.XLOOKUP(AO2,'TFS Details'!I:I,'TFS Details'!AE:AE) -> vikrant.r.mohite
A3: =_xlfn.XLOOKUP(F3,'TFS Details'!F:F,'TFS Details'!D:D) -> Common | B3: =_xlfn.XLOOKUP(F3,'TFS Details'!F:F,'TFS Details'!A:A) -> Security-specific services when the Opportunity RDE is set to "Security" | C3: =_xlfn.XLOOKUP(F3,'TFS Details'!F:F,'TFS Details'!E:E) -> 4443757 | D3: Pirtheebaa | E3: As an myISP user, I want the Scope Services/Offerings section to display only the security-specific services when the Opportunity RDE is set to "Security", So that users see only relevant AMS and SI security services. | F3: 4443754 | G3: Mary | H3: Janardhan/Sadhik | I3: Mary.jacob | J3: Yes | M3: Medium | N3: 5 | O3: 0.05 | P3: 20 | Q3: 5 | R3: 0 | V3: Completed | W3: Not Started | X3: Completed | Y3: Not Started | Z3: 50 | AA3: 9 | AB3: 1 | AC3: 10 | AD3: 0.95 | AE3: 0.8 | AF3: =_xlfn.XLOOKUP(F3,'TFS Details'!F:F,'TFS Details'!H:H) -> Active | AG3: 0 | AH3: 0 | AI3: 0 | AJ3: 10 | AK3: =SUM(AG3:AJ3) -> 10 | AL3: =IF(AG3+AH3=0,0,SUM(AG3:AH3)/AK3) -> 0 | AM3: =IF(AG3=0,0,AG3/(SUM(AG3:AI3))) -> 0 | AO3: =_xlfn.XLOOKUP(F3,'TFS Details'!F:F,'TFS Details'!I:I) -> TechWarriors | AP3: =_xlfn.XLOOKUP(AO3,'TFS Details'!I:I,'TFS Details'!AE:AE) -> Supriya.a.dhingra
A4: =_xlfn.XLOOKUP(F4,'TFS Details'!F:F,'TFS Details'!D:D) -> Common | B4: =_xlfn.XLOOKUP(F4,'TFS Details'!F:F,'TFS Details'!A:A) -> Market Maker Enterprise Solution Architect role from MMS in MMS Team Details | C4: =_xlfn.XLOOKUP(F4,'TFS Details'!F:F,'TFS Details'!E:E) -> 4443779 | D4: Pirtheebaa | E4: As a myISP User, I should be able to view the Market Maker Enterprise Solution Architect role from MMS in MMS Team Details so that team visibility and consistent across myISP | F4: 4443764 | G4: Mary | H4: Janardhan/Sadhik | I4: Mary.jacob | J4: Partial | K4: Partial as this US includes scenario where data should flow from MMS .Data available in UI can be verified in insprint automation | L4: external Integration validation | M4: Simple | N4: 5 | O4: 0.1 | P4: 20 | Q4: 5 | R4: 1 | V4: Completed | W4: Completed | X4: Completed | Y4: Completed | Z4: 40 | AA4: 7 | AB4: 0 | AC4: 7 | AD4: 0.95 | AE4: 0.8 | AF4: =_xlfn.XLOOKUP(F4,'TFS Details'!F:F,'TFS Details'!H:H) -> PT In Test | AG4: 7 | AH4: 0 | AI4: 0 | AJ4: 0 | AK4: =SUM(AG4:AJ4) -> 7 | AL4: =IF(AG4+AH4=0,0,SUM(AG4:AH4)/AK4) -> 1 | AM4: =IF(AG4=0,0,AG4/(SUM(AG4:AI4))) -> 1 | AO4: =_xlfn.XLOOKUP(F4,'TFS Details'!F:F,'TFS Details'!I:I) -> GoRetro | AP4: =_xlfn.XLOOKUP(AO4,'TFS Details'!I:I,'TFS Details'!AE:AE) -> sowjanya.kari
A5: =_xlfn.XLOOKUP(F5,'TFS Details'!F:F,'TFS Details'!D:D) -> PMO | B5: =_xlfn.XLOOKUP(F5,'TFS Details'!F:F,'TFS Details'!A:A) -> [PMO] URL update for Manage and Dashboard screens | C5: =_xlfn.XLOOKUP(F5,'TFS Details'!F:F,'TFS Details'!E:E) -> 4440976 | D5: Pirtheebaa | E5: [PMO] As a PMO user, I should be able to navigate to Manage / Dashboard screen with the new URL from Opportunity Workflow page | F5: 4443502 | G5: Vinayak | H5: Saranya | I5: Vinayak.Sangale | J5: Yes | M5: Simple | O5: 0.1 | V5: Completed | W5: Completed | X5: Completed | Y5: Not Started | AF5: =_xlfn.XLOOKUP(F5,'TFS Details'!F:F,'TFS Details'!H:H) -> Active | AG5: 0 | AH5: 0 | AI5: 0 | AJ5: 7 | AK5: =SUM(AG5:AJ5) -> 7 | AL5: =IF(AG5+AH5=0,0,SUM(AG5:AH5)/AK5) -> 0 | AM5: =IF(AG5=0,0,AG5/(SUM(AG5:AI5))) -> 0 | AO5: =_xlfn.XLOOKUP(F5,'TFS Details'!F:F,'TFS Details'!I:I) -> TechWarriors | AP5: =_xlfn.XLOOKUP(AO5,'TFS Details'!I:I,'TFS Details'!AE:AE) -> Supriya.a.dhingra
A6: =_xlfn.XLOOKUP(F6,'TFS Details'!F:F,'TFS Details'!D:D) -> PMO | B6: =_xlfn.XLOOKUP(F6,'TFS Details'!F:F,'TFS Details'!A:A) -> [PMO] URL update for Manage and Dashboard screens | C6: =_xlfn.XLOOKUP(F6,'TFS Details'!F:F,'TFS Details'!E:E) -> 4440976 | D6: Pirtheebaa | E6: [PMO] As a PMO user, I should be able to navigate to Manage / Dashboard screen with the new URL from Define Team | F6: 4443510 | G6: Vinayak | H6: Saranya | I6: Vinayak.Sangale | J6: Yes | M6: Simple | O6: 0.1 | V6: Completed | W6: Completed | X6: Completed | Y6: In Progress | AF6: =_xlfn.XLOOKUP(F6,'TFS Details'!F:F,'TFS Details'!H:H) -> PT In Test | AG6: 8 | AH6: 0 | AI6: 0 | AJ6: 4 | AK6: =SUM(AG6:AJ6) -> 12 | AL6: =IF(AG6+AH6=0,0,SUM(AG6:AH6)/AK6) -> 0.66666667 | AM6: =IF(AG6=0,0,AG6/(SUM(AG6:AI6))) -> 1 | AO6: =_xlfn.XLOOKUP(F6,'TFS Details'!F:F,'TFS Details'!I:I) -> TechPhantoms | AP6: =_xlfn.XLOOKUP(AO6,'TFS Details'!I:I,'TFS Details'!AE:AE) -> sowjanya.kari
A7: =_xlfn.XLOOKUP(F7,'TFS Details'!F:F,'TFS Details'!D:D) -> PMO | B7: =_xlfn.XLOOKUP(F7,'TFS Details'!F:F,'TFS Details'!A:A) -> [PMO] URL update for Manage and Dashboard screens | C7: =_xlfn.XLOOKUP(F7,'TFS Details'!F:F,'TFS Details'!E:E) -> 4440976 | D7: Pirtheebaa | E7: [PMO] As a PMO user, I should be able to navigate to Manage / Dashboard screen with the new URL from WRWS | F7: 4443516 | G7: Vinayak | H7: Saranya | I7: Vinayak.Sangale | J7: Yes | M7: Simple | O7: 0.1 | V7: Completed | W7: Completed | X7: Completed | Y7: Not Started | AF7: =_xlfn.XLOOKUP(F7,'TFS Details'!F:F,'TFS Details'!H:H) -> New | AG7: 0 | AH7: 0 | AI7: 0 | AJ7: 6 | AK7: =SUM(AG7:AJ7) -> 6 | AL7: =IF(AG7+AH7=0,0,SUM(AG7:AH7)/AK7) -> 0 | AM7: =IF(AG7=0,0,AG7/(SUM(AG7:AI7))) -> 0 | AO7: =_xlfn.XLOOKUP(F7,'TFS Details'!F:F,'TFS Details'!I:I) -> TechWarriors | AP7: =_xlfn.XLOOKUP(AO7,'TFS Details'!I:I,'TFS Details'!AE:AE) -> Supriya.a.dhingra
A8: =_xlfn.XLOOKUP(F8,'TFS Details'!F:F,'TFS Details'!D:D) -> PMO | B8: =_xlfn.XLOOKUP(F8,'TFS Details'!F:F,'TFS Details'!A:A) -> [PMO] URL update for Manage and Dashboard screens | C8: =_xlfn.XLOOKUP(F8,'TFS Details'!F:F,'TFS Details'!E:E) -> 4440976 | D8: Pirtheebaa | E8: [PMO] As a PMO user, I should be able to navigate to Manage screen with the new URL | F8: 4440990 | G8: Vinayak | H8: Saranya | I8: Saranya.datla | J8: Yes | M8: Simple | N8: 2 | O8: 0.2 | V8: Completed | W8: Completed | X8: Completed | Y8: Not Started | AF8: =_xlfn.XLOOKUP(F8,'TFS Details'!F:F,'TFS Details'!H:H) -> In Development | AG8: 0 | AH8: 0 | AI8: 0 | AJ8: 12 | AK8: =SUM(AG8:AJ8) -> 12 | AL8: =IF(AG8+AH8=0,0,SUM(AG8:AH8)/AK8) -> 0 | AM8: =IF(AG8=0,0,AG8/(SUM(AG8:AI8))) -> 0 | AO8: =_xlfn.XLOOKUP(F8,'TFS Details'!F:F,'TFS Details'!I:I) -> GoRetro | AP8: =_xlfn.XLOOKUP(AO8,'TFS Details'!I:I,'TFS Details'!AE:AE) -> sowjanya.kari
A9: =_xlfn.XLOOKUP(F9,'TFS Details'!F:F,'TFS Details'!D:D) -> PMO | B9: =_xlfn.XLOOKUP(F9,'TFS Details'!F:F,'TFS Details'!A:A) -> [PMO] URL update for Manage and Dashboard screens | C9: =_xlfn.XLOOKUP(F9,'TFS Details'!F:F,'TFS Details'!E:E) -> 4440976 | D9: Pirtheebaa | E9: [PMO] As a PMO user, I should be able to navigate to PMO Dashboard screen with the new URL | F9: 4441001 | G9: Vinayak | H9: Saranya | I9: Saranya.datla | J9: Yes | M9: Medium | N9: 2 | O9: 0.2 | V9: Completed | W9: Completed | X9: Completed | Y9: Not Started | AF9: =_xlfn.XLOOKUP(F9,'TFS Details'!F:F,'TFS Details'!H:H) -> In Development | AG9: 0 | AH9: 0 | AI9: 0 | AJ9: 4 | AK9: =SUM(AG9:AJ9) -> 4 | AL9: =IF(AG9+AH9=0,0,SUM(AG9:AH9)/AK9) -> 0 | AM9: =IF(AG9=0,0,AG9/(SUM(AG9:AI9))) -> 0 | AO9: =_xlfn.XLOOKUP(F9,'TFS Details'!F:F,'TFS Details'!I:I) -> GoRetro | AP9: =_xlfn.XLOOKUP(AO9,'TFS Details'!I:I,'TFS Details'!AE:AE) -> sowjanya.kari
A10: =_xlfn.XLOOKUP(F10,'TFS Details'!F:F,'TFS Details'!D:D) -> myCalendar | B10: =_xlfn.XLOOKUP(F10,'TFS Details'!F:F,'TFS Details'!A:A) -> myCalendar: Simplify calender funtionality for Solution Architect | C10: =_xlfn.XLOOKUP(F10,'TFS Details'!F:F,'TFS Details'!E:E) -> 4447848 | D10: Pirtheebaa | E10: **As a** Solution Architect, **I want** to verify that all fields sent from myCalendar to the SA Bandwidth Report continue to function correctly after the myCalendar revamp changes, **So that** the SA Bandwidth Report accurately reflects all related data | F10: 4467824 | G10: Mary | H10: Janardhan/Sadhik | I10: Vinayak.Sangale | J10: Yes | M10: Medium | O10: 0.05 | V10: Completed | W10: Not Started | X10: Completed | Y10: Not Started | Z10: 56 | AA10: 37 | AB10: 0 | AC10: 37 | AD10: 0.95 | AE10: 0.8 | AF10: =_xlfn.XLOOKUP(F10,'TFS Details'!F:F,'TFS Details'!H:H) -> Active | AG10: 0 | AH10: 0 | AI10: 0 | AJ10: 37 | AK10: =SUM(AG10:AJ10) -> 37 | AL10: =IF(AG10+AH10=0,0,SUM(AG10:AH10)/AK10) -> 0 | AM10: =IF(AG10=0,0,AG10/(SUM(AG10:AI10))) -> 0
A11: =_xlfn.XLOOKUP(F11,'TFS Details'!F:F,'TFS Details'!D:D) -> BPMS Onboarding | B11: =_xlfn.XLOOKUP(F11,'TFS Details'!F:F,'TFS Details'!A:A) -> Raise Request Email Template Standardization - Deal Value and Date Format | C11: =_xlfn.XLOOKUP(F11,'TFS Details'!F:F,'TFS Details'!E:E) -> 4441965 | D11: Pirtheebaa | E11: As a Business User, I should receive Raise Request emails with standardized deal value and date formats so that information is clear and consistent | F11: 4441959 | G11: Vinayak | H11: Saranya | J11: No | K11: All the Acceptance Criteria validation is required particularly in Email body templete so can not be automatable | L11: Basic email validation after just login | V11: Completed | W11: Completed | X11: Completed | Y11: In Progress | AF11: =_xlfn.XLOOKUP(F11,'TFS Details'!F:F,'TFS Details'!H:H) -> PT In Test | AG11: 5 | AH11: 0 | AI11: 0 | AJ11: 2 | AK11: =SUM(AG11:AJ11) -> 7 | AL11: =IF(AG11+AH11=0,0,SUM(AG11:AH11)/AK11) -> 0.71428571 | AM11: =IF(AG11=0,0,AG11/(SUM(AG11:AI11))) -> 1 | AO11: =_xlfn.XLOOKUP(F11,'TFS Details'!F:F,'TFS Details'!I:I) -> TechPhantoms | AP11: =_xlfn.XLOOKUP(AO11,'TFS Details'!I:I,'TFS Details'!AE:AE) -> sowjanya.kari
A12: =_xlfn.XLOOKUP(F12,'TFS Details'!F:F,'TFS Details'!D:D) -> Common | B12: =_xlfn.XLOOKUP(F12,'TFS Details'!F:F,'TFS Details'!A:A) -> Enter special characters, spaces, and bullet-point text for all 5 Opportunity on a Page questions | C12: =_xlfn.XLOOKUP(F12,'TFS Details'!F:F,'TFS Details'!E:E) -> 4441971 | D12: Pirtheebaa | E12: As a Business User, I should be able to enter special characters, spaces, and bullet-point text for all 5 Opportunity on a Page questions so that I can capture complete client context clearly | F12: 4441970 | G12: Mary | H12: Janardhan/Sadhik | I12: Mary.jacob | J12: Yes | M12: Medium | N12: 5 | O12: 0.05 | P12: 20 | Q12: 5 | R12: 1 | V12: Completed | W12: Not Started | X12: Completed | Y12: Not Started | Z12: 70 | AA12: 7 | AB12: 0 | AC12: 7 | AD12: 0.95 | AE12: 0.8 | AF12: =_xlfn.XLOOKUP(F12,'TFS Details'!F:F,'TFS Details'!H:H) -> Active | AG12: 0 | AH12: 0 | AI12: 0 | AJ12: 7 | AK12: =SUM(AG12:AJ12) -> 7 | AL12: =IF(AG12+AH12=0,0,SUM(AG12:AH12)/AK12) -> 0 | AM12: =IF(AG12=0,0,AG12/(SUM(AG12:AI12))) -> 0 | AO12: =_xlfn.XLOOKUP(F12,'TFS Details'!F:F,'TFS Details'!I:I) -> TechWarriors | AP12: =_xlfn.XLOOKUP(AO12,'TFS Details'!I:I,'TFS Details'!AE:AE) -> Supriya.a.dhingra
A13: =_xlfn.XLOOKUP(F13,'TFS Details'!F:F,'TFS Details'!D:D) -> Common | B13: =_xlfn.XLOOKUP(F13,'TFS Details'!F:F,'TFS Details'!A:A) -> Stage Update Date on the Timeline screen | C13: =_xlfn.XLOOKUP(F13,'TFS Details'!F:F,'TFS Details'!E:E) -> 4441973 | D13: Pirtheebaa | E13: As a Business User, I should see Stage Update Date on the Timeline screen under View MMS Details so that the latest stage change information is visible and fetched from the correct DB mapping | F13: 4441972 | G13: Mary | H13: Janardhan/Sadhik | I13: Mary.jacob | J13: Partial | K13: DB Change in UI we can just check the date is displaying or not as part of insprint | L13: Technical US - Full regression Required | M13: Simple | N13: 5 | O13: 0.4 | P13: 31 | Q13: 5 | R13: 0 | V13: Completed | W13: Completed | X13: Completed | Y13: Completed | Z13: 36 | AA13: 7 | AB13: 0 | AC13: 7 | AD13: 0.95 | AE13: 0.8 | AF13: =_xlfn.XLOOKUP(F13,'TFS Details'!F:F,'TFS Details'!H:H) -> Test Complete | AG13: 7 | AH13: 0 | AI13: 0 | AJ13: 0 | AK13: =SUM(AG13:AJ13) -> 7 | AL13: =IF(AG13+AH13=0,0,SUM(AG13:AH13)/AK13) -> 1 | AM13: =IF(AG13=0,0,AG13/(SUM(AG13:AI13))) -> 1 | AO13: =_xlfn.XLOOKUP(F13,'TFS Details'!F:F,'TFS Details'!I:I) -> GoRetro | AP13: =_xlfn.XLOOKUP(AO13,'TFS Details'!I:I,'TFS Details'!AE:AE) -> sowjanya.kari
A14: =_xlfn.XLOOKUP(F14,'TFS Details'!F:F,'TFS Details'!D:D) -> common | B14: =_xlfn.XLOOKUP(F14,'TFS Details'!F:F,'TFS Details'!A:A) -> Deal Hierarchy info text at the right-bottom of the MMS Details screen | C14: =_xlfn.XLOOKUP(F14,'TFS Details'!F:F,'TFS Details'!E:E) -> 4441977 | D14: Pirtheebaa | E14: As a Business User, I should see the Deal Hierarchy info text at the right-bottom of the MMS Details screen so that the message is visible without disturbing the data grid | F14: 4441975 | G14: Mary | H14: Janardhan/Sadhik | I14: Mary.jacob | J14: Yes | M14: Simple | N14: 5 | O14: 0.25 | P14: 21 | Q14: 5 | R14: 0 | V14: Completed | W14: Completed | X14: Completed | Y14: Completed | Z14: 56 | AA14: 14 | AB14: 0 | AC14: 14 | AD14: 0.95 | AE14: 0.8 | AF14: =_xlfn.XLOOKUP(F14,'TFS Details'!F:F,'TFS Details'!H:H) -> Test Complete | AG14: 14 | AH14: 0 | AI14: 0 | AJ14: 0 | AK14: =SUM(AG14:AJ14) -> 14 | AL14: =IF(AG14+AH14=0,0,SUM(AG14:AH14)/AK14) -> 1 | AM14: =IF(AG14=0,0,AG14/(SUM(AG14:AI14))) -> 1 | AO14: =_xlfn.XLOOKUP(F14,'TFS Details'!F:F,'TFS Details'!I:I) -> GoRetro | AP14: =_xlfn.XLOOKUP(AO14,'TFS Details'!I:I,'TFS Details'!AE:AE) -> sowjanya.kari
A15: =_xlfn.XLOOKUP(F15,'TFS Details'!F:F,'TFS Details'!D:D) -> PMO | B15: =_xlfn.XLOOKUP(F15,'TFS Details'!F:F,'TFS Details'!A:A) -> [PMO] URL update for Manage and Dashboard screens | C15: =_xlfn.XLOOKUP(F15,'TFS Details'!F:F,'TFS Details'!E:E) -> 4440976 | D15: Pirtheebaa | E15: [PMO] As a PMO user, I should be able to navigate to PMOInterimCreation(Sample Deal) screen with the new URL | F15: 4441883 | G15: Vinayak | H15: Saranya | I15: Saranya.datla | J15: Yes | M15: Medium | N15: 2 | O15: 0.2 | V15: Completed | W15: Completed | X15: Completed | Y15: Not Started | AF15: =_xlfn.XLOOKUP(F15,'TFS Details'!F:F,'TFS Details'!H:H) -> In Development | AG15: 0 | AH15: 0 | AI15: 0 | AJ15: 7 | AK15: =SUM(AG15:AJ15) -> 7 | AL15: =IF(AG15+AH15=0,0,SUM(AG15:AH15)/AK15) -> 0 | AM15: =IF(AG15=0,0,AG15/(SUM(AG15:AI15))) -> 0 | AO15: =_xlfn.XLOOKUP(F15,'TFS Details'!F:F,'TFS Details'!I:I) -> GoRetro | AP15: =_xlfn.XLOOKUP(AO15,'TFS Details'!I:I,'TFS Details'!AE:AE) -> sowjanya.kari
A16: =_xlfn.XLOOKUP(F16,'TFS Details'!F:F,'TFS Details'!D:D) -> SA Team manager | B16: =_xlfn.XLOOKUP(F16,'TFS Details'!F:F,'TFS Details'!A:A) -> SA Team manager UI updates.1. Capability to be autopopulate for Operations 2. Dependency of Deployment field for capability in left side slicer. | C16: =_xlfn.XLOOKUP(F16,'TFS Details'!F:F,'TFS Details'!E:E) -> 4441867 | D16: Pirtheebaa | E16: As a SA Team Manager user, I want Deployment, Capability, and Alignment fields to behave conditionally and dependently on the SA Team Manager screen so that selections are accurate and consistent. | F16: 4441886 | G16: Manisha | H16: Namrata | I16: Manisha.m.sharma | J16: Yes | M16: Medium | O16: 0 | V16: Completed | W16: Completed | X16: Not Started | Y16: In Progress | AF16: =_xlfn.XLOOKUP(F16,'TFS Details'!F:F,'TFS Details'!H:H) -> PT In Test | AG16: 0 | AH16: 0 | AI16: 0 | AJ16: 25 | AK16: =SUM(AG16:AJ16) -> 25 | AL16: =IF(AG16+AH16=0,0,SUM(AG16:AH16)/AK16) -> 0 | AM16: =IF(AG16=0,0,AG16/(SUM(AG16:AI16))) -> 0 | AO16: =_xlfn.XLOOKUP(F16,'TFS Details'!F:F,'TFS Details'!I:I) -> GoRetro | AP16: =_xlfn.XLOOKUP(AO16,'TFS Details'!I:I,'TFS Details'!AE:AE) -> sowjanya.kari
A17: =_xlfn.XLOOKUP(F17,'TFS Details'!F:F,'TFS Details'!D:D) -> SA Team manager | B17: =_xlfn.XLOOKUP(F17,'TFS Details'!F:F,'TFS Details'!A:A) -> SA Team manager UI updates.1. Capability to be autopopulate for Operations 2. Dependency of Deployment field for capability in left side slicer. | C17: =_xlfn.XLOOKUP(F17,'TFS Details'!F:F,'TFS Details'!E:E) -> 4441867 | D17: Pirtheebaa | E17: As a user registering through the Register Now pop‑up, I want conditional auto‑population and searchable alignment for Operations deployment so that I can complete registration accurately. | F17: 4441890 | G17: Manisha | H17: Namrata | J17: No | K17: Register Now is 1 time activity, which can't be enabled everytime in all the env's. Not feasible to automate | L17: Everytime new User validation | V17: Completed | W17: Completed | X17: Not Started | Y17: In Progress | AF17: =_xlfn.XLOOKUP(F17,'TFS Details'!F:F,'TFS Details'!H:H) -> Test Complete | AG17: 0 | AH17: 0 | AI17: 0 | AJ17: 0 | AK17: =SUM(AG17:AJ17) -> 0 | AL17: =IF(AG17+AH17=0,0,SUM(AG17:AH17)/AK17) -> 0 | AM17: =IF(AG17=0,0,AG17/(SUM(AG17:AI17))) -> 0 | AO17: =_xlfn.XLOOKUP(F17,'TFS Details'!F:F,'TFS Details'!I:I) -> GoRetro | AP17: =_xlfn.XLOOKUP(AO17,'TFS Details'!I:I,'TFS Details'!AE:AE) -> sowjanya.kari
A18: =_xlfn.XLOOKUP(F18,'TFS Details'!F:F,'TFS Details'!D:D) -> SA Team manager | B18: =_xlfn.XLOOKUP(F18,'TFS Details'!F:F,'TFS Details'!A:A) -> SA Team manager UI updates.1. Capability to be autopopulate for Operations 2. Dependency of Deployment field for capability in left side slicer. | C18: =_xlfn.XLOOKUP(F18,'TFS Details'!F:F,'TFS Details'!E:E) -> 4441867 | D18: Pirtheebaa | E18: As a PMO , I want conditional auto‑population and searchable alignment for Operations in pending user requests tab so that requests are reviewed and processed accurately. | F18: 4441892 | G18: Manisha | H18: Namrata | J18: No | K18: Register Now is 1 time activity, which can't be enabled everytime in all the env's. Not feasible to automate | L18: Everytime new User validation | V18: Completed | W18: Completed | X18: Not Started | Y18: In Progress | AF18: =_xlfn.XLOOKUP(F18,'TFS Details'!F:F,'TFS Details'!H:H) -> Test Complete | AG18: 0 | AH18: 0 | AI18: 0 | AJ18: 0 | AK18: =SUM(AG18:AJ18) -> 0 | AL18: =IF(AG18+AH18=0,0,SUM(AG18:AH18)/AK18) -> 0 | AM18: =IF(AG18=0,0,AG18/(SUM(AG18:AI18))) -> 0 | AO18: =_xlfn.XLOOKUP(F18,'TFS Details'!F:F,'TFS Details'!I:I) -> GoRetro | AP18: =_xlfn.XLOOKUP(AO18,'TFS Details'!I:I,'TFS Details'!AE:AE) -> sowjanya.kari
A19: =_xlfn.XLOOKUP(F19,'TFS Details'!F:F,'TFS Details'!D:D) -> myISP | B19: =_xlfn.XLOOKUP(F19,'TFS Details'!F:F,'TFS Details'!A:A) -> SI - Estimators/Calculators(Opp level screen) & Attach Estimates(Version level screen) - feedback alignment | C19: =_xlfn.XLOOKUP(F19,'TFS Details'!F:F,'TFS Details'!E:E) -> 4445141 | D19: Pirtheebaa | E19: As a Solution Architect, I want the Estimators screen's Create and Edit Estimator popups to have improved usability, So that I can efficiently view, enter, and review workstream hours without confusion or excessive scrolling. | F19: 4424629 | G19: Manisha | H19: Namrata | J19: No | K19: Realted to design changes need to check the column gaps between the grid .Not feasible to automate | L19: Everytime new User validation | V19: Completed | W19: Completed | X19: Not Started | Y19: Not Started | AF19: =_xlfn.XLOOKUP(F19,'TFS Details'!F:F,'TFS Details'!H:H) -> Active | AG19: 0 | AH19: 0 | AI19: 0 | AJ19: 0 | AK19: =SUM(AG19:AJ19) -> 0 | AL19: =IF(AG19+AH19=0,0,SUM(AG19:AH19)/AK19) -> 0 | AM19: =IF(AG19=0,0,AG19/(SUM(AG19:AI19))) -> 0 | AO19: =_xlfn.XLOOKUP(F19,'TFS Details'!F:F,'TFS Details'!I:I) -> TechWarriors | AP19: =_xlfn.XLOOKUP(AO19,'TFS Details'!I:I,'TFS Details'!AE:AE) -> Supriya.a.dhingra
A20: =_xlfn.XLOOKUP(F20,'TFS Details'!F:F,'TFS Details'!D:D) -> SA Team manager | B20: =_xlfn.XLOOKUP(F20,'TFS Details'!F:F,'TFS Details'!A:A) -> New user Registration for Song changes in SA team manager | C20: =_xlfn.XLOOKUP(F20,'TFS Details'!F:F,'TFS Details'!E:E) -> 4425959 | D20: Pirtheebaa | E20: As a PMO, I want Full Time SA, Reports to Lead, and Comments to be mandatory in Pending User Request tab so that incomplete registrations are not processed | F20: 4425965 | G20: Manisha | H20: Namrata | J20: No | K20: Register Now is 1 time activity, which can't be enabled everytime in all the env's. Not feasible to automate | L20: Everytime new User validation | V20: Completed | W20: Completed | X20: Not Started | Y20: In Progress | AF20: =_xlfn.XLOOKUP(F20,'TFS Details'!F:F,'TFS Details'!H:H) -> Test Complete | AG20: 0 | AH20: 0 | AI20: 0 | AJ20: 0 | AK20: =SUM(AG20:AJ20) -> 0 | AL20: =IF(AG20+AH20=0,0,SUM(AG20:AH20)/AK20) -> 0 | AM20: =IF(AG20=0,0,AG20/(SUM(AG20:AI20))) -> 0 | AO20: =_xlfn.XLOOKUP(F20,'TFS Details'!F:F,'TFS Details'!I:I) -> GoRetro | AP20: =_xlfn.XLOOKUP(AO20,'TFS Details'!I:I,'TFS Details'!AE:AE) -> sowjanya.kari
A21: =_xlfn.XLOOKUP(F21,'TFS Details'!F:F,'TFS Details'!D:D) -> SA Team manager | B21: =_xlfn.XLOOKUP(F21,'TFS Details'!F:F,'TFS Details'!A:A) -> New user Registration for Song changes in SA team manager | C21: =_xlfn.XLOOKUP(F21,'TFS Details'!F:F,'TFS Details'!E:E) -> 4425959 | D21: Pirtheebaa | E21: As an SA Team Manager, I want Full Time SA, Reports to Lead, and Comments to be mandatory in the SA Team Manager tab so that incomplete registrations are not processed | F21: 4425971 | G21: Manisha | H21: Namrata | I21: namrata.g.umardand | J21: Yes | M21: Complex | O21: 0.05 | V21: Completed | W21: Completed | X21: Not Started | Y21: In Progress | AF21: =_xlfn.XLOOKUP(F21,'TFS Details'!F:F,'TFS Details'!H:H) -> Test Complete | AG21: 0 | AH21: 0 | AI21: 0 | AJ21: 20 | AK21: =SUM(AG21:AJ21) -> 20 | AL21: =IF(AG21+AH21=0,0,SUM(AG21:AH21)/AK21) -> 0 | AM21: =IF(AG21=0,0,AG21/(SUM(AG21:AI21))) -> 0 | AO21: =_xlfn.XLOOKUP(F21,'TFS Details'!F:F,'TFS Details'!I:I) -> GoRetro | AP21: =_xlfn.XLOOKUP(AO21,'TFS Details'!I:I,'TFS Details'!AE:AE) -> sowjanya.kari
A22: =_xlfn.XLOOKUP(F22,'TFS Details'!F:F,'TFS Details'!D:D) -> myISP Enhancements | B22: =_xlfn.XLOOKUP(F22,'TFS Details'!F:F,'TFS Details'!A:A) -> March Release NextGen Enhancements | C22: =_xlfn.XLOOKUP(F22,'TFS Details'!F:F,'TFS Details'!E:E) -> 4365826 | D22: Pirtheebaa | E22: As a myISP User, I want to Add "Sync All from MMS" button for an Opportunity in (Opportunity On A Page) under WRWS to sync all 5 answers from MMS to myISP so that user can get the answers in in one go. | F22: 4358782 | G22: Vinayak | H22: Saranya | I22: Vinayak.Sangale | J22: Yes | M22: Medium | O22: 0.1 | V22: Completed | W22: Completed | X22: Completed | Y22: Not Started | AF22: =_xlfn.XLOOKUP(F22,'TFS Details'!F:F,'TFS Details'!H:H) -> Active | AG22: 0 | AH22: 0 | AI22: 0 | AJ22: 24 | AK22: =SUM(AG22:AJ22) -> 24 | AL22: =IF(AG22+AH22=0,0,SUM(AG22:AH22)/AK22) -> 0 | AM22: =IF(AG22=0,0,AG22/(SUM(AG22:AI22))) -> 0 | AO22: =_xlfn.XLOOKUP(F22,'TFS Details'!F:F,'TFS Details'!I:I) -> TechWarriors | AP22: =_xlfn.XLOOKUP(AO22,'TFS Details'!I:I,'TFS Details'!AE:AE) -> Supriya.a.dhingra
A23: =_xlfn.XLOOKUP(F23,'TFS Details'!F:F,'TFS Details'!D:D) -> WRWS | B23: =_xlfn.XLOOKUP(F23,'TFS Details'!F:F,'TFS Details'!A:A) -> Estimator/Calculator - Expand-Collapse icon Type and Position | C23: =_xlfn.XLOOKUP(F23,'TFS Details'!F:F,'TFS Details'!E:E) -> 4174547 | D23: Pirtheebaa | E23: As a myISP user I should be able to see expand and collapse icon in WRWS screen as per UI revamp standards | F23: 4174624 | G23: Vinayak | H23: Saranya | I23: Mary.jacob | J23: Yes | M23: Simple | N23: 15 | O23: 0.4 | P23: 28 | Q23: 14 | R23: 1 | S23: 15 | T23: 0.95 | U23: 0.9 | V23: Completed | W23: Completed | X23: Completed | Y23: Not Started | AF23: =_xlfn.XLOOKUP(F23,'TFS Details'!F:F,'TFS Details'!H:H) -> Active | AG23: 0 | AH23: 0 | AI23: 0 | AJ23: 10 | AK23: =SUM(AG23:AJ23) -> 10 | AL23: =IF(AG23+AH23=0,0,SUM(AG23:AH23)/AK23) -> 0 | AM23: =IF(AG23=0,0,AG23/(SUM(AG23:AI23))) -> 0 | AO23: =_xlfn.XLOOKUP(F23,'TFS Details'!F:F,'TFS Details'!I:I) -> TechWarriors | AP23: =_xlfn.XLOOKUP(AO23,'TFS Details'!I:I,'TFS Details'!AE:AE) -> Supriya.a.dhingra
A24: =_xlfn.XLOOKUP(F24,'TFS Details'!F:F,'TFS Details'!D:D) -> myISP Enhancements | B24: =_xlfn.XLOOKUP(F24,'TFS Details'!F:F,'TFS Details'!A:A) -> March Release NextGen Enhancements | C24: =_xlfn.XLOOKUP(F24,'TFS Details'!F:F,'TFS Details'!E:E) -> 4365826 | D24: Pirtheebaa | E24: As a myISP User, I want to view the definitions of the various "Service "on Hover in Service / Offerings section under WRWS so that acceptance criteria are achieved | F24: 4271493 | G24: Vinayak | H24: Saranya | I24: Saranya.datla | J24: Yes | M24: Medium | N24: 2 | O24: 0.2 | V24: Completed | W24: Completed | X24: Completed | Y24: Not Started | AF24: =_xlfn.XLOOKUP(F24,'TFS Details'!F:F,'TFS Details'!H:H) -> Active | AG24: 0 | AH24: 0 | AI24: 0 | AJ24: 9 | AK24: =SUM(AG24:AJ24) -> 9 | AL24: =IF(AG24+AH24=0,0,SUM(AG24:AH24)/AK24) -> 0 | AM24: =IF(AG24=0,0,AG24/(SUM(AG24:AI24))) -> 0 | AO24: =_xlfn.XLOOKUP(F24,'TFS Details'!F:F,'TFS Details'!I:I) -> TechWarriors | AP24: =_xlfn.XLOOKUP(AO24,'TFS Details'!I:I,'TFS Details'!AE:AE) -> Supriya.a.dhingra
A25: =_xlfn.XLOOKUP(F25,'TFS Details'!F:F,'TFS Details'!D:D) -> IMS | B25: =_xlfn.XLOOKUP(F25,'TFS Details'!F:F,'TFS Details'!A:A) -> Enhancement in Generative AI for AMS, SI, IMS service group | C25: =_xlfn.XLOOKUP(F25,'TFS Details'!F:F,'TFS Details'!E:E) -> 4443485 | D25: Pirtheebaa | E25: IMS: AMS: As a mySolutionPlanner user, I want to enhance the Generative AI screen with conditional non-mandatory fields for “In Progress” status, sync Agentic Productivity fields with the PMO Extract Report, and update the Gen AI Productivity info message. | F25: 4443505 | G25: Shalini | H25: Nivetha | I25: Shalini.b.pandey | J25: Yes | M25: Complex | O25: 0.05 | V25: Completed | W25: Completed | X25: Completed | Y25: Completed | Z25: 53 | AA25: 19 | AB25: 8 | AC25: 27 | AD25: 0.75 | AE25: 0.7 | AF25: =_xlfn.XLOOKUP(F25,'TFS Details'!F:F,'TFS Details'!H:H) -> UAT In Test | AG25: 27 | AH25: 0 | AI25: 0 | AJ25: 0 | AK25: =SUM(AG25:AJ25) -> 27 | AL25: =IF(AG25+AH25=0,0,SUM(AG25:AH25)/AK25) -> 1 | AM25: =IF(AG25=0,0,AG25/(SUM(AG25:AI25))) -> 1 | AN25: Delivered to UAT | AO25: =_xlfn.XLOOKUP(F25,'TFS Details'!F:F,'TFS Details'!I:I) -> CodeCrafters | AP25: =_xlfn.XLOOKUP(AO25,'TFS Details'!I:I,'TFS Details'!AE:AE) -> sona.job
A26: =_xlfn.XLOOKUP(F26,'TFS Details'!F:F,'TFS Details'!D:D) -> AMS | B26: =_xlfn.XLOOKUP(F26,'TFS Details'!F:F,'TFS Details'!A:A) -> Enhancement in Generative AI for AMS, SI, IMS service group | C26: =_xlfn.XLOOKUP(F26,'TFS Details'!F:F,'TFS Details'!E:E) -> 4443485 | D26: Pirtheebaa | E26: AMS: As a mySolutionPlanner user, I want to enhance the Generative AI screen with conditional non-mandatory fields for “In Progress” status, sync Agentic Productivity fields with the PMO Extract Report, and update the Gen AI Productivity info message. | F26: 4443486 | G26: Manisha | H26: Namrata | I26: Manisha.m.sharma | J26: Partial | K26: PMO Reports Validation | L26: Power BI report validation | O26: 0 | V26: Completed | W26: Completed | X26: Not Started | Y26: In Progress | AF26: =_xlfn.XLOOKUP(F26,'TFS Details'!F:F,'TFS Details'!H:H) -> UAT In Test | AG26: 0 | AH26: 0 | AI26: 0 | AJ26: 0 | AK26: =SUM(AG26:AJ26) -> 0 | AL26: =IF(AG26+AH26=0,0,SUM(AG26:AH26)/AK26) -> 0 | AM26: =IF(AG26=0,0,AG26/(SUM(AG26:AI26))) -> 0 | AO26: =_xlfn.XLOOKUP(F26,'TFS Details'!F:F,'TFS Details'!I:I) -> CodeCrafters | AP26: =_xlfn.XLOOKUP(AO26,'TFS Details'!I:I,'TFS Details'!AE:AE) -> sona.job
A27: =_xlfn.XLOOKUP(F27,'TFS Details'!F:F,'TFS Details'!D:D) -> SI | B27: =_xlfn.XLOOKUP(F27,'TFS Details'!F:F,'TFS Details'!A:A) -> Enhancement in Generative AI for AMS, SI, IMS service group | C27: =_xlfn.XLOOKUP(F27,'TFS Details'!F:F,'TFS Details'!E:E) -> 4443485 | D27: Pirtheebaa | E27: SI: As a mySolutionPlanner user, I want to enhance the Generative AI screen with conditional non-mandatory fields for “In Progress” status, sync Agentic Productivity fields with the PMO Extract Report, and update the Gen AI Productivity info message. | F27: 4443500 | G27: Vinayak | H27: Saranya | I27: vinayak.sangale | J27: Yes | M27: Complex | O27: 0.1 | V27: Completed | W27: Completed | X27: Completed | Y27: Completed | AF27: =_xlfn.XLOOKUP(F27,'TFS Details'!F:F,'TFS Details'!H:H) -> UAT In Test | AG27: 17 | AH27: 0 | AI27: 0 | AJ27: 0 | AK27: =SUM(AG27:AJ27) -> 17 | AL27: =IF(AG27+AH27=0,0,SUM(AG27:AH27)/AK27) -> 1 | AM27: =IF(AG27=0,0,AG27/(SUM(AG27:AI27))) -> 1 | AO27: =_xlfn.XLOOKUP(F27,'TFS Details'!F:F,'TFS Details'!I:I) -> CodeCrafters | AP27: =_xlfn.XLOOKUP(AO27,'TFS Details'!I:I,'TFS Details'!AE:AE) -> sona.job
A28: =_xlfn.XLOOKUP(F28,'TFS Details'!F:F,'TFS Details'!D:D) -> Reviewer Approver | B28: =_xlfn.XLOOKUP(F28,'TFS Details'!F:F,'TFS Details'!A:A) -> RA - Option to send reminder manually to the approver | C28: =_xlfn.XLOOKUP(F28,'TFS Details'!F:F,'TFS Details'!E:E) -> 4437646 | D28: Pirtheebaa | E28: **As a RA stakeholder user managing the Meeting Tracker **I want** to see a warning popup when I attempt to delete a meeting that is linked to one or more reviewer/approver records in View Approval Requests So that I am preventing unintended data loss | F28: 4437663 | G28: Manisha | H28: Namrata | I28: Manisha.m.sharma | J28: Yes | M28: Medium | O28: 0 | V28: Completed | W28: Completed | X28: Not Started | Y28: Completed | AF28: =_xlfn.XLOOKUP(F28,'TFS Details'!F:F,'TFS Details'!H:H) -> UAT In Test | AG28: 0 | AH28: 0 | AI28: 0 | AJ28: 0 | AK28: =SUM(AG28:AJ28) -> 0 | AL28: =IF(AG28+AH28=0,0,SUM(AG28:AH28)/AK28) -> 0 | AM28: =IF(AG28=0,0,AG28/(SUM(AG28:AI28))) -> 0 | AO28: =_xlfn.XLOOKUP(F28,'TFS Details'!F:F,'TFS Details'!I:I) -> BPMSBloggers | AP28: =_xlfn.XLOOKUP(AO28,'TFS Details'!I:I,'TFS Details'!AE:AE) -> sona.job
A29: =_xlfn.XLOOKUP(F29,'TFS Details'!F:F,'TFS Details'!D:D) -> Reviewer Approver | B29: =_xlfn.XLOOKUP(F29,'TFS Details'!F:F,'TFS Details'!A:A) -> RA - Option to send reminder manually to the approver | C29: =_xlfn.XLOOKUP(F29,'TFS Details'!F:F,'TFS Details'!E:E) -> 4437646 | D29: Pirtheebaa | E29: As a RA module stakeholder I want** to see a "Send Reminder" action button in the Actions Pane of the Request Grid **So that** I can manually trigger a reminder email to the assigned Reviewer/Approver without waiting for the next automatic reminder cycle | F29: 4437636 | G29: Mary | H29: Janardhan/Sadhik | J29: No | K29: Completely Email Scenario and includes reminder emails | L29: Basic email validation after just login | V29: Completed | W29: Completed | X29: Completed | Y29: Not Started | Z29: 55 | AA29: 13 | AB29: 2 | AC29: 15 | AD29: 0.95 | AE29: 0.8 | AF29: =_xlfn.XLOOKUP(F29,'TFS Details'!F:F,'TFS Details'!H:H) -> Active | AG29: 0 | AH29: 0 | AI29: 0 | AJ29: 15 | AK29: =SUM(AG29:AJ29) -> 15 | AL29: =IF(AG29+AH29=0,0,SUM(AG29:AH29)/AK29) -> 0 | AM29: =IF(AG29=0,0,AG29/(SUM(AG29:AI29))) -> 0 | AO29: =_xlfn.XLOOKUP(F29,'TFS Details'!F:F,'TFS Details'!I:I) -> BPMSBloggers | AP29: =_xlfn.XLOOKUP(AO29,'TFS Details'!I:I,'TFS Details'!AE:AE) -> sona.job
A30: =_xlfn.XLOOKUP(F30,'TFS Details'!F:F,'TFS Details'!D:D) -> DCSO | B30: =_xlfn.XLOOKUP(F30,'TFS Details'!F:F,'TFS Details'!A:A) -> myISP DCSO - Delivery Lead Assignments | C30: =_xlfn.XLOOKUP(F30,'TFS Details'!F:F,'TFS Details'!E:E) -> 4446526 | D30: Pirtheebaa | E30: As a Delivery Lead - ATCI, I want to access the WRWS tile in read-only mode so that I can view workflow details without making any changes. | F30: 4446470 | G30: Vinayak | H30: Saranya | I30: Manisha.m.sharma | J30: Yes | O30: 0 | V30: Completed | W30: Completed | X30: Completed | Y30: Not Started | AF30: =_xlfn.XLOOKUP(F30,'TFS Details'!F:F,'TFS Details'!H:H) -> New | AG30: 0 | AH30: 0 | AI30: 0 | AJ30: 8 | AK30: =SUM(AG30:AJ30) -> 8 | AL30: =IF(AG30+AH30=0,0,SUM(AG30:AH30)/AK30) -> 0 | AM30: =IF(AG30=0,0,AG30/(SUM(AG30:AI30))) -> 0 | AO30: =_xlfn.XLOOKUP(F30,'TFS Details'!F:F,'TFS Details'!I:I) -> TechWarriors | AP30: =_xlfn.XLOOKUP(AO30,'TFS Details'!I:I,'TFS Details'!AE:AE) -> Supriya.a.dhingra
A31: =_xlfn.XLOOKUP(F31,'TFS Details'!F:F,'TFS Details'!D:D) -> SA Team manager | B31: =_xlfn.XLOOKUP(F31,'TFS Details'!F:F,'TFS Details'!A:A) -> SA Team manager UI updates.1. Capability to be autopopulate for Operations 2. Dependency of Deployment field for capability in left side slicer. | C31: =_xlfn.XLOOKUP(F31,'TFS Details'!F:F,'TFS Details'!E:E) -> 4441867 | D31: Pirtheebaa | E31: As an SA Team Manager user, I want to add “Ops Activation” as an option in the Alignment dropdown in Register now pop up so that operations-related users can be correctly aligned across all SA Team Manager workflows. | F31: 4449855 | G31: Vinayak | H31: Saranya | J31: No | K31: Register Now is 1 time activity, which can't be enabled everytime in all the env's. Not feasible to automate | L31: Everytime new User validation | V31: Completed | W31: Completed | X31: Completed | Y31: In Progress | AF31: =_xlfn.XLOOKUP(F31,'TFS Details'!F:F,'TFS Details'!H:H) -> PT In Test | AG31: 7 | AH31: 0 | AI31: 0 | AJ31: 0 | AK31: =SUM(AG31:AJ31) -> 7 | AL31: =IF(AG31+AH31=0,0,SUM(AG31:AH31)/AK31) -> 1 | AM31: =IF(AG31=0,0,AG31/(SUM(AG31:AI31))) -> 1 | AO31: =_xlfn.XLOOKUP(F31,'TFS Details'!F:F,'TFS Details'!I:I) -> GoRetro | AP31: =_xlfn.XLOOKUP(AO31,'TFS Details'!I:I,'TFS Details'!AE:AE) -> sowjanya.kari
A32: =_xlfn.XLOOKUP(F32,'TFS Details'!F:F,'TFS Details'!D:D) -> SA Team manager | B32: =_xlfn.XLOOKUP(F32,'TFS Details'!F:F,'TFS Details'!A:A) -> SA Team manager UI updates.1. Capability to be autopopulate for Operations 2. Dependency of Deployment field for capability in left side slicer. | C32: =_xlfn.XLOOKUP(F32,'TFS Details'!F:F,'TFS Details'!E:E) -> 4441867 | D32: Pirtheebaa | E32: As an SA Team Manager user, I want the Alignment field to support multi?select when Deployment and Capability are Operations so that multiple operational alignments can be captured accurately. | F32: 4449887 | G32: Shalini | H32: Nivetha | I32: Shalini.b.pandey | J32: Yes | M32: Medium | O32: 0.05 | V32: Completed | W32: Completed | X32: Completed | Y32: Not Started | Z32: 30 | AA32: 9 | AB32: 3 | AC32: 12 | AD32: 0.95 | AE32: 0.95 | AF32: =_xlfn.XLOOKUP(F32,'TFS Details'!F:F,'TFS Details'!H:H) -> In Development | AG32: 0 | AH32: 0 | AI32: 0 | AJ32: 12 | AK32: =SUM(AG32:AJ32) -> 12 | AL32: =IF(AG32+AH32=0,0,SUM(AG32:AH32)/AK32) -> 0 | AM32: =IF(AG32=0,0,AG32/(SUM(AG32:AI32))) -> 0 | AO32: =_xlfn.XLOOKUP(F32,'TFS Details'!F:F,'TFS Details'!I:I) -> GoRetro | AP32: =_xlfn.XLOOKUP(AO32,'TFS Details'!I:I,'TFS Details'!AE:AE) -> sowjanya.kari
A33: =_xlfn.XLOOKUP(F33,'TFS Details'!F:F,'TFS Details'!D:D) -> SA Team manager | B33: =_xlfn.XLOOKUP(F33,'TFS Details'!F:F,'TFS Details'!A:A) -> SA Team manager UI updates.1. Capability to be autopopulate for Operations 2. Dependency of Deployment field for capability in left side slicer. | C33: =_xlfn.XLOOKUP(F33,'TFS Details'!F:F,'TFS Details'!E:E) -> 4441867 | D33: Pirtheebaa | E33: As an SA Team Manager user, I want the Alignment field to support multi‑select when Deployment and Capability are Operations in Register now pop, so that multiple operational alignments can be captured accurately. | F33: 4450923 | G33: Shalini | H33: Nivetha | J33: No | K33: Register Now is 1 time activity, which can't be enabled everytime in all the env's. Not feasible to automate | L33: Everytime new User validation | V33: Completed | W33: Completed | X33: Completed | Y33: Not Started | Z33: 40 | AA33: 12 | AB33: 0 | AC33: 12 | AD33: 1 | AE33: 1 | AF33: =_xlfn.XLOOKUP(F33,'TFS Details'!F:F,'TFS Details'!H:H) -> In Development | AG33: 0 | AH33: 0 | AI33: 0 | AJ33: 11 | AK33: =SUM(AG33:AJ33) -> 11 | AL33: =IF(AG33+AH33=0,0,SUM(AG33:AH33)/AK33) -> 0 | AM33: =IF(AG33=0,0,AG33/(SUM(AG33:AI33))) -> 0 | AO33: =_xlfn.XLOOKUP(F33,'TFS Details'!F:F,'TFS Details'!I:I) -> GoRetro | AP33: =_xlfn.XLOOKUP(AO33,'TFS Details'!I:I,'TFS Details'!AE:AE) -> sowjanya.kari
A34: =_xlfn.XLOOKUP(F34,'TFS Details'!F:F,'TFS Details'!D:D) -> SA Team manager | B34: =_xlfn.XLOOKUP(F34,'TFS Details'!F:F,'TFS Details'!A:A) -> SA Team manager UI updates.1. Capability to be autopopulate for Operations 2. Dependency of Deployment field for capability in left side slicer. | C34: =_xlfn.XLOOKUP(F34,'TFS Details'!F:F,'TFS Details'!E:E) -> 4441867 | D34: Pirtheebaa | E34: As an SA Team Manager user, I want the Alignment field to support multi‑select when Deployment and Capability are Operations in Pending user request tab, so that multiple operational alignments can be captured accurately. | F34: 4450935 | G34: Manisha | H34: Namrata | J34: No | K34: Register Now is 1 time activity, which can't be enabled everytime in all the env's. Not feasible to automate | L34: Everytime new User validation | V34: Completed | W34: Completed | X34: Not Started | Y34: Not Started | AF34: =_xlfn.XLOOKUP(F34,'TFS Details'!F:F,'TFS Details'!H:H) -> In Development | AG34: 0 | AH34: 0 | AI34: 0 | AJ34: 17 | AK34: =SUM(AG34:AJ34) -> 17 | AL34: =IF(AG34+AH34=0,0,SUM(AG34:AH34)/AK34) -> 0 | AM34: =IF(AG34=0,0,AG34/(SUM(AG34:AI34))) -> 0 | AO34: =_xlfn.XLOOKUP(F34,'TFS Details'!F:F,'TFS Details'!I:I) -> GoRetro | AP34: =_xlfn.XLOOKUP(AO34,'TFS Details'!I:I,'TFS Details'!AE:AE) -> sowjanya.kari
A35: =_xlfn.XLOOKUP(F35,'TFS Details'!F:F,'TFS Details'!D:D) -> SA Team manager | B35: =_xlfn.XLOOKUP(F35,'TFS Details'!F:F,'TFS Details'!A:A) -> SA Team manager UI updates.1. Capability to be autopopulate for Operations 2. Dependency of Deployment field for capability in left side slicer. | C35: =_xlfn.XLOOKUP(F35,'TFS Details'!F:F,'TFS Details'!E:E) -> 4441867 | D35: Pirtheebaa | E35: As an SA Team Manager user, I want to add “Ops Activation” as an option in the Alignment dropdown in SA team manager dashboard so that operations-related users can be correctly aligned across all SA Team Manager workflows. - Copy | F35: 4450948 | G35: Manisha | H35: Namrata | I35: Manisha.m.sharma | J35: Yes | M35: Medium | O35: 0 | V35: Completed | W35: Completed | X35: Not Started | Y35: In Progress | AF35: =_xlfn.XLOOKUP(F35,'TFS Details'!F:F,'TFS Details'!H:H) -> PT In Test | AG35: 0 | AH35: 0 | AI35: 0 | AJ35: 7 | AK35: =SUM(AG35:AJ35) -> 7 | AL35: =IF(AG35+AH35=0,0,SUM(AG35:AH35)/AK35) -> 0 | AM35: =IF(AG35=0,0,AG35/(SUM(AG35:AI35))) -> 0 | AO35: =_xlfn.XLOOKUP(F35,'TFS Details'!F:F,'TFS Details'!I:I) -> GoRetro | AP35: =_xlfn.XLOOKUP(AO35,'TFS Details'!I:I,'TFS Details'!AE:AE) -> sowjanya.kari
A36: =_xlfn.XLOOKUP(F36,'TFS Details'!F:F,'TFS Details'!D:D) -> SA Team manager | B36: =_xlfn.XLOOKUP(F36,'TFS Details'!F:F,'TFS Details'!A:A) -> SA Team manager UI updates.1. Capability to be autopopulate for Operations 2. Dependency of Deployment field for capability in left side slicer. | C36: =_xlfn.XLOOKUP(F36,'TFS Details'!F:F,'TFS Details'!E:E) -> 4441867 | D36: Pirtheebaa | E36: As an SA Team Manager user, I want to add “Ops Activation” as an option in the Alignment dropdown in Pending user requests tab so that operations-related users can be correctly aligned across all SA Team Manager workflows. | F36: 4450949 | G36: Mary | H36: Janardhan/Sadhik | J36: No | K36: Related to Pending request tab which will not have access. | L36: Everytime new User validation | V36: Completed | W36: Completed | X36: Completed | Y36: Completed | Z36: 38 | AA36: 29 | AB36: 0 | AC36: 29 | AD36: 0.95 | AE36: 0.8 | AF36: =_xlfn.XLOOKUP(F36,'TFS Details'!F:F,'TFS Details'!H:H) -> PT In Test | AG36: 29 | AH36: 0 | AI36: 0 | AJ36: 0 | AK36: =SUM(AG36:AJ36) -> 29 | AL36: =IF(AG36+AH36=0,0,SUM(AG36:AH36)/AK36) -> 1 | AM36: =IF(AG36=0,0,AG36/(SUM(AG36:AI36))) -> 1 | AO36: =_xlfn.XLOOKUP(F36,'TFS Details'!F:F,'TFS Details'!I:I) -> GoRetro | AP36: =_xlfn.XLOOKUP(AO36,'TFS Details'!I:I,'TFS Details'!AE:AE) -> sowjanya.kari
A37: =_xlfn.XLOOKUP(F37,'TFS Details'!F:F,'TFS Details'!D:D) -> myCalendar | B37: =_xlfn.XLOOKUP(F37,'TFS Details'!F:F,'TFS Details'!A:A) -> myCalendar: Simplify calender funtionality for Solution Architect | C37: =_xlfn.XLOOKUP(F37,'TFS Details'!F:F,'TFS Details'!E:E) -> 4447848 | D37: Pirtheebaa | E37: As a Solution Architect, I want to view all my saved absence entries listed in the Special Absence (Dates) column for each week row, so that I can see a summary of all logged absences and add more if needed | F37: 4450103 | G37: Shalini | H37: Nivetha | I37: Shalini.b.pandey | J37: Yes | M37: Complex | O37: 0.05 | V37: Completed | W37: Completed | X37: Completed | Y37: Not Started | Z37: 40 | AA37: 13 | AB37: 4 | AC37: 17 | AD37: 0.95 | AE37: 0.9 | AF37: =_xlfn.XLOOKUP(F37,'TFS Details'!F:F,'TFS Details'!H:H) -> Active | AG37: 0 | AH37: 0 | AI37: 0 | AJ37: 15 | AK37: =SUM(AG37:AJ37) -> 15 | AL37: =IF(AG37+AH37=0,0,SUM(AG37:AH37)/AK37) -> 0 | AM37: =IF(AG37=0,0,AG37/(SUM(AG37:AI37))) -> 0 | AO37: =_xlfn.XLOOKUP(F37,'TFS Details'!F:F,'TFS Details'!I:I) -> NGTransformers | AP37: =_xlfn.XLOOKUP(AO37,'TFS Details'!I:I,'TFS Details'!AE:AE) -> sowjanya.kari
A38: =_xlfn.XLOOKUP(F38,'TFS Details'!F:F,'TFS Details'!D:D) -> myCalendar | B38: =_xlfn.XLOOKUP(F38,'TFS Details'!F:F,'TFS Details'!A:A) -> myCalendar: Simplify calender funtionality for Solution Architect | C38: =_xlfn.XLOOKUP(F38,'TFS Details'!F:F,'TFS Details'!E:E) -> 4447848 | D38: Pirtheebaa | E38: As a Solution Architect, I want to edit or delete an existing absence entry from the Special Absence (Dates) column, so that I can correct or remove previously logged absence details without recreating the data from scratch | F38: 4450104 | G38: Manisha | H38: Namrata | I38: Manisha.m.sharma | J38: Yes | M38: Medium | O38: 0 | V38: Completed | W38: Completed | X38: Not Started | Y38: Not Started | AF38: =_xlfn.XLOOKUP(F38,'TFS Details'!F:F,'TFS Details'!H:H) -> Active | AG38: 0 | AH38: 0 | AI38: 0 | AJ38: 0 | AK38: =SUM(AG38:AJ38) -> 0 | AL38: =IF(AG38+AH38=0,0,SUM(AG38:AH38)/AK38) -> 0 | AM38: =IF(AG38=0,0,AG38/(SUM(AG38:AI38))) -> 0 | AO38: =_xlfn.XLOOKUP(F38,'TFS Details'!F:F,'TFS Details'!I:I) -> NGTransformers | AP38: =_xlfn.XLOOKUP(AO38,'TFS Details'!I:I,'TFS Details'!AE:AE) -> sowjanya.kari
A39: =_xlfn.XLOOKUP(F39,'TFS Details'!F:F,'TFS Details'!D:D) -> myCalendar | B39: =_xlfn.XLOOKUP(F39,'TFS Details'!F:F,'TFS Details'!A:A) -> myCalendar: Simplify calender funtionality for Solution Architect | C39: =_xlfn.XLOOKUP(F39,'TFS Details'!F:F,'TFS Details'!E:E) -> 4447848 | D39: Pirtheebaa | E39: As a Solution Architect, I want to add a Special Absence entry for a specific week on the Create Event tab, so that I can log my planned leave or absence periods with the relevant event type and date details | F39: 4449975 | G39: Mary | H39: Janardhan/Sadhik | I39: Vinayak.Sangale | J39: Partial | K39: Includes email functionality. | L39: Email validation | M39: Complex | O39: 0.05 | V39: Completed | W39: Completed | X39: Completed | Y39: Not Started | Z39: 48 | AA39: 34 | AB39: 0 | AC39: 34 | AD39: 0.95 | AE39: 0.8 | AF39: =_xlfn.XLOOKUP(F39,'TFS Details'!F:F,'TFS Details'!H:H) -> Active | AG39: 0 | AH39: 0 | AI39: 0 | AJ39: 34 | AK39: =SUM(AG39:AJ39) -> 34 | AL39: =IF(AG39+AH39=0,0,SUM(AG39:AH39)/AK39) -> 0 | AM39: =IF(AG39=0,0,AG39/(SUM(AG39:AI39))) -> 0 | AO39: =_xlfn.XLOOKUP(F39,'TFS Details'!F:F,'TFS Details'!I:I) -> NGTransformers | AP39: =_xlfn.XLOOKUP(AO39,'TFS Details'!I:I,'TFS Details'!AE:AE) -> sowjanya.kari
A40: =_xlfn.XLOOKUP(F40,'TFS Details'!F:F,'TFS Details'!D:D) -> myCalendar | B40: =_xlfn.XLOOKUP(F40,'TFS Details'!F:F,'TFS Details'!A:A) -> myCalendar: Simplify calender funtionality for Solution Architect | C40: =_xlfn.XLOOKUP(F40,'TFS Details'!F:F,'TFS Details'!E:E) -> 4447848 | D40: Pirtheebaa | E40: As a Solution Architect, I want to be navigated to the Create Event tab when I click Create event from View Events empty state, so that I can quickly enter my availability details for the selected month | F40: 4448855 | G40: Shalini | H40: Nivetha | I40: n.selvakumar | J40: Yes | M40: Medium | O40: 0.1 | V40: Completed | W40: Completed | X40: Completed | Y40: Not Started | Z40: 51 | AA40: 17 | AB40: 4 | AC40: 21 | AD40: 0.95 | AE40: 0.9 | AF40: =_xlfn.XLOOKUP(F40,'TFS Details'!F:F,'TFS Details'!H:H) -> Active | AG40: 0 | AH40: 0 | AI40: 0 | AJ40: 21 | AK40: =SUM(AG40:AJ40) -> 21 | AL40: =IF(AG40+AH40=0,0,SUM(AG40:AH40)/AK40) -> 0 | AM40: =IF(AG40=0,0,AG40/(SUM(AG40:AI40))) -> 0 | AO40: =_xlfn.XLOOKUP(F40,'TFS Details'!F:F,'TFS Details'!I:I) -> NGTransformers | AP40: =_xlfn.XLOOKUP(AO40,'TFS Details'!I:I,'TFS Details'!AE:AE) -> sowjanya.kari
A41: =_xlfn.XLOOKUP(F41,'TFS Details'!F:F,'TFS Details'!D:D) -> myCalendar | B41: =_xlfn.XLOOKUP(F41,'TFS Details'!F:F,'TFS Details'!A:A) -> myCalendar: Simplify calender funtionality for Solution Architect | C41: =_xlfn.XLOOKUP(F41,'TFS Details'!F:F,'TFS Details'!E:E) -> 4447848 | D41: Pirtheebaa | E41: As a Solution Architect, I want to select multiple Opportunities/Tasks and add Special Absence entries per week on the Create Event tab, so that I can accurately capture my weekly availability commitments and planned leave periods | F41: 4448856 | G41: Shalini | H41: Nivetha | I41: Shalini.b.pandey | J41: Yes | M41: Complex | O41: 0.05 | V41: Completed | W41: Completed | X41: Completed | Y41: Not Started | Z41: 35 | AA41: 12 | AB41: 4 | AC41: 16 | AD41: 0.9 | AE41: 0.9 | AF41: =_xlfn.XLOOKUP(F41,'TFS Details'!F:F,'TFS Details'!H:H) -> Active | AG41: 0 | AH41: 0 | AI41: 0 | AJ41: 16 | AK41: =SUM(AG41:AJ41) -> 16 | AL41: =IF(AG41+AH41=0,0,SUM(AG41:AH41)/AK41) -> 0 | AM41: =IF(AG41=0,0,AG41/(SUM(AG41:AI41))) -> 0 | AO41: =_xlfn.XLOOKUP(F41,'TFS Details'!F:F,'TFS Details'!I:I) -> NGTransformers | AP41: =_xlfn.XLOOKUP(AO41,'TFS Details'!I:I,'TFS Details'!AE:AE) -> sowjanya.kari
A42: =_xlfn.XLOOKUP(F42,'TFS Details'!F:F,'TFS Details'!D:D) -> myCalendar | B42: =_xlfn.XLOOKUP(F42,'TFS Details'!F:F,'TFS Details'!A:A) -> myCalendar: Simplify calender funtionality for Solution Architect | C42: =_xlfn.XLOOKUP(F42,'TFS Details'!F:F,'TFS Details'!E:E) -> 4447848 | D42: Pirtheebaa | E42: As a solution architect, I want to land on the My availability screen on clicking of view details from manage screen, so that user can log their events. | F42: 4448150 | G42: Shalini | H42: Nivetha | I42: n.selvakumar | J42: Yes | M42: Complex | O42: 0.2 | V42: Completed | W42: Completed | X42: Completed | Y42: Not Started | Z42: 43 | AA42: 18 | AB42: 3 | AC42: 21 | AD42: 0.95 | AE42: 0.9 | AF42: =_xlfn.XLOOKUP(F42,'TFS Details'!F:F,'TFS Details'!H:H) -> Active | AG42: 0 | AH42: 0 | AI42: 0 | AJ42: 21 | AK42: =SUM(AG42:AJ42) -> 21 | AL42: =IF(AG42+AH42=0,0,SUM(AG42:AH42)/AK42) -> 0 | AM42: =IF(AG42=0,0,AG42/(SUM(AG42:AI42))) -> 0 | AO42: =_xlfn.XLOOKUP(F42,'TFS Details'!F:F,'TFS Details'!I:I) -> NGTransformers | AP42: =_xlfn.XLOOKUP(AO42,'TFS Details'!I:I,'TFS Details'!AE:AE) -> sowjanya.kari
A43: =_xlfn.XLOOKUP(F43,'TFS Details'!F:F,'TFS Details'!D:D) -> myCalendar | B43: =_xlfn.XLOOKUP(F43,'TFS Details'!F:F,'TFS Details'!A:A) -> myCalendar: Simplify calender funtionality for Solution Architect | C43: =_xlfn.XLOOKUP(F43,'TFS Details'!F:F,'TFS Details'!E:E) -> 4447848 | D43: Pirtheebaa | E43: As a solution Architect, I want My Availability to be added in Manage screen , so that user can navigate from manage screen to My Availability screen | F43: 4448151 | G43: Manisha | H43: Namrata | I43: namrata.g.umardand | J43: Yes | M43: Medium | O43: 0.05 | V43: Completed | W43: Completed | X43: Not Started | Y43: Not Started | AF43: =_xlfn.XLOOKUP(F43,'TFS Details'!F:F,'TFS Details'!H:H) -> Active | AG43: 0 | AH43: 0 | AI43: 0 | AJ43: 0 | AK43: =SUM(AG43:AJ43) -> 0 | AL43: =IF(AG43+AH43=0,0,SUM(AG43:AH43)/AK43) -> 0 | AM43: =IF(AG43=0,0,AG43/(SUM(AG43:AI43))) -> 0 | AO43: =_xlfn.XLOOKUP(F43,'TFS Details'!F:F,'TFS Details'!I:I) -> NGTransformers | AP43: =_xlfn.XLOOKUP(AO43,'TFS Details'!I:I,'TFS Details'!AE:AE) -> sowjanya.kari
A44: =_xlfn.XLOOKUP(F44,'TFS Details'!F:F,'TFS Details'!D:D) -> DCSO | B44: =_xlfn.XLOOKUP(F44,'TFS Details'!F:F,'TFS Details'!A:A) -> myISP DCSO - Delivery Lead Assignments | C44: =_xlfn.XLOOKUP(F44,'TFS Details'!F:F,'TFS Details'!E:E) -> 4446526 | D44: Pirtheebaa | E44: As a Delivery Lead - ATCI/ATCP/Global, I want to access the Opportunity workflow for AMS/IMS/SI so that I can view workflow details without making any changes. | F44: 4456104 | G44: Mary | H44: Janardhan/Sadhik | I44: Mary.jacob | J44: Yes | L44: external Integration validation | M44: Medium | N44: 5 | O44: 0.05 | P44: 20 | Q44: 5 | R44: 0 | V44: Completed | W44: Completed | X44: Completed | Y44: Not Started | Z44: 50 | AA44: 39 | AB44: 0 | AC44: 39 | AD44: 0.95 | AE44: 0.8 | AF44: =_xlfn.XLOOKUP(F44,'TFS Details'!F:F,'TFS Details'!H:H) -> Active | AG44: 0 | AH44: 0 | AI44: 0 | AJ44: 39 | AK44: =SUM(AG44:AJ44) -> 39 | AL44: =IF(AG44+AH44=0,0,SUM(AG44:AH44)/AK44) -> 0 | AM44: =IF(AG44=0,0,AG44/(SUM(AG44:AI44))) -> 0 | AO44: =_xlfn.XLOOKUP(F44,'TFS Details'!F:F,'TFS Details'!I:I) -> TechWarriors | AP44: =_xlfn.XLOOKUP(AO44,'TFS Details'!I:I,'TFS Details'!AE:AE) -> Supriya.a.dhingra
A45: =_xlfn.XLOOKUP(F45,'TFS Details'!F:F,'TFS Details'!D:D) -> myCalendar | B45: =_xlfn.XLOOKUP(F45,'TFS Details'!F:F,'TFS Details'!A:A) -> myCalendar: Simplify calender funtionality for Solution Architect | C45: =_xlfn.XLOOKUP(F45,'TFS Details'!F:F,'TFS Details'!E:E) -> 4447848 | D45: Pirtheebaa | E45: As a Solution Architect, I want to enter my availability percentage for each week row in the Create Event tab, so that I can accurately communicate how much of my time is available for solution activities that week. | F45: 4450161 | G45: Shalini | H45: Nivetha | I45: n.selvakumar | J45: Yes | M45: Complex | O45: 0.1 | V45: Completed | W45: Completed | X45: Completed | Y45: Not Started | Z45: 12 | AA45: 12 | AB45: 0 | AC45: 12 | AD45: 0.95 | AE45: 0.9 | AF45: =_xlfn.XLOOKUP(F45,'TFS Details'!F:F,'TFS Details'!H:H) -> Active | AG45: 0 | AH45: 0 | AI45: 0 | AJ45: 12 | AK45: =SUM(AG45:AJ45) -> 12 | AL45: =IF(AG45+AH45=0,0,SUM(AG45:AH45)/AK45) -> 0 | AM45: =IF(AG45=0,0,AG45/(SUM(AG45:AI45))) -> 0 | AO45: =_xlfn.XLOOKUP(F45,'TFS Details'!F:F,'TFS Details'!I:I) -> NGTransformers | AP45: =_xlfn.XLOOKUP(AO45,'TFS Details'!I:I,'TFS Details'!AE:AE) -> sowjanya.kari
A46: =_xlfn.XLOOKUP(F46,'TFS Details'!F:F,'TFS Details'!D:D) -> myCalendar | B46: =_xlfn.XLOOKUP(F46,'TFS Details'!F:F,'TFS Details'!A:A) -> myCalendar: Simplify calender funtionality for Solution Architect | C46: =_xlfn.XLOOKUP(F46,'TFS Details'!F:F,'TFS Details'!E:E) -> 4447848 | D46: Pirtheebaa | E46: As a BPMS User, I want to fill in additional organisational details when adding an absence entry in the Create Event tab, so that the system captures OOO delegation, backup ownership, and lead assignments relevant to my role. | F46: 4450197 | G46: Shalini | H46: Nivetha | I46: n.selvakumar | J46: Partial | K46: Includes email functionality | M46: Complex | O46: 0.1 | V46: Completed | W46: Completed | X46: Completed | Y46: Not Started | Z46: 50 | AA46: 50 | AB46: 1 | AC46: 51 | AD46: 0.95 | AE46: 0.9 | AF46: =_xlfn.XLOOKUP(F46,'TFS Details'!F:F,'TFS Details'!H:H) -> Active | AG46: 0 | AH46: 0 | AI46: 0 | AJ46: 51 | AK46: =SUM(AG46:AJ46) -> 51 | AL46: =IF(AG46+AH46=0,0,SUM(AG46:AH46)/AK46) -> 0 | AM46: =IF(AG46=0,0,AG46/(SUM(AG46:AI46))) -> 0 | AO46: =_xlfn.XLOOKUP(F46,'TFS Details'!F:F,'TFS Details'!I:I) -> NGTransformers | AP46: =_xlfn.XLOOKUP(AO46,'TFS Details'!I:I,'TFS Details'!AE:AE) -> sowjanya.kari
A47: =_xlfn.XLOOKUP(F47,'TFS Details'!F:F,'TFS Details'!D:D) -> myCalendar | B47: =_xlfn.XLOOKUP(F47,'TFS Details'!F:F,'TFS Details'!A:A) -> myCalendar: Simplify calender funtionality for Solution Architect | C47: =_xlfn.XLOOKUP(F47,'TFS Details'!F:F,'TFS Details'!E:E) -> 4447848 | D47: Pirtheebaa | E47: As a Solution Architect, I want to view all my saved availability events for the selected month in the View Events tab and edit any absence entry inline, so that I can review and update my calendar data without switching to the Create Event tab. | F47: 4450214 | G47: Shalini | H47: Nivetha | I47: Shalini.b.pandey | J47: Yes | M47: Complex | O47: 0.05 | V47: Completed | W47: Completed | X47: Completed | Y47: Not Started | Z47: 21 | AA47: 17 | AB47: 1 | AC47: 18 | AD47: 0.9 | AE47: 0.9 | AF47: =_xlfn.XLOOKUP(F47,'TFS Details'!F:F,'TFS Details'!H:H) -> Active | AG47: 0 | AH47: 0 | AI47: 0 | AJ47: 18 | AK47: =SUM(AG47:AJ47) -> 18 | AL47: =IF(AG47+AH47=0,0,SUM(AG47:AH47)/AK47) -> 0 | AM47: =IF(AG47=0,0,AG47/(SUM(AG47:AI47))) -> 0 | AO47: =_xlfn.XLOOKUP(F47,'TFS Details'!F:F,'TFS Details'!I:I) -> NGTransformers | AP47: =_xlfn.XLOOKUP(AO47,'TFS Details'!I:I,'TFS Details'!AE:AE) -> sowjanya.kari
A48: =_xlfn.XLOOKUP(F48,'TFS Details'!F:F,'TFS Details'!D:D) -> myCalendar | B48: =_xlfn.XLOOKUP(F48,'TFS Details'!F:F,'TFS Details'!A:A) -> myCalendar: Simplify calender funtionality for Solution Architect | C48: =_xlfn.XLOOKUP(F48,'TFS Details'!F:F,'TFS Details'!E:E) -> 4447848 | D48: Pirtheebaa | E48: As a Solution Architect, I want an Edit Event button on the View Events screen, so that I can navigate directly to the Create Event screen to add or modify absence entries | F48: 4451718 | G48: Shalini | H48: Nivetha | I48: Shalini.b.pandey | J48: Yes | M48: Medium | O48: 0.05 | V48: Completed | W48: Completed | X48: Completed | Y48: Not Started | Z48: 12 | AA48: 12 | AB48: 0 | AC48: 12 | AD48: 0.95 | AE48: 0.95 | AF48: =_xlfn.XLOOKUP(F48,'TFS Details'!F:F,'TFS Details'!H:H) -> Active | AG48: 0 | AH48: 0 | AI48: 0 | AJ48: 12 | AK48: =SUM(AG48:AJ48) -> 12 | AL48: =IF(AG48+AH48=0,0,SUM(AG48:AH48)/AK48) -> 0 | AM48: =IF(AG48=0,0,AG48/(SUM(AG48:AI48))) -> 0 | AO48: =_xlfn.XLOOKUP(F48,'TFS Details'!F:F,'TFS Details'!I:I) -> NGTransformers | AP48: =_xlfn.XLOOKUP(AO48,'TFS Details'!I:I,'TFS Details'!AE:AE) -> sowjanya.kari
A49: =_xlfn.XLOOKUP(F49,'TFS Details'!F:F,'TFS Details'!D:D) -> PMO | B49: =_xlfn.XLOOKUP(F49,'TFS Details'!F:F,'TFS Details'!A:A) -> [PMO] URL update for Manage and Dashboard screens | C49: =_xlfn.XLOOKUP(F49,'TFS Details'!F:F,'TFS Details'!E:E) -> 4440976 | D49: Pirtheebaa | E49: [PMO] As a PMO user, I should be able to navigate to Manage / Dashboard screen with the new URL from Estimator/Calculator | F49: 4446593 | G49: Shalini | H49: Nivetha | I49: Shalini.b.pandey | J49: Yes | M49: Simple | O49: 0.05 | P49: 20 | Q49: 5 | R49: 2 | S49: 7 | T49: 0.8 | U49: 0.4 | V49: Completed | W49: Completed | X49: Completed | Y49: Not Started | Z49: 11 | AA49: 11 | AB49: 0 | AC49: 11 | AD49: 0.95 | AE49: 0.95 | AF49: =_xlfn.XLOOKUP(F49,'TFS Details'!F:F,'TFS Details'!H:H) -> New | AG49: 0 | AH49: 0 | AI49: 0 | AJ49: 11 | AK49: =SUM(AG49:AJ49) -> 11 | AL49: =IF(AG49+AH49=0,0,SUM(AG49:AH49)/AK49) -> 0 | AM49: =IF(AG49=0,0,AG49/(SUM(AG49:AI49))) -> 0 | AO49: =_xlfn.XLOOKUP(F49,'TFS Details'!F:F,'TFS Details'!I:I) -> TechWarriors | AP49: =_xlfn.XLOOKUP(AO49,'TFS Details'!I:I,'TFS Details'!AE:AE) -> Supriya.a.dhingra
A50: =_xlfn.XLOOKUP(F50,'TFS Details'!F:F,'TFS Details'!D:D) -> PMO | B50: =_xlfn.XLOOKUP(F50,'TFS Details'!F:F,'TFS Details'!A:A) -> [PMO] URL update for Manage and Dashboard screens | C50: =_xlfn.XLOOKUP(F50,'TFS Details'!F:F,'TFS Details'!E:E) -> 4440976 | D50: Pirtheebaa | E50: [PMO] As a PMO user, I should be able to navigate to Manage / Dashboard screen with the new URL from Review Approval | F50: 4446675 | G50: Manisha | H50: Namrata | I50: namrata.g.umardand | J50: Yes | M50: Simple | O50: 0.05 | V50: Completed | W50: Completed | X50: Not Started | Y50: Not Started | AF50: =_xlfn.XLOOKUP(F50,'TFS Details'!F:F,'TFS Details'!H:H) -> PT In Test | AG50: 0 | AH50: 0 | AI50: 0 | AJ50: 0 | AK50: =SUM(AG50:AJ50) -> 0 | AL50: =IF(AG50+AH50=0,0,SUM(AG50:AH50)/AK50) -> 0 | AM50: =IF(AG50=0,0,AG50/(SUM(AG50:AI50))) -> 0 | AO50: =_xlfn.XLOOKUP(F50,'TFS Details'!F:F,'TFS Details'!I:I) -> CodeCrafters | AP50: =_xlfn.XLOOKUP(AO50,'TFS Details'!I:I,'TFS Details'!AE:AE) -> sona.job
A51: =_xlfn.XLOOKUP(F51,'TFS Details'!F:F,'TFS Details'!D:D) -> PMO | B51: =_xlfn.XLOOKUP(F51,'TFS Details'!F:F,'TFS Details'!A:A) -> [PMO] URL update for Manage and Dashboard screens | C51: =_xlfn.XLOOKUP(F51,'TFS Details'!F:F,'TFS Details'!E:E) -> 4440976 | D51: Pirtheebaa | E51: [PMO] As a PMO user, I should be able to navigate to Manage / Dashboard screen with the new URL from Transition to Delivery | F51: 4447065 | G51: Shalini | H51: Nivetha | I51: namrata.g.umardand | J51: Yes | M51: Simple | O51: 0.05 | V51: Completed | W51: Completed | X51: Completed | Y51: In Progress | Z51: 20 | AA51: 19 | AB51: 0 | AC51: 19 | AD51: 0.95 | AE51: 0.95 | AF51: =_xlfn.XLOOKUP(F51,'TFS Details'!F:F,'TFS Details'!H:H) -> PT In Test | AG51: 16 | AH51: 0 | AI51: 0 | AJ51: 3 | AK51: =SUM(AG51:AJ51) -> 19 | AL51: =IF(AG51+AH51=0,0,SUM(AG51:AH51)/AK51) -> 0.84210526 | AM51: =IF(AG51=0,0,AG51/(SUM(AG51:AI51))) -> 1 | AO51: =_xlfn.XLOOKUP(F51,'TFS Details'!F:F,'TFS Details'!I:I) -> HustleHub | AP51: =_xlfn.XLOOKUP(AO51,'TFS Details'!I:I,'TFS Details'!AE:AE) -> pandidurai.ks
A52: =_xlfn.XLOOKUP(F52,'TFS Details'!F:F,'TFS Details'!D:D) -> PMO | B52: =_xlfn.XLOOKUP(F52,'TFS Details'!F:F,'TFS Details'!A:A) -> [PMO] URL update for Manage and Dashboard screens | C52: =_xlfn.XLOOKUP(F52,'TFS Details'!F:F,'TFS Details'!E:E) -> 4440976 | D52: Pirtheebaa | E52: [PMO] As a PMO user, I should be able to navigate to Manage / Dashboard screen with the new URL from Solution Component - AMS | F52: 4446596 | G52: Mary | H52: Janardhan/Sadhik | I52: Manisha.m.sharma | J52: Yes | M52: Simple | O52: 0 | V52: Completed | W52: Completed | X52: Completed | Y52: In Progress | Z52: 52 | AA52: 20 | AB52: 0 | AC52: 20 | AD52: 0.95 | AE52: 0.8 | AF52: =_xlfn.XLOOKUP(F52,'TFS Details'!F:F,'TFS Details'!H:H) -> PT In Test | AG52: 1 | AH52: 0 | AI52: 0 | AJ52: 19 | AK52: =SUM(AG52:AJ52) -> 20 | AL52: =IF(AG52+AH52=0,0,SUM(AG52:AH52)/AK52) -> 0.05 | AM52: =IF(AG52=0,0,AG52/(SUM(AG52:AI52))) -> 1 | AO52: =_xlfn.XLOOKUP(F52,'TFS Details'!F:F,'TFS Details'!I:I) -> TechMavericks | AP52: =_xlfn.XLOOKUP(AO52,'TFS Details'!I:I,'TFS Details'!AE:AE) -> Francis.Deepak
A53: =_xlfn.XLOOKUP(F53,'TFS Details'!F:F,'TFS Details'!D:D) -> Learn | B53: =_xlfn.XLOOKUP(F53,'TFS Details'!F:F,'TFS Details'!A:A) -> Services - Learn & Launch enhancements | C53: =_xlfn.XLOOKUP(F53,'TFS Details'!F:F,'TFS Details'!E:E) -> 4443471 | D53: Pirtheebaa | E53: As a myISP platform administrator I want to update the "Give Feedback" link across all touchpoints in myISP to point to the new feedback form So that user feedback is routed to the correct owner | F53: 4471400 | G53: Manisha | H53: Namrata | I53: namrata.g.umardand | J53: Yes | M53: Medium | O53: 0.05 | V53: Completed | W53: Completed | AK53: =SUM(AG53:AJ53) -> 0 | AL53: =IF(AG53+AH53=0,0,SUM(AG53:AH53)/AK53) -> 0 | AM53: =IF(AG53=0,0,AG53/(SUM(AG53:AI53))) -> 0
A54: =_xlfn.XLOOKUP(F54,'TFS Details'!F:F,'TFS Details'!D:D) -> Learn | B54: =_xlfn.XLOOKUP(F54,'TFS Details'!F:F,'TFS Details'!A:A) -> Services - Learn & Launch enhancements | C54: =_xlfn.XLOOKUP(F54,'TFS Details'!F:F,'TFS Details'!E:E) -> 4443471 | D54: Pirtheebaa | E54: As a myISP platform administrator I want to update the "Give Feedback" link across all touchpoints in myISP to point to the new feedback form So that user feedback is routed to the correct owner | F54: 4450213 | G54: Manisha | H54: Namrata | I54: namrata.g.umardand | J54: Yes | M54: Medium | O54: 0.05 | V54: Completed | W54: Completed | X54: Not Started | Y54: Not Started | AF54: =_xlfn.XLOOKUP(F54,'TFS Details'!F:F,'TFS Details'!H:H) -> PT In Test | AG54: 0 | AH54: 0 | AI54: 0 | AJ54: 0 | AK54: =SUM(AG54:AJ54) -> 0 | AL54: =IF(AG54+AH54=0,0,SUM(AG54:AH54)/AK54) -> 0 | AM54: =IF(AG54=0,0,AG54/(SUM(AG54:AI54))) -> 0 | AO54: =_xlfn.XLOOKUP(F54,'TFS Details'!F:F,'TFS Details'!I:I) -> NGTransformers | AP54: =_xlfn.XLOOKUP(AO54,'TFS Details'!I:I,'TFS Details'!AE:AE) -> sowjanya.kari
A55: =_xlfn.XLOOKUP(F55,'TFS Details'!F:F,'TFS Details'!D:D) -> Auto-mailers | B55: =_xlfn.XLOOKUP(F55,'TFS Details'!F:F,'TFS Details'!A:A) -> CDAT PMO_ UI changes and addition of email template | C55: =_xlfn.XLOOKUP(F55,'TFS Details'!F:F,'TFS Details'!E:E) -> 4017211 | D55: Rajeswari | E55: As a myISP CDAT PMO user, I want the "CDAT request method" column and "initial mailer date" column in the PMO dashboard to be automatically updated by myISP when auto mailer is triggered So that I can have accurate tracking without manual data entry | F55: 4272036 | G55: Pavithra | H55: Sowndarya | J55: No | K55: Mailer - Fresh deal required | L55: Fresh Deal creation required everytime | V55: Completed | W55: Completed | X55: In Progress | Y55: Not Started | Z55: 25 | AA55: 6 | AB55: 0 | AC55: 6 | AF55: =_xlfn.XLOOKUP(F55,'TFS Details'!F:F,'TFS Details'!H:H) -> In Development | AG55: 0 | AH55: 0 | AI55: 0 | AJ55: 10 | AK55: 6 | AL55: =IF(AG55+AH55=0,0,SUM(AG55:AH55)/AK55) -> 0 | AM55: =IF(AG55=0,0,AG55/(SUM(AG55:AI55))) -> 0 | AO55: =_xlfn.XLOOKUP(F55,'TFS Details'!F:F,'TFS Details'!I:I) -> TechPhantoms | AP55: =_xlfn.XLOOKUP(AO55,'TFS Details'!I:I,'TFS Details'!AE:AE) -> sowjanya.kari
A56: =_xlfn.XLOOKUP(F56,'TFS Details'!F:F,'TFS Details'!D:D) -> CDAT | B56: =_xlfn.XLOOKUP(F56,'TFS Details'!F:F,'TFS Details'!A:A) -> BPMS Onboarding to CDAT | C56: =_xlfn.XLOOKUP(F56,'TFS Details'!F:F,'TFS Details'!E:E) -> 4459051 | D56: Rajeswari | E56: As a CDAT SME user or CDAT CM SME or CDAT Reviewer, I want a new editable dropdown field "Contract Submission Status" on the Assessment Details page | F56: 4449651 | G56: Agnes | H56: Shiva | I56: anto.aldrin.missier | J56: Yes | L56: Excel Validation | M56: Complex | O56: 0.15 | P56: 12 | V56: Completed | W56: Completed | X56: In Progress | Y56: Not Started | Z56: 40 | AA56: 9 | AB56: 3 | AC56: 9 | AF56: =_xlfn.XLOOKUP(F56,'TFS Details'!F:F,'TFS Details'!H:H) -> PT In Test | AG56: 0 | AH56: 0 | AI56: 0 | AJ56: 11 | AK56: 9 | AL56: =IF(AG56+AH56=0,0,SUM(AG56:AH56)/AK56) -> 0 | AM56: =IF(AG56=0,0,AG56/(SUM(AG56:AI56))) -> 0 | AO56: =_xlfn.XLOOKUP(F56,'TFS Details'!F:F,'TFS Details'!I:I) -> TechTribe | AP56: =_xlfn.XLOOKUP(AO56,'TFS Details'!I:I,'TFS Details'!AE:AE) -> pandidurai.ks
A57: =_xlfn.XLOOKUP(F57,'TFS Details'!F:F,'TFS Details'!D:D) -> CDAT | B57: =_xlfn.XLOOKUP(F57,'TFS Details'!F:F,'TFS Details'!A:A) -> BPMS Onboarding to CDAT | C57: =_xlfn.XLOOKUP(F57,'TFS Details'!F:F,'TFS Details'!E:E) -> 4459051 | D57: Rajeswari | E57: As a CDAT SME user or CDAT CM SME or CDAT Reviewer, I want the system to display a Validation Popup for Contract Submission Status During First Cut Analysis Generation | F57: 4450386 | G57: Sowndarya | H57: Jabeen | J57: No | K57: Requires fresh deal everytime to configure | L57: Fresh Deal creation required everytime | V57: Completed | W57: Completed | X57: In Progress | Y57: Not Started | Z57: 40 | AA57: 23 | AB57: 0 | AC57: 23 | AF57: =_xlfn.XLOOKUP(F57,'TFS Details'!F:F,'TFS Details'!H:H) -> Ready for Test | AG57: 0 | AH57: 0 | AI57: 0 | AJ57: 24 | AK57: 23 | AL57: =IF(AG57+AH57=0,0,SUM(AG57:AH57)/AK57) -> 0 | AM57: =IF(AG57=0,0,AG57/(SUM(AG57:AI57))) -> 0 | AO57: =_xlfn.XLOOKUP(F57,'TFS Details'!F:F,'TFS Details'!I:I) -> TechTribe | AP57: =_xlfn.XLOOKUP(AO57,'TFS Details'!I:I,'TFS Details'!AE:AE) -> pandidurai.ks
A58: =_xlfn.XLOOKUP(F58,'TFS Details'!F:F,'TFS Details'!D:D) -> CDAT | B58: =_xlfn.XLOOKUP(F58,'TFS Details'!F:F,'TFS Details'!A:A) -> BPMS Onboarding to CDAT | C58: =_xlfn.XLOOKUP(F58,'TFS Details'!F:F,'TFS Details'!E:E) -> 4459051 | D58: Rajeswari | E58: As a CDAT PMO, I want to Onboard BPMS Opportunities to PMO Tracker Dashboard with Filtering, MMS ID Hyperlink, and Standard PMO Edit Access | F58: 4450388 | G58: Shivaprasad | H58: Jabeen | I58: shivaprasad.malekar | J58: Yes | L58: Excel Validation | O58: 0.2 | P58: 40 | V58: Completed | W58: Completed | X58: In Progress | Y58: Not Started | Z58: 40 | AA58: 40 | AB58: 0 | AC58: 40 | AF58: =_xlfn.XLOOKUP(F58,'TFS Details'!F:F,'TFS Details'!H:H) -> Ready for Test | AG58: 0 | AH58: 0 | AI58: 0 | AJ58: 40 | AK58: 40 | AL58: =IF(AG58+AH58=0,0,SUM(AG58:AH58)/AK58) -> 0 | AM58: =IF(AG58=0,0,AG58/(SUM(AG58:AI58))) -> 0 | AO58: =_xlfn.XLOOKUP(F58,'TFS Details'!F:F,'TFS Details'!I:I) -> TechTribe | AP58: =_xlfn.XLOOKUP(AO58,'TFS Details'!I:I,'TFS Details'!AE:AE) -> pandidurai.ks
A59: =_xlfn.XLOOKUP(F59,'TFS Details'!F:F,'TFS Details'!D:D) -> CDAT | B59: =_xlfn.XLOOKUP(F59,'TFS Details'!F:F,'TFS Details'!A:A) -> BPMS Onboarding to CDAT | C59: =_xlfn.XLOOKUP(F59,'TFS Details'!F:F,'TFS Details'!E:E) -> 4459051 | D59: Rajeswari | E59: As a CDAT SME / CDAT Lead / CDAT Reviewer, I want to land on the Assessment Detail page via Solution to Contract Analysis | F59: 4450390 | G59: Jabeen | H59: Shiva | I59: jabeen.iqbal | J59: Yes | M59: Complex | N59: 15 | O59: 0.15 | P59: 33 | Q59: 15 | R59: 1 | S59: 15 | V59: Completed | W59: Completed | X59: In Progress | Y59: Blocked | Z59: 75 | AA59: 55 | AB59: 0 | AC59: 55 | AF59: =_xlfn.XLOOKUP(F59,'TFS Details'!F:F,'TFS Details'!H:H) -> Ready for Test | AG59: 0 | AH59: 0 | AI59: 0 | AJ59: 53 | AK59: 55 | AL59: =IF(AG59+AH59=0,0,SUM(AG59:AH59)/AK59) -> 0 | AM59: =IF(AG59=0,0,AG59/(SUM(AG59:AI59))) -> 0 | AO59: =_xlfn.XLOOKUP(F59,'TFS Details'!F:F,'TFS Details'!I:I) -> TechTribe | AP59: =_xlfn.XLOOKUP(AO59,'TFS Details'!I:I,'TFS Details'!AE:AE) -> pandidurai.ks
A60: =_xlfn.XLOOKUP(F60,'TFS Details'!F:F,'TFS Details'!D:D) -> CDAT | B60: =_xlfn.XLOOKUP(F60,'TFS Details'!F:F,'TFS Details'!A:A) -> BPMS Onboarding to CDAT | C60: =_xlfn.XLOOKUP(F60,'TFS Details'!F:F,'TFS Details'!E:E) -> 4459051 | D60: Rajeswari | E60: As a CDAT user I want BPMS deals created and managed in myISP to flow seamlessly into the CDAT platform So that all BPMS deals are centrally available for assessment, tracking, review, and governance within CDAT. | F60: 4392723 | G60: Jabeen | H60: Shiva | J60: No | K60: More complex which includes multiple roles and multiple screens validation | L60: Technical US - Full regression Required | V60: Completed | W60: Completed | X60: In Progress | Y60: Blocked | Z60: 40 | AA60: 14 | AB60: 0 | AC60: 14 | AF60: =_xlfn.XLOOKUP(F60,'TFS Details'!F:F,'TFS Details'!H:H) -> Ready for Test | AG60: 0 | AH60: 0 | AI60: 0 | AJ60: 12 | AK60: 14 | AL60: =IF(AG60+AH60=0,0,SUM(AG60:AH60)/AK60) -> 0 | AM60: =IF(AG60=0,0,AG60/(SUM(AG60:AI60))) -> 0 | AO60: =_xlfn.XLOOKUP(F60,'TFS Details'!F:F,'TFS Details'!I:I) -> TechTribe | AP60: =_xlfn.XLOOKUP(AO60,'TFS Details'!I:I,'TFS Details'!AE:AE) -> pandidurai.ks
A61: =_xlfn.XLOOKUP(F61,'TFS Details'!F:F,'TFS Details'!D:D) -> CDAT | B61: =_xlfn.XLOOKUP(F61,'TFS Details'!F:F,'TFS Details'!A:A) -> BPMS Onboarding to CDAT | C61: =_xlfn.XLOOKUP(F61,'TFS Details'!F:F,'TFS Details'!E:E) -> 4459051 | D61: Rajeswari | E61: As a CDAT Solution Architect (SA) I want to navigate CDAT Summary Tile for BPMS on DSP via Solution to Contract Analysis (CDAT SME Driven) | F61: 4432326 | G61: Jabeen | H61: Shiva | J61: No | K61: More complex which includes multiple roles and multiple screens validation | L61: Complex user story which involves multiple screen validation and multiple roles validation and requires more time to automate | V61: Completed | W61: Completed | X61: In Progress | Y61: In Progress | Z61: 70 | AA61: 64 | AB61: 0 | AC61: 64 | AF61: =_xlfn.XLOOKUP(F61,'TFS Details'!F:F,'TFS Details'!H:H) -> PT In Test | AG61: 17 | AH61: 0 | AI61: 0 | AJ61: 45 | AK61: 64 | AL61: =IF(AG61+AH61=0,0,SUM(AG61:AH61)/AK61) -> 0.265625 | AM61: =IF(AG61=0,0,AG61/(SUM(AG61:AI61))) -> 1 | AO61: =_xlfn.XLOOKUP(F61,'TFS Details'!F:F,'TFS Details'!I:I) -> Pixel Pioneers | AP61: =_xlfn.XLOOKUP(AO61,'TFS Details'!I:I,'TFS Details'!AE:AE) -> pandidurai.ks
A62: =_xlfn.XLOOKUP(F62,'TFS Details'!F:F,'TFS Details'!D:D) -> CDAT | B62: =_xlfn.XLOOKUP(F62,'TFS Details'!F:F,'TFS Details'!A:A) -> BPMS Onboarding to CDAT | C62: =_xlfn.XLOOKUP(F62,'TFS Details'!F:F,'TFS Details'!E:E) -> 4459051 | D62: Rajeswari | E62: As a CDAT SME / CDAT CM SME / Lead SA, I want to add comment on number of GAPS on BPMS Assessment Outcome Screen | F62: 4450401 | G62: Agnes | H62: Sowndarya | J62: No | K62: More complex which includes multiple roles and multiple screens validation | L62: Complex user story which involves multiple screen validation and multiple roles validation and requires more time to automate | V62: Completed | W62: Completed | X62: In Progress | Y62: Not Started | Z62: 65 | AA62: 33 | AB62: 0 | AC62: 33 | AF62: =_xlfn.XLOOKUP(F62,'TFS Details'!F:F,'TFS Details'!H:H) -> Ready for Test | AG62: 0 | AH62: 0 | AI62: 0 | AJ62: 32 | AK62: 33 | AL62: =IF(AG62+AH62=0,0,SUM(AG62:AH62)/AK62) -> 0 | AM62: =IF(AG62=0,0,AG62/(SUM(AG62:AI62))) -> 0 | AO62: =_xlfn.XLOOKUP(F62,'TFS Details'!F:F,'TFS Details'!I:I) -> TechTribe | AP62: =_xlfn.XLOOKUP(AO62,'TFS Details'!I:I,'TFS Details'!AE:AE) -> pandidurai.ks
A63: =_xlfn.XLOOKUP(F63,'TFS Details'!F:F,'TFS Details'!D:D) -> CDAT | B63: =_xlfn.XLOOKUP(F63,'TFS Details'!F:F,'TFS Details'!A:A) -> BPMS Onboarding to CDAT | C63: =_xlfn.XLOOKUP(F63,'TFS Details'!F:F,'TFS Details'!E:E) -> 4459051 | D63: Rajeswari | E63: As a CDAT SME / CDAT CM SME, I want to add and manage BPMS Documents | F63: 4450402 | G63: Shivaprasad | H63: Jabeen | I63: shivaprasad.malekar | J63: Yes | M63: Medium | O63: 0.2 | P63: 38 | V63: Completed | W63: Completed | X63: In Progress | Y63: In Progress | Z63: 76 | AA63: 63 | AB63: 0 | AC63: 63 | AF63: =_xlfn.XLOOKUP(F63,'TFS Details'!F:F,'TFS Details'!H:H) -> Ready for Test | AG63: 6 | AH63: 0 | AI63: 0 | AJ63: 57 | AK63: 63 | AL63: =IF(AG63+AH63=0,0,SUM(AG63:AH63)/AK63) -> 0.095238095 | AM63: =IF(AG63=0,0,AG63/(SUM(AG63:AI63))) -> 1 | AO63: =_xlfn.XLOOKUP(F63,'TFS Details'!F:F,'TFS Details'!I:I) -> TechTribe | AP63: =_xlfn.XLOOKUP(AO63,'TFS Details'!I:I,'TFS Details'!AE:AE) -> pandidurai.ks
A64: =_xlfn.XLOOKUP(F64,'TFS Details'!F:F,'TFS Details'!D:D) -> CDAT | B64: =_xlfn.XLOOKUP(F64,'TFS Details'!F:F,'TFS Details'!A:A) -> BPMS Onboarding to CDAT | C64: =_xlfn.XLOOKUP(F64,'TFS Details'!F:F,'TFS Details'!E:E) -> 4459051 | D64: Rajeswari | E64: As a CDAT user, I want to View Assessment Summary from Solution to Contract Analysis | F64: 4450405 | G64: Jabeen | H64: Shiva | J64: No | K64: More complex which includes multiple roles and multiple screens validation | L64: Complex user story which involves multiple screen validation and multiple roles validation and requires more time to automate | V64: Completed | W64: Completed | X64: In Progress | Y64: Blocked | Z64: 60 | AA64: 41 | AB64: 0 | AC64: 41 | AF64: =_xlfn.XLOOKUP(F64,'TFS Details'!F:F,'TFS Details'!H:H) -> Ready for Test | AG64: 0 | AH64: 0 | AI64: 0 | AJ64: 40 | AK64: 41 | AL64: =IF(AG64+AH64=0,0,SUM(AG64:AH64)/AK64) -> 0 | AM64: =IF(AG64=0,0,AG64/(SUM(AG64:AI64))) -> 0 | AO64: =_xlfn.XLOOKUP(F64,'TFS Details'!F:F,'TFS Details'!I:I) -> TechTribe | AP64: =_xlfn.XLOOKUP(AO64,'TFS Details'!I:I,'TFS Details'!AE:AE) -> pandidurai.ks
A65: =_xlfn.XLOOKUP(F65,'TFS Details'!F:F,'TFS Details'!D:D) -> CDAT | B65: =_xlfn.XLOOKUP(F65,'TFS Details'!F:F,'TFS Details'!A:A) -> BPMS Onboarding to CDAT | C65: =_xlfn.XLOOKUP(F65,'TFS Details'!F:F,'TFS Details'!E:E) -> 4459051 | D65: Rajeswari | E65: As a CDAT user, I want to View and Update Tracker Details from Solution to Contract Analysis | F65: 4450410 | G65: Shivaprasad | H65: Jabeen | J65: No | K65: Requires fresh deal everytime to configure | L65: Fresh Deal creation required everytime | V65: Completed | W65: Completed | X65: In Progress | Y65: In Progress | Z65: 70 | AA65: 68 | AB65: 0 | AC65: 68 | AF65: =_xlfn.XLOOKUP(F65,'TFS Details'!F:F,'TFS Details'!H:H) -> Ready for Test | AG65: 21 | AH65: 0 | AI65: 0 | AJ65: 47 | AK65: 68 | AL65: =IF(AG65+AH65=0,0,SUM(AG65:AH65)/AK65) -> 0.30882353 | AM65: =IF(AG65=0,0,AG65/(SUM(AG65:AI65))) -> 1 | AO65: =_xlfn.XLOOKUP(F65,'TFS Details'!F:F,'TFS Details'!I:I) -> TechTribe | AP65: =_xlfn.XLOOKUP(AO65,'TFS Details'!I:I,'TFS Details'!AE:AE) -> pandidurai.ks
A66: =_xlfn.XLOOKUP(F66,'TFS Details'!F:F,'TFS Details'!D:D) -> CDAT | B66: =_xlfn.XLOOKUP(F66,'TFS Details'!F:F,'TFS Details'!A:A) -> BPMS Onboarding to CDAT | C66: =_xlfn.XLOOKUP(F66,'TFS Details'!F:F,'TFS Details'!E:E) -> 4459051 | D66: Rajeswari | E66: As a CDAT Lead I want to Populate BPMS Question Master Repository | F66: 4450395 | G66: Agnes | H66: Sowndarya | I66: sowndarya.sowrirajan | J66: Yes | L66: Complex user story which involves multiple screen validation and multiple roles validation and requires more time to automate | O66: 0.15 | P66: 44 | V66: Completed | W66: Completed | X66: In Progress | Y66: Not Started | Z66: 49 | AA66: 20 | AB66: 0 | AC66: 20 | AF66: =_xlfn.XLOOKUP(F66,'TFS Details'!F:F,'TFS Details'!H:H) -> Ready for Test | AG66: 0 | AH66: 0 | AI66: 0 | AJ66: 20 | AK66: 20 | AL66: =IF(AG66+AH66=0,0,SUM(AG66:AH66)/AK66) -> 0 | AM66: =IF(AG66=0,0,AG66/(SUM(AG66:AI66))) -> 0 | AO66: =_xlfn.XLOOKUP(F66,'TFS Details'!F:F,'TFS Details'!I:I) -> TechTribe | AP66: =_xlfn.XLOOKUP(AO66,'TFS Details'!I:I,'TFS Details'!AE:AE) -> pandidurai.ks
A67: =_xlfn.XLOOKUP(F67,'TFS Details'!F:F,'TFS Details'!D:D) -> CDAT | B67: =_xlfn.XLOOKUP(F67,'TFS Details'!F:F,'TFS Details'!A:A) -> Automailer, Follow-Ups & Escalation Steps | C67: =_xlfn.XLOOKUP(F67,'TFS Details'!F:F,'TFS Details'!E:E) -> 4349307 | D67: Rajeswari | E67: As a myISP user, I want a follow‑on revenue clarification reminder 1 so that CDAT review applicability can be determined accurately. | F67: 4432443 | G67: Pavithra | H67: Sowndarya/Revisit | J67: No | K67: Mailer - Fresh deal required | L67: Fresh Deal creation required everytime | V67: Completed | W67: Completed | X67: In Progress | Y67: Not Started | Z67: 38 | AA67: 25 | AB67: 0 | AC67: 25 | AF67: =_xlfn.XLOOKUP(F67,'TFS Details'!F:F,'TFS Details'!H:H) -> In Development | AG67: 0 | AH67: 0 | AI67: 0 | AJ67: 53 | AK67: 25 | AL67: =IF(AG67+AH67=0,0,SUM(AG67:AH67)/AK67) -> 0 | AM67: =IF(AG67=0,0,AG67/(SUM(AG67:AI67))) -> 0 | AO67: =_xlfn.XLOOKUP(F67,'TFS Details'!F:F,'TFS Details'!I:I) -> TechPhantoms | AP67: =_xlfn.XLOOKUP(AO67,'TFS Details'!I:I,'TFS Details'!AE:AE) -> sowjanya.kari
A68: =_xlfn.XLOOKUP(F68,'TFS Details'!F:F,'TFS Details'!D:D) -> CDAT | B68: =_xlfn.XLOOKUP(F68,'TFS Details'!F:F,'TFS Details'!A:A) -> Automailer, Follow-Ups & Escalation Steps | C68: =_xlfn.XLOOKUP(F68,'TFS Details'!F:F,'TFS Details'!E:E) -> 4349307 | D68: Rajeswari | E68: As a myISP user, I want to send CDAT Mailer – Future Dated but Won Deal Confirmation [Follow up reason] | F68: 4436336 | G68: Pavithra | H68: Sowndarya/Revisit | J68: No | K68: Mailer - Fresh deal required | L68: Fresh Deal creation required everytime | V68: Completed | W68: Completed | X68: In Progress | Y68: Not Started | Z68: 34 | AA68: 23 | AB68: 0 | AC68: 23 | AF68: =_xlfn.XLOOKUP(F68,'TFS Details'!F:F,'TFS Details'!H:H) -> In Development | AG68: 0 | AH68: 0 | AI68: 0 | AJ68: 47 | AK68: 23 | AL68: =IF(AG68+AH68=0,0,SUM(AG68:AH68)/AK68) -> 0 | AM68: =IF(AG68=0,0,AG68/(SUM(AG68:AI68))) -> 0 | AO68: =_xlfn.XLOOKUP(F68,'TFS Details'!F:F,'TFS Details'!I:I) -> TechPhantoms | AP68: =_xlfn.XLOOKUP(AO68,'TFS Details'!I:I,'TFS Details'!AE:AE) -> sowjanya.kari
A69: =_xlfn.XLOOKUP(F69,'TFS Details'!F:F,'TFS Details'!D:D) -> CDAT | B69: =_xlfn.XLOOKUP(F69,'TFS Details'!F:F,'TFS Details'!A:A) -> Automailer, Follow-Ups & Escalation Steps | C69: =_xlfn.XLOOKUP(F69,'TFS Details'!F:F,'TFS Details'!E:E) -> 4349307 | D69: Rajeswari | E69: As a myISP user, I want a follow‑on revenue clarification reminder 2 so that CDAT review applicability can be determined accurately. | F69: 4437632 | G69: Pavithra | H69: Sowndarya | J69: No | K69: Mailer - Fresh deal required | L69: Fresh Deal creation required everytime | V69: Completed | W69: Completed | X69: In Progress | Y69: Not Started | Z69: 42 | AA69: 41 | AB69: 0 | AC69: 41 | AF69: =_xlfn.XLOOKUP(F69,'TFS Details'!F:F,'TFS Details'!H:H) -> In Development | AG69: 0 | AH69: 0 | AI69: 0 | AJ69: 41 | AK69: 41 | AL69: =IF(AG69+AH69=0,0,SUM(AG69:AH69)/AK69) -> 0 | AM69: =IF(AG69=0,0,AG69/(SUM(AG69:AI69))) -> 0 | AO69: =_xlfn.XLOOKUP(F69,'TFS Details'!F:F,'TFS Details'!I:I) -> TechPhantoms | AP69: =_xlfn.XLOOKUP(AO69,'TFS Details'!I:I,'TFS Details'!AE:AE) -> sowjanya.kari
A70: =_xlfn.XLOOKUP(F70,'TFS Details'!F:F,'TFS Details'!D:D) -> CDAT | B70: =_xlfn.XLOOKUP(F70,'TFS Details'!F:F,'TFS Details'!A:A) -> Automailer, Follow-Ups & Escalation Steps | C70: =_xlfn.XLOOKUP(F70,'TFS Details'!F:F,'TFS Details'!E:E) -> 4349307 | D70: Rajeswari | E70: As a myISP user, I want the system to send a First reminder deal email for CDAT‑eligible opportunities with an upcoming proposal submission date so that key stakeholders engage at the right time for CDAT readiness and review | F70: 4443793 | G70: Pavithra | H70: Sowndarya | J70: No | K70: Mailer - Fresh deal required | L70: Fresh Deal creation required everytime | V70: Completed | W70: Completed | X70: In Progress | Y70: Not Started | Z70: 57 | AA70: 57 | AB70: 0 | AC70: 57 | AF70: =_xlfn.XLOOKUP(F70,'TFS Details'!F:F,'TFS Details'!H:H) -> In Development | AG70: 0 | AH70: 0 | AI70: 0 | AJ70: 57 | AK70: 57 | AL70: =IF(AG70+AH70=0,0,SUM(AG70:AH70)/AK70) -> 0 | AM70: =IF(AG70=0,0,AG70/(SUM(AG70:AI70))) -> 0 | AO70: =_xlfn.XLOOKUP(F70,'TFS Details'!F:F,'TFS Details'!I:I) -> TechPhantoms | AP70: =_xlfn.XLOOKUP(AO70,'TFS Details'!I:I,'TFS Details'!AE:AE) -> sowjanya.kari
A71: =_xlfn.XLOOKUP(F71,'TFS Details'!F:F,'TFS Details'!D:D) -> CDAT | B71: =_xlfn.XLOOKUP(F71,'TFS Details'!F:F,'TFS Details'!A:A) -> Automailer, Follow-Ups & Escalation Steps | C71: =_xlfn.XLOOKUP(F71,'TFS Details'!F:F,'TFS Details'!E:E) -> 4349307 | D71: Rajeswari | E71: As a myISP user, I want the system to send a Second reminder email for CDAT‑eligible opportunities with an upcoming proposal submission deal date so that key stakeholders engage at the right time for CDAT readiness and review | F71: 4443800 | G71: Sowndarya | H71: Pavithra | J71: No | K71: Mailer - Fresh deal required | L71: Fresh Deal creation required everytime | V71: Completed | W71: Completed | X71: In Progress | Y71: Not Started | Z71: 50 | AA71: 31 | AB71: 0 | AC71: 31 | AF71: =_xlfn.XLOOKUP(F71,'TFS Details'!F:F,'TFS Details'!H:H) -> In Development | AG71: 0 | AH71: 0 | AI71: 0 | AJ71: 25 | AK71: 31 | AL71: =IF(AG71+AH71=0,0,SUM(AG71:AH71)/AK71) -> 0 | AM71: =IF(AG71=0,0,AG71/(SUM(AG71:AI71))) -> 0 | AO71: =_xlfn.XLOOKUP(F71,'TFS Details'!F:F,'TFS Details'!I:I) -> TechPhantoms | AP71: =_xlfn.XLOOKUP(AO71,'TFS Details'!I:I,'TFS Details'!AE:AE) -> sowjanya.kari
A72: =_xlfn.XLOOKUP(F72,'TFS Details'!F:F,'TFS Details'!D:D) -> CDAT | B72: =_xlfn.XLOOKUP(F72,'TFS Details'!F:F,'TFS Details'!A:A) -> Automailer, Follow-Ups & Escalation Steps | C72: =_xlfn.XLOOKUP(F72,'TFS Details'!F:F,'TFS Details'!E:E) -> 4349307 | D72: Rajeswari | E72: As a CDAT PMO I want reminder emails to be triggered using the correct template based on the Follow‑Up Reason and Reminder Status selected in the PMO Dashboard So that stakeholders receive accurate, context‑specific follow‑ups. | F72: 4444184 | G72: Sowndarya | H72: Pavithra | J72: No | K72: Mailer - Fresh deal required | L72: Fresh Deal creation required everytime | V72: Completed | W72: Completed | X72: In Progress | Y72: Not Started | Z72: 39 | AA72: 32 | AB72: 0 | AC72: 32 | AF72: =_xlfn.XLOOKUP(F72,'TFS Details'!F:F,'TFS Details'!H:H) -> In Development | AG72: 0 | AH72: 0 | AI72: 0 | AJ72: 32 | AK72: 32 | AL72: =IF(AG72+AH72=0,0,SUM(AG72:AH72)/AK72) -> 0 | AM72: =IF(AG72=0,0,AG72/(SUM(AG72:AI72))) -> 0 | AO72: =_xlfn.XLOOKUP(F72,'TFS Details'!F:F,'TFS Details'!I:I) -> TechPhantoms | AP72: =_xlfn.XLOOKUP(AO72,'TFS Details'!I:I,'TFS Details'!AE:AE) -> sowjanya.kari
A73: =_xlfn.XLOOKUP(F73,'TFS Details'!F:F,'TFS Details'!D:D) -> CDAT Auto-mailers | B73: =_xlfn.XLOOKUP(F73,'TFS Details'!F:F,'TFS Details'!A:A) -> Automailer, Follow-Ups & Escalation Steps | C73: =_xlfn.XLOOKUP(F73,'TFS Details'!F:F,'TFS Details'!E:E) -> 4349307 | D73: Rajeswari | E73: As a CDAT system I want to trigger reminders emails based on proposal submission date that stakeholders receive timely follow‑ups. [Scenarios] | F73: 4392686 | G73: Sowndarya | H73: Pavithra | J73: No | K73: Mailer - Fresh deal required | L73: Fresh Deal creation required everytime | V73: Completed | W73: Completed | X73: In Progress | Y73: Not Started | Z73: 44 | AA73: 42 | AB73: 0 | AC73: 42 | AF73: =_xlfn.XLOOKUP(F73,'TFS Details'!F:F,'TFS Details'!H:H) -> In Development | AG73: 0 | AH73: 0 | AI73: 0 | AJ73: 33 | AK73: 42 | AL73: =IF(AG73+AH73=0,0,SUM(AG73:AH73)/AK73) -> 0 | AM73: =IF(AG73=0,0,AG73/(SUM(AG73:AI73))) -> 0 | AO73: =_xlfn.XLOOKUP(F73,'TFS Details'!F:F,'TFS Details'!I:I) -> TechPhantoms | AP73: =_xlfn.XLOOKUP(AO73,'TFS Details'!I:I,'TFS Details'!AE:AE) -> sowjanya.kari
A74: =_xlfn.XLOOKUP(F74,'TFS Details'!F:F,'TFS Details'!D:D) -> CDAT Auto-mailers | B74: =_xlfn.XLOOKUP(F74,'TFS Details'!F:F,'TFS Details'!A:A) -> Automailer, Follow-Ups & Escalation Steps | C74: =_xlfn.XLOOKUP(F74,'TFS Details'!F:F,'TFS Details'!E:E) -> 4349307 | D74: Rajeswari | E74: As a CDAT system I want to validate strict preconditions and eligibility rules before sending reminder emails So that reminders are sent only for valid, in‑scope, and pending deals. | F74: 4392687 | G74: Sowndarya | H74: Pavithra | J74: No | K74: Mailer - Fresh deal required | L74: Fresh Deal creation required everytime | V74: Completed | W74: Completed | X74: In Progress | Y74: Not Started | Z74: 34 | AA74: 23 | AB74: 0 | AC74: 23 | AF74: =_xlfn.XLOOKUP(F74,'TFS Details'!F:F,'TFS Details'!H:H) -> In Development | AG74: 0 | AH74: 0 | AI74: 0 | AJ74: 24 | AK74: 23 | AL74: =IF(AG74+AH74=0,0,SUM(AG74:AH74)/AK74) -> 0 | AM74: =IF(AG74=0,0,AG74/(SUM(AG74:AI74))) -> 0 | AO74: =_xlfn.XLOOKUP(F74,'TFS Details'!F:F,'TFS Details'!I:I) -> TechPhantoms | AP74: =_xlfn.XLOOKUP(AO74,'TFS Details'!I:I,'TFS Details'!AE:AE) -> sowjanya.kari
A75: =_xlfn.XLOOKUP(F75,'TFS Details'!F:F,'TFS Details'!D:D) -> CDAT | B75: =_xlfn.XLOOKUP(F75,'TFS Details'!F:F,'TFS Details'!A:A) -> CDAT Enhancements | C75: =_xlfn.XLOOKUP(F75,'TFS Details'!F:F,'TFS Details'!E:E) -> 4392317 | D75: Rajeswari | E75: As a user working on a BPMS opportunity (SA / CDAT SME / CDAT Lead / CDAT PMO / Reviewer / CM SME) I want the 9th tile CDAT SME Driven to be enabled for BPMS deals So that BPMS opportunities are consistently assessed through the standard CDAT process | F75: 4349320 | G75: Agnes | H75: Shiva | J75: No | K75: More complex which includes multiple roles and multiple screens validation | L75: Technical US - Full regression Required | V75: Completed | W75: Completed | X75: In Progress | Y75: Not Started | Z75: 38 | AA75: 35 | AB75: 0 | AC75: 35 | AF75: =_xlfn.XLOOKUP(F75,'TFS Details'!F:F,'TFS Details'!H:H) -> Active | AG75: 0 | AH75: 0 | AI75: 0 | AJ75: 21 | AK75: 35 | AL75: =IF(AG75+AH75=0,0,SUM(AG75:AH75)/AK75) -> 0 | AM75: =IF(AG75=0,0,AG75/(SUM(AG75:AI75))) -> 0 | AO75: =_xlfn.XLOOKUP(F75,'TFS Details'!F:F,'TFS Details'!I:I) -> TechWarriors | AP75: =_xlfn.XLOOKUP(AO75,'TFS Details'!I:I,'TFS Details'!AE:AE) -> Supriya.a.dhingra
A76: =_xlfn.XLOOKUP(F76,'TFS Details'!F:F,'TFS Details'!D:D) -> CDAT | B76: =_xlfn.XLOOKUP(F76,'TFS Details'!F:F,'TFS Details'!A:A) -> BPMS Onboarding to CDAT | C76: =_xlfn.XLOOKUP(F76,'TFS Details'!F:F,'TFS Details'!E:E) -> 4459051 | D76: Rajeswari | E76: As a CDAT SME / Lead SA, I want to create BPMS Version Creation, First Cut Workflow & List of Areas Navigation | F76: 4450391 | G76: Jabeen | H76: Shiva | J76: No | K76: Requires fresh deal everytime to configure | L76: Fresh Deal creation required everytime | V76: Completed | W76: Completed | X76: In Progress | Y76: Blocked | Z76: 68 | AA76: 51 | AB76: 0 | AC76: 51 | AF76: =_xlfn.XLOOKUP(F76,'TFS Details'!F:F,'TFS Details'!H:H) -> Ready for Test | AG76: 0 | AH76: 0 | AI76: 0 | AJ76: 51 | AK76: 51 | AL76: =IF(AG76+AH76=0,0,SUM(AG76:AH76)/AK76) -> 0 | AM76: =IF(AG76=0,0,AG76/(SUM(AG76:AI76))) -> 0 | AO76: =_xlfn.XLOOKUP(F76,'TFS Details'!F:F,'TFS Details'!I:I) -> TechTribe | AP76: =_xlfn.XLOOKUP(AO76,'TFS Details'!I:I,'TFS Details'!AE:AE) -> pandidurai.ks
A77: =_xlfn.XLOOKUP(F77,'TFS Details'!F:F,'TFS Details'!D:D) -> CDAT | B77: =_xlfn.XLOOKUP(F77,'TFS Details'!F:F,'TFS Details'!A:A) -> BPMS Onboarding to CDAT | C77: =_xlfn.XLOOKUP(F77,'TFS Details'!F:F,'TFS Details'!E:E) -> 4459051 | D77: Rajeswari | E77: As a CDAT PMO user, I want the ability to upload an exported excel Upload for Edited PMO Export | F77: 4448602 | G77: Pavithra | H77: Sowndarya | I77: p.mohandass | J77: Yes | L77: Excel Validation | O77: 0.15 | P77: 56 | Q77: 8 | R77: 0 | V77: Completed | W77: Completed | X77: In Progress | Y77: Not Started | Z77: 66 | AA77: 52 | AB77: 0 | AC77: 52 | AF77: =_xlfn.XLOOKUP(F77,'TFS Details'!F:F,'TFS Details'!H:H) -> Active | AG77: 0 | AH77: 0 | AI77: 0 | AJ77: 52 | AK77: 52 | AL77: =IF(AG77+AH77=0,0,SUM(AG77:AH77)/AK77) -> 0 | AM77: =IF(AG77=0,0,AG77/(SUM(AG77:AI77))) -> 0 | AO77: =_xlfn.XLOOKUP(F77,'TFS Details'!F:F,'TFS Details'!I:I) -> TechTribe | AP77: =_xlfn.XLOOKUP(AO77,'TFS Details'!I:I,'TFS Details'!AE:AE) -> pandidurai.ks
A78: =_xlfn.XLOOKUP(F78,'TFS Details'!F:F,'TFS Details'!D:D) -> CDAT | B78: =_xlfn.XLOOKUP(F78,'TFS Details'!F:F,'TFS Details'!A:A) -> BPMS Onboarding to CDAT | C78: =_xlfn.XLOOKUP(F78,'TFS Details'!F:F,'TFS Details'!E:E) -> 4459051 | D78: Rajeswari | E78: As a CDAT PMO I want to Configure BPMS Role Catalog for Define Team so that I can go ahead with CDAT flow for BPMS deals | F78: 4450399 | G78: Agnes | H78: Pavithra | J78: No | K78: Mailer - Fresh deal required | L78: Fresh Deal creation required everytime | V78: Completed | W78: Completed | X78: In Progress | Y78: Not Started | Z78: 55 | AA78: 26 | AB78: 0 | AC78: 26 | AF78: =_xlfn.XLOOKUP(F78,'TFS Details'!F:F,'TFS Details'!H:H) -> In Development | AG78: 0 | AH78: 0 | AI78: 0 | AJ78: 19 | AK78: 26 | AL78: =IF(AG78+AH78=0,0,SUM(AG78:AH78)/AK78) -> 0 | AM78: =IF(AG78=0,0,AG78/(SUM(AG78:AI78))) -> 0 | AO78: =_xlfn.XLOOKUP(F78,'TFS Details'!F:F,'TFS Details'!I:I) -> TechPhantoms | AP78: =_xlfn.XLOOKUP(AO78,'TFS Details'!I:I,'TFS Details'!AE:AE) -> sowjanya.kari
A79: =_xlfn.XLOOKUP(F79,'TFS Details'!F:F,'TFS Details'!D:D) -> Differentiation | B79: =_xlfn.XLOOKUP(F79,'TFS Details'!F:F,'TFS Details'!A:A) -> Differentiation Decommission | C79: =_xlfn.XLOOKUP(F79,'TFS Details'!F:F,'TFS Details'!E:E) -> 4372017 | D79: Anand | E79: As a Solution Architect I want the SDL to be updated to use Attach Calculator data in place of Differentiation So that SDL functionality remains accurate after the Differentiation screen is decommissioned | F79: 4362088 | G79: Sairam | H79: Naveen S | I79: sairam.pamarthi | J79: Yes | M79: Complex | N79: 1 | O79: 0.2 | P79: 4 | Q79: 2 | S79: 1 | T79: 0.5 | U79: 0.4 | V79: Completed | W79: Completed | X79: In Progress | Y79: In Progress | Z79: 12 | AA79: 3 | AB79: 5 | AC79: 8 | AD79: 0.4 | AE79: 0.3 | AF79: =_xlfn.XLOOKUP(F79,'TFS Details'!F:F,'TFS Details'!H:H) -> PT In Test | AG79: 6 | AH79: 0 | AI79: 0 | AJ79: 3 | AK79: =SUM(AG79:AJ79) -> 9 | AL79: =IF(AG79+AH79=0,0,SUM(AG79:AH79)/AK79) -> 0.66666667 | AM79: =IF(AG79=0,0,AG79/(SUM(AG79:AI79))) -> 1 | AO79: =_xlfn.XLOOKUP(F79,'TFS Details'!F:F,'TFS Details'!I:I) -> DevStormers | AP79: =_xlfn.XLOOKUP(AO79,'TFS Details'!I:I,'TFS Details'!AE:AE) -> mervinkumar.manickam
A80: =_xlfn.XLOOKUP(F80,'TFS Details'!F:F,'TFS Details'!D:D) -> PCW | B80: =_xlfn.XLOOKUP(F80,'TFS Details'!F:F,'TFS Details'!A:A) -> Standard Role Implementation in PCW & Online SI - May Release | C80: =_xlfn.XLOOKUP(F80,'TFS Details'!F:F,'TFS Details'!E:E) -> 4436131 | D80: Anand | E80: Handle 'Overwrite Role Type' column during carting and copying to create myISP PCW versions | F80: 4423815 | G80: Naveen S | H80: Sneha | J80: No | K80: PCW User Story | L80: PCW User Story | V80: Completed | W80: In Progress | X80: Not Started | Y80: In Progress | Z80: 30 | AA80: 16 | AB80: 4 | AC80: 20 | AD80: 0.98 | AE80: 1 | AF80: =_xlfn.XLOOKUP(F80,'TFS Details'!F:F,'TFS Details'!H:H) -> Ready for Test | AG80: 12 | AH80: 0 | AI80: 0 | AJ80: 8 | AK80: =SUM(AG80:AJ80) -> 20 | AL80: =IF(AG80+AH80=0,0,SUM(AG80:AH80)/AK80) -> 0.6 | AM80: =IF(AG80=0,0,AG80/(SUM(AG80:AI80))) -> 1 | AN80: Delivered to Parallel UAT | AO80: =_xlfn.XLOOKUP(F80,'TFS Details'!F:F,'TFS Details'!I:I) -> DevStormers | AP80: =_xlfn.XLOOKUP(AO80,'TFS Details'!I:I,'TFS Details'!AE:AE) -> mervinkumar.manickam
A81: =_xlfn.XLOOKUP(F81,'TFS Details'!F:F,'TFS Details'!D:D) -> OCP | B81: =_xlfn.XLOOKUP(F81,'TFS Details'!F:F,'TFS Details'!A:A) -> Online SI CR - March | C81: =_xlfn.XLOOKUP(F81,'TFS Details'!F:F,'TFS Details'!E:E) -> 4283187 | D81: Anand | E81: As a SA i want to automatically update Staffing Baseline when Rate Per Hour is changed in Rate Card | F81: 4431151 | G81: Sneha | H81: Viji | I81: sai.sneha.l.malapati | J81: Partial | K81: Excel related needs to generate all pricing routes, SDL,OCP,DCTA and MMP FFP. Hence it is not feasibile to automate | L81: Excel Validation | O81: 0.2 | V81: Completed | W81: In Progress | X81: Not Started | Y81: Blocked | Z81: 8 | AA81: 5 | AB81: 15 | AC81: 5 | AD81: 0.2 | AE81: 0.3 | AF81: =_xlfn.XLOOKUP(F81,'TFS Details'!F:F,'TFS Details'!H:H) -> PT In Test | AG81: 5 | AH81: 0 | AI81: 12 | AJ81: 0 | AK81: =SUM(AG81:AJ81) -> 17 | AL81: =IF(AG81+AH81=0,0,SUM(AG81:AH81)/AK81) -> 0.29411765 | AM81: =IF(AG81=0,0,AG81/(SUM(AG81:AI81))) -> 0.29411765 | AN81: BUg : 4490583 (C) | AO81: =_xlfn.XLOOKUP(F81,'TFS Details'!F:F,'TFS Details'!I:I) -> TechWizards | AP81: =_xlfn.XLOOKUP(AO81,'TFS Details'!I:I,'TFS Details'!AE:AE) -> mervinkumar.manickam
A82: =_xlfn.XLOOKUP(F82,'TFS Details'!F:F,'TFS Details'!D:D) -> PCW | B82: =_xlfn.XLOOKUP(F82,'TFS Details'!F:F,'TFS Details'!A:A) -> DNP Simplification - May Release | C82: =_xlfn.XLOOKUP(F82,'TFS Details'!F:F,'TFS Details'!E:E) -> 4436144 | D82: Anand | E82: PCW - Auto-populate Local Currency in DNP sheets when Local Currency is blank | F82: 4435907 | G82: Sairam | H82: Kiruthiga | J82: No | K82: PCW User Story | L82: PCW User Story | V82: Completed | W82: Completed | X82: In Progress | Y82: Not Started | Z82: 14 | AA82: 5 | AB82: 3 | AC82: 8 | AD82: 0.6 | AE82: 0.25 | AF82: =_xlfn.XLOOKUP(F82,'TFS Details'!F:F,'TFS Details'!H:H) -> Active | AG82: 0 | AH82: 0 | AI82: 0 | AJ82: 8 | AK82: =SUM(AG82:AJ82) -> 8 | AL82: =IF(AG82+AH82=0,0,SUM(AG82:AH82)/AK82) -> 0 | AM82: =IF(AG82=0,0,AG82/(SUM(AG82:AI82))) -> 0 | AO82: =_xlfn.XLOOKUP(F82,'TFS Details'!F:F,'TFS Details'!I:I) -> Tech Ensemble | AP82: =_xlfn.XLOOKUP(AO82,'TFS Details'!I:I,'TFS Details'!AE:AE) -> mervinkumar.manickam
A83: =_xlfn.XLOOKUP(F83,'TFS Details'!F:F,'TFS Details'!D:D) -> PCW | B83: =_xlfn.XLOOKUP(F83,'TFS Details'!F:F,'TFS Details'!A:A) -> MMP FFP Export update - May release | C83: =_xlfn.XLOOKUP(F83,'TFS Details'!F:F,'TFS Details'!E:E) -> 4436136 | D83: Anand | E83: PCW - MMP FFP Export: Send only filtered staffing rows to API for Role Type, Accenture Role/Rate and Pricing Workstream identification | F83: 4436093 | G83: Viji | H83: kiruthiga | J83: No | K83: PCW User Story | L83: PCW User Story | V83: Completed | W83: In Progress | X83: Not Started | Y83: Not Started | Z83: 15 | AA83: 15 | AB83: 8 | AC83: 11 | AD83: 1 | AE83: 0.85 | AF83: =_xlfn.XLOOKUP(F83,'TFS Details'!F:F,'TFS Details'!H:H) -> New | AG83: 0 | AH83: 0 | AI83: 0 | AJ83: 11 | AK83: =SUM(AG83:AJ83) -> 11 | AL83: =IF(AG83+AH83=0,0,SUM(AG83:AH83)/AK83) -> 0 | AM83: =IF(AG83=0,0,AG83/(SUM(AG83:AI83))) -> 0 | AO83: =_xlfn.XLOOKUP(F83,'TFS Details'!F:F,'TFS Details'!I:I) -> Tech Ensemble | AP83: =_xlfn.XLOOKUP(AO83,'TFS Details'!I:I,'TFS Details'!AE:AE) -> mervinkumar.manickam
A84: =_xlfn.XLOOKUP(F84,'TFS Details'!F:F,'TFS Details'!D:D) -> myISP | B84: =_xlfn.XLOOKUP(F84,'TFS Details'!F:F,'TFS Details'!A:A) -> SI - Estimators/Calculators(Opp level screen) & Attach Estimates(Version level screen) - feedback alignment | C84: =_xlfn.XLOOKUP(F84,'TFS Details'!F:F,'TFS Details'!E:E) -> 4445141 | D84: Anand | E84: As a Solution Architect, I want the Attach Estimate screen's Create and Edit Estimator popups to have improved usability, So that I can efficiently view, enter, and review workstream hours without confusion or excessive scrolling. | F84: 3967653 | G84: Kiruthiga | H84: Viji | I84: k.tamilzharasu | J84: Partial | K84: Perfomance upgrade Cannot be automated | L84: Review required | M84: Medium | N84: 1 | O84: 0.8 | P84: 4 | Q84: 2 | R84: 0 | S84: 1 | T84: 0.7 | U84: 0.65 | V84: Completed | W84: Completed | X84: Not Started | Y84: In Progress | Z84: 40 | AA84: 12 | AB84: 0 | AC84: 12 | AD84: 1 | AE84: 0.9 | AF84: =_xlfn.XLOOKUP(F84,'TFS Details'!F:F,'TFS Details'!H:H) -> PT In Test | AG84: 12 | AH84: 0 | AI84: 0 | AJ84: 0 | AK84: =SUM(AG84:AJ84) -> 12 | AL84: =IF(AG84+AH84=0,0,SUM(AG84:AH84)/AK84) -> 1 | AM84: =IF(AG84=0,0,AG84/(SUM(AG84:AI84))) -> 1 | AO84: =_xlfn.XLOOKUP(F84,'TFS Details'!F:F,'TFS Details'!I:I) -> TechAvengers | AP84: =_xlfn.XLOOKUP(AO84,'TFS Details'!I:I,'TFS Details'!AE:AE) -> mervinkumar.manickam
A85: =_xlfn.XLOOKUP(F85,'TFS Details'!F:F,'TFS Details'!D:D) -> PCW | B85: =_xlfn.XLOOKUP(F85,'TFS Details'!F:F,'TFS Details'!A:A) -> PCW Enhancements and User Feedback - March Release | C85: =_xlfn.XLOOKUP(F85,'TFS Details'!F:F,'TFS Details'!E:E) -> 4389866 | D85: Anand | E85: Carting - IPC Toolkit cost in PCW versions | F85: 4361280 | G85: Sneha | H85: Sairam | J85: No | K85: PCW User Story | L85: PCW User Story | V85: Completed | W85: In Progress | X85: Not Started | Y85: In Progress | Z85: 8 | AA85: 4 | AB85: 5 | AC85: 6 | AD85: 0.3 | AE85: 0.3 | AF85: =_xlfn.XLOOKUP(F85,'TFS Details'!F:F,'TFS Details'!H:H) -> Blocked in PT | AG85: 1 | AH85: 0 | AI85: 0 | AJ85: 5 | AK85: =SUM(AG85:AJ85) -> 6 | AL85: =IF(AG85+AH85=0,0,SUM(AG85:AH85)/AK85) -> 0.16666667 | AM85: =IF(AG85=0,0,AG85/(SUM(AG85:AI85))) -> 1 | AO85: =_xlfn.XLOOKUP(F85,'TFS Details'!F:F,'TFS Details'!I:I) -> DevStormers | AP85: =_xlfn.XLOOKUP(AO85,'TFS Details'!I:I,'TFS Details'!AE:AE) -> mervinkumar.manickam
A86: =_xlfn.XLOOKUP(F86,'TFS Details'!F:F,'TFS Details'!D:D) -> PCW | B86: =_xlfn.XLOOKUP(F86,'TFS Details'!F:F,'TFS Details'!A:A) -> IPC Calculator | Cost Update to Standard Package | C86: =_xlfn.XLOOKUP(F86,'TFS Details'!F:F,'TFS Details'!E:E) -> 4341363 | D86: Anand | E86: Add new IPC Cost Types for PCW versions and update existing IPC Cost Type | F86: 4368217 | G86: Viji | H86: Sneha | J86: No | K86: PCW User Story | L86: PCW User Story | V86: Completed | W86: In Progress | X86: Not Started | Y86: In Progress | Z86: 15 | AA86: 10 | AB86: 5 | AC86: 10 | AD86: 1 | AE86: 0.85 | AF86: =_xlfn.XLOOKUP(F86,'TFS Details'!F:F,'TFS Details'!H:H) -> Ready for Test | AG86: 5 | AH86: 1 | AI86: 0 | AJ86: 4 | AK86: =SUM(AG86:AJ86) -> 10 | AL86: =IF(AG86+AH86=0,0,SUM(AG86:AH86)/AK86) -> 0.6 | AM86: =IF(AG86=0,0,AG86/(SUM(AG86:AI86))) -> 0.83333333 | AN86: Bug id : 4482797(M) | AO86: =_xlfn.XLOOKUP(F86,'TFS Details'!F:F,'TFS Details'!I:I) -> DevStormers | AP86: =_xlfn.XLOOKUP(AO86,'TFS Details'!I:I,'TFS Details'!AE:AE) -> mervinkumar.manickam
A87: =_xlfn.XLOOKUP(F87,'TFS Details'!F:F,'TFS Details'!D:D) -> myISP_ DNP | B87: =_xlfn.XLOOKUP(F87,'TFS Details'!F:F,'TFS Details'!A:A) -> DNP - seat charges WFO design change (YOY WFO % level) - Online SI and PCW | C87: =_xlfn.XLOOKUP(F87,'TFS Details'!F:F,'TFS Details'!E:E) -> 4262937 | D87: Anand | E87: As a Solution Architect, I want to add Adjustment % at the Contract Year level in the DNP screen so that, I can calculate Seat Charges (Work from Office) based on the yearly adjustment %- OU changes. | F87: 4317632 | G87: Viji | H87: kiruthiga | I87: v.b.sivakumar | J87: Partial | K87: Offline Utility OU related(Excel) Functionality Cannot be Automated | L87: Excel Validation | M87: Complex | O87: 0.45 | P87: 10 | Q87: 2 | R87: 1 | S87: 1 | T87: 1 | U87: 1 | V87: Completed | W87: In Progress | X87: Not Started | Y87: Not Started | Z87: 10 | AA87: 10 | AB87: 12 | AC87: 10 | AD87: 1 | AE87: 0.9 | AF87: =_xlfn.XLOOKUP(F87,'TFS Details'!F:F,'TFS Details'!H:H) -> In Development | AG87: 0 | AH87: 0 | AI87: 0 | AJ87: 10 | AK87: =SUM(AG87:AJ87) -> 10 | AL87: =IF(AG87+AH87=0,0,SUM(AG87:AH87)/AK87) -> 0 | AM87: =IF(AG87=0,0,AG87/(SUM(AG87:AI87))) -> 0 | AO87: =_xlfn.XLOOKUP(F87,'TFS Details'!F:F,'TFS Details'!I:I) -> DevStormers | AP87: =_xlfn.XLOOKUP(AO87,'TFS Details'!I:I,'TFS Details'!AE:AE) -> mervinkumar.manickam
A88: =_xlfn.XLOOKUP(F88,'TFS Details'!F:F,'TFS Details'!D:D) -> myISP UI | B88: =_xlfn.XLOOKUP(F88,'TFS Details'!F:F,'TFS Details'!A:A) -> PCW CRs - Jan Release | C88: =_xlfn.XLOOKUP(F88,'TFS Details'!F:F,'TFS Details'!E:E) -> 4268320 | D88: Anand | E88: Export the Fixed cost types to Online SDL even if no matching profile is available in Staffing for PCW versions | F88: 4187514 | G88: Naveen S | J88: No | K88: PCW User Story | L88: PCW User Story | V88: Completed | W88: In Progress | X88: Not Started | Y88: In Progress | Z88: 33 | AA88: 15 | AB88: 0 | AC88: 15 | AD88: 1 | AE88: 1 | AF88: =_xlfn.XLOOKUP(F88,'TFS Details'!F:F,'TFS Details'!H:H) -> Ready to Deploy | AG88: 2 | AH88: 0 | AI88: 0 | AJ88: 13 | AK88: =SUM(AG88:AJ88) -> 15 | AL88: =IF(AG88+AH88=0,0,SUM(AG88:AH88)/AK88) -> 0.13333333 | AM88: =IF(AG88=0,0,AG88/(SUM(AG88:AI88))) -> 1 | AO88: =_xlfn.XLOOKUP(F88,'TFS Details'!F:F,'TFS Details'!I:I) -> DevStormers | AP88: =_xlfn.XLOOKUP(AO88,'TFS Details'!I:I,'TFS Details'!AE:AE) -> mervinkumar.manickam
A89: =_xlfn.XLOOKUP(F89,'TFS Details'!F:F,'TFS Details'!D:D) -> myISP_DNP | B89: =_xlfn.XLOOKUP(F89,'TFS Details'!F:F,'TFS Details'!A:A) -> DNP - seat charges WFO design change (YOY WFO % level) - Online SI and PCW | C89: =_xlfn.XLOOKUP(F89,'TFS Details'!F:F,'TFS Details'!E:E) -> 4262937 | D89: Anand | E89: As a Solution Architect, I want to calculate Seat Charges (Work from Office) based on the yearly adjustment % so that all calculation scenarios are accurately covered. | F89: 4261173 | G89: Viji | H89: kiruthiga | I89: v.b.sivakumar | J89: Partial | K89: This uesr story needs to exceuted with different logics and caluculation Hence it is not feasible to automate | L89: Complex user story which involves multiple screen validation and multiple roles validation and requires more time to automate | M89: Complex | O89: 0.35 | P89: 15 | Q89: 2 | R89: 1 | S89: 1 | T89: 1 | U89: 1 | V89: Completed | W89: In Progress | X89: Not Started | Y89: Not Started | Z89: 20 | AA89: 12 | AB89: 8 | AC89: 10 | AD89: 1 | AE89: 0.9 | AF89: =_xlfn.XLOOKUP(F89,'TFS Details'!F:F,'TFS Details'!H:H) -> In Development | AG89: 0 | AH89: 0 | AI89: 0 | AJ89: 10 | AK89: =SUM(AG89:AJ89) -> 10 | AL89: =IF(AG89+AH89=0,0,SUM(AG89:AH89)/AK89) -> 0 | AM89: =IF(AG89=0,0,AG89/(SUM(AG89:AI89))) -> 0 | AO89: =_xlfn.XLOOKUP(F89,'TFS Details'!F:F,'TFS Details'!I:I) -> DevStormers | AP89: =_xlfn.XLOOKUP(AO89,'TFS Details'!I:I,'TFS Details'!AE:AE) -> mervinkumar.manickam
A90: =_xlfn.XLOOKUP(F90,'TFS Details'!F:F,'TFS Details'!D:D) -> myISP_DNP | B90: =_xlfn.XLOOKUP(F90,'TFS Details'!F:F,'TFS Details'!A:A) -> Online SI May Cr's | C90: =_xlfn.XLOOKUP(F90,'TFS Details'!F:F,'TFS Details'!E:E) -> 4334542 | D90: Anand | E90: As a Solution Architect, I want the Adjustment % and Local Currency fields to be excluded from the lock feature, So that the latest updated data gets reflected on fly | F90: 4430431 | G90: Sairam | H90: Kiruthiga | I90: sairam.pamarthi | J90: Yes | M90: Complex | N90: 2 | O90: 0.2 | P90: 4 | Q90: 1 | R90: 1 | S90: 2 | T90: 0.5 | U90: 0.45 | V90: Completed | W90: Completed | X90: In Progress | Y90: Not Started | Z90: 16 | AA90: 3 | AB90: 4 | AC90: 7 | AD90: 0.57 | AE90: 0.35 | AF90: =_xlfn.XLOOKUP(F90,'TFS Details'!F:F,'TFS Details'!H:H) -> In Development | AG90: 0 | AH90: 0 | AI90: 0 | AJ90: 7 | AK90: =SUM(AG90:AJ90) -> 7 | AL90: =IF(AG90+AH90=0,0,SUM(AG90:AH90)/AK90) -> 0 | AM90: =IF(AG90=0,0,AG90/(SUM(AG90:AI90))) -> 0 | AO90: =_xlfn.XLOOKUP(F90,'TFS Details'!F:F,'TFS Details'!I:I) -> DevStormers | AP90: =_xlfn.XLOOKUP(AO90,'TFS Details'!I:I,'TFS Details'!AE:AE) -> mervinkumar.manickam
A91: =_xlfn.XLOOKUP(F91,'TFS Details'!F:F,'TFS Details'!D:D) -> myISP_ DNP | B91: =_xlfn.XLOOKUP(F91,'TFS Details'!F:F,'TFS Details'!A:A) -> DNP - seat charges WFO design change (YOY WFO % level) - Online SI and PCW | C91: =_xlfn.XLOOKUP(F91,'TFS Details'!F:F,'TFS Details'!E:E) -> 4262937 | D91: Anand | E91: As a Solution Architect, I want to add Adjustment % at the Contract Year level in the DNP screen so that, I can calculate Seat Charges (Work from Office) based on the yearly adjustment %- UI changes. | F91: 4184295 | G91: Sneha | I91: sai.sneha.l.malapati | J91: Partial | K91: This uesr story needs to exceuted with different logics and caluculation Hence it is not feasible to automate | L91: Complex user story which involves multiple screen validation and multiple roles validation and requires more time to automate | M91: Complex | O91: 0.2 | V91: Completed | W91: In Progress | X91: Not Started | Y91: Not Started | Z91: 8 | AA91: 3 | AB91: 36 | AC91: 40 | AD91: 0.4 | AE91: 0.4 | AF91: =_xlfn.XLOOKUP(F91,'TFS Details'!F:F,'TFS Details'!H:H) -> In Development | AG91: 0 | AH91: 0 | AI91: 0 | AJ91: 40 | AK91: =SUM(AG91:AJ91) -> 40 | AL91: =IF(AG91+AH91=0,0,SUM(AG91:AH91)/AK91) -> 0 | AM91: =IF(AG91=0,0,AG91/(SUM(AG91:AI91))) -> 0 | AO91: =_xlfn.XLOOKUP(F91,'TFS Details'!F:F,'TFS Details'!I:I) -> DevStormers | AP91: =_xlfn.XLOOKUP(AO91,'TFS Details'!I:I,'TFS Details'!AE:AE) -> mervinkumar.manickam
A92: =_xlfn.XLOOKUP(F92,'TFS Details'!F:F,'TFS Details'!D:D) -> PCW | B92: =_xlfn.XLOOKUP(F92,'TFS Details'!F:F,'TFS Details'!A:A) -> IPC Calculator | Cost Update to Standard Package | C92: =_xlfn.XLOOKUP(F92,'TFS Details'!F:F,'TFS Details'!E:E) -> 4341363 | D92: Anand | E92: PCW - IPC Month-of-Month ACN Cost Conversion to Deal Currency in DNP Baseline and DNP Forecast | F92: 4439846 | G92: Naveen S | H92: Sneha | J92: No | K92: PCW User Story | L92: PCW User Story | V92: Completed | W92: In Progress | X92: Not Started | Y92: Not Started | Z92: 36 | AA92: 20 | AB92: 4 | AC92: 24 | AD92: 0.9 | AE92: 1 | AF92: =_xlfn.XLOOKUP(F92,'TFS Details'!F:F,'TFS Details'!H:H) -> Ready to Deploy | AG92: 0 | AH92: 0 | AI92: 0 | AJ92: 24 | AK92: =SUM(AG92:AJ92) -> 24 | AL92: =IF(AG92+AH92=0,0,SUM(AG92:AH92)/AK92) -> 0 | AM92: =IF(AG92=0,0,AG92/(SUM(AG92:AI92))) -> 0 | AO92: =_xlfn.XLOOKUP(F92,'TFS Details'!F:F,'TFS Details'!I:I) -> Tech Ensemble | AP92: =_xlfn.XLOOKUP(AO92,'TFS Details'!I:I,'TFS Details'!AE:AE) -> mervinkumar.manickam
A93: =_xlfn.XLOOKUP(F93,'TFS Details'!F:F,'TFS Details'!D:D) -> Online SI | B93: =_xlfn.XLOOKUP(F93,'TFS Details'!F:F,'TFS Details'!A:A) -> Rate card screen UI change | C93: =_xlfn.XLOOKUP(F93,'TFS Details'!F:F,'TFS Details'!E:E) -> 4151502 | D93: Anand | E93: As a SA, I need to fix Ratecard UI display and redesign tab order for improved user journey | F93: 4351779 | G93: Kiruthiga | H93: Naveen S | I93: k.tamilzharasu | J93: Yes | K93: UI Improvement - Functioanlity is already automated | L93: Review required | O93: 0.6 | P93: 4 | Q93: 3 | R93: 0 | S93: 1 | T93: 0.9 | U93: 1 | V93: Completed | W93: Completed | X93: Not Started | Y93: In Progress | Z93: 52 | AA93: 25 | AB93: 5 | AC93: 30 | AD93: 0.9 | AE93: 0.95 | AF93: =_xlfn.XLOOKUP(F93,'TFS Details'!F:F,'TFS Details'!H:H) -> PT In Test | AG93: 30 | AH93: 3 | AI93: 0 | AJ93: 0 | AK93: =SUM(AG93:AJ93) -> 33 | AL93: =IF(AG93+AH93=0,0,SUM(AG93:AH93)/AK93) -> 1 | AM93: =IF(AG93=0,0,AG93/(SUM(AG93:AI93))) -> 0.90909091 | AO93: =_xlfn.XLOOKUP(F93,'TFS Details'!F:F,'TFS Details'!I:I) -> TechWizards | AP93: =_xlfn.XLOOKUP(AO93,'TFS Details'!I:I,'TFS Details'!AE:AE) -> mervinkumar.manickam
A94: =_xlfn.XLOOKUP(F94,'TFS Details'!F:F,'TFS Details'!D:D) -> PCW | B94: =_xlfn.XLOOKUP(F94,'TFS Details'!F:F,'TFS Details'!A:A) -> MMP FFP Export update - May release | C94: =_xlfn.XLOOKUP(F94,'TFS Details'!F:F,'TFS Details'!E:E) -> 4436136 | D94: Anand | E94: PCW - Update the FFP Roles at SSG level in Staffing Baseline | F94: 4368139 | G94: Kiruthiga | H94: Sneha | J94: No | K94: PCW User Story | L94: PCW User Story | V94: Completed | W94: Completed | X94: Not Started | Y94: Not Started | Z94: 22 | AA94: 10 | AB94: 4 | AC94: 14 | AD94: 0.8 | AE94: 0.85 | AF94: =_xlfn.XLOOKUP(F94,'TFS Details'!F:F,'TFS Details'!H:H) -> In Development | AG94: 0 | AH94: 0 | AI94: 0 | AJ94: 12 | AK94: =SUM(AG94:AJ94) -> 12 | AL94: =IF(AG94+AH94=0,0,SUM(AG94:AH94)/AK94) -> 0 | AM94: =IF(AG94=0,0,AG94/(SUM(AG94:AI94))) -> 0 | AO94: =_xlfn.XLOOKUP(F94,'TFS Details'!F:F,'TFS Details'!I:I) -> Tech Ensemble | AP94: =_xlfn.XLOOKUP(AO94,'TFS Details'!I:I,'TFS Details'!AE:AE) -> mervinkumar.manickam
A95: =_xlfn.XLOOKUP(F95,'TFS Details'!F:F,'TFS Details'!D:D) -> PCW | B95: =_xlfn.XLOOKUP(F95,'TFS Details'!F:F,'TFS Details'!A:A) -> DNP - seat charges WFO design change (YOY WFO % level) - Online SI and PCW | C95: =_xlfn.XLOOKUP(F95,'TFS Details'!F:F,'TFS Details'!E:E) -> 4262937 | D95: Anand | E95: API - Save the Adjustment % of Hourly Seat Charges from DNP Baseline into YoY adjustment % columns for all the Contract Years across the Deal Duration | F95: 4265946 | G95: Sairam | H95: Naveen S | J95: No | K95: PCW User Story | L95: PCW User Story | V95: Completed | W95: Completed | X95: In Progress | Y95: Not Started | Z95: 14 | AA95: 2 | AB95: 3 | AC95: 5 | AD95: 0.57 | AE95: 0.25 | AF95: =_xlfn.XLOOKUP(F95,'TFS Details'!F:F,'TFS Details'!H:H) -> Active | AG95: 0 | AH95: 0 | AI95: 0 | AJ95: 5 | AK95: =SUM(AG95:AJ95) -> 5 | AL95: =IF(AG95+AH95=0,0,SUM(AG95:AH95)/AK95) -> 0 | AM95: =IF(AG95=0,0,AG95/(SUM(AG95:AI95))) -> 0 | AO95: =_xlfn.XLOOKUP(F95,'TFS Details'!F:F,'TFS Details'!I:I) -> TechAvatar | AP95: =_xlfn.XLOOKUP(AO95,'TFS Details'!I:I,'TFS Details'!AE:AE) -> mervinkumar.manickam
A96: =_xlfn.XLOOKUP(F96,'TFS Details'!F:F,'TFS Details'!D:D) -> PCW | B96: =_xlfn.XLOOKUP(F96,'TFS Details'!F:F,'TFS Details'!A:A) -> IPC Calculator | Cost Update to Standard Package | C96: =_xlfn.XLOOKUP(F96,'TFS Details'!F:F,'TFS Details'!E:E) -> 4341363 | D96: Anand | E96: PCW - IPC Toolkit Cost Update | F96: 4368214 | G96: Sneha | H96: Naveen S | J96: No | K96: PCW User Story | L96: PCW User Story | V96: Completed | W96: In Progress | X96: Not Started | Y96: Not Started | Z96: 8 | AA96: 3 | AB96: 13 | AC96: 16 | AD96: 0.5 | AE96: 0.6 | AF96: =_xlfn.XLOOKUP(F96,'TFS Details'!F:F,'TFS Details'!H:H) -> Ready to Deploy | AG96: 0 | AH96: 0 | AI96: 0 | AJ96: 16 | AK96: =SUM(AG96:AJ96) -> 16 | AL96: =IF(AG96+AH96=0,0,SUM(AG96:AH96)/AK96) -> 0 | AM96: =IF(AG96=0,0,AG96/(SUM(AG96:AI96))) -> 0 | AO96: =_xlfn.XLOOKUP(F96,'TFS Details'!F:F,'TFS Details'!I:I) -> Tech Ensemble | AP96: =_xlfn.XLOOKUP(AO96,'TFS Details'!I:I,'TFS Details'!AE:AE) -> mervinkumar.manickam
A97: =_xlfn.XLOOKUP(F97,'TFS Details'!F:F,'TFS Details'!D:D) -> SI Profile | B97: =_xlfn.XLOOKUP(F97,'TFS Details'!F:F,'TFS Details'!A:A) -> Update the restricted SSGs in profile screen info | C97: =_xlfn.XLOOKUP(F97,'TFS Details'!F:F,'TFS Details'!E:E) -> 4282657 | D97: Anand | E97: As a myISP Solution Architect, I want to update the SI profile screen to include the new restricted SSGs (SI/AMS/IMS/BPMS) and display revised messages in the info, So that user can identify which SSGs have staffing restrictions and pricing limitations. | F97: 4267330 | G97: Sairam | H97: Sneha | I97: sairam.pamarthi | J97: Yes | M97: Simple | N97: 1 | O97: 0.9 | P97: 4 | Q97: 2 | R97: 1 | S97: 1 | T97: 0.6 | U97: 0.6 | V97: Completed | W97: Completed | X97: In Progress | Y97: In Progress | Z97: 17 | AA97: 3 | AB97: 2 | AC97: 2 | AD97: 0.56 | AE97: 0.43 | AF97: =_xlfn.XLOOKUP(F97,'TFS Details'!F:F,'TFS Details'!H:H) -> PT In Test | AG97: 2 | AH97: 0 | AI97: 0 | AJ97: 1 | AK97: =SUM(AG97:AJ97) -> 3 | AL97: =IF(AG97+AH97=0,0,SUM(AG97:AH97)/AK97) -> 0.66666667 | AM97: =IF(AG97=0,0,AG97/(SUM(AG97:AI97))) -> 1 | AO97: =_xlfn.XLOOKUP(F97,'TFS Details'!F:F,'TFS Details'!I:I) -> TechWizards | AP97: =_xlfn.XLOOKUP(AO97,'TFS Details'!I:I,'TFS Details'!AE:AE) -> mervinkumar.manickam
A98: =_xlfn.XLOOKUP(F98,'TFS Details'!F:F,'TFS Details'!D:D) -> myISP_DNP | B98: =_xlfn.XLOOKUP(F98,'TFS Details'!F:F,'TFS Details'!A:A) -> Online SI May Cr's | C98: =_xlfn.XLOOKUP(F98,'TFS Details'!F:F,'TFS Details'!E:E) -> 4334542 | D98: Anand | E98: As a Solution Architect, I want the cost type attribute values aligned with MRDB data and Local Currency defaults corrected in the DNP Master Cost, so that DNP cost calculations use accurate profiles and deal currency values. | F98: 4424935 | G98: Naveen S | H98: Viji | I98: n.sargurunathan | J98: Partial | K98: This uesr story needs to executed with different calculations for each of the cost type. Hence it is not feasible to automate | L98: Complex user story which involves multiple cost type calculation which is different for each of them | O98: 0.4 | V98: Completed | W98: In Progress | X98: Not Started | Y98: In Progress | Z98: 41 | AA98: 22 | AB98: 4 | AC98: 26 | AD98: 1 | AE98: 0.7 | AF98: =_xlfn.XLOOKUP(F98,'TFS Details'!F:F,'TFS Details'!H:H) -> PT In Test | AG98: 2 | AH98: 0 | AI98: 0 | AJ98: 24 | AK98: =SUM(AG98:AJ98) -> 26 | AL98: =IF(AG98+AH98=0,0,SUM(AG98:AH98)/AK98) -> 0.076923077 | AM98: =IF(AG98=0,0,AG98/(SUM(AG98:AI98))) -> 1 | AO98: =_xlfn.XLOOKUP(F98,'TFS Details'!F:F,'TFS Details'!I:I) -> DevStormers | AP98: =_xlfn.XLOOKUP(AO98,'TFS Details'!I:I,'TFS Details'!AE:AE) -> mervinkumar.manickam
A99: =_xlfn.XLOOKUP(F99,'TFS Details'!F:F,'TFS Details'!D:D) -> IPC Calculator | B99: =_xlfn.XLOOKUP(F99,'TFS Details'!F:F,'TFS Details'!A:A) -> IPC Calculator | Package and Cost screen UI changes | C99: =_xlfn.XLOOKUP(F99,'TFS Details'!F:F,'TFS Details'!E:E) -> 4313249 | D99: Anand | E99: As a mySP user, I need to see updated costs being displayed when auto sync functionality for IPC Calculator is initiated by adding Lead PMO role in Staffing Baseline | F99: 4371247 | G99: Sneha | H99: Viji | I99: sai.sneha.l.malapati | J99: Partial | K99: Due to dynamic backend‑driven cost calculations, versioned calculators, and async auto‑sync , we cannot automable | L99: Review required | O99: 0.1 | V99: Completed | W99: Completed | X99: Not Started | Y99: Not Started | Z99: 8 | AA99: 4 | AB99: 3 | AC99: 5 | AD99: 0.6 | AE99: 0.5 | AF99: =_xlfn.XLOOKUP(F99,'TFS Details'!F:F,'TFS Details'!H:H) -> In Development | AG99: 0 | AH99: 0 | AI99: 0 | AJ99: 5 | AK99: =SUM(AG99:AJ99) -> 5 | AL99: =IF(AG99+AH99=0,0,SUM(AG99:AH99)/AK99) -> 0 | AM99: =IF(AG99=0,0,AG99/(SUM(AG99:AI99))) -> 0 | AO99: =_xlfn.XLOOKUP(F99,'TFS Details'!F:F,'TFS Details'!I:I) -> TechWizards | AP99: =_xlfn.XLOOKUP(AO99,'TFS Details'!I:I,'TFS Details'!AE:AE) -> mervinkumar.manickam
A100: =_xlfn.XLOOKUP(F100,'TFS Details'!F:F,'TFS Details'!D:D) -> IPC Calculator | B100: =_xlfn.XLOOKUP(F100,'TFS Details'!F:F,'TFS Details'!A:A) -> IPC Calculator | Updated RAG logic for IPC Delivery Toolkit and IPC Lead PMO | C100: =_xlfn.XLOOKUP(F100,'TFS Details'!F:F,'TFS Details'!E:E) -> 4341338 | D100: Anand | E100: As a mySP user, I need to configure the staffing baseline as per the updated career level guidance for IPC Lead PMO in staffing baseline screen | F100: 4357874 | G100: Kiruthiga | H100: Viji | J100: No | K100: Revenue details to be fetched from MMS ID for different RAG status which will be complex to automate | L100: external Integration validation | V100: Completed | W100: Completed | X100: Not Started | Y100: Not Started | Z100: 23 | AA100: 18 | AB100: 0 | AC100: 8 | AD100: 0.9 | AE100: 0.9 | AF100: =_xlfn.XLOOKUP(F100,'TFS Details'!F:F,'TFS Details'!H:H) -> In Development | AG100: 0 | AH100: 0 | AI100: 0 | AJ100: 8 | AK100: =SUM(AG100:AJ100) -> 8 | AL100: =IF(AG100+AH100=0,0,SUM(AG100:AH100)/AK100) -> 0 | AM100: =IF(AG100=0,0,AG100/(SUM(AG100:AI100))) -> 0 | AO100: =_xlfn.XLOOKUP(F100,'TFS Details'!F:F,'TFS Details'!I:I) -> TechAvengers | AP100: =_xlfn.XLOOKUP(AO100,'TFS Details'!I:I,'TFS Details'!AE:AE) -> mervinkumar.manickam
...

Sheet Leads Pivot
A2: PT Lead | B2: Sum of Passed | C2: Sum of Failed | D2: Sum of Blocked | E2: Sum of Not Run | F2: Sum of Total | H2: Execution % | I2: Pass% | J2: Risk Points | K2: ETA to complete not run | L2: Blocker Bug ids
A3: Anand | B3: 85 | C3: 5 | D3: 12 | E3: 337 | F3: 439 | H3: =IF(B3+C3=0,0,SUM(B3:D3)/F3) -> 0.23234624 | I3: =IF(B3=0,0,B3/(SUM(B3:D3))) -> 0.83333333 | J3: 4 user stories blocked with high bugs | K3: based on bug resolution | L3: High-4423607, 4423487, 4423233
A4: Devika | B4: 123 | C4: 3 | D4: 208 | E4: 1014 | F4: 1406 | H4: =IF(B4+C4=0,0,SUM(B4:D4)/F4) -> 0.23755334 | I4: =IF(B4=0,0,B4/(SUM(B4:D4))) -> 0.36826347 | J4: 1 US not delivered PT 4 stories blocked with high bug | K4: Based on defect resoltuion | L4: High - 4427916, 4425106, 4424806
A5: Hajara | B5: 169 | C5: 11 | D5: 1 | E5: 528 | F5: 688 | H5: =IF(B5+C5=0,0,SUM(B5:D5)/F5) -> 0.2630814 | I5: =IF(B5=0,0,B5/(SUM(B5:D5))) -> 0.93370166 | J5: 3 not delivered to PT OBM - there are data issues | K5: Rest not run ETA - Friday EOD OBM - depend on data issues resolution | L5: High - 4372048, 4418785, 4426061, 4427785
A6: Himanshu | B6: 73 | C6: 3 | D6: 47 | E6: 113 | F6: 236 | H6: =IF(B6+C6=0,0,SUM(B6:D6)/F6) -> 0.52118644 | I6: =IF(B6=0,0,B6/(SUM(B6:D6))) -> 0.59349593 | J6: 2 Blocked US because of high bug | K6: Rest not run ETA - Thursday EOD | L6: High-4426382,4426061,4425767
A7: Jaya | B7: 73 | C7: 17 | D7: 0 | E7: 569 | F7: 659 | H7: =IF(B7+C7=0,0,SUM(B7:D7)/F7) -> 0.13657056 | I7: =IF(B7=0,0,B7/(SUM(B7:D7))) -> 0.81111111 | J7: 2 not delivered to PT 4 US blocked with high bugs | K7: Rest not run ETA - Thursday EOD | L7: 4428481(H), 4427044(H), 4427142(H), 4425522(H), 4425287(H)
A8: Kavi | B8: 38 | C8: 0 | D8: 0 | E8: 467 | F8: 505 | H8: =IF(B8+C8=0,0,SUM(B8:D8)/F8) -> 0.075247525 | I8: =IF(B8=0,0,B8/(SUM(B8:D8))) -> 1 | J8: No blockers | K8: NOT run ETA - Thursday EOD
A9: Leena | B9: 178 | C9: 7 | D9: 0 | E9: 519 | F9: 717 | H9: =IF(B9+C9=0,0,SUM(B9:D9)/F9) -> 0.25801953 | I9: =IF(B9=0,0,B9/(SUM(B9:D9))) -> 0.96216216 | J9: 13 Not delivered to PT 2 US blocked with high bugs | K9: Rest not run ETA - Friday 1 PM | L9: 4425220(H),
A10: Nandini | B10: 865 | C10: 21 | D10: 106 | E10: 2271 | F10: 3263 | H10: =IF(B10+C10=0,0,SUM(B10:D10)/F10) -> 0.30401471 | I10: =IF(B10=0,0,B10/(SUM(B10:D10))) -> 0.87197581 | J10: 1 US blocked with high bug | K10: Rest not run ETA - Friday 1 PM | L10: 4427422 - H
A11: Omkar | B11: 0 | C11: 0 | D11: 0 | E11: 0 | F11: 0 | H11: =IF(B11+C11=0,0,SUM(B11:D11)/F11) -> 0 | I11: =IF(B11=0,0,B11/(SUM(B11:D11))) -> 0
A12: Pirtheebaa | B12: 149 | C12: 0 | D12: 0 | E12: 526 | F12: 675 | H12: =IF(B12+C12=0,0,SUM(B12:D12)/F12) -> 0.22074074 | I12: =IF(B12=0,0,B12/(SUM(B12:D12))) -> 1 | J12: No blockers | K12: NOT run ETA - Thursday EOD
A13: Rajeswari | B13: 44 | C13: 0 | D13: 0 | E13: 846 | F13: 890 | H13: =IF(B13+C13=0,0,SUM(B13:D13)/F13) -> 0.049438202 | I13: =IF(B13=0,0,B13/(SUM(B13:D13))) -> 1 | J13: No blockers | K13: Not Run - Friday 1 PM
A14: Shini | B14: 72 | C14: 11 | D14: 1 | E14: 351 | F14: 482 | H14: =IF(B14+C14=0,0,SUM(B14:D14)/F14) -> 0.17427386 | I14: =IF(B14=0,0,B14/(SUM(B14:D14))) -> 0.85714286 | J14: 2 US blocked with C and H bug | K14: Rest not run ETA - Friday 1 PM | L14: 4427905 -C,4427541(H),4428646(H),4427330(H),4427541(H),4427684(H),4426302(H),4424934(H),4425358(H),4418463(H),4420794(H),4423481(H)
A15: Surbhi | B15: 8 | C15: 2 | D15: 0 | E15: 48 | F15: 58 | H15: =IF(B15+C15=0,0,SUM(B15:D15)/F15) -> 0.17241379 | I15: =IF(B15=0,0,B15/(SUM(B15:D15))) -> 0.8
A16: Vaidheki | B16: 0 | C16: 0 | D16: 0 | E16: 0 | F16: 0 | H16: =IF(B16+C16=0,0,SUM(B16:D16)/F16) -> 0 | I16: =IF(B16=0,0,B16/(SUM(B16:D16))) -> 0
A17: Grand Total | B17: 1877 | C17: 80 | D17: 375 | E17: 7589 | F17: 10018 | H17: =IF(B17+C17=0,0,SUM(B17:D17)/F17) -> 0.23278099 | I17: =IF(B17=0,0,B17/(SUM(B17:D17))) -> 0.80488851

Sheet Environment Details
A1: System | B1: PT | C1: UAT
A2: myISP | B2: https://myspnextgen-ops.ciostage.accenture.com | C2: https://myISPnextgen1-uat.ciotest.accenture.com
A3: MMS | B3: https://accenture--AprAglTst.sandbox.my.salesforce.com/ | C3: https://accenture--Q2Stg.sandbox.my.salesforce.com/ | E3: Test Rebar beta - Switch on Jan 12th - Marqtrtst | F3: after 16th march, Test MMS URL
A4: MMP | B4: MMP Test | C4: MMP Stage | E4: Test rebar stage - No change - Q2 stage.
A7: myISP - Mar 28th Release
B8: PT | C8: UAT | D8: POC | E8: Comments
A9: myISP | B9: https://myspnextgen-ops.ciostage.accenture.com | C9: https://myISPnextgen1-uat.ciotest.accenture.com | D9: Release POCs
A10: IMS | B10: https://myispimsstage1-services.ciostage.accenture.com/ | C10: https://myisp-imsuat1.ciostage.accenture.com | D10: Aqil/Release POCs
A11: BPMS | C11: https://bpmssolutionestimator.uat.accenture.com
A12: MDA | C12: MDA Instance 2 | D12: Pirtheebaa
A13: Analytics | C13: Analytics Instance 2 | D13: Shini
A14: DATA KDA | D14: Devika
A15: SSA | B15: SSA PT | C15: SSA Demo | D15: Devika
A16: SCA | B16: SCA PT | C16: SCA UAT | D16: Kavi
A17: Costing SCC | D17: Jaya
A18: AC- Gen Wizard | D18: Nandini
A19: Gen AI | D19: Hajara
A20: IDRA | D20: Jaya
A21: AAI - Apps | D21: Nandini
A22: AC - Gen AI Assets | D22: Nandini
A23: mydiagnostics | D23: Nandini
A24: CDAT | D24: Raji

Sheet TFS Details
A1: Parent Title | B1: mySP Initiative | C1: Sub Initiative | D1: TextVerification | E1: Parent | F1: ID | G1: Title | H1: State | I1: Node Name | J1: Testing POC | K1: Planned for PT Date | L1: Actual PT Date | M1: Planned UAT Date | N1: Actual UAT Date | O1: Assigned To | P1: Production Deployment Date | Q1: Story Points | R1: Original Estimate | S1: Priority | T1: ETA | U1: UT Results Attached | V1: Code Review Completed | W1: Created By | X1: Created Date | Y1: Tags | Z1: Area Path | AA1: Iteration Path | AB1: Plan | AC1: Remaining | AD1: TextVerification1 | AE1: ExternalRef ID
A2: Services - Learn & Launch enhancements with BPMS support button | B2: Platform Consolidation | C2: NextGen | D2: Learn | E2: 4443474 | F2: 4435598 | G2: As a myISP user, I want to see "BPMS" as a support option alongside AMS, SI, and IMS in both the "Email" support sections on all 10-step screens. So that I can easily raise BPMS-related support requests. | H2: Test Complete | I2: MYISP_Revamp_UI | J2: Krishnan, Pirtheebaa <pirtheebaa.krishnan@accenture.com> | K2: 46134.229 | L2: 46119.934 | O2: Shaik, Sadhik A. <sadhik.a.shaik@accenture.com> | P2: 46151.229 | Q2: 1 | S2: 2 | U2: Yes | V2: Yes | W2: Kaliki, Tulasi Reddy <tulasi.reddy.kaliki@accenture.com> | X2: 46099.747 | Y2: 9th May; Learn; MFE Host; UAT Testing Not Required | Z2: AutomationProcess_29697\mySPIntegratedSolutionPlatform\MYISP_Revamp_UI | AA2: AutomationProcess_29697\mySolutionPlanner\R44\Sprint 107 | AD2: Launch, & Services (PART 1) | AE2: vikrant.r.mohite
A3: Angular upgrade version 19 to version 21 - 9th May | B3: Rapid Soln | C3: NextGen | D3: Drop 4 - Angular upgrade v19 to v21 | E3: 4444328 | F3: 4444330 | G3: As a myISP Solution Architect, I want to see the Value Shaping - MFE App migrated to Angular 21 | H3: PT In Test | I3: MYISP_Revamp_UI | J3: Baskaran, Nandini <nandini.baskaran@accenture.com> | K3: 46119.855 | L3: 46120.062 | O3: Bindu, Vadde <vadde.bindu@accenture.com> | P3: 46151.229 | Q3: 3 | S3: 2 | U3: Yes | V3: Yes | W3: Kamble, Pallavi <pallavi.kamble@accenture.com> | X3: 46107.569 | Y3: Angular upgrade v19 to v21; PT Regression; UAT Testing Not Required; ValueShaping - MFE | Z3: AutomationProcess_29697\mySPIntegratedSolutionPlatform\MYISP_Revamp_UI | AA3: AutomationProcess_29697\mySolutionPlannerIntegratedSolutionPlatform | AD3: Value Shaping - MFE | AE3: vikrant.r.mohite
A4: Angular upgrade version 19 to version 21 - 9th May | B4: Rapid Soln | C4: NextGen | D4: Drop 4 - Angular upgrade v19 to v21 | E4: 4444328 | F4: 4444334 | G4: As a myISP Solution Architect, I want to see the Generic Calculator App migrated to Angular 21 | H4: PT In Test | I4: MYISP_Revamp_UI | J4: Baskaran, Nandini <nandini.baskaran@accenture.com> | K4: 46119.981 | L4: 46120.062 | O4: Ramkumar, Yuvanitharsana <r.yuvanitharsana@accenture.com> | P4: 46151.229 | Q4: 3 | S4: 2 | U4: Yes | V4: Yes | W4: Kamble, Pallavi <pallavi.kamble@accenture.com> | X4: 46107.571 | Y4: Angular upgrade v19 to v21; Generic Calculator App; PT Regression; UAT Testing Not Required | Z4: AutomationProcess_29697\mySPIntegratedSolutionPlatform\MYISP_Revamp_UI | AA4: AutomationProcess_29697\mySolutionPlannerIntegratedSolutionPlatform | AD4: Generic Calculator App | AE4: vikrant.r.mohite
A5: Angular upgrade version 19 to version 21 - 9th May | B5: Rapid Soln | C5: NextGen | D5: Drop 4 - Angular upgrade v19 to v21 | E5: 4444328 | F5: 4444335 | G5: As a myISP Solution Architect, I want to see the Automation Calculator App migrated to Angular 21 | H5: Test Complete | I5: MYISP_Revamp_UI | J5: Baskaran, Nandini <nandini.baskaran@accenture.com> | K5: 46121.624 | L5: 46121.062 | O5: Pachipulusu, Naga Venkata Sai Durga Rohitha <naga.v.pachipulusu@accenture.com> | P5: 46151.229 | Q5: 3 | S5: 2 | U5: Yes | V5: NA | W5: Kamble, Pallavi <pallavi.kamble@accenture.com> | X5: 46107.573 | Y5: Angular upgrade v19 to v21; Automation Calculator App; PT Regression; UAT Testing Not Required | Z5: AutomationProcess_29697\mySPIntegratedSolutionPlatform\MYISP_Revamp_UI | AA5: AutomationProcess_29697\mySolutionPlannerIntegratedSolutionPlatform | AD5: Automation Calculator App | AE5: vikrant.r.mohite
A6: Angular upgrade version 19 to version 21 - 9th May | B6: Rapid Soln | C6: NextGen | D6: Drop 4 - Angular upgrade v19 to v21 | E6: 4444328 | F6: 4444345 | G6: As a myISP Solution Architect, I want to see the BPMS Generic Calculator App migrated to Angular 21 | H6: PT In Test | I6: MYISP_Revamp_UI | J6: Vv, Shini <shini.vv@accenture.com> | K6: 46121.622 | L6: 46126.705 | O6: E J, Lakshmi <lakshmi.e.j@accenture.com> | P6: 46151.229 | Q6: 3 | S6: 2 | U6: No | V6: No | W6: Kamble, Pallavi <pallavi.kamble@accenture.com> | X6: 46107.574 | Y6: Angular upgrade v19 to v21; BPMS Generic Calculator App; PT Regression; UAT Testing Not Required | Z6: AutomationProcess_29697\mySPIntegratedSolutionPlatform\MYISP_Revamp_UI | AA6: AutomationProcess_29697\mySolutionPlannerIntegratedSolutionPlatform | AD6: BPMS Generic Calculator App | AE6: vikrant.r.mohite
A7: [PMO] URL update for Manage and Dashboard screens | B7: Platform Consolidation | C7: NextGen | D7: PMO | E7: 4440976 | F7: 4446503 | G7: [PMO] As a PMO user, I should be able to navigate to Manage / Dashboard screen with the new URL from MFhost screens | H7: PT In Test | I7: MYISP_Revamp_UI | J7: Vv, Shini <shini.vv@accenture.com> | K7: 46134.229 | L7: 46125.968 | M7: 46134.229 | O7: Sheik Fusulee A, Mohamed <m.sheik.fusulee.a@accenture.com> | P7: 46151.229 | Q7: 1 | S7: 2 | U7: Yes | V7: Yes | W7: Vijay Deshpande, Prajakta <p.vijay.deshpande@accenture.com> | X7: 46108.671 | Y7: 9th May; MFE Host; UAT Testing Not Required | Z7: AutomationProcess_29697\mySPIntegratedSolutionPlatform\MYISP_Revamp_UI | AA7: AutomationProcess_29697\mySolutionPlannerIntegratedSolutionPlatform | AD7: PMO - Manage | AE7: vikrant.r.mohite
A8: Attach Calculator | B8: V2V | C8: Calculator | D8: Attach Calculator | E8: 4372279 | F8: 4454065 | G8: [Attach Calculator]As a myISP user, I need to see the updated UI in R2 screens when Attach Calculator is introduced along with Differentiation screen | H8: UAT In Test | I8: MYISP_Revamp_UI | J8: Baskaran, Nandini <nandini.baskaran@accenture.com> | K8: 46134.229 | L8: 46119.938 | M8: 46135.229 | N8: 46121.933 | O8: Magundanavar, Dinesh <dinesh.magundanavar@accenture.com> | P8: 46151.229 | Q8: 1 | S8: 2 | U8: Yes | V8: Yes | W8: Pandey, Ansh <ansh.pandey@accenture.com> | X8: 46112.719 | Y8: 9th May; CCB Approved; MFE Host | Z8: AutomationProcess_29697\mySPIntegratedSolutionPlatform\MYISP_Revamp_UI | AA8: AutomationProcess_29697 | AD8: Preference Setting | AE8: vikrant.r.mohite
A9: Angular upgrade version 19 to version 21 - 9th May | B9: Rapid Soln | C9: NextGen | D9: Drop 4 - Angular upgrade v19 to v21 | E9: 4444328 | F9: 4461628 | G9: As a myISP Solution Architect, I want to see the DSP GenAI App migrated to Angular 21 | H9: Active | I9: MYISP_Revamp_UI | J9: Das, Leena <leena.a.das@accenture.com> | K9: 46139.229 | M9: 46134.229 | O9: Babu, Csd <csd.babu@accenture.com> | P9: 46151.229 | Q9: 3 | S9: 2 | U9: No | V9: No | W9: Kamble, Pallavi <pallavi.kamble@accenture.com> | X9: 46115.569 | Y9: Angular upgrade v19 to v21; CCB Yet to Approve; DSPGenAI; PT Regression; UAT Testing Not Required | Z9: AutomationProcess_29697\mySPIntegratedSolutionPlatform\MYISP_Revamp_UI | AA9: AutomationProcess_29697\mySolutionPlannerIntegratedSolutionPlatform | AD9: DSP GenAI | AE9: vikrant.r.mohite
A10: Services - Learn & Launch enhancements | B10: Platform Consolidation | C10: NextGen | D10: Learn | E10: 4443471 | F10: 4471400 | G10: As a myISP platform administrator I want to update the "Give Feedback" link across all touchpoints in MFHost, myISP to point to the new feedback form So that user feedback is routed to the correct owner | H10: PT In Test | I10: MYISP_Revamp_UI | J10: Krishnan, Pirtheebaa <pirtheebaa.krishnan@accenture.com> | K10: 46129.229 | L10: 46127.679 | M10: 46134.229 | O10: Umardand, Namrata G. <namrata.g.umardand@accenture.com> | P10: 46151.229 | Q10: 0.75 | S10: 1 | U10: Yes | V10: Yes | W10: Kaliki, Tulasi Reddy <tulasi.reddy.kaliki@accenture.com> | X10: 46122.43 | Y10: CCB Approved; Development Request; Learn; UAT Testing Not Required | Z10: AutomationProcess_29697\mySPIntegratedSolutionPlatform\MYISP_Revamp_UI | AA10: AutomationProcess_29697\mySolutionPlanner\R44\Sprint 107 | AD10: Launch, & Services (PART 1) | AE10: vikrant.r.mohite
A11: 0 | B11: Platform Consolidation | C11: Inspire | D11: May Release | F11: 4475473 | G11: INSPIRE Home Screen � Validation of Career Track and Economic Profile Combinations | H11: New | I11: myISP_IMS | K11: 46134.229 | M11: 46140.229 | O11: P K, Prabitha <prabitha.p.k@accenture.com> | P11: 46151.229 | Q11: 1 | S11: 2 | W11: Srinivasan, Vaidheki <vaidheki.srinivasan@accenture.com> | X11: 46125.799 | Y11: IMS BAU | Z11: AutomationProcess_29697\mySPIntegratedSolutionPlatform\myISP_IMS | AA11: AutomationProcess_29697\mySolutionPlannerRapidSolutioning\R65\Sprint165 | AD11: INSPIRE | AE11: supriya.a.dhingra
A12: IMS Modernization common screens | B12: Platform Consolidation | C12: Inspire | D12: Solution Components- Navigation | E12: 4413810 | F12: 4465888 | G12: As an IMS Solution Architect, I want to navigate to Modernization flow on clicking Solution Components tab and have the Estimators/Calculators enabled. | H12: Active | I12: TechWarriors | J12: Baskaran, Nandini <nandini.baskaran@accenture.com> | K12: 46137.104 | M12: 46141.062 | O12: Indra, Vandana <vandana.indra@accenture.com> | P12: 46151.229 | Q12: 1 | S12: 2 | W12: Zanpure, Priti <priti.s.zanpure@accenture.com> | X12: 46119.503 | Y12: CCB Approved; IMS Modernization | Z12: AutomationProcess_29697\mySPRapidSolutioning\TechWarriors | AA12: AutomationProcess_29697\mySolutionPlannerRapidSolutioning\IMSModernization\MVP1.3-Drop2 | AD12: Solution Components- Navigation | AE12: Supriya.a.dhingra
A13: IMS BAU - Multi Tower Pricing (OCP for SI) | B13: Platform Consolidation | C13: Inspire | D13: May Release | E13: 4459024 | F13: 4449701 | G13: As a Solution Architect, I want a dedicated SEP Pricing Inputs UI for SI with prerequisite validations, so that I can provide all mandatory inputs required to successfully trigger SI OCP generation | H13: PT In Test | I13: myISP_IMS | J13: Srinivasan, Vaidheki <vaidheki.srinivasan@accenture.com> | K13: 46134.229 | L13: 46128.229 | M13: 46140.229 | O13: P K, Prabitha <prabitha.p.k@accenture.com> | P13: 46151.229 | Q13: 8 | S13: 2 | U13: Yes | V13: Yes | W13: Srinivasan, Vaidheki <vaidheki.srinivasan@accenture.com> | X13: 46111.755 | Y13: IMS BAU; UAT Testing Not Required | Z13: AutomationProcess_29697\mySPIntegratedSolutionPlatform\myISP_IMS | AA13: AutomationProcess_29697\mySolutionPlannerRapidSolutioning\R65\Sprint165 | AD13: INSPIRE | AE13: supriya.a.dhingra
A14: IMS BAU - Multi Tower Pricing (OCP for SI) | B14: Platform Consolidation | C14: Inspire | D14: May Release | E14: 4459024 | F14: 4449702 | G14: As a Solution Architect, I want to define system-defined and custom groups for SI, so that pricing and contingency can be managed at the appropriate grouping level. | H14: PT In Test | I14: myISP_IMS | J14: Srinivasan, Vaidheki <vaidheki.srinivasan@accenture.com> | K14: 46134.229 | L14: 46128.229 | M14: 46140.229 | O14: P K, Prabitha <prabitha.p.k@accenture.com> | P14: 46151.229 | Q14: 8 | S14: 2 | U14: Yes | V14: Yes | W14: Srinivasan, Vaidheki <vaidheki.srinivasan@accenture.com> | X14: 46111.755 | Y14: IMS BAU; UAT Testing Not Required | Z14: AutomationProcess_29697\mySPIntegratedSolutionPlatform\myISP_IMS | AA14: AutomationProcess_29697\mySolutionPlannerRapidSolutioning\R65\Sprint165 | AD14: INSPIRE | AE14: supriya.a.dhingra
A15: IMS BAU - Multi Tower Pricing (OCP for SI) | B15: Platform Consolidation | C15: Inspire | D15: May Release | E15: 4459024 | F15: 4449703 | G15: As a Solution Architect, I want to define contractual coverage and FX risk details for SI, so that pricing reflects contract-driven risk exposure. | H15: PT In Test | I15: myISP_IMS | J15: Srinivasan, Vaidheki <vaidheki.srinivasan@accenture.com> | K15: 46134.229 | L15: 46128.229 | M15: 46140.229 | O15: P K, Prabitha <prabitha.p.k@accenture.com> | P15: 46151.229 | Q15: 8 | S15: 2 | U15: Yes | V15: Yes | W15: Srinivasan, Vaidheki <vaidheki.srinivasan@accenture.com> | X15: 46111.755 | Y15: IMS BAU; UAT Testing Not Required | Z15: AutomationProcess_29697\mySPIntegratedSolutionPlatform\myISP_IMS | AA15: AutomationProcess_29697\mySolutionPlannerRapidSolutioning\R65\Sprint165 | AD15: INSPIRE | AE15: supriya.a.dhingra
A16: IMS BAU - Multi Tower Pricing (OCP for SI) | B16: Platform Consolidation | C16: Inspire | D16: May Release | E16: 4459024 | F16: 4449704 | G16: As a Solution Architect, I want to define contingency and PMO parameters for SI, so that risk buffers are accurately included in pricing. | H16: PT In Test | I16: myISP_IMS | J16: Srinivasan, Vaidheki <vaidheki.srinivasan@accenture.com> | K16: 46134.229 | L16: 46128.229 | M16: 46140.229 | O16: P K, Prabitha <prabitha.p.k@accenture.com> | P16: 46151.229 | Q16: 8 | S16: 2 | U16: Yes | V16: Yes | W16: Srinivasan, Vaidheki <vaidheki.srinivasan@accenture.com> | X16: 46111.755 | Y16: IMS BAU; UAT Testing Not Required | Z16: AutomationProcess_29697\mySPIntegratedSolutionPlatform\myISP_IMS | AA16: AutomationProcess_29697\mySolutionPlannerRapidSolutioning\R65\Sprint165 | AD16: INSPIRE | AE16: supriya.a.dhingra
A17: IMS BAU - Multi Tower Pricing (OCP for SI) | B17: Platform Consolidation | C17: Inspire | D17: May Release | E17: 4459024 | F17: 4449705 | G17: As a Solution Architect, I want to configure billing terms and SLA service credits for SI, so that pricing aligns with contractual billing structures. | H17: PT In Test | I17: myISP_IMS | J17: Srinivasan, Vaidheki <vaidheki.srinivasan@accenture.com> | K17: 46134.229 | L17: 46128.229 | M17: 46140.229 | O17: P K, Prabitha <prabitha.p.k@accenture.com> | P17: 46151.229 | Q17: 8 | S17: 2 | U17: Yes | V17: Yes | W17: Srinivasan, Vaidheki <vaidheki.srinivasan@accenture.com> | X17: 46111.755 | Y17: IMS BAU; UAT Testing Not Required | Z17: AutomationProcess_29697\mySPIntegratedSolutionPlatform\myISP_IMS | AA17: AutomationProcess_29697\mySolutionPlannerRapidSolutioning\R65\Sprint165 | AD17: INSPIRE | AE17: supriya.a.dhingra
A18: IMS BAU - Multi Tower Pricing (OCP for SI) | B18: Platform Consolidation | C18: Inspire | D18: May Release | E18: 4459024 | F18: 4449706 | G18: As a Solution Architect, I want to choose between deal-wide pricing or pricing by group, so that SI pricing can be modeled accurately. | H18: PT In Test | I18: myISP_IMS | J18: Srinivasan, Vaidheki <vaidheki.srinivasan@accenture.com> | K18: 46134.229 | L18: 46128.229 | M18: 46140.229 | O18: P K, Prabitha <prabitha.p.k@accenture.com> | P18: 46151.229 | Q18: 8 | S18: 2 | U18: Yes | V18: Yes | W18: Srinivasan, Vaidheki <vaidheki.srinivasan@accenture.com> | X18: 46111.755 | Y18: IMS BAU; UAT Testing Not Required | Z18: AutomationProcess_29697\mySPIntegratedSolutionPlatform\myISP_IMS | AA18: AutomationProcess_29697\mySolutionPlannerRapidSolutioning\R65\Sprint165 | AD18: INSPIRE | AE18: supriya.a.dhingra
A19: IMS BAU - Multi Tower Pricing (OCP for SI) | B19: Platform Consolidation | C19: Inspire | D19: May Release | E19: 4459024 | F19: 4449707 | G19: As a Solution Architect, I want to configure rate cards for SI, so that labor pricing is calculated correctly in OCP. | H19: PT In Test | I19: myISP_IMS | J19: Srinivasan, Vaidheki <vaidheki.srinivasan@accenture.com> | K19: 46134.229 | L19: 46128.229 | M19: 46140.229 | O19: P K, Prabitha <prabitha.p.k@accenture.com> | P19: 46151.229 | Q19: 8 | S19: 2 | U19: Yes | V19: Yes | W19: Srinivasan, Vaidheki <vaidheki.srinivasan@accenture.com> | X19: 46111.755 | Y19: IMS BAU; UAT Testing Not Required | Z19: AutomationProcess_29697\mySPIntegratedSolutionPlatform\myISP_IMS | AA19: AutomationProcess_29697\mySolutionPlannerRapidSolutioning\R65\Sprint165 | AD19: INSPIRE | AE19: supriya.a.dhingra
A20: IMS BAU - Multi Tower Pricing (OCP for SI) | B20: Platform Consolidation | C20: Inspire | D20: May Release | E20: 4459024 | F20: 4449708 | G20: As a Solution Architect, I want to trigger the One Click Pricing (OCP) Engine for IMS and SI with clear sync behavior and user selection, so that cost and price simulations reflect exactly the service data I intend to sync. | H20: PT In Test | I20: myISP_IMS | J20: Srinivasan, Vaidheki <vaidheki.srinivasan@accenture.com> | K20: 46134.229 | L20: 46128.229 | M20: 46140.229 | O20: P K, Prabitha <prabitha.p.k@accenture.com> | P20: 46151.229 | Q20: 8 | S20: 2 | U20: Yes | V20: Yes | W20: Srinivasan, Vaidheki <vaidheki.srinivasan@accenture.com> | X20: 46111.755 | Y20: IMS BAU; UAT Testing Not Required | Z20: AutomationProcess_29697\mySPIntegratedSolutionPlatform\myISP_IMS | AA20: AutomationProcess_29697\mySolutionPlannerRapidSolutioning\R65\Sprint165 | AD20: INSPIRE | AE20: supriya.a.dhingra
A21: MDA personalization | B21: Platform Consolidation | C21: Inspire | D21: May Release | E21: 4278295 | F21: 4449709 | G21: As a Solution Architect, I want the ability to abort an in?progress Multi?Service Deal Analytics (MSDA) sync from INSPIRE, so that I can stop long?running or incorrect MSDA simulations without waiting for completion. | H21: PT In Test | I21: myISP_IMS | J21: Srinivasan, Vaidheki <vaidheki.srinivasan@accenture.com> | K21: 46134.229 | L21: 46125.229 | M21: 46140.229 | O21: P K, Prabitha <prabitha.p.k@accenture.com> | P21: 46151.229 | Q21: 5 | S21: 2 | U21: Yes | V21: Yes | W21: Srinivasan, Vaidheki <vaidheki.srinivasan@accenture.com> | X21: 46111.755 | Y21: IMS BAU; UAT Testing Not Required | Z21: AutomationProcess_29697\mySPIntegratedSolutionPlatform\myISP_IMS | AA21: AutomationProcess_29697\mySolutionPlannerRapidSolutioning\R65\Sprint165 | AD21: INSPIRE | AE21: supriya.a.dhingra
A22: IMS BAU - Change Requests | B22: Platform Consolidation | C22: Inspire | D22: May Release | E22: 4386339 | F22: 4450101 | G22: As a system user, I want to configure new offerings, services, and sub?services, So that the service catalog reflects expanded operational capabilities | H22: PT In Test | I22: myISP_IMS | J22: Srinivasan, Vaidheki <vaidheki.srinivasan@accenture.com> | K22: 46134.229 | L22: 46125.229 | M22: 46140.229 | O22: P K, Prabitha <prabitha.p.k@accenture.com> | P22: 46151.229 | Q22: 8 | S22: 2 | U22: Yes | V22: Yes | W22: Srinivasan, Vaidheki <vaidheki.srinivasan@accenture.com> | X22: 46111.838 | Y22: IMS BAU; UAT Testing Not Required | Z22: AutomationProcess_29697\mySPIntegratedSolutionPlatform\myISP_IMS | AA22: AutomationProcess_29697\mySolutionPlannerRapidSolutioning\R65\Sprint165 | AD22: INSPIRE | AE22: supriya.a.dhingra
A23: UAT CRs | B23: Platform Consolidation | C23: Inspire | D23: May Release | E23: 4275871 | F23: 4450106 | G23: UAT CRs | H23: PT In Test | I23: myISP_IMS | J23: Srinivasan, Vaidheki <vaidheki.srinivasan@accenture.com> | K23: 46134.229 | L23: 46125.229 | M23: 46140.229 | O23: P K, Prabitha <prabitha.p.k@accenture.com> | P23: 46151.229 | Q23: 5 | S23: 2 | U23: Yes | V23: Yes | W23: Srinivasan, Vaidheki <vaidheki.srinivasan@accenture.com> | X23: 46111.84 | Y23: IMS BAU; UAT Testing Not Required | Z23: AutomationProcess_29697\mySPIntegratedSolutionPlatform\myISP_IMS | AA23: AutomationProcess_29697\mySolutionPlannerRapidSolutioning\R65\Sprint165 | AD23: INSPIRE | AE23: supriya.a.dhingra
A24: IMS BAU - Monthy MRDB | B24: Platform Consolidation | C24: Inspire | D24: May Release | E24: 4386335 | F24: 4450108 | G24: Monthly MRDB - May'26 Release | H24: Active | I24: myISP_IMS | J24: Srinivasan, Vaidheki <vaidheki.srinivasan@accenture.com> | K24: 46134.229 | M24: 46140.229 | O24: P K, Prabitha <prabitha.p.k@accenture.com> | P24: 46151.229 | Q24: 1 | S24: 2 | U24: Yes | V24: Yes | W24: Srinivasan, Vaidheki <vaidheki.srinivasan@accenture.com> | X24: 46111.842 | Y24: IMS BAU; UAT Testing Not Required | Z24: AutomationProcess_29697\mySPIntegratedSolutionPlatform\myISP_IMS | AA24: AutomationProcess_29697\mySolutionPlannerRapidSolutioning\R65\Sprint165 | AD24: INSPIRE | AE24: supriya.a.dhingra
A25: IMS BAU - Regression Testing | B25: Platform Consolidation | C25: Inspire | D25: May Release | E25: 4386333 | F25: 4450110 | G25: May Release - Regression Testing | H25: Active | I25: myISP_IMS | J25: Srinivasan, Vaidheki <vaidheki.srinivasan@accenture.com> | K25: 46134.229 | M25: 46140.229 | O25: P K, Prabitha <prabitha.p.k@accenture.com> | P25: 46151.229 | Q25: 5 | S25: 2 | U25: Yes | V25: Yes | W25: Srinivasan, Vaidheki <vaidheki.srinivasan@accenture.com> | X25: 46111.843 | Y25: IMS BAU; UAT Testing Not Required | Z25: AutomationProcess_29697\mySPIntegratedSolutionPlatform\myISP_IMS | AA25: AutomationProcess_29697\mySolutionPlannerRapidSolutioning\R65\Sprint165 | AD25: INSPIRE | AE25: supriya.a.dhingra
A26: IMS BAU - Technical User Stories | B26: Platform Consolidation | C26: Inspire | D26: May Release | E26: 4317300 | F26: 4450111 | G26: Sonar Lint - 1 | H26: Active | I26: myISP_IMS | J26: Srinivasan, Vaidheki <vaidheki.srinivasan@accenture.com> | K26: 46134.229 | M26: 46140.229 | O26: P K, Prabitha <prabitha.p.k@accenture.com> | P26: 46151.229 | Q26: 8 | S26: 2 | U26: Yes | V26: Yes | W26: Srinivasan, Vaidheki <vaidheki.srinivasan@accenture.com> | X26: 46111.844 | Y26: IMS BAU; UAT Testing Not Required | Z26: AutomationProcess_29697\mySPIntegratedSolutionPlatform\myISP_IMS | AA26: AutomationProcess_29697\mySolutionPlannerRapidSolutioning\R65\Sprint165 | AD26: INSPIRE | AE26: supriya.a.dhingra
A27: IMS BAU - Technical User Stories | B27: Platform Consolidation | C27: Inspire | D27: May Release | E27: 4317300 | F27: 4450112 | G27: Sonar Lint - 2 | H27: Active | I27: myISP_IMS | J27: Srinivasan, Vaidheki <vaidheki.srinivasan@accenture.com> | K27: 46134.229 | M27: 46140.229 | O27: P K, Prabitha <prabitha.p.k@accenture.com> | P27: 46151.229 | Q27: 8 | S27: 2 | U27: Yes | V27: Yes | W27: Srinivasan, Vaidheki <vaidheki.srinivasan@accenture.com> | X27: 46111.844 | Y27: IMS BAU; UAT Testing Not Required | Z27: AutomationProcess_29697\mySPIntegratedSolutionPlatform\myISP_IMS | AA27: AutomationProcess_29697\mySolutionPlannerRapidSolutioning\R65\Sprint165 | AD27: INSPIRE | AE27: supriya.a.dhingra
A28: IMS BAU - Technical User Stories | B28: Platform Consolidation | C28: Inspire | D28: May Release | E28: 4317300 | F28: 4450113 | G28: Sonar Lint -3 | H28: Active | I28: myISP_IMS | J28: Srinivasan, Vaidheki <vaidheki.srinivasan@accenture.com> | K28: 46134.229 | M28: 46140.229 | O28: P K, Prabitha <prabitha.p.k@accenture.com> | P28: 46151.229 | Q28: 5 | S28: 2 | U28: Yes | V28: Yes | W28: Srinivasan, Vaidheki <vaidheki.srinivasan@accenture.com> | X28: 46111.844 | Y28: IMS BAU; UAT Testing Not Required | Z28: AutomationProcess_29697\mySPIntegratedSolutionPlatform\myISP_IMS | AA28: AutomationProcess_29697\mySolutionPlannerRapidSolutioning\R65\Sprint165 | AD28: INSPIRE | AE28: supriya.a.dhingra
A29: IMS BAU - Technical User Stories | B29: Platform Consolidation | C29: Inspire | D29: May Release | E29: 4317300 | F29: 4450114 | G29: Node Js Upgrade - 1 | H29: PT In Test | I29: myISP_IMS | J29: Srinivasan, Vaidheki <vaidheki.srinivasan@accenture.com> | K29: 46134.229 | L29: 46125.229 | M29: 46140.229 | O29: P K, Prabitha <prabitha.p.k@accenture.com> | P29: 46151.229 | Q29: 5 | S29: 2 | U29: Yes | V29: Yes | W29: Srinivasan, Vaidheki <vaidheki.srinivasan@accenture.com> | X29: 46111.846 | Y29: IMS BAU; UAT Testing Not Required | Z29: AutomationProcess_29697\mySPIntegratedSolutionPlatform\myISP_IMS | AA29: AutomationProcess_29697\mySolutionPlannerRapidSolutioning\R65\Sprint165 | AD29: INSPIRE | AE29: supriya.a.dhingra
A30: IMS BAU - Technical User Stories | B30: Platform Consolidation | C30: Inspire | D30: May Release | E30: 4317300 | F30: 4450115 | G30: Node Js Upgarde - 2 | H30: PT In Test | I30: myISP_IMS | J30: Srinivasan, Vaidheki <vaidheki.srinivasan@accenture.com> | K30: 46134.229 | L30: 46125.229 | M30: 46140.229 | O30: P K, Prabitha <prabitha.p.k@accenture.com> | P30: 46151.229 | Q30: 3 | S30: 2 | U30: Yes | V30: Yes | W30: Srinivasan, Vaidheki <vaidheki.srinivasan@accenture.com> | X30: 46111.846 | Y30: IMS BAU; UAT Testing Not Required | Z30: AutomationProcess_29697\mySPIntegratedSolutionPlatform\myISP_IMS | AA30: AutomationProcess_29697\mySolutionPlannerRapidSolutioning\R65\Sprint165 | AD30: INSPIRE | AE30: supriya.a.dhingra
